[
  {
    "instruction": "Create a Area Chart chart named 'Chart Example 0' plotting 'Discount' against 'Order Date'. The data should be sorted in desc order and displayed using a horizontal layout. A secondary Y-axis is included, representing 'Price'. The y-axis should be labeled as 'Axis Label' and positioned at 'center' with a name gap of 24 pixels. The secondary Y-axis should be labeled as 'Axis Label' with a name gap of 23 pixels. The column 'Profit' should be aggregating using SUM function, y-axis values should be hidden, filled with color #f0f0f0, values should be suffixed with 'USD'. The column 'Demand' should be aggregating using SUM function, tooltip should display 'Tooltip Label'. The column 'Mega_watt' should be tooltip should display 'Tooltip Label', values should be rounded to 0 decimal places, values should be suffixed with 'USD'. The column 'Price' should be aggregating using MIN function, filled with color #f8b0y1, lowest values should be colored #f0f0f0, tooltip should display 'Tooltip Label', values should be rounded to 0 decimal places, values should be prefixed with '#'. The column 'Discount' should be filled with color #1d3b7a, highest values should be colored #f8b0y1, tooltip should display 'Tooltip Label'. The column 'Revenue' should be aggregating using COUNT function, tooltip should display 'Tooltip Label', values should be rounded to 3 decimal places, values should be prefixed with '$'.",
    "input": "{\"dataSources\":[{\"dataSourceId\":\"ds-6199\",\"queryKey\":\"API:+auto-task$$auto_65\",\"cols\":[{\"jsonName\":\"Profit\",\"type\":\"number\"},{\"jsonName\":\"Country\",\"type\":\"string\"},{\"jsonName\":\"Order Date\",\"type\":\"date\"},{\"jsonName\":\"Demand\",\"type\":\"number\"},{\"jsonName\":\"Mega_watt\",\"type\":\"number\"},{\"jsonName\":\"Region\",\"type\":\"string\"},{\"jsonName\":\"Price\",\"type\":\"number\"},{\"jsonName\":\"Discount\",\"type\":\"number\"},{\"jsonName\":\"Revenue\",\"type\":\"number\"}],\"params\":[]}]}",
    "output": "{\n    \"dataSources\": [\n        {\n            \"dataSourceId\": \"ds-6199\",\n            \"queryKey\": \"API:+auto-task$$auto_65\",\n            \"cols\": [\n                {\n                    \"jsonName\": \"Profit\",\n                    \"type\": \"number\",\n                    \"aggFn\": \"SUM\",\n                    \"isYAxisValueVisible\": false,\n                    \"fillColor\": \"#f0f0f0\",\n                    \"suffix\": \"USD\"\n                },\n                {\n                    \"jsonName\": \"Country\",\n                    \"type\": \"string\"\n                },\n                {\n                    \"jsonName\": \"Order Date\",\n                    \"type\": \"date\"\n                },\n                {\n                    \"jsonName\": \"Demand\",\n                    \"type\": \"number\",\n                    \"aggFn\": \"SUM\",\n                    \"label\": \"Tooltip Label\"\n                },\n                {\n                    \"jsonName\": \"Mega_watt\",\n                    \"type\": \"number\",\n                    \"label\": \"Tooltip Label\",\n                    \"decimalPlaces\": 0,\n                    \"suffix\": \"USD\"\n                },\n                {\n                    \"jsonName\": \"Region\",\n                    \"type\": \"string\"\n                },\n                {\n                    \"jsonName\": \"Price\",\n                    \"type\": \"number\",\n                    \"aggFn\": \"MIN\",\n                    \"fillColor\": \"#f8b0y1\",\n                    \"fillLowestColor\": \"#f0f0f0\",\n                    \"label\": \"Tooltip Label\",\n                    \"decimalPlaces\": 0,\n                    \"prefix\": \"#\"\n                },\n                {\n                    \"jsonName\": \"Discount\",\n                    \"type\": \"number\",\n                    \"fillColor\": \"#1d3b7a\",\n                    \"fillHighestColor\": \"#f8b0y1\",\n                    \"label\": \"Tooltip Label\"\n                },\n                {\n                    \"jsonName\": \"Revenue\",\n                    \"type\": \"number\",\n                    \"aggFn\": \"COUNT\",\n                    \"label\": \"Tooltip Label\",\n                    \"decimalPlaces\": 3,\n                    \"prefix\": \"$\"\n                }\n            ],\n            \"params\": []\n        }\n    ],\n    \"chartLayout\": \"horizontal\",\n    \"attributes\": {\n        \"chartType\": \"Area Chart\",\n        \"sortOrder\": \"Desc\",\n        \"slider\": true,\n        \"saveImage\": true\n    },\n    \"chartName\": \"Chart Example 0\",\n    \"xAxis\": {\n        \"fields\": [\n            \"Order Date\"\n        ]\n    },\n    \"yAxis\": {\n        \"fields\": [\n            \"Discount\"\n        ],\n        \"label\": \"Axis Label\",\n        \"nameLocation\": \"center\",\n        \"nameGap\": 24\n    },\n    \"secondaryYAxis\": {\n        \"fields\": [\n            \"Price\"\n        ],\n        \"label\": \"Axis Label\",\n        \"nameGap\": 23\n    }\n}"
  },
  {
    "instruction": "Create a Tree Map chart named 'Chart Example 2' plotting 'Mega_watt' against 'Customer'. The data should be sorted in asc order and displayed using a horizontal layout. The x-axis should be labeled as 'Axis Label' with a name gap of 49 pixels. The y-axis should be labeled as 'Axis Label' with a name gap of 30 pixels. The column 'Mega_watt' should be aggregating using COUNT function, y-axis values should be hidden, tooltip should display 'Tooltip Label', values should be rounded to 3 decimal places. The column 'latitude' should be aggregating using MAX function, highest values should be colored #1d3b7a, lowest values should be colored #866666, values should be rounded to 1 decimal places, values should be suffixed with 'USD'. The column 'coordinate_lg' should be aggregating using COUNT function, lowest values should be colored #99ff95, tooltip should display 'Tooltip Label', values should be rounded to 3 decimal places, values should be suffixed with 'USD'. The column 'Sales' should be aggregating using COUNT function, highest values should be colored #1d3b7a, lowest values should be colored #99ff95, values should be rounded to 1 decimal places, values should be suffixed with 'MW'.",
    "input": "{\"dataSources\":[{\"dataSourceId\":\"ds-3032\",\"queryKey\":\"API:+auto-task$$auto-task_4\",\"cols\":[{\"jsonName\":\"Mega_watt\",\"type\":\"number\"},{\"jsonName\":\"location\",\"type\":\"string\"},{\"jsonName\":\"Customer\",\"type\":\"string\"},{\"jsonName\":\"Country\",\"type\":\"string\"},{\"jsonName\":\"latitude\",\"type\":\"number\"},{\"jsonName\":\"coordinate_lg\",\"type\":\"number\"},{\"jsonName\":\"Sales\",\"type\":\"number\"},{\"jsonName\":\"Order Date\",\"type\":\"date\"}],\"params\":[]}]}",
    "output": "{\n    \"dataSources\": [\n        {\n            \"dataSourceId\": \"ds-3032\",\n            \"queryKey\": \"API:+auto-task$$auto-task_4\",\n            \"cols\": [\n                {\n                    \"jsonName\": \"Mega_watt\",\n                    \"type\": \"number\",\n                    \"aggFn\": \"COUNT\",\n                    \"isYAxisValueVisible\": false,\n                    \"label\": \"Tooltip Label\",\n                    \"decimalPlaces\": 3\n                },\n                {\n                    \"jsonName\": \"location\",\n                    \"type\": \"string\"\n                },\n                {\n                    \"jsonName\": \"Customer\",\n                    \"type\": \"string\"\n                },\n                {\n                    \"jsonName\": \"Country\",\n                    \"type\": \"string\"\n                },\n                {\n                    \"jsonName\": \"latitude\",\n                    \"type\": \"number\",\n                    \"aggFn\": \"MAX\",\n                    \"fillHighestColor\": \"#1d3b7a\",\n                    \"fillLowestColor\": \"#866666\",\n                    \"decimalPlaces\": 1,\n                    \"suffix\": \"USD\"\n                },\n                {\n                    \"jsonName\": \"coordinate_lg\",\n                    \"type\": \"number\",\n                    \"aggFn\": \"COUNT\",\n                    \"fillLowestColor\": \"#99ff95\",\n                    \"label\": \"Tooltip Label\",\n                    \"decimalPlaces\": 3,\n                    \"suffix\": \"USD\"\n                },\n                {\n                    \"jsonName\": \"Sales\",\n                    \"type\": \"number\",\n                    \"aggFn\": \"COUNT\",\n                    \"fillHighestColor\": \"#1d3b7a\",\n                    \"fillLowestColor\": \"#99ff95\",\n                    \"decimalPlaces\": 1,\n                    \"suffix\": \"MW\"\n                },\n                {\n                    \"jsonName\": \"Order Date\",\n                    \"type\": \"date\"\n                }\n            ],\n            \"params\": []\n        }\n    ],\n    \"chartLayout\": \"horizontal\",\n    \"attributes\": {\n        \"chartType\": \"Tree Map\",\n        \"sortOrder\": \"Asc\",\n        \"slider\": true,\n        \"saveImage\": true\n    },\n    \"chartName\": \"Chart Example 2\",\n    \"xAxis\": {\n        \"fields\": [\n            \"Customer\"\n        ],\n        \"label\": \"Axis Label\",\n        \"nameGap\": 49\n    },\n    \"yAxis\": {\n        \"fields\": [\n            \"Mega_watt\"\n        ],\n        \"label\": \"Axis Label\",\n        \"nameGap\": 30\n    }\n}"
  },
  {
    "instruction": "Create a Scattered Chart chart named 'Chart Example 3' plotting 'Revenue' against 'Category'. The data should be sorted in desc order and displayed using a vertical layout. A Z-axis is also present, containing 'Cost'. The x-axis should be labeled as 'Axis Label' and positioned at 'center' The column 'longitude' should be aggregating using AVG function, tooltip should display 'Tooltip Label', values should be rounded to 0 decimal places, values should be suffixed with 'p'. The column 'latitude' should be aggregating using MAX function, filled with color #866666, tooltip should display 'Tooltip Label', values should be rounded to 2 decimal places. The column 'Revenue' should be y-axis values should be visible, tooltip should display 'Tooltip Label', values should be rounded to 2 decimal places, values should be prefixed with '*'. The column 'Cost' should be filled with color #1d3b7a, tooltip should display 'Tooltip Label', values should be rounded to 1 decimal places, values should be prefixed with '#'. The column 'coordinate_lg' should be aggregating using AVG function, values should be rounded to 1 decimal places, values should be suffixed with 'p'.",
    "input": "{\"dataSources\":[{\"dataSourceId\":\"ds-2682\",\"queryKey\":\"API:+jdbc$$Oracle$$Energy_API_12\",\"cols\":[{\"jsonName\":\"Place\",\"type\":\"string\"},{\"jsonName\":\"Category\",\"type\":\"string\"},{\"jsonName\":\"longitude\",\"type\":\"number\"},{\"jsonName\":\"latitude\",\"type\":\"number\"},{\"jsonName\":\"Revenue\",\"type\":\"number\"},{\"jsonName\":\"Cost\",\"type\":\"number\"},{\"jsonName\":\"coordinate_lg\",\"type\":\"number\"},{\"jsonName\":\"location\",\"type\":\"string\"}],\"params\":[]}]}",
    "output": "{\n    \"dataSources\": [\n        {\n            \"dataSourceId\": \"ds-2682\",\n            \"queryKey\": \"API:+jdbc$$Oracle$$Energy_API_12\",\n            \"cols\": [\n                {\n                    \"jsonName\": \"Place\",\n                    \"type\": \"string\"\n                },\n                {\n                    \"jsonName\": \"Category\",\n                    \"type\": \"string\"\n                },\n                {\n                    \"jsonName\": \"longitude\",\n                    \"type\": \"number\",\n                    \"aggFn\": \"AVG\",\n                    \"label\": \"Tooltip Label\",\n                    \"decimalPlaces\": 0,\n                    \"suffix\": \"p\"\n                },\n                {\n                    \"jsonName\": \"latitude\",\n                    \"type\": \"number\",\n                    \"aggFn\": \"MAX\",\n                    \"fillColor\": \"#866666\",\n                    \"label\": \"Tooltip Label\",\n                    \"decimalPlaces\": 2\n                },\n                {\n                    \"jsonName\": \"Revenue\",\n                    \"type\": \"number\",\n                    \"isYAxisValueVisible\": true,\n                    \"label\": \"Tooltip Label\",\n                    \"decimalPlaces\": 2,\n                    \"prefix\": \"*\"\n                },\n                {\n                    \"jsonName\": \"Cost\",\n                    \"type\": \"number\",\n                    \"fillColor\": \"#1d3b7a\",\n                    \"label\": \"Tooltip Label\",\n                    \"decimalPlaces\": 1,\n                    \"prefix\": \"#\"\n                },\n                {\n                    \"jsonName\": \"coordinate_lg\",\n                    \"type\": \"number\",\n                    \"aggFn\": \"AVG\",\n                    \"decimalPlaces\": 1,\n                    \"suffix\": \"p\"\n                },\n                {\n                    \"jsonName\": \"location\",\n                    \"type\": \"string\"\n                }\n            ],\n            \"params\": []\n        }\n    ],\n    \"chartLayout\": \"vertical\",\n    \"attributes\": {\n        \"chartType\": \"Scattered Chart\",\n        \"sortOrder\": \"Desc\",\n        \"slider\": true,\n        \"saveImage\": true\n    },\n    \"chartName\": \"Chart Example 3\",\n    \"xAxis\": {\n        \"fields\": [\n            \"Category\"\n        ],\n        \"label\": \"Axis Label\",\n        \"nameLocation\": \"center\"\n    },\n    \"yAxis\": {\n        \"fields\": [\n            \"Revenue\"\n        ]\n    },\n    \"zAxis\": {\n        \"fields\": [\n            \"Cost\"\n        ]\n    }\n}"
  },
  {
    "instruction": "Create a Bar Chart chart named 'Chart Example 5' plotting 'Mega_watt' against 'Place'. The data should be sorted in desc order and displayed using a horizontal layout. A secondary Y-axis is included, representing 'Price'. The x-axis should be labeled as 'Axis Label' The y-axis should be labeled as 'Axis Label' The secondary Y-axis should be labeled as 'Axis Label' with a name gap of 13 pixels. The column 'Price' should be aggregating using MAX function, tooltip should display 'Tooltip Label', values should be rounded to 1 decimal places, values should be suffixed with 'p'. The column 'coordinate_lg' should be tooltip should display 'Tooltip Label', values should be rounded to 0 decimal places, values should be prefixed with '*'. The column 'Mega_watt' should be aggregating using SUM function, tooltip should display 'Tooltip Label', values should be rounded to 1 decimal places, values should be prefixed with '*'. The column 'longitude' should be filled with color #99ff95, tooltip should display 'Tooltip Label', values should be rounded to 3 decimal places.",
    "input": "{\"dataSources\":[{\"dataSourceId\":\"ds-2095\",\"queryKey\":\"API:+jdbc$$dataService$$_61\",\"cols\":[{\"jsonName\":\"Price\",\"type\":\"number\"},{\"jsonName\":\"coordinate_lg\",\"type\":\"number\"},{\"jsonName\":\"SubCategory\",\"type\":\"string\"},{\"jsonName\":\"Mega_watt\",\"type\":\"number\"},{\"jsonName\":\"longitude\",\"type\":\"number\"},{\"jsonName\":\"Region\",\"type\":\"string\"},{\"jsonName\":\"Place\",\"type\":\"string\"},{\"jsonName\":\"Customer\",\"type\":\"string\"}],\"params\":[]}]}",
    "output": "{\n    \"dataSources\": [\n        {\n            \"dataSourceId\": \"ds-2095\",\n            \"queryKey\": \"API:+jdbc$$dataService$$_61\",\n            \"cols\": [\n                {\n                    \"jsonName\": \"Price\",\n                    \"type\": \"number\",\n                    \"aggFn\": \"MAX\",\n                    \"label\": \"Tooltip Label\",\n                    \"decimalPlaces\": 1,\n                    \"suffix\": \"p\"\n                },\n                {\n                    \"jsonName\": \"coordinate_lg\",\n                    \"type\": \"number\",\n                    \"label\": \"Tooltip Label\",\n                    \"decimalPlaces\": 0,\n                    \"prefix\": \"*\"\n                },\n                {\n                    \"jsonName\": \"SubCategory\",\n                    \"type\": \"string\"\n                },\n                {\n                    \"jsonName\": \"Mega_watt\",\n                    \"type\": \"number\",\n                    \"aggFn\": \"SUM\",\n                    \"label\": \"Tooltip Label\",\n                    \"decimalPlaces\": 1,\n                    \"prefix\": \"*\"\n                },\n                {\n                    \"jsonName\": \"longitude\",\n                    \"type\": \"number\",\n                    \"fillColor\": \"#99ff95\",\n                    \"label\": \"Tooltip Label\",\n                    \"decimalPlaces\": 3\n                },\n                {\n                    \"jsonName\": \"Region\",\n                    \"type\": \"string\"\n                },\n                {\n                    \"jsonName\": \"Place\",\n                    \"type\": \"string\"\n                },\n                {\n                    \"jsonName\": \"Customer\",\n                    \"type\": \"string\"\n                }\n            ],\n            \"params\": []\n        }\n    ],\n    \"chartLayout\": \"horizontal\",\n    \"attributes\": {\n        \"chartType\": \"Bar Chart\",\n        \"sortOrder\": \"Desc\",\n        \"slider\": true,\n        \"saveImage\": true\n    },\n    \"chartName\": \"Chart Example 5\",\n    \"xAxis\": {\n        \"fields\": [\n            \"Place\"\n        ],\n        \"label\": \"Axis Label\"\n    },\n    \"yAxis\": {\n        \"fields\": [\n            \"Mega_watt\"\n        ],\n        \"label\": \"Axis Label\"\n    },\n    \"secondaryYAxis\": {\n        \"fields\": [\n            \"Price\"\n        ],\n        \"label\": \"Axis Label\",\n        \"nameGap\": 13\n    }\n}"
  },
  {
    "instruction": "Create a Gantt Chart chart titled 'Chart Example 6' with 'assigned_date' and 'submission_date' against 'location'. The data should be sorted in asc order and displayed using a horizontal layout. The x-axis should be labeled as 'Axis Label' and positioned at 'center' The y-axis should be labeled as 'Axis Label' with a name gap of 14 pixels. The column 'submission_date' should be y-axis values should be visible, filled with color #99ff95, highest values should be colored #f0f0f0. The column 'assigned_date' should be aggregating using SUM function, highest values should be colored #866666, lowest values should be colored #99ff95, tooltip should display 'Tooltip Label', values should be rounded to 2 decimal places, values should be prefixed with '@'. The column 'longitude' should be y-axis values should be visible, filled with color #f0f0f0, highest values should be colored #866666, tooltip should display 'Tooltip Label', values should be rounded to 2 decimal places, values should be suffixed with '%'. The column 'Generation' should be aggregating using AVG function, highest values should be colored #f8b0y1, tooltip should display 'Tooltip Label', values should be rounded to 1 decimal places, values should be suffixed with 'USD'. The column 'Discount' should be aggregating using SUM function, values should be suffixed with 'p'.",
    "input": "{\"dataSources\":[{\"dataSourceId\":\"ds-1680\",\"queryKey\":\"API:+lookup$$lookup$$_95\",\"cols\":[{\"jsonName\":\"location\",\"type\":\"string\"},{\"jsonName\":\"submission_date\",\"type\":\"date\"},{\"jsonName\":\"Order Date\",\"type\":\"date\"},{\"jsonName\":\"Country\",\"type\":\"string\"},{\"jsonName\":\"assigned_date\",\"type\":\"date\"},{\"jsonName\":\"longitude\",\"type\":\"number\"},{\"jsonName\":\"Generation\",\"type\":\"number\"},{\"jsonName\":\"Discount\",\"type\":\"number\"}],\"params\":[]}]}",
    "output": "{\n    \"dataSources\": [\n        {\n            \"dataSourceId\": \"ds-1680\",\n            \"queryKey\": \"API:+lookup$$lookup$$_95\",\n            \"cols\": [\n                {\n                    \"jsonName\": \"location\",\n                    \"type\": \"string\"\n                },\n                {\n                    \"jsonName\": \"submission_date\",\n                    \"type\": \"date\",\n                    \"isYAxisValueVisible\": true,\n                    \"fillColor\": \"#99ff95\",\n                    \"fillHighestColor\": \"#f0f0f0\"\n                },\n                {\n                    \"jsonName\": \"Order Date\",\n                    \"type\": \"date\"\n                },\n                {\n                    \"jsonName\": \"Country\",\n                    \"type\": \"string\"\n                },\n                {\n                    \"jsonName\": \"assigned_date\",\n                    \"type\": \"date\",\n                    \"aggFn\": \"SUM\",\n                    \"fillHighestColor\": \"#866666\",\n                    \"fillLowestColor\": \"#99ff95\",\n                    \"label\": \"Tooltip Label\",\n                    \"decimalPlaces\": 2,\n                    \"prefix\": \"@\"\n                },\n                {\n                    \"jsonName\": \"longitude\",\n                    \"type\": \"number\",\n                    \"isYAxisValueVisible\": true,\n                    \"fillColor\": \"#f0f0f0\",\n                    \"fillHighestColor\": \"#866666\",\n                    \"label\": \"Tooltip Label\",\n                    \"decimalPlaces\": 2,\n                    \"suffix\": \"%\"\n                },\n                {\n                    \"jsonName\": \"Generation\",\n                    \"type\": \"number\",\n                    \"aggFn\": \"AVG\",\n                    \"fillHighestColor\": \"#f8b0y1\",\n                    \"label\": \"Tooltip Label\",\n                    \"decimalPlaces\": 1,\n                    \"suffix\": \"USD\"\n                },\n                {\n                    \"jsonName\": \"Discount\",\n                    \"type\": \"number\",\n                    \"aggFn\": \"SUM\",\n                    \"suffix\": \"p\"\n                }\n            ],\n            \"params\": []\n        }\n    ],\n    \"chartLayout\": \"horizontal\",\n    \"attributes\": {\n        \"chartType\": \"Gantt Chart\",\n        \"sortOrder\": \"Asc\",\n        \"slider\": true,\n        \"saveImage\": true\n    },\n    \"chartName\": \"Chart Example 6\",\n    \"xAxis\": {\n        \"fields\": [\n            \"location\"\n        ],\n        \"label\": \"Axis Label\",\n        \"nameLocation\": \"center\"\n    },\n    \"yAxis\": {\n        \"fields\": [\n            \"assigned_date\"\n,   \"submission_date\"\n          ],\n        \"label\": \"Axis Label\",\n        \"nameGap\": 14\n    }\n}"
  },
  {
    "instruction": "Create a Scattered Chart chart named 'Chart Example 7' plotting 'Cost' against 'location'. The data should be sorted in desc order and displayed using a horizontal layout. A Z-axis is also present, containing 'Generation'. The y-axis should be labeled as 'Axis Label' and positioned at 'center' The column 'Sales' should be filled with color #99ff95, values should be suffixed with '%'. The column 'Generation' should be aggregating using COUNT function, lowest values should be colored #f0f0f0, tooltip should display 'Tooltip Label', values should be rounded to 3 decimal places, values should be suffixed with 'MW'. The column 'longitude' should be aggregating using MAX function, filled with color #f0f0f0, values should be rounded to 3 decimal places, values should be prefixed with '#'. The column 'coordinate_lg' should be y-axis values should be visible, highest values should be colored #f8b0y1, tooltip should display 'Tooltip Label', values should be prefixed with '$'. The column 'Cost' should be aggregating using SUM function, filled with color #99ff95, highest values should be colored #f0f0f0, lowest values should be colored #1d3b7a, tooltip should display 'Tooltip Label', values should be rounded to 0 decimal places, values should be prefixed with '$'. The column 'latitude' should be aggregating using MIN function, values should be rounded to 3 decimal places, values should be suffixed with 'MW'. The column 'Mega_watt' should be y-axis values should be hidden, highest values should be colored #866666, tooltip should display 'Tooltip Label', values should be rounded to 2 decimal places, values should be prefixed with '$'.",
    "input": "{\"dataSources\":[{\"dataSourceId\":\"ds-7456\",\"queryKey\":\"API:+auto-task$$auto_8\",\"cols\":[{\"jsonName\":\"Sales\",\"type\":\"number\"},{\"jsonName\":\"Generation\",\"type\":\"number\"},{\"jsonName\":\"longitude\",\"type\":\"number\"},{\"jsonName\":\"location\",\"type\":\"string\"},{\"jsonName\":\"Region\",\"type\":\"string\"},{\"jsonName\":\"coordinate_lg\",\"type\":\"number\"},{\"jsonName\":\"Cost\",\"type\":\"number\"},{\"jsonName\":\"Order Date\",\"type\":\"date\"},{\"jsonName\":\"latitude\",\"type\":\"number\"},{\"jsonName\":\"Mega_watt\",\"type\":\"number\"}],\"params\":[]}]}",
    "output": "{\n    \"dataSources\": [\n        {\n            \"dataSourceId\": \"ds-7456\",\n            \"queryKey\": \"API:+auto-task$$auto_8\",\n            \"cols\": [\n                {\n                    \"jsonName\": \"Sales\",\n                    \"type\": \"number\",\n                    \"fillColor\": \"#99ff95\",\n                    \"suffix\": \"%\"\n                },\n                {\n                    \"jsonName\": \"Generation\",\n                    \"type\": \"number\",\n                    \"aggFn\": \"COUNT\",\n                    \"fillLowestColor\": \"#f0f0f0\",\n                    \"label\": \"Tooltip Label\",\n                    \"decimalPlaces\": 3,\n                    \"suffix\": \"MW\"\n                },\n                {\n                    \"jsonName\": \"longitude\",\n                    \"type\": \"number\",\n                    \"aggFn\": \"MAX\",\n                    \"fillColor\": \"#f0f0f0\",\n                    \"decimalPlaces\": 3,\n                    \"prefix\": \"#\"\n                },\n                {\n                    \"jsonName\": \"location\",\n                    \"type\": \"string\"\n                },\n                {\n                    \"jsonName\": \"Region\",\n                    \"type\": \"string\"\n                },\n                {\n                    \"jsonName\": \"coordinate_lg\",\n                    \"type\": \"number\",\n                    \"isYAxisValueVisible\": true,\n                    \"fillHighestColor\": \"#f8b0y1\",\n                    \"label\": \"Tooltip Label\",\n                    \"prefix\": \"$\"\n                },\n                {\n                    \"jsonName\": \"Cost\",\n                    \"type\": \"number\",\n                    \"aggFn\": \"SUM\",\n                    \"fillColor\": \"#99ff95\",\n                    \"fillHighestColor\": \"#f0f0f0\",\n                    \"fillLowestColor\": \"#1d3b7a\",\n                    \"label\": \"Tooltip Label\",\n                    \"decimalPlaces\": 0,\n                    \"prefix\": \"$\"\n                },\n                {\n                    \"jsonName\": \"Order Date\",\n                    \"type\": \"date\"\n                },\n                {\n                    \"jsonName\": \"latitude\",\n                    \"type\": \"number\",\n                    \"aggFn\": \"MIN\",\n                    \"decimalPlaces\": 3,\n                    \"suffix\": \"MW\"\n                },\n                {\n                    \"jsonName\": \"Mega_watt\",\n                    \"type\": \"number\",\n                    \"isYAxisValueVisible\": false,\n                    \"fillHighestColor\": \"#866666\",\n                    \"label\": \"Tooltip Label\",\n                    \"decimalPlaces\": 2,\n                    \"prefix\": \"$\"\n                }\n            ],\n            \"params\": []\n        }\n    ],\n    \"chartLayout\": \"horizontal\",\n    \"attributes\": {\n        \"chartType\": \"Scattered Chart\",\n        \"sortOrder\": \"Desc\",\n        \"slider\": true,\n        \"saveImage\": true\n    },\n    \"chartName\": \"Chart Example 7\",\n    \"xAxis\": {\n        \"fields\": [\n            \"location\"\n        ]\n    },\n    \"yAxis\": {\n        \"fields\": [\n            \"Cost\"\n        ],\n        \"label\": \"Axis Label\",\n        \"nameLocation\": \"center\"\n    },\n    \"zAxis\": {\n        \"fields\": [\n            \"Generation\"\n        ]\n    }\n}"
  },
  {
    "instruction": "Create a Tree Map chart named 'Chart Example 8' plotting 'Sales' against 'Category'. The data should be sorted in desc order and displayed using a horizontal layout. The x-axis should be labeled as 'Axis Label' and positioned at 'end' The column 'Revenue' should be aggregating using AVG function, filled with color #f8b0y1, lowest values should be colored #99ff95, tooltip should display 'Tooltip Label', values should be rounded to 1 decimal places, values should be prefixed with '#'. The column 'Profit' should be aggregating using AVG function, tooltip should display 'Tooltip Label', values should be rounded to 2 decimal places, values should be prefixed with '@'. The column 'Generation' should be aggregating using COUNT function, highest values should be colored #866666, values should be rounded to 0 decimal places, values should be prefixed with '$'. The column 'Sales' should be aggregating using AVG function, lowest values should be colored #99ff95, tooltip should display 'Tooltip Label', values should be prefixed with '#'.",
    "input": "{\"dataSources\":[{\"dataSourceId\":\"ds-5643\",\"queryKey\":\"API:+auto-task$$auto-task_96\",\"cols\":[{\"jsonName\":\"Revenue\",\"type\":\"number\"},{\"jsonName\":\"Profit\",\"type\":\"number\"},{\"jsonName\":\"Place\",\"type\":\"string\"},{\"jsonName\":\"Order Date\",\"type\":\"date\"},{\"jsonName\":\"Generation\",\"type\":\"number\"},{\"jsonName\":\"Category\",\"type\":\"string\"},{\"jsonName\":\"Sales\",\"type\":\"number\"}],\"params\":[]}]}",
    "output": "{\n    \"dataSources\": [\n        {\n            \"dataSourceId\": \"ds-5643\",\n            \"queryKey\": \"API:+auto-task$$auto-task_96\",\n            \"cols\": [\n                {\n                    \"jsonName\": \"Revenue\",\n                    \"type\": \"number\",\n                    \"aggFn\": \"AVG\",\n                    \"fillColor\": \"#f8b0y1\",\n                    \"fillLowestColor\": \"#99ff95\",\n                    \"label\": \"Tooltip Label\",\n                    \"decimalPlaces\": 1,\n                    \"prefix\": \"#\"\n                },\n                {\n                    \"jsonName\": \"Profit\",\n                    \"type\": \"number\",\n                    \"aggFn\": \"AVG\",\n                    \"label\": \"Tooltip Label\",\n                    \"decimalPlaces\": 2,\n                    \"prefix\": \"@\"\n                },\n                {\n                    \"jsonName\": \"Place\",\n                    \"type\": \"string\"\n                },\n                {\n                    \"jsonName\": \"Order Date\",\n                    \"type\": \"date\"\n                },\n                {\n                    \"jsonName\": \"Generation\",\n                    \"type\": \"number\",\n                    \"aggFn\": \"COUNT\",\n                    \"fillHighestColor\": \"#866666\",\n                    \"decimalPlaces\": 0,\n                    \"prefix\": \"$\"\n                },\n                {\n                    \"jsonName\": \"Category\",\n                    \"type\": \"string\"\n                },\n                {\n                    \"jsonName\": \"Sales\",\n                    \"type\": \"number\",\n                    \"aggFn\": \"AVG\",\n                    \"fillLowestColor\": \"#99ff95\",\n                    \"label\": \"Tooltip Label\",\n                    \"prefix\": \"#\"\n                }\n            ],\n            \"params\": []\n        }\n    ],\n    \"chartLayout\": \"horizontal\",\n    \"attributes\": {\n        \"chartType\": \"Tree Map\",\n        \"sortOrder\": \"Desc\",\n        \"slider\": true,\n        \"saveImage\": true\n}\n    },\n    \"chartName\": \"Chart Example 8\",\n    \"xAxis\": {\n        \"fields\": [\n            \"Category\"\n        ],\n        \"label\": \"Axis Label\",\n        \"nameLocation\": \"end\"\n    },\n    \"yAxis\": {\n        \"fields\": [\n            \"Sales\"\n        ]\n    }\n}"
  },
  {
    "instruction": "Create a Pie Chart chart named 'Chart Example 9' plotting 'Cost' against 'SubCategory'. The data should be sorted in asc order and displayed using a horizontal layout. The y-axis should be labeled as 'Axis Label' and positioned at 'start'. Chart should be rotated by 162 degree. The column 'Discount' should be lowest values should be colored #f8b0y1, values should be rounded to 0 decimal places, values should be prefixed with '#'. The column 'longitude' should be aggregating using MIN function, filled with color #866666, highest values should be colored #99ff95, lowest values should be colored #f0f0f0, values should be prefixed with '₹'. The column 'Cost' should be aggregating using MAX function, values should be rounded to 0 decimal places, values should be prefixed with '#'. The column 'Mega_watt' should be tooltip should display 'Tooltip Label', values should be rounded to 3 decimal places, values should be prefixed with '*'.",
    "input": "{\"dataSources\":[{\"dataSourceId\":\"ds-4831\",\"queryKey\":\"API:+jdbc$$dataService$$_46\",\"cols\":[{\"jsonName\":\"Discount\",\"type\":\"number\"},{\"jsonName\":\"SubCategory\",\"type\":\"string\"},{\"jsonName\":\"Category\",\"type\":\"string\"},{\"jsonName\":\"Order Date\",\"type\":\"date\"},{\"jsonName\":\"longitude\",\"type\":\"number\"},{\"jsonName\":\"Customer\",\"type\":\"string\"},{\"jsonName\":\"Cost\",\"type\":\"number\"},{\"jsonName\":\"Mega_watt\",\"type\":\"number\"}],\"params\":[]}]}",
    "output": "{\n    \"dataSources\": [\n        {\n            \"dataSourceId\": \"ds-4831\",\n            \"queryKey\": \"API:+jdbc$$dataService$$_46\",\n            \"cols\": [\n                {\n                    \"jsonName\": \"Discount\",\n                    \"type\": \"number\",\n                    \"fillLowestColor\": \"#f8b0y1\",\n                    \"decimalPlaces\": 0,\n                    \"prefix\": \"#\"\n                },\n                {\n                    \"jsonName\": \"SubCategory\",\n                    \"type\": \"string\"\n                },\n                {\n                    \"jsonName\": \"Category\",\n                    \"type\": \"string\"\n                },\n                {\n                    \"jsonName\": \"Order Date\",\n                    \"type\": \"date\"\n                },\n                {\n                    \"jsonName\": \"longitude\",\n                    \"type\": \"number\",\n                    \"aggFn\": \"MIN\",\n                    \"fillColor\": \"#866666\",\n                    \"fillHighestColor\": \"#99ff95\",\n                    \"fillLowestColor\": \"#f0f0f0\",\n                    \"prefix\": \"\\u20b9\"\n                },\n                {\n                    \"jsonName\": \"Customer\",\n                    \"type\": \"string\"\n                },\n                {\n                    \"jsonName\": \"Cost\",\n                    \"type\": \"number\",\n                    \"aggFn\": \"MAX\",\n                    \"decimalPlaces\": 0,\n                    \"prefix\": \"#\"\n                },\n                {\n                    \"jsonName\": \"Mega_watt\",\n                    \"type\": \"number\",\n                    \"label\": \"Tooltip Label\",\n                    \"decimalPlaces\": 3,\n                    \"prefix\": \"*\"\n                }\n            ],\n            \"params\": []\n        }\n    ],\n    \"chartLayout\": \"horizontal\",\n    \"attributes\": {\n        \"chartType\": \"Pie Chart\",\n        \"sortOrder\": \"Asc\",\n        \"slider\": true,\n        \"saveImage\": true,\n        \"chartSubType\": \"normal\",\n        \"rotation\": 162\n    },\n    \"chartName\": \"Chart Example 9\",\n    \"xAxis\": {\n        \"fields\": [\n            \"SubCategory\"\n        ]\n    },\n    \"yAxis\": {\n        \"fields\": [\n            \"Cost\"\n        ],\n        \"label\": \"Axis Label\",\n        \"nameLocation\": \"start\"\n    }\n}"
  },
  {
    "instruction": "Create a filled based Geo Chart chart named 'Chart Example 10' plotting 'N/A' against 'N/A'. The data should be sorted in desc order and displayed using a horizontal layout. The column 'coordinate_lt' should be aggregating using AVG function, tooltip should display 'Tooltip Label', values should be prefixed with '#'. The column 'latitude' should be aggregating using SUM function, lowest values should be colored #1d3b7a, values should be rounded to 3 decimal places, values should be prefixed with '*'. The column 'coordinate_lg' should be lowest values should be colored #1d3b7a, values should be rounded to 2 decimal places, values should be prefixed with '@'. The column 'Price' should be aggregating using SUM function, y-axis values should be hidden, filled with color #99ff95, highest values should be colored #1d3b7a, lowest values should be colored #1d3b7a, tooltip should display 'Tooltip Label', values should be prefixed with '*'. The column 'Profit' should be aggregating using COUNT function, filled with color #f0f0f0, tooltip should display 'Tooltip Label', values should be rounded to 1 decimal places, values should be prefixed with '*'. The column 'Demand' should be lowest values should be colored #f0f0f0, tooltip should display 'Tooltip Label', values should be rounded to 2 decimal places, values should be prefixed with '@'.",
    "input": "{\"dataSources\":[{\"dataSourceId\":\"ds-6919\",\"queryKey\":\"API:+auto-task$$auto-task_61\",\"cols\":[{\"jsonName\":\"coordinate_lt\",\"type\":\"number\"},{\"jsonName\":\"latitude\",\"type\":\"number\"},{\"jsonName\":\"Country\",\"type\":\"string\"},{\"jsonName\":\"coordinate_lg\",\"type\":\"number\"},{\"jsonName\":\"Customer\",\"type\":\"string\"},{\"jsonName\":\"Price\",\"type\":\"number\"},{\"jsonName\":\"Profit\",\"type\":\"number\"},{\"jsonName\":\"Demand\",\"type\":\"number\"},{\"jsonName\":\"location\",\"type\":\"string\"}],\"params\":[]}]}",
    "output": "{\n    \"dataSources\": [\n        {\n            \"dataSourceId\": \"ds-6919\",\n            \"queryKey\": \"API:+auto-task$$auto-task_61\",\n            \"cols\": [\n                {\n                    \"jsonName\": \"coordinate_lt\",\n                    \"type\": \"number\",\n                    \"aggFn\": \"AVG\",\n                    \"label\": \"Tooltip Label\",\n                    \"prefix\": \"#\"\n                },\n                {\n                    \"jsonName\": \"latitude\",\n                    \"type\": \"number\",\n                    \"aggFn\": \"SUM\",\n                    \"fillLowestColor\": \"#1d3b7a\",\n                    \"decimalPlaces\": 3,\n                    \"prefix\": \"*\"\n                },\n                {\n                    \"jsonName\": \"Country\",\n                    \"type\": \"string\"\n                },\n                {\n                    \"jsonName\": \"coordinate_lg\",\n                    \"type\": \"number\",\n                    \"fillLowestColor\": \"#1d3b7a\",\n                    \"decimalPlaces\": 2,\n                    \"prefix\": \"@\"\n                },\n                {\n                    \"jsonName\": \"Customer\",\n                    \"type\": \"string\"\n                },\n                {\n                    \"jsonName\": \"Price\",\n                    \"type\": \"number\",\n                    \"aggFn\": \"SUM\",\n                    \"isYAxisValueVisible\": false,\n                    \"fillColor\": \"#99ff95\",\n                    \"fillHighestColor\": \"#1d3b7a\",\n                    \"fillLowestColor\": \"#1d3b7a\",\n                    \"label\": \"Tooltip Label\",\n                    \"prefix\": \"*\"\n                },\n                {\n                    \"jsonName\": \"Profit\",\n                    \"type\": \"number\",\n                    \"aggFn\": \"COUNT\",\n                    \"fillColor\": \"#f0f0f0\",\n                    \"label\": \"Tooltip Label\",\n                    \"decimalPlaces\": 1,\n                    \"prefix\": \"*\"\n                },\n                {\n                    \"jsonName\": \"Demand\",\n                    \"type\": \"number\",\n                    \"fillLowestColor\": \"#f0f0f0\",\n                    \"label\": \"Tooltip Label\",\n                    \"decimalPlaces\": 2,\n                    \"prefix\": \"@\"\n                },\n                {\n                    \"jsonName\": \"location\",\n                    \"type\": \"string\"\n                }\n            ],\n            \"params\": []\n        }\n    ],\n    \"chartLayout\": \"horizontal\",\n    \"attributes\": {\n        \"chartType\": \"Geo Chart\",\n        \"sortOrder\": \"Desc\",\n        \"slider\": true,\n        \"saveImage\": true,\n        \"chartSubType\": \"filledMap\"\n    },\n    \"chartName\": \"Chart Example 10\",\n    \"xAxis\": {},\n    \"yAxis\": {},\n    \"location\": {\n        \"fields\": [\n            \"location\"\n        ]\n    },\n    \"values\": {\n        \"fields\": [\n            \"Profit\"\n        ]\n    }\n}"
  },
  {
    "instruction": "Create a Bar Chart chart named 'Chart Example 11' plotting 'Profit' against 'Place'. The data should be sorted in desc order and displayed using a vertical layout. A secondary Y-axis is included, representing 'Revenue'. The x-axis should be labeled as 'Axis Label' with a name gap of 24 pixels. The y-axis should be labeled as 'Axis Label' The secondary Y-axis should be labeled as 'Axis Label' and positioned at 'start' The column 'Demand' should be aggregating using SUM function, filled with color #866666, tooltip should display 'Tooltip Label', values should be rounded to 2 decimal places, values should be suffixed with '%'. The column 'Sales' should be aggregating using AVG function, filled with color #99ff95, values should be rounded to 3 decimal places, values should be prefixed with '₹'. The column 'Profit' should be values should be rounded to 3 decimal places. The column 'Revenue' should be aggregating using COUNT function, filled with color #f8b0y1, highest values should be colored #1d3b7a, lowest values should be colored #866666, values should be rounded to 1 decimal places, values should be prefixed with '@'. The column 'Price' should be aggregating using AVG function, filled with color #f8b0y1, tooltip should display 'Tooltip Label', values should be prefixed with '@'. The column 'latitude' should be aggregating using COUNT function, y-axis values should be visible, filled with color #99ff95, values should be prefixed with '*'.",
    "input": "{\"dataSources\":[{\"dataSourceId\":\"ds-1013\",\"queryKey\":\"API:+jdbc$$Oracle$$Energy_API_71\",\"cols\":[{\"jsonName\":\"Demand\",\"type\":\"number\"},{\"jsonName\":\"Region\",\"type\":\"string\"},{\"jsonName\":\"Sales\",\"type\":\"number\"},{\"jsonName\":\"Profit\",\"type\":\"number\"},{\"jsonName\":\"Category\",\"type\":\"string\"},{\"jsonName\":\"Revenue\",\"type\":\"number\"},{\"jsonName\":\"Price\",\"type\":\"number\"},{\"jsonName\":\"Customer\",\"type\":\"string\"},{\"jsonName\":\"Place\",\"type\":\"string\"},{\"jsonName\":\"latitude\",\"type\":\"number\"}],\"params\":[]}]}",
    "output": "{\n    \"dataSources\": [\n        {\n            \"dataSourceId\": \"ds-1013\",\n            \"queryKey\": \"API:+jdbc$$Oracle$$Energy_API_71\",\n            \"cols\": [\n                {\n                    \"jsonName\": \"Demand\",\n                    \"type\": \"number\",\n                    \"aggFn\": \"SUM\",\n                    \"fillColor\": \"#866666\",\n                    \"label\": \"Tooltip Label\",\n                    \"decimalPlaces\": 2,\n                    \"suffix\": \"%\"\n                },\n                {\n                    \"jsonName\": \"Region\",\n                    \"type\": \"string\"\n                },\n                {\n                    \"jsonName\": \"Sales\",\n                    \"type\": \"number\",\n                    \"aggFn\": \"AVG\",\n                    \"fillColor\": \"#99ff95\",\n                    \"decimalPlaces\": 3,\n                    \"prefix\": \"\\u20b9\"\n                },\n                {\n                    \"jsonName\": \"Profit\",\n                    \"type\": \"number\",\n                    \"decimalPlaces\": 3\n                },\n                {\n                    \"jsonName\": \"Category\",\n                    \"type\": \"string\"\n                },\n                {\n                    \"jsonName\": \"Revenue\",\n                    \"type\": \"number\",\n                    \"aggFn\": \"COUNT\",\n                    \"fillColor\": \"#f8b0y1\",\n                    \"fillHighestColor\": \"#1d3b7a\",\n                    \"fillLowestColor\": \"#866666\",\n                    \"decimalPlaces\": 1,\n                    \"prefix\": \"@\"\n                },\n                {\n                    \"jsonName\": \"Price\",\n                    \"type\": \"number\",\n                    \"aggFn\": \"AVG\",\n                    \"fillColor\": \"#f8b0y1\",\n                    \"label\": \"Tooltip Label\",\n                    \"prefix\": \"@\"\n                },\n                {\n                    \"jsonName\": \"Customer\",\n                    \"type\": \"string\"\n                },\n                {\n                    \"jsonName\": \"Place\",\n                    \"type\": \"string\"\n                },\n                {\n                    \"jsonName\": \"latitude\",\n                    \"type\": \"number\",\n                    \"aggFn\": \"COUNT\",\n                    \"isYAxisValueVisible\": true,\n                    \"fillColor\": \"#99ff95\",\n                    \"prefix\": \"*\"\n                }\n            ],\n            \"params\": []\n        }\n    ],\n    \"chartLayout\": \"vertical\",\n    \"attributes\": {\n        \"chartType\": \"Bar Chart\",\n        \"sortOrder\": \"Desc\",\n        \"slider\": true,\n        \"saveImage\": true\n    },\n    \"chartName\": \"Chart Example 11\",\n    \"xAxis\": {\n        \"fields\": [\n            \"Place\"\n        ],\n        \"label\": \"Axis Label\",\n        \"nameGap\": 24\n    },\n    \"yAxis\": {\n        \"fields\": [\n            \"Profit\"\n        ],\n        \"label\": \"Axis Label\"\n    },\n    \"secondaryYAxis\": {\n        \"fields\": [\n            \"Revenue\"\n        ],\n        \"label\": \"Axis Label\",\n        \"nameLocation\": \"start\"\n    }\n}"
  },
  {
    "instruction": "Create a Tree Map chart named 'Chart Example 12' plotting 'Cost' against 'Order Date'. The data should be sorted in desc order and displayed using a vertical layout. The x-axis should be labeled as 'Axis Label' with a name gap of 30 pixels. The y-axis should be labeled as 'Axis Label' and positioned at 'end'. The column 'Revenue' should be lowest values should be colored #1d3b7a, values should be rounded to 1 decimal places. The column 'Cost' should be filled with color #f8b0y1, lowest values should be colored #f8b0y1, tooltip should display 'Tooltip Label', values should be rounded to 1 decimal places, values should be prefixed with '#'. The column 'Generation' should be aggregating using AVG function, lowest values should be colored #f0f0f0, values should be rounded to 1 decimal places, values should be prefixed with '#'. The column 'Price' should be highest values should be colored #866666, tooltip should display 'Tooltip Label', values should be rounded to 0 decimal places, values should be prefixed with '₹'. The column 'coordinate_lt' should be aggregating using MIN function, filled with color #866666, highest values should be colored #866666, lowest values should be colored #866666. The column 'Demand' should be aggregating using MIN function, filled with color #866666, lowest values should be colored #f8b0y1, values should be rounded to 0 decimal places. The column 'Mega_watt' should be tooltip should display 'Tooltip Label', values should be rounded to 0 decimal places.",
    "input": "{\"dataSources\":[{\"dataSourceId\":\"ds-7776\",\"queryKey\":\"API:+lookup$$lookup$$_65\",\"cols\":[{\"jsonName\":\"Revenue\",\"type\":\"number\"},{\"jsonName\":\"Order Date\",\"type\":\"date\"},{\"jsonName\":\"Cost\",\"type\":\"number\"},{\"jsonName\":\"Generation\",\"type\":\"number\"},{\"jsonName\":\"Price\",\"type\":\"number\"},{\"jsonName\":\"coordinate_lt\",\"type\":\"number\"},{\"jsonName\":\"Demand\",\"type\":\"number\"},{\"jsonName\":\"Mega_watt\",\"type\":\"number\"},{\"jsonName\":\"Place\",\"type\":\"string\"},{\"jsonName\":\"Category\",\"type\":\"string\"}],\"params\":[]}]}",
    "output": "{\n    \"dataSources\": [\n        {\n            \"dataSourceId\": \"ds-7776\",\n            \"queryKey\": \"API:+lookup$$lookup$$_65\",\n            \"cols\": [\n                {\n                    \"jsonName\": \"Revenue\",\n                    \"type\": \"number\",\n                    \"fillLowestColor\": \"#1d3b7a\",\n                    \"decimalPlaces\": 1\n                },\n                {\n                    \"jsonName\": \"Order Date\",\n                    \"type\": \"date\"\n                },\n                {\n                    \"jsonName\": \"Cost\",\n                    \"type\": \"number\",\n                    \"fillColor\": \"#f8b0y1\",\n                    \"fillLowestColor\": \"#f8b0y1\",\n                    \"label\": \"Tooltip Label\",\n                    \"decimalPlaces\": 1,\n                    \"prefix\": \"#\"\n                },\n                {\n                    \"jsonName\": \"Generation\",\n                    \"type\": \"number\",\n                    \"aggFn\": \"AVG\",\n                    \"fillLowestColor\": \"#f0f0f0\",\n                    \"decimalPlaces\": 1,\n                    \"prefix\": \"#\"\n                },\n                {\n                    \"jsonName\": \"Price\",\n                    \"type\": \"number\",\n                    \"fillHighestColor\": \"#866666\",\n                    \"label\": \"Tooltip Label\",\n                    \"decimalPlaces\": 0,\n                    \"prefix\": \"\\u20b9\"\n                },\n                {\n                    \"jsonName\": \"coordinate_lt\",\n                    \"type\": \"number\",\n                    \"aggFn\": \"MIN\",\n                    \"fillColor\": \"#866666\",\n                    \"fillHighestColor\": \"#866666\",\n                    \"fillLowestColor\": \"#866666\"\n                },\n                {\n                    \"jsonName\": \"Demand\",\n                    \"type\": \"number\",\n                    \"aggFn\": \"MIN\",\n                    \"fillColor\": \"#866666\",\n                    \"fillLowestColor\": \"#f8b0y1\",\n                    \"decimalPlaces\": 0\n                },\n                {\n                    \"jsonName\": \"Mega_watt\",\n                    \"type\": \"number\",\n                    \"label\": \"Tooltip Label\",\n                    \"decimalPlaces\": 0\n                },\n                {\n                    \"jsonName\": \"Place\",\n                    \"type\": \"string\"\n                },\n                {\n                    \"jsonName\": \"Category\",\n                    \"type\": \"string\"\n                }\n            ],\n            \"params\": []\n        }\n    ],\n    \"chartLayout\": \"vertical\",\n    \"attributes\": {\n        \"chartType\": \"Tree Map\",\n        \"sortOrder\": \"Desc\",\n        \"slider\": true,\n        \"saveImage\": true\n    },\n    \"chartName\": \"Chart Example 12\",\n    \"xAxis\": {\n        \"fields\": [\n            \"Order Date\"\n        ],\n        \"label\": \"Axis Label\",\n        \"nameGap\": 30\n    },\n    \"yAxis\": {\n        \"fields\": [\n            \"Cost\"\n        ],\n        \"label\": \"Axis Label\",\n        \"nameLocation\": \"end\"\n    }\n}"
  },
  {
    "instruction": "Create a Pie Chart chart named 'Chart Example 14' plotting 'Discount' against 'Employee'. The data should be sorted in asc order and displayed using a horizontal layout. The x-axis should be labeled as 'Axis Label' The rotation should be 291 and subtype is doughnut. The column 'coordinate_lg' should be aggregating using MIN function, filled with color #866666, tooltip should display 'Tooltip Label', values should be rounded to 3 decimal places, values should be prefixed with '*'. The column 'Discount' should be tooltip should display 'Tooltip Label', values should be rounded to 3 decimal places, values should be prefixed with '@'. The column 'Sales' should be y-axis values should be visible, tooltip should display 'Tooltip Label', values should be rounded to 0 decimal places. The column 'Revenue' should be highest values should be colored #f0f0f0, values should be rounded to 3 decimal places, values should be prefixed with '#'. The column 'coordinate_lt' should be aggregating using COUNT function, y-axis values should be hidden, filled with color #99ff95, highest values should be colored #1d3b7a, lowest values should be colored #866666, values should be prefixed with '@'.",
    "input": "{\"dataSources\":[{\"dataSourceId\":\"ds-9033\",\"queryKey\":\"API:+auto-task$$auto_75\",\"cols\":[{\"jsonName\":\"coordinate_lg\",\"type\":\"number\"},{\"jsonName\":\"Discount\",\"type\":\"number\"},{\"jsonName\":\"Sales\",\"type\":\"number\"},{\"jsonName\":\"Revenue\",\"type\":\"number\"},{\"jsonName\":\"Order Date\",\"type\":\"date\"},{\"jsonName\":\"Employee\",\"type\":\"string\"},{\"jsonName\":\"SubCategory\",\"type\":\"string\"},{\"jsonName\":\"coordinate_lt\",\"type\":\"number\"},{\"jsonName\":\"Country\",\"type\":\"string\"},{\"jsonName\":\"Category\",\"type\":\"string\"}],\"params\":[]}]}",
    "output": "{\n    \"dataSources\": [\n        {\n            \"dataSourceId\": \"ds-9033\",\n            \"queryKey\": \"API:+auto-task$$auto_75\",\n            \"cols\": [\n                {\n                    \"jsonName\": \"coordinate_lg\",\n                    \"type\": \"number\",\n                    \"aggFn\": \"MIN\",\n                    \"fillColor\": \"#866666\",\n                    \"label\": \"Tooltip Label\",\n                    \"decimalPlaces\": 3,\n                    \"prefix\": \"*\"\n                },\n                {\n                    \"jsonName\": \"Discount\",\n                    \"type\": \"number\",\n                    \"label\": \"Tooltip Label\",\n                    \"decimalPlaces\": 3,\n                    \"prefix\": \"@\"\n                },\n                {\n                    \"jsonName\": \"Sales\",\n                    \"type\": \"number\",\n                    \"isYAxisValueVisible\": true,\n                    \"label\": \"Tooltip Label\",\n                    \"decimalPlaces\": 0\n                },\n                {\n                    \"jsonName\": \"Revenue\",\n                    \"type\": \"number\",\n                    \"fillHighestColor\": \"#f0f0f0\",\n                    \"decimalPlaces\": 3,\n                    \"prefix\": \"#\"\n                },\n                {\n                    \"jsonName\": \"Order Date\",\n                    \"type\": \"date\"\n                },\n                {\n                    \"jsonName\": \"Employee\",\n                    \"type\": \"string\"\n                },\n                {\n                    \"jsonName\": \"SubCategory\",\n                    \"type\": \"string\"\n                },\n                {\n                    \"jsonName\": \"coordinate_lt\",\n                    \"type\": \"number\",\n                    \"aggFn\": \"COUNT\",\n                    \"isYAxisValueVisible\": false,\n                    \"fillColor\": \"#99ff95\",\n                    \"fillHighestColor\": \"#1d3b7a\",\n                    \"fillLowestColor\": \"#866666\",\n                    \"prefix\": \"@\"\n                },\n                {\n                    \"jsonName\": \"Country\",\n                    \"type\": \"string\"\n                },\n                {\n                    \"jsonName\": \"Category\",\n                    \"type\": \"string\"\n                }\n            ],\n            \"params\": []\n        }\n    ],\n    \"chartLayout\": \"horizontal\",\n    \"attributes\": {\n        \"chartType\": \"Pie Chart\",\n        \"sortOrder\": \"Asc\",\n        \"slider\": true,\n        \"saveImage\": true,\n        \"chartSubType\": \"doughnut\",\n        \"rotation\": 291\n    },\n    \"chartName\": \"Chart Example 14\",\n    \"xAxis\": {\n        \"fields\": [\n            \"Employee\"\n        ],\n        \"label\": \"Axis Label\"\n    },\n    \"yAxis\": {\n        \"fields\": [\n            \"Discount\"\n        ]\n    }\n}"
  },
  {
    "instruction": "Create a Area Chart chart named 'Chart Example 15' plotting 'Cost' against 'Country'. The data should be sorted in desc order and displayed using a vertical layout. The column 'Cost' should be y-axis values should be hidden, filled with color #99ff95, highest values should be colored #f8b0y1, lowest values should be colored #1d3b7a, tooltip should display 'Tooltip Label', values should be rounded to 0 decimal places, values should be prefixed with '$'. The column 'coordinate_lt' should be aggregating using AVG function, highest values should be colored #f8b0y1, tooltip should display 'Tooltip Label', values should be prefixed with '₹'. The column 'Price' should be aggregating using MIN function, tooltip should display 'Tooltip Label', values should be rounded to 0 decimal places, values should be prefixed with '@'. The column 'Profit' should be aggregating using MIN function, filled with color #866666, tooltip should display 'Tooltip Label', values should be rounded to 2 decimal places, values should be suffixed with 'p'.",
    "input": "{\"dataSources\":[{\"dataSourceId\":\"ds-9767\",\"queryKey\":\"API:+jdbc$$pmgr$$caps_18\",\"cols\":[{\"jsonName\":\"Cost\",\"type\":\"number\"},{\"jsonName\":\"Employee\",\"type\":\"string\"},{\"jsonName\":\"Country\",\"type\":\"string\"},{\"jsonName\":\"location\",\"type\":\"string\"},{\"jsonName\":\"coordinate_lt\",\"type\":\"number\"},{\"jsonName\":\"Price\",\"type\":\"number\"},{\"jsonName\":\"Profit\",\"type\":\"number\"}],\"params\":[]}]}",
    "output": "{\n    \"dataSources\": [\n        {\n            \"dataSourceId\": \"ds-9767\",\n            \"queryKey\": \"API:+jdbc$$pmgr$$caps_18\",\n            \"cols\": [\n                {\n                    \"jsonName\": \"Cost\",\n                    \"type\": \"number\",\n                    \"isYAxisValueVisible\": false,\n                    \"fillColor\": \"#99ff95\",\n                    \"fillHighestColor\": \"#f8b0y1\",\n                    \"fillLowestColor\": \"#1d3b7a\",\n                    \"label\": \"Tooltip Label\",\n                    \"decimalPlaces\": 0,\n                    \"prefix\": \"$\"\n                },\n                {\n                    \"jsonName\": \"Employee\",\n                    \"type\": \"string\"\n                },\n                {\n                    \"jsonName\": \"Country\",\n                    \"type\": \"string\"\n                },\n                {\n                    \"jsonName\": \"location\",\n                    \"type\": \"string\"\n                },\n                {\n                    \"jsonName\": \"coordinate_lt\",\n                    \"type\": \"number\",\n                    \"aggFn\": \"AVG\",\n                    \"fillHighestColor\": \"#f8b0y1\",\n                    \"label\": \"Tooltip Label\",\n                    \"prefix\": \"\\u20b9\"\n                },\n                {\n                    \"jsonName\": \"Price\",\n                    \"type\": \"number\",\n                    \"aggFn\": \"MIN\",\n                    \"label\": \"Tooltip Label\",\n                    \"decimalPlaces\": 0,\n                    \"prefix\": \"@\"\n                },\n                {\n                    \"jsonName\": \"Profit\",\n                    \"type\": \"number\",\n                    \"aggFn\": \"MIN\",\n                    \"fillColor\": \"#866666\",\n                    \"label\": \"Tooltip Label\",\n                    \"decimalPlaces\": 2,\n                    \"suffix\": \"p\"\n                }\n            ],\n            \"params\": []\n        }\n    ],\n    \"chartLayout\": \"vertical\",\n    \"attributes\": {\n        \"chartType\": \"Area Chart\",\n        \"sortOrder\": \"Desc\",\n        \"slider\": true,\n        \"saveImage\": true\n    },\n    \"chartName\": \"Chart Example 15\",\n    \"xAxis\": {\n        \"fields\": [\n            \"Country\"\n        ]\n    },\n    \"yAxis\": {\n        \"fields\": [\n            \"Cost\"\n        ]\n    }\n}"
  },
  {
    "instruction": "Create a Composed Chart chart named 'Chart Example 16' plotting 'Cost' against 'Employee'. The data should be sorted in asc order and displayed using a vertical layout. The y-axis should be labeled as 'Axis Label' The column 'latitude' should be aggregating using COUNT function, lowest values should be colored #99ff95, values should be prefixed with '₹'. The column 'Cost' should be filled with color #f0f0f0, subtype Bar Chart, highest values should be colored #866666, tooltip should display 'Tooltip Label', values should be rounded to 2 decimal places, values should be prefixed with '@'.",
    "input": "{\"dataSources\":[{\"dataSourceId\":\"ds-1973\",\"queryKey\":\"API:+jdbc$$TEMP$$us_station_city_geo_data_70\",\"cols\":[{\"jsonName\":\"Category\",\"type\":\"string\"},{\"jsonName\":\"latitude\",\"type\":\"number\"},{\"jsonName\":\"Customer\",\"type\":\"string\"},{\"jsonName\":\"Employee\",\"type\":\"string\"},{\"jsonName\":\"location\",\"type\":\"string\"},{\"jsonName\":\"Cost\",\"type\":\"number\"},{\"jsonName\":\"SubCategory\",\"type\":\"string\"},{\"jsonName\":\"Region\",\"type\":\"string\"},{\"jsonName\":\"Country\",\"type\":\"string\"}],\"params\":[]}]}",
    "output": "{\n    \"dataSources\": [\n        {\n            \"dataSourceId\": \"ds-1973\",\n            \"queryKey\": \"API:+jdbc$$TEMP$$us_station_city_geo_data_70\",\n            \"cols\": [\n                {\n                    \"jsonName\": \"Category\",\n                    \"type\": \"string\"\n                },\n                {\n                    \"jsonName\": \"latitude\",\n                    \"type\": \"number\",\n                    \"aggFn\": \"COUNT\",\n                    \"fillLowestColor\": \"#99ff95\",\n                    \"prefix\": \"\\u20b9\"\n                },\n                {\n                    \"jsonName\": \"Customer\",\n                    \"type\": \"string\"\n                },\n                {\n                    \"jsonName\": \"Employee\",\n                    \"type\": \"string\"\n                },\n                {\n                    \"jsonName\": \"location\",\n                    \"type\": \"string\"\n                },\n                {\n                    \"jsonName\": \"Cost\",\n                    \"type\": \"number\",\n                    \"composedChartType\": \"Bar Chart\",\n                         \"fillColor\": \"#f0f0f0\",\n                    \"fillHighestColor\": \"#866666\",\n                    \"label\": \"Tooltip Label\",\n                    \"decimalPlaces\": 2,\n                    \"prefix\": \"@\"\n                },\n                {\n                    \"jsonName\": \"SubCategory\",\n                    \"type\": \"string\"\n                },\n                {\n                    \"jsonName\": \"Region\",\n                    \"type\": \"string\"\n                },\n                {\n                    \"jsonName\": \"Country\",\n                    \"type\": \"string\"\n                }\n            ],\n            \"params\": []\n        }\n    ],\n    \"chartLayout\": \"vertical\",\n    \"attributes\": {\n        \"chartType\": \"Composed Chart\",\n        \"sortOrder\": \"Asc\",\n        \"slider\": true,\n        \"saveImage\": true\n},\n    \"chartName\": \"Chart Example 16\",\n    \"xAxis\": {\n        \"fields\": [\n            \"Employee\"\n        ]\n    },\n    \"yAxis\": {\n        \"fields\": [\n            \"Cost\"\n        ],\n        \"label\": \"Axis Label\"\n    }\n}"
  },
  {
    "instruction": "Create a Geo Chart chart subtype basic map named 'Chart Example 17' plotting 'N/A' against 'N/A'. The data should be sorted in desc order and displayed using a vertical layout. The column 'coordinate_lt' should be filled with color #1d3b7a, highest values should be colored #f8b0y1, tooltip should display 'Tooltip Label', values should be rounded to 1 decimal places, values should be prefixed with '#'. The column 'Price' should be filled with color #99ff95, highest values should be colored #866666, values should be rounded to 1 decimal places, values should be prefixed with '₹'. The column 'longitude' should be filled with color #866666, values should be rounded to 0 decimal places, values should be prefixed with '@'. The column 'latitude' should be aggregating using COUNT function, filled with color #99ff95, highest values should be colored #f8b0y1, lowest values should be colored #f8b0y1, tooltip should display 'Tooltip Label', values should be prefixed with '@'.",
    "input": "{\"dataSources\":[{\"dataSourceId\":\"ds-6143\",\"queryKey\":\"API:+jdbc$$aws$$_42\",\"cols\":[{\"jsonName\":\"Customer\",\"type\":\"string\"},{\"jsonName\":\"coordinate_lt\",\"type\":\"number\"},{\"jsonName\":\"Price\",\"type\":\"number\"},{\"jsonName\":\"Category\",\"type\":\"string\"},{\"jsonName\":\"Place\",\"type\":\"string\"},{\"jsonName\":\"longitude\",\"type\":\"number\"},{\"jsonName\":\"Employee\",\"type\":\"string\"},{\"jsonName\":\"Order Date\",\"type\":\"date\"},{\"jsonName\":\"latitude\",\"type\":\"number\"}],\"params\":[]}]}",
    "output": "{\n    \"dataSources\": [\n        {\n            \"dataSourceId\": \"ds-6143\",\n            \"queryKey\": \"API:+jdbc$$aws$$_42\",\n            \"cols\": [\n                {\n                    \"jsonName\": \"Customer\",\n                    \"type\": \"string\"\n                },\n                {\n                    \"jsonName\": \"coordinate_lt\",\n                    \"type\": \"number\",\n                    \"fillColor\": \"#1d3b7a\",\n                    \"fillHighestColor\": \"#f8b0y1\",\n                    \"label\": \"Tooltip Label\",\n                    \"decimalPlaces\": 1,\n                    \"prefix\": \"#\"\n                },\n                {\n                    \"jsonName\": \"Price\",\n                    \"type\": \"number\",\n                    \"fillColor\": \"#99ff95\",\n                    \"fillHighestColor\": \"#866666\",\n                    \"decimalPlaces\": 1,\n                    \"prefix\": \"\\u20b9\"\n                },\n                {\n                    \"jsonName\": \"Category\",\n                    \"type\": \"string\"\n                },\n                {\n                    \"jsonName\": \"Place\",\n                    \"type\": \"string\"\n                },\n                {\n                    \"jsonName\": \"longitude\",\n                    \"type\": \"number\",\n                    \"fillColor\": \"#866666\",\n                    \"decimalPlaces\": 0,\n                    \"prefix\": \"@\"\n                },\n                {\n                    \"jsonName\": \"Employee\",\n                    \"type\": \"string\"\n                },\n                {\n                    \"jsonName\": \"Order Date\",\n                    \"type\": \"date\"\n                },\n                {\n                    \"jsonName\": \"latitude\",\n                    \"type\": \"number\",\n                    \"aggFn\": \"COUNT\",\n                    \"fillColor\": \"#99ff95\",\n                    \"fillHighestColor\": \"#f8b0y1\",\n                    \"fillLowestColor\": \"#f8b0y1\",\n                    \"label\": \"Tooltip Label\",\n                    \"prefix\": \"@\"\n                }\n            ],\n            \"params\": []\n        }\n    ],\n    \"chartLayout\": \"vertical\",\n    \"attributes\": {\n        \"chartType\": \"Geo Chart\",\n        \"sortOrder\": \"Desc\",\n        \"slider\": true,\n        \"saveImage\": true,\n        \"chartSubType\": \"map\"\n    },\n    \"chartName\": \"Chart Example 17\",\n    \"xAxis\": {},\n    \"yAxis\": {},\n    \"longitude\": {\n        \"fields\": [\n            \"longitude\"\n        ]\n    },\n    \"latitude\": {\n        \"fields\": [\n            \"coordinate_lt\"\n        ]\n    },\n    \"values\": {\n        \"fields\": [\n            \"Price\"\n        ]\n    }\n}"
  },
  {
    "instruction": "Create a Gantt Chart chart named 'Chart Example 18' showing 'departure_date' and 'arrival_date' on y axis and 'Category' on x axis. The data should be sorted in asc order and displayed using a vertical layout. The x-axis should be labeled as 'Axis Label' The column 'latitude' should be aggregating using COUNT function, values should be rounded to 3 decimal places, values should be prefixed with '*'. The column 'Mega_watt' should be lowest values should be colored #f8b0y1, tooltip should display 'Tooltip Label', values should be rounded to 3 decimal places, values should be prefixed with '$'. The column 'departure_date' should be filled with color #866666, highest values should be colored #f0f0f0, tooltip should display 'Tooltip Label', values should be prefixed with '*'.",
    "input": "{\"dataSources\":[{\"dataSourceId\":\"ds-7425\",\"queryKey\":\"API:+auto-task$$auto_32\",\"cols\":[{\"jsonName\":\"arrival_date\",\"type\":\"date\"},{\"jsonName\":\"Order Date\",\"type\":\"date\"},{\"jsonName\":\"Place\",\"type\":\"string\"},{\"jsonName\":\"latitude\",\"type\":\"number\"},{\"jsonName\":\"Category\",\"type\":\"string\"},{\"jsonName\":\"Mega_watt\",\"type\":\"number\"},{\"jsonName\":\"departure_date\",\"type\":\"date\"}],\"params\":[]}]}",
    "output": "{\n    \"dataSources\": [\n        {\n            \"dataSourceId\": \"ds-7425\",\n            \"queryKey\": \"API:+auto-task$$auto_32\",\n            \"cols\": [\n                {\n                    \"jsonName\": \"arrival_date\",\n                    \"type\": \"date\"\n                },\n                {\n                    \"jsonName\": \"Order Date\",\n                    \"type\": \"date\"\n                },\n                {\n                    \"jsonName\": \"Place\",\n                    \"type\": \"string\"\n                },\n                {\n                    \"jsonName\": \"latitude\",\n                    \"type\": \"number\",\n                    \"aggFn\": \"COUNT\",\n                    \"decimalPlaces\": 3,\n                    \"prefix\": \"*\"\n                },\n                {\n                    \"jsonName\": \"Category\",\n                    \"type\": \"string\"\n                },\n                {\n                    \"jsonName\": \"Mega_watt\",\n                    \"type\": \"number\",\n                    \"fillLowestColor\": \"#f8b0y1\",\n                    \"label\": \"Tooltip Label\",\n                    \"decimalPlaces\": 3,\n                    \"prefix\": \"$\"\n                },\n                {\n                    \"jsonName\": \"departure_date\",\n                    \"type\": \"date\",\n                    \"fillColor\": \"#866666\",\n                    \"fillHighestColor\": \"#f0f0f0\",\n                    \"label\": \"Tooltip Label\",\n                    \"prefix\": \"*\"\n                }\n            ],\n            \"params\": []\n        }\n    ],\n    \"chartLayout\": \"vertical\",\n    \"attributes\": {\n        \"chartType\": \"Gantt Chart\",\n        \"sortOrder\": \"Asc\",\n        \"slider\": true,\n        \"saveImage\": true\n    },\n    \"chartName\": \"Chart Example 18\",\n    \"xAxis\": {\n        \"fields\": [\n            \"Category\"\n        ],\n        \"label\": \"Axis Label\"\n    },\n    \"yAxis\": {\n        \"fields\": [\n            \"departure_date\"\n,  \"arrival_date\"\n        ]\n    }\n}"
  },
  {
    "instruction": "Create a Composed Chart chart named 'Chart Example 19' plotting 'Mega_watt' as 'Line Chart' against 'Region'. The data should be sorted in desc order and displayed using a vertical layout. A secondary Y-axis is included, representing 'Price' as 'Bar Chart'. The y-axis should be labeled as 'Axis Label' and positioned at 'center' The column 'Mega_watt' should be aggregating using MAX function, values should be rounded to 3 decimal places, values should be prefixed with '#'. The column 'Price' should be tooltip should display 'Tooltip Label', values should be prefixed with '#'. The column 'Demand' should be y-axis values should be hidden, filled with color #866666, tooltip should display 'Tooltip Label', values should be rounded to 2 decimal places. The column 'Profit' should be filled with color #99ff95, highest values should be colored #866666, tooltip should display 'Tooltip Label', values should be rounded to 0 decimal places, values should be prefixed with '₹'. The column 'longitude' should be aggregating using MIN function, filled with color #f0f0f0, highest values should be colored #1d3b7a, lowest values should be colored #f0f0f0, tooltip should display 'Tooltip Label', values should be prefixed with '*'. The column 'latitude' should be aggregating using SUM function, lowest values should be colored #1d3b7a, tooltip should display 'Tooltip Label', values should be rounded to 1 decimal places, values should be prefixed with '#'. The column 'Discount' should be aggregating using MIN function, highest values should be colored #f0f0f0, tooltip should display 'Tooltip Label'.",
    "input": "{\"dataSources\":[{\"dataSourceId\":\"ds-1858\",\"queryKey\":\"API:+lookup$$lookup$$_66\",\"cols\":[{\"jsonName\":\"Mega_watt\",\"type\":\"number\"},{\"jsonName\":\"Price\",\"type\":\"number\"},{\"jsonName\":\"Demand\",\"type\":\"number\"},{\"jsonName\":\"Region\",\"type\":\"string\"},{\"jsonName\":\"Profit\",\"type\":\"number\"},{\"jsonName\":\"longitude\",\"type\":\"number\"},{\"jsonName\":\"latitude\",\"type\":\"number\"},{\"jsonName\":\"Discount\",\"type\":\"number\"}],\"params\":[]}]}",
    "output": "{\n    \"dataSources\": [\n        {\n            \"dataSourceId\": \"ds-1858\",\n            \"queryKey\": \"API:+lookup$$lookup$$_66\",\n            \"cols\": [\n                {\n                    \"jsonName\": \"Mega_watt\",\n                    \"type\": \"number\",\n                    \"composedChartType\": \"Line Chart\",\n                  \"aggFn\": \"MAX\",\n                    \"decimalPlaces\": 3,\n                    \"prefix\": \"#\"\n                },\n                {\n                    \"jsonName\": \"Price\",\n                    \"type\": \"number\",\n                    \"composedChartType\": \"Bar Chart\",\n                \"label\": \"Tooltip Label\",\n                    \"prefix\": \"#\"\n                },\n                {\n                    \"jsonName\": \"Demand\",\n                    \"type\": \"number\",\n                    \"isYAxisValueVisible\": false,\n                    \"fillColor\": \"#866666\",\n                    \"label\": \"Tooltip Label\",\n                    \"decimalPlaces\": 2\n                },\n                {\n                    \"jsonName\": \"Region\",\n                    \"type\": \"string\"\n                },\n                {\n                    \"jsonName\": \"Profit\",\n                    \"type\": \"number\",\n                    \"fillColor\": \"#99ff95\",\n                    \"fillHighestColor\": \"#866666\",\n                    \"label\": \"Tooltip Label\",\n                    \"decimalPlaces\": 0,\n                    \"prefix\": \"\\u20b9\"\n                },\n                {\n                    \"jsonName\": \"longitude\",\n                    \"type\": \"number\",\n                    \"aggFn\": \"MIN\",\n                    \"fillColor\": \"#f0f0f0\",\n                    \"fillHighestColor\": \"#1d3b7a\",\n                    \"fillLowestColor\": \"#f0f0f0\",\n                    \"label\": \"Tooltip Label\",\n                    \"prefix\": \"*\"\n                },\n                {\n                    \"jsonName\": \"latitude\",\n                    \"type\": \"number\",\n                    \"aggFn\": \"SUM\",\n                    \"fillLowestColor\": \"#1d3b7a\",\n                    \"label\": \"Tooltip Label\",\n                    \"decimalPlaces\": 1,\n                    \"prefix\": \"#\"\n                },\n                {\n                    \"jsonName\": \"Discount\",\n                    \"type\": \"number\",\n                    \"aggFn\": \"MIN\",\n                    \"fillHighestColor\": \"#f0f0f0\",\n                    \"label\": \"Tooltip Label\"\n                }\n            ],\n            \"params\": []\n        }\n    ],\n    \"chartLayout\": \"vertical\",\n    \"attributes\": {\n        \"chartType\": \"Composed Chart\",\n        \"sortOrder\": \"Desc\",\n        \"slider\": true,\n        \"saveImage\": true\n    },\n    \"chartName\": \"Chart Example 19\",\n    \"xAxis\": {\n        \"fields\": [\n            \"Region\"\n        ]\n    },\n    \"yAxis\": {\n        \"fields\": [\n            \"Mega_watt\"\n        ],\n        \"label\": \"Axis Label\",\n        \"nameLocation\": \"center\"\n    },\n    \"secondaryYAxis\": {\n        \"fields\": [\n            \"Price\"\n        ]\n    }\n}"
  },
  {
    "instruction": "Create a Geo Chart chart with subtype filled map named 'Chart Example 20' plotting 'N/A' against 'N/A'. The data should be sorted in desc order and displayed using a horizontal layout. The column 'Demand' should be highest values should be colored #99ff95, lowest values should be colored #1d3b7a, values should be rounded to 3 decimal places, values should be prefixed with '*'. The column 'coordinate_lg' should be lowest values should be colored #f8b0y1, tooltip should display 'Tooltip Label', values should be suffixed with '%'. The column 'Cost' should be aggregating using SUM function, lowest values should be colored #f0f0f0, tooltip should display 'Tooltip Label', values should be prefixed with '#'. The column 'Profit' should be aggregating using MIN function, y-axis values should be visible, highest values should be colored #866666, tooltip should display 'Tooltip Label', values should be rounded to 1 decimal places, values should be prefixed with '@'. The column 'Sales' should be aggregating using MAX function, tooltip should display 'Tooltip Label', values should be rounded to 2 decimal places, values should be prefixed with '@'.",
    "input": "{\"dataSources\":[{\"dataSourceId\":\"ds-9460\",\"queryKey\":\"API:+jdbc$$TEMP$$us_station_city_geo_data_14\",\"cols\":[{\"jsonName\":\"Demand\",\"type\":\"number\"},{\"jsonName\":\"SubCategory\",\"type\":\"string\"},{\"jsonName\":\"coordinate_lg\",\"type\":\"number\"},{\"jsonName\":\"location\",\"type\":\"string\"},{\"jsonName\":\"Cost\",\"type\":\"number\"},{\"jsonName\":\"Country\",\"type\":\"string\"},{\"jsonName\":\"Order Date\",\"type\":\"date\"},{\"jsonName\":\"Profit\",\"type\":\"number\"},{\"jsonName\":\"Sales\",\"type\":\"number\"},{\"jsonName\":\"Employee\",\"type\":\"string\"}],\"params\":[]}]}",
    "output": "{\n    \"dataSources\": [\n        {\n            \"dataSourceId\": \"ds-9460\",\n            \"queryKey\": \"API:+jdbc$$TEMP$$us_station_city_geo_data_14\",\n            \"cols\": [\n                {\n                    \"jsonName\": \"Demand\",\n                    \"type\": \"number\",\n                    \"fillHighestColor\": \"#99ff95\",\n                    \"fillLowestColor\": \"#1d3b7a\",\n                    \"decimalPlaces\": 3,\n                    \"prefix\": \"*\"\n                },\n                {\n                    \"jsonName\": \"SubCategory\",\n                    \"type\": \"string\"\n                },\n                {\n                    \"jsonName\": \"coordinate_lg\",\n                    \"type\": \"number\",\n                    \"fillLowestColor\": \"#f8b0y1\",\n                    \"label\": \"Tooltip Label\",\n                    \"suffix\": \"%\"\n                },\n                {\n                    \"jsonName\": \"location\",\n                    \"type\": \"string\"\n                },\n                {\n                    \"jsonName\": \"Cost\",\n                    \"type\": \"number\",\n                    \"aggFn\": \"SUM\",\n                    \"fillLowestColor\": \"#f0f0f0\",\n                    \"label\": \"Tooltip Label\",\n                    \"prefix\": \"#\"\n                },\n                {\n                    \"jsonName\": \"Country\",\n                    \"type\": \"string\"\n                },\n                {\n                    \"jsonName\": \"Order Date\",\n                    \"type\": \"date\"\n                },\n                {\n                    \"jsonName\": \"Profit\",\n                    \"type\": \"number\",\n                    \"aggFn\": \"MIN\",\n                    \"isYAxisValueVisible\": true,\n                    \"fillHighestColor\": \"#866666\",\n                    \"label\": \"Tooltip Label\",\n                    \"decimalPlaces\": 1,\n                    \"prefix\": \"@\"\n                },\n                {\n                    \"jsonName\": \"Sales\",\n                    \"type\": \"number\",\n                    \"aggFn\": \"MAX\",\n                    \"label\": \"Tooltip Label\",\n                    \"decimalPlaces\": 2,\n                    \"prefix\": \"@\"\n                },\n                {\n                    \"jsonName\": \"Employee\",\n                    \"type\": \"string\"\n                }\n            ],\n            \"params\": []\n        }\n    ],\n    \"chartLayout\": \"horizontal\",\n    \"attributes\": {\n        \"chartType\": \"Geo Chart\",\n        \"sortOrder\": \"Desc\",\n        \"slider\": true,\n        \"saveImage\": true,\n        \"chartSubType\": \"filledMap\"\n    },\n    \"chartName\": \"Chart Example 20\",\n    \"xAxis\": {},\n    \"yAxis\": {},\n    \"location\": {\n        \"fields\": [\n            \"Country\"\n        ]\n    },\n    \"values\": {\n        \"fields\": [\n            \"Sales\"\n        ]\n    }\n}"
  },
  {
    "instruction": "Create a Tree Map chart named 'Chart Example 21' plotting 'Revenue' against 'Order Date'. The data should be sorted in asc order and displayed using a horizontal layout. The x-axis should be labeled as 'Axis Label' with a name gap of 44 pixels. The column 'Generation' should be aggregating using MIN function, values should be rounded to 3 decimal places, values should be prefixed with '*'. The column 'Cost' should be aggregating using AVG function, filled with color #f8b0y1, highest values should be colored #1d3b7a, values should be prefixed with '#'. The column 'Revenue' should be aggregating using AVG function, filled with color #866666, tooltip should display 'Tooltip Label', values should be rounded to 1 decimal places, values should be suffixed with 'p'. The column 'Demand' should be aggregating using MIN function, y-axis values should be hidden, filled with color #f0f0f0, tooltip should display 'Tooltip Label', values should be rounded to 2 decimal places.",
    "input": "{\"dataSources\":[{\"dataSourceId\":\"ds-6386\",\"queryKey\":\"API:+auto-task$$auto-task_99\",\"cols\":[{\"jsonName\":\"SubCategory\",\"type\":\"string\"},{\"jsonName\":\"Generation\",\"type\":\"number\"},{\"jsonName\":\"Order Date\",\"type\":\"date\"},{\"jsonName\":\"Cost\",\"type\":\"number\"},{\"jsonName\":\"Revenue\",\"type\":\"number\"},{\"jsonName\":\"Demand\",\"type\":\"number\"},{\"jsonName\":\"Category\",\"type\":\"string\"}],\"params\":[]}]}",
    "output": "{\n    \"dataSources\": [\n        {\n            \"dataSourceId\": \"ds-6386\",\n            \"queryKey\": \"API:+auto-task$$auto-task_99\",\n            \"cols\": [\n                {\n                    \"jsonName\": \"SubCategory\",\n                    \"type\": \"string\"\n                },\n                {\n                    \"jsonName\": \"Generation\",\n                    \"type\": \"number\",\n                    \"aggFn\": \"MIN\",\n                    \"decimalPlaces\": 3,\n                    \"prefix\": \"*\"\n                },\n                {\n                    \"jsonName\": \"Order Date\",\n                    \"type\": \"date\"\n                },\n                {\n                    \"jsonName\": \"Cost\",\n                    \"type\": \"number\",\n                    \"aggFn\": \"AVG\",\n                    \"fillColor\": \"#f8b0y1\",\n                    \"fillHighestColor\": \"#1d3b7a\",\n                    \"prefix\": \"#\"\n                },\n                {\n                    \"jsonName\": \"Revenue\",\n                    \"type\": \"number\",\n                    \"aggFn\": \"AVG\",\n                    \"fillColor\": \"#866666\",\n                    \"label\": \"Tooltip Label\",\n                    \"decimalPlaces\": 1,\n                    \"suffix\": \"p\"\n                },\n                {\n                    \"jsonName\": \"Demand\",\n                    \"type\": \"number\",\n                    \"aggFn\": \"MIN\",\n                    \"isYAxisValueVisible\": false,\n                    \"fillColor\": \"#f0f0f0\",\n                    \"label\": \"Tooltip Label\",\n                    \"decimalPlaces\": 2\n                },\n                {\n                    \"jsonName\": \"Category\",\n                    \"type\": \"string\"\n                }\n            ],\n            \"params\": []\n        }\n    ],\n    \"chartLayout\": \"horizontal\",\n    \"attributes\": {\n        \"chartType\": \"Tree Map\",\n        \"sortOrder\": \"Asc\",\n        \"slider\": true,\n        \"saveImage\": true\n    },\n    \"chartName\": \"Chart Example 21\",\n    \"xAxis\": {\n        \"fields\": [\n            \"Order Date\"\n        ],\n        \"label\": \"Axis Label\",\n        \"nameGap\": 44\n    },\n    \"yAxis\": {\n        \"fields\": [\n            \"Revenue\"\n        ]\n    }\n}"
  },
  {
    "instruction": "Create a TimeLine Chart chart named 'Chart Example 22' plotting 'Mega_watt' against 'Place'. The data should be sorted in desc order and displayed using a horizontal layout. The y-axis should be labeled as 'Axis Label' with a name gap of 17 pixels. The column 'Mega_watt' should be filled with color #99ff95, highest values should be colored #f0f0f0, tooltip should display 'Tooltip Label', values should be prefixed with '@'. The column 'Profit' should be filled with color #f0f0f0, highest values should be colored #866666, lowest values should be colored #866666, tooltip should display 'Tooltip Label', values should be rounded to 3 decimal places. The column 'Generation' should be tooltip should display 'Tooltip Label', values should be rounded to 1 decimal places, values should be prefixed with '@'. The column 'coordinate_lg' should be aggregating using MAX function, highest values should be colored #f8b0y1, lowest values should be colored #866666, tooltip should display 'Tooltip Label', values should be rounded to 3 decimal places, values should be prefixed with '₹'. The column 'Price' should be filled with color #f8b0y1, highest values should be colored #1d3b7a. The column 'Demand' should be aggregating using MAX function, filled with color #f8b0y1, highest values should be colored #f0f0f0, lowest values should be colored #f8b0y1, tooltip should display 'Tooltip Label', values should be rounded to 0 decimal places, values should be prefixed with '@'. The column 'Sales' should be aggregating using COUNT function, filled with color #866666, lowest values should be colored #f0f0f0, tooltip should display 'Tooltip Label', values should be rounded to 0 decimal places, values should be prefixed with '$'.",
    "input": "{\"dataSources\":[{\"dataSourceId\":\"ds-5154\",\"queryKey\":\"API:+jdbc$$dataService$$_47\",\"cols\":[{\"jsonName\":\"Mega_watt\",\"type\":\"number\"},{\"jsonName\":\"Profit\",\"type\":\"number\"},{\"jsonName\":\"Country\",\"type\":\"string\"},{\"jsonName\":\"Generation\",\"type\":\"number\"},{\"jsonName\":\"coordinate_lg\",\"type\":\"number\"},{\"jsonName\":\"Price\",\"type\":\"number\"},{\"jsonName\":\"Demand\",\"type\":\"number\"},{\"jsonName\":\"Place\",\"type\":\"string\"},{\"jsonName\":\"Sales\",\"type\":\"number\"}],\"params\":[]}]}",
    "output": "{\n    \"dataSources\": [\n        {\n            \"dataSourceId\": \"ds-5154\",\n            \"queryKey\": \"API:+jdbc$$dataService$$_47\",\n            \"cols\": [\n                {\n                    \"jsonName\": \"Mega_watt\",\n                    \"type\": \"number\",\n                    \"fillColor\": \"#99ff95\",\n                    \"fillHighestColor\": \"#f0f0f0\",\n                    \"label\": \"Tooltip Label\",\n                    \"prefix\": \"@\"\n                },\n                {\n                    \"jsonName\": \"Profit\",\n                    \"type\": \"number\",\n                    \"fillColor\": \"#f0f0f0\",\n                    \"fillHighestColor\": \"#866666\",\n                    \"fillLowestColor\": \"#866666\",\n                    \"label\": \"Tooltip Label\",\n                    \"decimalPlaces\": 3\n                },\n                {\n                    \"jsonName\": \"Country\",\n                    \"type\": \"string\"\n                },\n                {\n                    \"jsonName\": \"Generation\",\n                    \"type\": \"number\",\n                    \"label\": \"Tooltip Label\",\n                    \"decimalPlaces\": 1,\n                    \"prefix\": \"@\"\n                },\n                {\n                    \"jsonName\": \"coordinate_lg\",\n                    \"type\": \"number\",\n                    \"aggFn\": \"MAX\",\n                    \"fillHighestColor\": \"#f8b0y1\",\n                    \"fillLowestColor\": \"#866666\",\n                    \"label\": \"Tooltip Label\",\n                    \"decimalPlaces\": 3,\n                    \"prefix\": \"\\u20b9\"\n                },\n                {\n                    \"jsonName\": \"Price\",\n                    \"type\": \"number\",\n                    \"fillColor\": \"#f8b0y1\",\n                    \"fillHighestColor\": \"#1d3b7a\"\n                },\n                {\n                    \"jsonName\": \"Demand\",\n                    \"type\": \"number\",\n                    \"aggFn\": \"MAX\",\n                    \"fillColor\": \"#f8b0y1\",\n                    \"fillHighestColor\": \"#f0f0f0\",\n                    \"fillLowestColor\": \"#f8b0y1\",\n                    \"label\": \"Tooltip Label\",\n                    \"decimalPlaces\": 0,\n                    \"prefix\": \"@\"\n                },\n                {\n                    \"jsonName\": \"Place\",\n                    \"type\": \"string\"\n                },\n                {\n                    \"jsonName\": \"Sales\",\n                    \"type\": \"number\",\n                    \"aggFn\": \"COUNT\",\n                    \"fillColor\": \"#866666\",\n                    \"fillLowestColor\": \"#f0f0f0\",\n                    \"label\": \"Tooltip Label\",\n                    \"decimalPlaces\": 0,\n                    \"prefix\": \"$\"\n                }\n            ],\n            \"params\": []\n        }\n    ],\n    \"chartLayout\": \"horizontal\",\n    \"attributes\": {\n        \"chartType\": \"TimeLine Chart\",\n        \"sortOrder\": \"Desc\",\n        \"slider\": true,\n        \"saveImage\": true\n},\n    \"chartName\": \"Chart Example 22\",\n    \"xAxis\": {\n        \"fields\": [\n            \"Place\"\n        ]\n    },\n    \"yAxis\": {\n        \"fields\": [\n            \"Mega_watt\"\n        ],\n        \"label\": \"Axis Label\",\n        \"nameGap\": 17\n    }\n}"
  },
  {
    "instruction": "Create a Bar Chart chart named 'Chart Example 24' plotting 'Mega_watt' against 'Region'. The data should be sorted in desc order and displayed using a vertical layout. A secondary Y-axis is included, representing 'Generation'. The x-axis should be labeled as 'Axis Label' with a name gap of 30 pixels. The y-axis should be labeled as 'Axis Label' and positioned at 'end' with a name gap of 45 pixels. The column 'Discount' should be aggregating using MIN function, highest values should be colored #f0f0f0, tooltip should display 'Tooltip Label', values should be rounded to 2 decimal places. The column 'Mega_watt' should be aggregating using SUM function, filled with color #f8b0y1, highest values should be colored #f0f0f0, lowest values should be colored #1d3b7a, values should be rounded to 1 decimal places, values should be prefixed with '₹'. The column 'Generation' should be aggregating using SUM function, y-axis values should be visible, highest values should be colored #f8b0y1, lowest values should be colored #866666, values should be prefixed with '#'. The column 'latitude' should be filled with color #1d3b7a, highest values should be colored #99ff95. The column 'Sales' should be aggregating using COUNT function, filled with color #866666, lowest values should be colored #1d3b7a, tooltip should display 'Tooltip Label', values should be rounded to 0 decimal places, values should be suffixed with 'p'.",
    "input": "{\"dataSources\":[{\"dataSourceId\":\"ds-2818\",\"queryKey\":\"API:+jdbc$$aws$$_100\",\"cols\":[{\"jsonName\":\"Discount\",\"type\":\"number\"},{\"jsonName\":\"Mega_watt\",\"type\":\"number\"},{\"jsonName\":\"Order Date\",\"type\":\"date\"},{\"jsonName\":\"Generation\",\"type\":\"number\"},{\"jsonName\":\"Region\",\"type\":\"string\"},{\"jsonName\":\"location\",\"type\":\"string\"},{\"jsonName\":\"latitude\",\"type\":\"number\"},{\"jsonName\":\"Sales\",\"type\":\"number\"},{\"jsonName\":\"Employee\",\"type\":\"string\"},{\"jsonName\":\"Customer\",\"type\":\"string\"}],\"params\":[]}]}",
    "output": "{\n    \"dataSources\": [\n        {\n            \"dataSourceId\": \"ds-2818\",\n            \"queryKey\": \"API:+jdbc$$aws$$_100\",\n            \"cols\": [\n                {\n                    \"jsonName\": \"Discount\",\n                    \"type\": \"number\",\n                    \"aggFn\": \"MIN\",\n                    \"fillHighestColor\": \"#f0f0f0\",\n                    \"label\": \"Tooltip Label\",\n                    \"decimalPlaces\": 2\n                },\n                {\n                    \"jsonName\": \"Mega_watt\",\n                    \"type\": \"number\",\n                    \"aggFn\": \"SUM\",\n                    \"fillColor\": \"#f8b0y1\",\n                    \"fillHighestColor\": \"#f0f0f0\",\n                    \"fillLowestColor\": \"#1d3b7a\",\n                    \"decimalPlaces\": 1,\n                    \"prefix\": \"\\u20b9\"\n                },\n                {\n                    \"jsonName\": \"Order Date\",\n                    \"type\": \"date\"\n                },\n                {\n                    \"jsonName\": \"Generation\",\n                    \"type\": \"number\",\n                    \"aggFn\": \"SUM\",\n                    \"isYAxisValueVisible\": true,\n                    \"fillHighestColor\": \"#f8b0y1\",\n                    \"fillLowestColor\": \"#866666\",\n                    \"prefix\": \"#\"\n                },\n                {\n                    \"jsonName\": \"Region\",\n                    \"type\": \"string\"\n                },\n                {\n                    \"jsonName\": \"location\",\n                    \"type\": \"string\"\n                },\n                {\n                    \"jsonName\": \"latitude\",\n                    \"type\": \"number\",\n                    \"fillColor\": \"#1d3b7a\",\n                    \"fillHighestColor\": \"#99ff95\"\n                },\n                {\n                    \"jsonName\": \"Sales\",\n                    \"type\": \"number\",\n                    \"aggFn\": \"COUNT\",\n                    \"fillColor\": \"#866666\",\n                    \"fillLowestColor\": \"#1d3b7a\",\n                    \"label\": \"Tooltip Label\",\n                    \"decimalPlaces\": 0,\n                    \"suffix\": \"p\"\n                },\n                {\n                    \"jsonName\": \"Employee\",\n                    \"type\": \"string\"\n                },\n                {\n                    \"jsonName\": \"Customer\",\n                    \"type\": \"string\"\n                }\n            ],\n            \"params\": []\n        }\n    ],\n    \"chartLayout\": \"vertical\",\n    \"attributes\": {\n        \"chartType\": \"Bar Chart\",\n        \"sortOrder\": \"Desc\",\n        \"slider\": true,\n        \"saveImage\": true,\n        \"referenceLines\": [\n            {\n                \"referenceValueSource\": \"FIXED\",\n                \"referenceFor\": \"Mega_watt\",\n                \"referenceLabel\": \"Label Mega_watt\",\n                \"referenceLineColor\": \"#f0f0f0\",\n                \"referenceValue\": \"706\",\n                \"showValue\": false\n            }\n        ]\n    },\n    \"chartName\": \"Chart Example 24\",\n    \"xAxis\": {\n        \"fields\": [\n            \"Region\"\n        ],\n        \"label\": \"Axis Label\",\n        \"nameGap\": 30\n    },\n    \"yAxis\": {\n        \"fields\": [\n            \"Mega_watt\"\n        ],\n        \"label\": \"Axis Label\",\n        \"nameLocation\": \"end\",\n        \"nameGap\": 45\n    },\n    \"secondaryYAxis\": {\n        \"fields\": [\n            \"Generation\"\n        ]\n    }\n}"
  },
  {
    "instruction": "Create a Pie Chart chart named 'Chart Example 25' plotting 'Sales' against 'SubCategory'. The data should be sorted in asc order and displayed using a horizontal layout. The x-axis should be labeled as 'Axis Label' with a name gap of 12 pixels. Chart should be rotated by 271 degree. The column 'Price' should be aggregating using AVG function. The column 'Profit' should be highest values should be colored #99ff95, tooltip should display 'Tooltip Label'. The column 'Sales' should be aggregating using COUNT function, filled with color #866666, highest values should be colored #1d3b7a, lowest values should be colored #1d3b7a, values should be prefixed with '₹'. The column 'Cost' should be aggregating using AVG function, values should be rounded to 3 decimal places, values should be suffixed with 'MW'. The column 'coordinate_lg' should be aggregating using MIN function, filled with color #f0f0f0, tooltip should display 'Tooltip Label', values should be rounded to 0 decimal places, values should be suffixed with 'USD'.",
    "input": "{\"dataSources\":[{\"dataSourceId\":\"ds-9898\",\"queryKey\":\"API:+jdbc$$dataService$$_88\",\"cols\":[{\"jsonName\":\"Price\",\"type\":\"number\"},{\"jsonName\":\"Profit\",\"type\":\"number\"},{\"jsonName\":\"Employee\",\"type\":\"string\"},{\"jsonName\":\"Sales\",\"type\":\"number\"},{\"jsonName\":\"Customer\",\"type\":\"string\"},{\"jsonName\":\"Cost\",\"type\":\"number\"},{\"jsonName\":\"Category\",\"type\":\"string\"},{\"jsonName\":\"SubCategory\",\"type\":\"string\"},{\"jsonName\":\"location\",\"type\":\"string\"},{\"jsonName\":\"coordinate_lg\",\"type\":\"number\"}],\"params\":[]}]}",
    "output": "{\n    \"dataSources\": [\n        {\n            \"dataSourceId\": \"ds-9898\",\n            \"queryKey\": \"API:+jdbc$$dataService$$_88\",\n            \"cols\": [\n                {\n                    \"jsonName\": \"Price\",\n                    \"type\": \"number\",\n                    \"aggFn\": \"AVG\"\n                },\n                {\n                    \"jsonName\": \"Profit\",\n                    \"type\": \"number\",\n                    \"fillHighestColor\": \"#99ff95\",\n                    \"label\": \"Tooltip Label\"\n                },\n                {\n                    \"jsonName\": \"Employee\",\n                    \"type\": \"string\"\n                },\n                {\n                    \"jsonName\": \"Sales\",\n                    \"type\": \"number\",\n                    \"aggFn\": \"COUNT\",\n                    \"fillColor\": \"#866666\",\n                    \"fillHighestColor\": \"#1d3b7a\",\n                    \"fillLowestColor\": \"#1d3b7a\",\n                    \"prefix\": \"\\u20b9\"\n                },\n                {\n                    \"jsonName\": \"Customer\",\n                    \"type\": \"string\"\n                },\n                {\n                    \"jsonName\": \"Cost\",\n                    \"type\": \"number\",\n                    \"aggFn\": \"AVG\",\n                    \"decimalPlaces\": 3,\n                    \"suffix\": \"MW\"\n                },\n                {\n                    \"jsonName\": \"Category\",\n                    \"type\": \"string\"\n                },\n                {\n                    \"jsonName\": \"SubCategory\",\n                    \"type\": \"string\"\n                },\n                {\n                    \"jsonName\": \"location\",\n                    \"type\": \"string\"\n                },\n                {\n                    \"jsonName\": \"coordinate_lg\",\n                    \"type\": \"number\",\n                    \"aggFn\": \"MIN\",\n                    \"fillColor\": \"#f0f0f0\",\n                    \"label\": \"Tooltip Label\",\n                    \"decimalPlaces\": 0,\n                    \"suffix\": \"USD\"\n                }\n            ],\n            \"params\": []\n        }\n    ],\n    \"chartLayout\": \"horizontal\",\n    \"attributes\": {\n        \"chartType\": \"Pie Chart\",\n        \"sortOrder\": \"Asc\",\n        \"slider\": true,\n        \"saveImage\": true,\n        \"chartSubType\": \"normal\",\n        \"rotation\": 271\n    },\n    \"chartName\": \"Chart Example 25\",\n    \"xAxis\": {\n        \"fields\": [\n            \"SubCategory\"\n        ],\n        \"label\": \"Axis Label\",\n        \"nameGap\": 12\n    },\n    \"yAxis\": {\n        \"fields\": [\n            \"Sales\"\n        ]\n    }\n}"
  },
  {
    "instruction": "Create a TimeLine Chart chart titled as 'Chart Example 26' plotting 'Mega_watt' against 'Employee'. The data should be sorted in asc order and displayed using a horizontal layout. The x-axis should be labeled as 'Axis Label' The y-axis should be labeled as 'Axis Label' with a name gap of 22 pixels. The column 'Discount' should be tooltip should display 'Tooltip Label', values should be rounded to 0 decimal places, values should be prefixed with '@'. The column 'Mega_watt' should be filled with color #866666, values should be rounded to 1 decimal places. The column 'Demand' should be aggregating using SUM function, y-axis values should be hidden, tooltip should display 'Tooltip Label', values should be rounded to 0 decimal places, values should be suffixed with '%'. The column 'longitude' should be highest values should be colored #866666, lowest values should be colored #f8b0y1, tooltip should display 'Tooltip Label', values should be rounded to 2 decimal places, values should be prefixed with '#'.",
    "input": "{\"dataSources\":[{\"dataSourceId\":\"ds-5780\",\"queryKey\":\"API:+lookup$$lookup$$_11\",\"cols\":[{\"jsonName\":\"Customer\",\"type\":\"string\"},{\"jsonName\":\"Category\",\"type\":\"string\"},{\"jsonName\":\"Discount\",\"type\":\"number\"},{\"jsonName\":\"Mega_watt\",\"type\":\"number\"},{\"jsonName\":\"SubCategory\",\"type\":\"string\"},{\"jsonName\":\"Employee\",\"type\":\"string\"},{\"jsonName\":\"Demand\",\"type\":\"number\"},{\"jsonName\":\"longitude\",\"type\":\"number\"}],\"params\":[]}]}",
    "output": "{\n    \"dataSources\": [\n        {\n            \"dataSourceId\": \"ds-5780\",\n            \"queryKey\": \"API:+lookup$$lookup$$_11\",\n            \"cols\": [\n                {\n                    \"jsonName\": \"Customer\",\n                    \"type\": \"string\"\n                },\n                {\n                    \"jsonName\": \"Category\",\n                    \"type\": \"string\"\n                },\n                {\n                    \"jsonName\": \"Discount\",\n                    \"type\": \"number\",\n                    \"label\": \"Tooltip Label\",\n                    \"decimalPlaces\": 0,\n                    \"prefix\": \"@\"\n                },\n                {\n                    \"jsonName\": \"Mega_watt\",\n                    \"type\": \"number\",\n                    \"fillColor\": \"#866666\",\n                    \"decimalPlaces\": 1\n                },\n                {\n                    \"jsonName\": \"SubCategory\",\n                    \"type\": \"string\"\n                },\n                {\n                    \"jsonName\": \"Employee\",\n                    \"type\": \"string\"\n                },\n                {\n                    \"jsonName\": \"Demand\",\n                    \"type\": \"number\",\n                    \"aggFn\": \"SUM\",\n                    \"isYAxisValueVisible\": false,\n                    \"label\": \"Tooltip Label\",\n                    \"decimalPlaces\": 0,\n                    \"suffix\": \"%\"\n                },\n                {\n                    \"jsonName\": \"longitude\",\n                    \"type\": \"number\",\n                    \"fillHighestColor\": \"#866666\",\n                    \"fillLowestColor\": \"#f8b0y1\",\n                    \"label\": \"Tooltip Label\",\n                    \"decimalPlaces\": 2,\n                    \"prefix\": \"#\"\n                }\n            ],\n            \"params\": []\n        }\n    ],\n    \"chartLayout\": \"horizontal\",\n    \"attributes\": {\n        \"chartType\": \"TimeLine Chart\",\n        \"sortOrder\": \"Asc\",\n        \"slider\": true,\n        \"saveImage\": true\n},\n    \"chartName\": \"Chart Example 26\",\n    \"xAxis\": {\n        \"fields\": [\n            \"Employee\"\n        ],\n        \"label\": \"Axis Label\"\n    },\n    \"yAxis\": {\n        \"fields\": [\n            \"Mega_watt\"\n        ],\n        \"label\": \"Axis Label\",\n        \"nameGap\": 22\n    }\n}"
  },
  {
    "instruction": "Create a Gantt Chart chart named 'Chart Example 27' has 'launched_date' and 'today_date' against 'Region'. The data should be sorted in asc order and displayed using a vertical layout. The x-axis should be labeled as 'Axis Label' The y-axis should be labeled as 'Axis Label' The column 'today_date' should be highest values should be colored #f0f0f0, tooltip should display 'Tooltip Label', values should be rounded to 2 decimal places, values should be prefixed with '#'. The column 'launched_date' should be filled with color #f0f0f0, highest values should be colored #f8b0y1, lowest values should be colored #866666, values should be rounded to 0 decimal places, values should be suffixed with 'USD'. The column 'Cost' should be aggregating using COUNT function, highest values should be colored #99ff95, lowest values should be colored #f0f0f0, tooltip should display 'Tooltip Label', values should be rounded to 1 decimal places, values should be prefixed with '$'. The column 'latitude' should be aggregating using MAX function, y-axis values should be visible, highest values should be colored #f8b0y1, tooltip should display 'Tooltip Label', values should be rounded to 0 decimal places, values should be prefixed with '$'. The column 'Demand' should be y-axis values should be visible, filled with color #99ff95, lowest values should be colored #1d3b7a, values should be rounded to 2 decimal places, values should be prefixed with '$'.",
    "input": "{\"dataSources\":[{\"dataSourceId\":\"ds-4803\",\"queryKey\":\"API:+jdbc$$pmgr$$caps_31\",\"cols\":[{\"jsonName\":\"today_date\",\"type\":\"date\"},{\"jsonName\":\"Country\",\"type\":\"string\"},{\"jsonName\":\"Employee\",\"type\":\"string\"},{\"jsonName\":\"Region\",\"type\":\"string\"},{\"jsonName\":\"launched_date\",\"type\":\"date\"},{\"jsonName\":\"Cost\",\"type\":\"number\"},{\"jsonName\":\"Customer\",\"type\":\"string\"},{\"jsonName\":\"latitude\",\"type\":\"number\"},{\"jsonName\":\"Demand\",\"type\":\"number\"},{\"jsonName\":\"Order Date\",\"type\":\"date\"}],\"params\":[]}]}",
    "output": "{\n    \"dataSources\": [\n        {\n            \"dataSourceId\": \"ds-4803\",\n            \"queryKey\": \"API:+jdbc$$pmgr$$caps_31\",\n            \"cols\": [\n                {\n                    \"jsonName\": \"today_date\",\n                    \"type\": \"date\",\n                    \"fillHighestColor\": \"#f0f0f0\",\n                    \"label\": \"Tooltip Label\",\n                    \"decimalPlaces\": 2,\n                    \"prefix\": \"#\"\n                },\n                {\n                    \"jsonName\": \"Country\",\n                    \"type\": \"string\"\n                },\n                {\n                    \"jsonName\": \"Employee\",\n                    \"type\": \"string\"\n                },\n                {\n                    \"jsonName\": \"Region\",\n                    \"type\": \"string\"\n                },\n                {\n                    \"jsonName\": \"launched_date\",\n                    \"type\": \"date\",\n                    \"fillColor\": \"#f0f0f0\",\n                    \"fillHighestColor\": \"#f8b0y1\",\n                    \"fillLowestColor\": \"#866666\",\n                    \"decimalPlaces\": 0,\n                    \"suffix\": \"USD\"\n                },\n                {\n                    \"jsonName\": \"Cost\",\n                    \"type\": \"number\",\n                    \"aggFn\": \"COUNT\",\n                    \"fillHighestColor\": \"#99ff95\",\n                    \"fillLowestColor\": \"#f0f0f0\",\n                    \"label\": \"Tooltip Label\",\n                    \"decimalPlaces\": 1,\n                    \"prefix\": \"$\"\n                },\n                {\n                    \"jsonName\": \"Customer\",\n                    \"type\": \"string\"\n                },\n                {\n                    \"jsonName\": \"latitude\",\n                    \"type\": \"number\",\n                    \"aggFn\": \"MAX\",\n                    \"isYAxisValueVisible\": true,\n                    \"fillHighestColor\": \"#f8b0y1\",\n                    \"label\": \"Tooltip Label\",\n                    \"decimalPlaces\": 0,\n                    \"prefix\": \"$\"\n                },\n                {\n                    \"jsonName\": \"Demand\",\n                    \"type\": \"number\",\n                    \"isYAxisValueVisible\": true,\n                    \"fillColor\": \"#99ff95\",\n                    \"fillLowestColor\": \"#1d3b7a\",\n                    \"decimalPlaces\": 2,\n                    \"prefix\": \"$\"\n                },\n                {\n                    \"jsonName\": \"Order Date\",\n                    \"type\": \"date\"\n                }\n            ],\n            \"params\": []\n        }\n    ],\n    \"chartLayout\": \"vertical\",\n    \"attributes\": {\n        \"chartType\": \"Gantt Chart\",\n        \"sortOrder\": \"Asc\",\n        \"slider\": true,\n        \"saveImage\": true\n    },\n    \"chartName\": \"Chart Example 27\",\n    \"xAxis\": {\n        \"fields\": [\n            \"Region\"\n        ],\n        \"label\": \"Axis Label\"\n    },\n    \"yAxis\": {\n        \"fields\": [\n            \"launched_date\"\n,    \"today_date\"\n        ],\n        \"label\": \"Axis Label\"\n    }\n}"
  },
  {
    "instruction": "Create a Area Chart chart named 'Chart Example 28' plotting 'Price' against 'Category'. The data should be sorted in desc order and displayed using a vertical layout. A secondary Y-axis is included, representing 'Discount'. The secondary Y-axis should be labeled as 'Axis Label' The column 'Discount' should be aggregating using AVG function, y-axis values should be hidden, filled with color #f0f0f0, values should be rounded to 0 decimal places. The column 'Sales' should be aggregating using MAX function, highest values should be colored #f8b0y1, tooltip should display 'Tooltip Label'. The column 'Price' should be aggregating using MAX function, lowest values should be colored #f0f0f0, tooltip should display 'Tooltip Label', values should be rounded to 0 decimal places, values should be suffixed with 'USD'. The column 'longitude' should be aggregating using AVG function, tooltip should display 'Tooltip Label', values should be suffixed with 'p'. The column 'coordinate_lg' should be highest values should be colored #f0f0f0, lowest values should be colored #f8b0y1, tooltip should display 'Tooltip Label', values should be rounded to 3 decimal places, values should be prefixed with '₹'.",
    "input": "{\"dataSources\":[{\"dataSourceId\":\"ds-6037\",\"queryKey\":\"API:+jdbc$$Oracle$$Energy_API_49\",\"cols\":[{\"jsonName\":\"Discount\",\"type\":\"number\"},{\"jsonName\":\"Sales\",\"type\":\"number\"},{\"jsonName\":\"Price\",\"type\":\"number\"},{\"jsonName\":\"Place\",\"type\":\"string\"},{\"jsonName\":\"Country\",\"type\":\"string\"},{\"jsonName\":\"longitude\",\"type\":\"number\"},{\"jsonName\":\"location\",\"type\":\"string\"},{\"jsonName\":\"coordinate_lg\",\"type\":\"number\"},{\"jsonName\":\"Category\",\"type\":\"string\"},{\"jsonName\":\"Region\",\"type\":\"string\"}],\"params\":[]}]}",
    "output": "{\n    \"dataSources\": [\n        {\n            \"dataSourceId\": \"ds-6037\",\n            \"queryKey\": \"API:+jdbc$$Oracle$$Energy_API_49\",\n            \"cols\": [\n                {\n                    \"jsonName\": \"Discount\",\n                    \"type\": \"number\",\n                    \"aggFn\": \"AVG\",\n                    \"isYAxisValueVisible\": false,\n                    \"fillColor\": \"#f0f0f0\",\n                    \"decimalPlaces\": 0\n                },\n                {\n                    \"jsonName\": \"Sales\",\n                    \"type\": \"number\",\n                    \"aggFn\": \"MAX\",\n                    \"fillHighestColor\": \"#f8b0y1\",\n                    \"label\": \"Tooltip Label\"\n                },\n                {\n                    \"jsonName\": \"Price\",\n                    \"type\": \"number\",\n                    \"aggFn\": \"MAX\",\n                    \"fillLowestColor\": \"#f0f0f0\",\n                    \"label\": \"Tooltip Label\",\n                    \"decimalPlaces\": 0,\n                    \"suffix\": \"USD\"\n                },\n                {\n                    \"jsonName\": \"Place\",\n                    \"type\": \"string\"\n                },\n                {\n                    \"jsonName\": \"Country\",\n                    \"type\": \"string\"\n                },\n                {\n                    \"jsonName\": \"longitude\",\n                    \"type\": \"number\",\n                    \"aggFn\": \"AVG\",\n                    \"label\": \"Tooltip Label\",\n                    \"suffix\": \"p\"\n                },\n                {\n                    \"jsonName\": \"location\",\n                    \"type\": \"string\"\n                },\n                {\n                    \"jsonName\": \"coordinate_lg\",\n                    \"type\": \"number\",\n                    \"fillHighestColor\": \"#f0f0f0\",\n                    \"fillLowestColor\": \"#f8b0y1\",\n                    \"label\": \"Tooltip Label\",\n                    \"decimalPlaces\": 3,\n                    \"prefix\": \"\\u20b9\"\n                },\n                {\n                    \"jsonName\": \"Category\",\n                    \"type\": \"string\"\n                },\n                {\n                    \"jsonName\": \"Region\",\n                    \"type\": \"string\"\n                }\n            ],\n            \"params\": []\n        }\n    ],\n    \"chartLayout\": \"vertical\",\n    \"attributes\": {\n        \"chartType\": \"Area Chart\",\n        \"sortOrder\": \"Desc\",\n        \"slider\": true,\n        \"saveImage\": true\n    },\n    \"chartName\": \"Chart Example 28\",\n    \"xAxis\": {\n        \"fields\": [\n            \"Category\"\n        ]\n    },\n    \"yAxis\": {\n        \"fields\": [\n            \"Price\"\n        ]\n    },\n    \"secondaryYAxis\": {\n        \"fields\": [\n            \"Discount\"\n        ],\n        \"label\": \"Axis Label\"\n    }\n}"
  },
  {
    "instruction": "Create a Composed Chart chart named 'Chart Example 29' plotting 'Mega_watt' against 'Place'. The data should be sorted in asc order and displayed using a horizontal layout. The y-axis should be labeled as 'Axis Label' and positioned at 'center' The column 'coordinate_lg' should be lowest values should be colored #866666, values should be rounded to 1 decimal places, values should be prefixed with '@'. The column 'Mega_watt' should be highest values should be colored #f8b0y1, lowest values should be colored #f0f0f0, values should be rounded to 3 decimal places, values should be prefixed with '$'. The column 'Discount' should be aggregating using SUM function, y-axis values should be visible, filled with color #866666, highest values should be colored #1d3b7a, tooltip should display 'Tooltip Label', values should be prefixed with '#'. The column 'Price' should be aggregating using MAX function, y-axis values should be visible, lowest values should be colored #99ff95, values should be rounded to 1 decimal places, values should be suffixed with 'p'. The column 'coordinate_lt' should be aggregating using AVG function, filled with color #99ff95, highest values should be colored #f0f0f0, lowest values should be colored #f8b0y1, values should be prefixed with '*'.",
    "input": "{\"dataSources\":[{\"dataSourceId\":\"ds-8605\",\"queryKey\":\"API:+jdbc$$pmgr$$caps_1\",\"cols\":[{\"jsonName\":\"Region\",\"type\":\"string\"},{\"jsonName\":\"coordinate_lg\",\"type\":\"number\"},{\"jsonName\":\"Mega_watt\",\"type\":\"number\"},{\"jsonName\":\"Discount\",\"type\":\"number\"},{\"jsonName\":\"Order Date\",\"type\":\"date\"},{\"jsonName\":\"Place\",\"type\":\"string\"},{\"jsonName\":\"Employee\",\"type\":\"string\"},{\"jsonName\":\"Price\",\"type\":\"number\"},{\"jsonName\":\"coordinate_lt\",\"type\":\"number\"}],\"params\":[]}]}",
    "output": "{\n    \"dataSources\": [\n        {\n            \"dataSourceId\": \"ds-8605\",\n            \"queryKey\": \"API:+jdbc$$pmgr$$caps_1\",\n            \"cols\": [\n                {\n                    \"jsonName\": \"Region\",\n                    \"type\": \"string\"\n                },\n                {\n                    \"jsonName\": \"coordinate_lg\",\n                    \"type\": \"number\",\n                    \"fillLowestColor\": \"#866666\",\n                    \"decimalPlaces\": 1,\n                    \"prefix\": \"@\"\n                },\n                {\n                    \"jsonName\": \"Mega_watt\",\n                    \"type\": \"number\",\n                    \"composedChartType\": \"Bar Chart\",\n                   \"fillHighestColor\": \"#f8b0y1\",\n                    \"fillLowestColor\": \"#f0f0f0\",\n                    \"decimalPlaces\": 3,\n                    \"prefix\": \"$\"\n                },\n                {\n                    \"jsonName\": \"Discount\",\n                    \"type\": \"number\",\n                    \"aggFn\": \"SUM\",\n                    \"isYAxisValueVisible\": true,\n                    \"fillColor\": \"#866666\",\n                    \"fillHighestColor\": \"#1d3b7a\",\n                    \"label\": \"Tooltip Label\",\n                    \"prefix\": \"#\"\n                },\n                {\n                    \"jsonName\": \"Order Date\",\n                    \"type\": \"date\"\n                },\n                {\n                    \"jsonName\": \"Place\",\n                    \"type\": \"string\"\n                },\n                {\n                    \"jsonName\": \"Employee\",\n                    \"type\": \"string\"\n                },\n                {\n                    \"jsonName\": \"Price\",\n                    \"type\": \"number\",\n                    \"aggFn\": \"MAX\",\n                    \"isYAxisValueVisible\": true,\n                    \"fillLowestColor\": \"#99ff95\",\n                    \"decimalPlaces\": 1,\n                    \"suffix\": \"p\"\n                },\n                {\n                    \"jsonName\": \"coordinate_lt\",\n                    \"type\": \"number\",\n                    \"aggFn\": \"AVG\",\n                    \"fillColor\": \"#99ff95\",\n                    \"fillHighestColor\": \"#f0f0f0\",\n                    \"fillLowestColor\": \"#f8b0y1\",\n                    \"prefix\": \"*\"\n                }\n            ],\n            \"params\": []\n        }\n    ],\n    \"chartLayout\": \"horizontal\",\n    \"attributes\": {\n        \"chartType\": \"Composed Chart\",\n        \"sortOrder\": \"Asc\",\n        \"slider\": true,\n        \"saveImage\": true\n},\n    \"chartName\": \"Chart Example 29\",\n    \"xAxis\": {\n        \"fields\": [\n            \"Place\"\n        ]\n    },\n    \"yAxis\": {\n        \"fields\": [\n            \"Mega_watt\"\n        ],\n        \"label\": \"Axis Label\",\n        \"nameLocation\": \"center\"\n    }\n}"
  },
  {
    "instruction": "Create a Scattered Chart chart named 'Chart Example 33' plotting 'Profit' against 'SubCategory'. The data should be sorted in desc order and displayed using a horizontal layout. A Z-axis is also present, containing 'Price'. The y-axis should be labeled as 'Axis Label' The column 'Profit' should be values should be rounded to 3 decimal places, values should be prefixed with '#'. The column 'Revenue' should be values should be prefixed with '#'. The column 'Price' should be aggregating using MIN function, highest values should be colored #f0f0f0, tooltip should display 'Tooltip Label', values should be rounded to 1 decimal places, values should be prefixed with '@'. The column 'Sales' should be tooltip should display 'Tooltip Label', values should be rounded to 1 decimal places, values should be prefixed with '#'. The column 'longitude' should be filled with color #99ff95, highest values should be colored #f0f0f0, tooltip should display 'Tooltip Label', values should be rounded to 1 decimal places, values should be prefixed with '$'. The column 'coordinate_lt' should be aggregating using COUNT function, y-axis values should be hidden, tooltip should display 'Tooltip Label', values should be rounded to 1 decimal places, values should be suffixed with '%'.",
    "input": "{\"dataSources\":[{\"dataSourceId\":\"ds-9077\",\"queryKey\":\"API:+auto-task$$auto_68\",\"cols\":[{\"jsonName\":\"Profit\",\"type\":\"number\"},{\"jsonName\":\"Revenue\",\"type\":\"number\"},{\"jsonName\":\"Price\",\"type\":\"number\"},{\"jsonName\":\"Sales\",\"type\":\"number\"},{\"jsonName\":\"Category\",\"type\":\"string\"},{\"jsonName\":\"Customer\",\"type\":\"string\"},{\"jsonName\":\"longitude\",\"type\":\"number\"},{\"jsonName\":\"coordinate_lt\",\"type\":\"number\"},{\"jsonName\":\"SubCategory\",\"type\":\"string\"}],\"params\":[]}]}",
    "output": "{\n    \"dataSources\": [\n        {\n            \"dataSourceId\": \"ds-9077\",\n            \"queryKey\": \"API:+auto-task$$auto_68\",\n            \"cols\": [\n                {\n                    \"jsonName\": \"Profit\",\n                    \"type\": \"number\",\n                    \"decimalPlaces\": 3,\n                    \"prefix\": \"#\"\n                },\n                {\n                    \"jsonName\": \"Revenue\",\n                    \"type\": \"number\",\n                    \"prefix\": \"#\"\n                },\n                {\n                    \"jsonName\": \"Price\",\n                    \"type\": \"number\",\n                    \"aggFn\": \"MIN\",\n                    \"fillHighestColor\": \"#f0f0f0\",\n                    \"label\": \"Tooltip Label\",\n                    \"decimalPlaces\": 1,\n                    \"prefix\": \"@\"\n                },\n                {\n                    \"jsonName\": \"Sales\",\n                    \"type\": \"number\",\n                    \"label\": \"Tooltip Label\",\n                    \"decimalPlaces\": 1,\n                    \"prefix\": \"#\"\n                },\n                {\n                    \"jsonName\": \"Category\",\n                    \"type\": \"string\"\n                },\n                {\n                    \"jsonName\": \"Customer\",\n                    \"type\": \"string\"\n                },\n                {\n                    \"jsonName\": \"longitude\",\n                    \"type\": \"number\",\n                    \"fillColor\": \"#99ff95\",\n                    \"fillHighestColor\": \"#f0f0f0\",\n                    \"label\": \"Tooltip Label\",\n                    \"decimalPlaces\": 1,\n                    \"prefix\": \"$\"\n                },\n                {\n                    \"jsonName\": \"coordinate_lt\",\n                    \"type\": \"number\",\n                    \"aggFn\": \"COUNT\",\n                    \"isYAxisValueVisible\": false,\n                    \"label\": \"Tooltip Label\",\n                    \"decimalPlaces\": 1,\n                    \"suffix\": \"%\"\n                },\n                {\n                    \"jsonName\": \"SubCategory\",\n                    \"type\": \"string\"\n                }\n            ],\n            \"params\": []\n        }\n    ],\n    \"chartLayout\": \"horizontal\",\n    \"attributes\": {\n        \"chartType\": \"Scattered Chart\",\n        \"sortOrder\": \"Desc\",\n        \"slider\": true,\n        \"saveImage\": true\n},\n    \"chartName\": \"Chart Example 33\",\n    \"xAxis\": {\n        \"fields\": [\n            \"SubCategory\"\n        ]\n    },\n    \"yAxis\": {\n        \"fields\": [\n            \"Profit\"\n        ],\n        \"label\": \"Axis Label\"\n    },\n    \"zAxis\": {\n        \"fields\": [\n            \"Price\"\n        ]\n    }\n}"
  },
  {
    "instruction": "Create a Tree Map chart named 'Chart Example 35' plotting 'Revenue' against 'Order Date'. The data should be sorted in desc order and displayed using a vertical layout. The y-axis should be labeled as 'Axis Label' and positioned at 'end' The column 'Discount' should be aggregating using MAX function, y-axis values should be visible, tooltip should display 'Tooltip Label', values should be rounded to 0 decimal places, values should be prefixed with '₹'. The column 'Revenue' should be aggregating using AVG function, tooltip should display 'Tooltip Label', values should be rounded to 0 decimal places, values should be prefixed with '₹'. The column 'Demand' should be filled with color #99ff95, tooltip should display 'Tooltip Label', values should be rounded to 0 decimal places, values should be prefixed with '@'.",
    "input": "{\"dataSources\":[{\"dataSourceId\":\"ds-7696\",\"queryKey\":\"API:+auto-task$$auto-task_3\",\"cols\":[{\"jsonName\":\"Discount\",\"type\":\"number\"},{\"jsonName\":\"Order Date\",\"type\":\"date\"},{\"jsonName\":\"Revenue\",\"type\":\"number\"},{\"jsonName\":\"Country\",\"type\":\"string\"},{\"jsonName\":\"Region\",\"type\":\"string\"},{\"jsonName\":\"Category\",\"type\":\"string\"},{\"jsonName\":\"Demand\",\"type\":\"number\"},{\"jsonName\":\"Place\",\"type\":\"string\"}],\"params\":[]}]}",
    "output": "{\n    \"dataSources\": [\n        {\n            \"dataSourceId\": \"ds-7696\",\n            \"queryKey\": \"API:+auto-task$$auto-task_3\",\n            \"cols\": [\n                {\n                    \"jsonName\": \"Discount\",\n                    \"type\": \"number\",\n                    \"aggFn\": \"MAX\",\n                    \"isYAxisValueVisible\": true,\n                    \"label\": \"Tooltip Label\",\n                    \"decimalPlaces\": 0,\n                    \"prefix\": \"\\u20b9\"\n                },\n                {\n                    \"jsonName\": \"Order Date\",\n                    \"type\": \"date\"\n                },\n                {\n                    \"jsonName\": \"Revenue\",\n                    \"type\": \"number\",\n                    \"aggFn\": \"AVG\",\n                    \"label\": \"Tooltip Label\",\n                    \"decimalPlaces\": 0,\n                    \"prefix\": \"\\u20b9\"\n                },\n                {\n                    \"jsonName\": \"Country\",\n                    \"type\": \"string\"\n                },\n                {\n                    \"jsonName\": \"Region\",\n                    \"type\": \"string\"\n                },\n                {\n                    \"jsonName\": \"Category\",\n                    \"type\": \"string\"\n                },\n                {\n                    \"jsonName\": \"Demand\",\n                    \"type\": \"number\",\n                    \"fillColor\": \"#99ff95\",\n                    \"label\": \"Tooltip Label\",\n                    \"decimalPlaces\": 0,\n                    \"prefix\": \"@\"\n                },\n                {\n                    \"jsonName\": \"Place\",\n                    \"type\": \"string\"\n                }\n            ],\n            \"params\": []\n        }\n    ],\n    \"chartLayout\": \"vertical\",\n    \"attributes\": {\n        \"chartType\": \"Tree Map\",\n        \"sortOrder\": \"Desc\",\n        \"slider\": true,\n        \"saveImage\": true\n},\n    \"chartName\": \"Chart Example 35\",\n    \"xAxis\": {\n        \"fields\": [\n            \"Order Date\"\n        ]\n    },\n    \"yAxis\": {\n        \"fields\": [\n            \"Revenue\"\n        ],\n        \"label\": \"Axis Label\",\n        \"nameLocation\": \"end\"\n    }\n}"
  },
  {
    "instruction": "Create a Bar Chart chart named 'Chart Example 36' plotting 'Generation' against 'Customer' with 'latitude' as legend field. The data should be sorted in desc order and displayed using a horizontal layout. The column 'Discount' should be aggregating using COUNT function, filled with color #99ff95, tooltip should display 'Tooltip Label', values should be rounded to 3 decimal places, values should be suffixed with 'USD'. The column 'Mega_watt' should be aggregating using MAX function, highest values should be colored #f0f0f0, lowest values should be colored #1d3b7a, tooltip should display 'Tooltip Label', values should be rounded to 2 decimal places, values should be suffixed with 'p'. The column 'coordinate_lg' should be filled with color #1d3b7a, highest values should be colored #1d3b7a, tooltip should display 'Tooltip Label', values should be prefixed with '*'. The column 'latitude' should be aggregating using MIN function, filled with color #f0f0f0, values should be rounded to 2 decimal places, values should be prefixed with '*'. The column 'coordinate_lt' should be filled with color #f0f0f0, highest values should be colored #99ff95, lowest values should be colored #f0f0f0, tooltip should display 'Tooltip Label', values should be prefixed with '$'. The column 'Generation' should be aggregating using SUM function, y-axis values should be hidden, filled with color #1d3b7a, values should be rounded to 3 decimal places. The column 'Price' should be aggregating using SUM function, filled with color #f0f0f0, tooltip should display 'Tooltip Label', values should be prefixed with '*'. The column 'longitude' should be filled with color #866666, highest values should be colored #1d3b7a, tooltip should display 'Tooltip Label', values should be rounded to 2 decimal places, values should be prefixed with '#'.",
    "input": "{\"dataSources\":[{\"dataSourceId\":\"ds-6340\",\"queryKey\":\"API:+jdbc$$aws$$_91\",\"cols\":[{\"jsonName\":\"Discount\",\"type\":\"number\"},{\"jsonName\":\"Mega_watt\",\"type\":\"number\"},{\"jsonName\":\"coordinate_lg\",\"type\":\"number\"},{\"jsonName\":\"latitude\",\"type\":\"number\"},{\"jsonName\":\"coordinate_lt\",\"type\":\"number\"},{\"jsonName\":\"Generation\",\"type\":\"number\"},{\"jsonName\":\"Order Date\",\"type\":\"date\"},{\"jsonName\":\"Price\",\"type\":\"number\"},{\"jsonName\":\"longitude\",\"type\":\"number\"},{\"jsonName\":\"Customer\",\"type\":\"string\"}],\"params\":[]}]}",
    "output": "{\n    \"dataSources\": [\n        {\n            \"dataSourceId\": \"ds-6340\",\n            \"queryKey\": \"API:+jdbc$$aws$$_91\",\n            \"cols\": [\n                {\n                    \"jsonName\": \"Discount\",\n                    \"type\": \"number\",\n                    \"aggFn\": \"COUNT\",\n                    \"fillColor\": \"#99ff95\",\n                    \"label\": \"Tooltip Label\",\n                    \"decimalPlaces\": 3,\n                    \"suffix\": \"USD\"\n                },\n                {\n                    \"jsonName\": \"Mega_watt\",\n                    \"type\": \"number\",\n                    \"aggFn\": \"MAX\",\n                    \"fillHighestColor\": \"#f0f0f0\",\n                    \"fillLowestColor\": \"#1d3b7a\",\n                    \"label\": \"Tooltip Label\",\n                    \"decimalPlaces\": 2,\n                    \"suffix\": \"p\"\n                },\n                {\n                    \"jsonName\": \"coordinate_lg\",\n                    \"type\": \"number\",\n                    \"fillColor\": \"#1d3b7a\",\n                    \"fillHighestColor\": \"#1d3b7a\",\n                    \"label\": \"Tooltip Label\",\n                    \"prefix\": \"*\"\n                },\n                {\n                    \"jsonName\": \"latitude\",\n                    \"type\": \"number\",\n                    \"aggFn\": \"MIN\",\n                    \"fillColor\": \"#f0f0f0\",\n                    \"decimalPlaces\": 2,\n                    \"prefix\": \"*\"\n                },\n                {\n                    \"jsonName\": \"coordinate_lt\",\n                    \"type\": \"number\",\n                    \"fillColor\": \"#f0f0f0\",\n                    \"fillHighestColor\": \"#99ff95\",\n                    \"fillLowestColor\": \"#f0f0f0\",\n                    \"label\": \"Tooltip Label\",\n                    \"prefix\": \"$\"\n                },\n                {\n                    \"jsonName\": \"Generation\",\n                    \"type\": \"number\",\n                    \"aggFn\": \"SUM\",\n                    \"isYAxisValueVisible\": false,\n                    \"fillColor\": \"#1d3b7a\",\n                    \"decimalPlaces\": 3\n                },\n                {\n                    \"jsonName\": \"Order Date\",\n                    \"type\": \"date\"\n                },\n                {\n                    \"jsonName\": \"Price\",\n                    \"type\": \"number\",\n                    \"aggFn\": \"SUM\",\n                    \"fillColor\": \"#f0f0f0\",\n                    \"label\": \"Tooltip Label\",\n                    \"prefix\": \"*\"\n                },\n                {\n                    \"jsonName\": \"longitude\",\n                    \"type\": \"number\",\n                    \"fillColor\": \"#866666\",\n                    \"fillHighestColor\": \"#1d3b7a\",\n                    \"label\": \"Tooltip Label\",\n                    \"decimalPlaces\": 2,\n                    \"prefix\": \"#\"\n                },\n                {\n                    \"jsonName\": \"Customer\",\n                    \"type\": \"string\"\n                }\n            ],\n            \"params\": []\n        }\n    ],\n    \"chartLayout\": \"horizontal\",\n    \"attributes\": {\n        \"chartType\": \"Bar Chart\",\n        \"sortOrder\": \"Desc\",\n        \"slider\": true,\n        \"saveImage\": true,\n        \"legend\": {\n            \"fields\": \"latitude\",\n            \"colors\": {}\n        }\n    },\n    \"chartName\": \"Chart Example 36\",\n    \"xAxis\": {\n        \"fields\": [\n            \"Customer\"\n        ]\n    },\n    \"yAxis\": {\n        \"fields\": [\n            \"Generation\"\n        ]\n    }\n}"
  },
  {
    "instruction": "Create a Tree Map chart named 'Chart Example 37' plotting 'Generation' against 'Customer'. The data should be sorted in asc order and displayed using a horizontal layout. The y-axis should be labeled as 'Axis Label' and positioned at 'start' The column 'Revenue' should be aggregating using SUM function, values should be rounded to 1 decimal places, values should be prefixed with '₹'. The column 'coordinate_lg' should be aggregating using COUNT function, lowest values should be colored #866666, tooltip should display 'Tooltip Label', values should be rounded to 3 decimal places, values should be prefixed with '@'. The column 'longitude' should be aggregating using MIN function, filled with color #f8b0y1, lowest values should be colored #99ff95, tooltip should display 'Tooltip Label', values should be rounded to 1 decimal places, values should be prefixed with '₹'. The column 'Demand' should be lowest values should be colored #99ff95, tooltip should display 'Tooltip Label'. The column 'Generation' should be aggregating using SUM function, lowest values should be colored #f8b0y1, values should be rounded to 2 decimal places. The column 'Profit' should be aggregating using MIN function, tooltip should display 'Tooltip Label', values should be rounded to 2 decimal places, values should be prefixed with '@'. The column 'coordinate_lt' should be y-axis values should be hidden, filled with color #1d3b7a, highest values should be colored #f8b0y1, lowest values should be colored #f8b0y1, values should be rounded to 1 decimal places, values should be prefixed with '#'.",
    "input": "{\"dataSources\":[{\"dataSourceId\":\"ds-3164\",\"queryKey\":\"API:+auto-task$$auto_93\",\"cols\":[{\"jsonName\":\"Revenue\",\"type\":\"number\"},{\"jsonName\":\"coordinate_lg\",\"type\":\"number\"},{\"jsonName\":\"Customer\",\"type\":\"string\"},{\"jsonName\":\"longitude\",\"type\":\"number\"},{\"jsonName\":\"Demand\",\"type\":\"number\"},{\"jsonName\":\"Employee\",\"type\":\"string\"},{\"jsonName\":\"Generation\",\"type\":\"number\"},{\"jsonName\":\"Profit\",\"type\":\"number\"},{\"jsonName\":\"Country\",\"type\":\"string\"},{\"jsonName\":\"coordinate_lt\",\"type\":\"number\"}],\"params\":[]}]}",
    "output": "{\n    \"dataSources\": [\n        {\n            \"dataSourceId\": \"ds-3164\",\n            \"queryKey\": \"API:+auto-task$$auto_93\",\n            \"cols\": [\n                {\n                    \"jsonName\": \"Revenue\",\n                    \"type\": \"number\",\n                    \"aggFn\": \"SUM\",\n                    \"decimalPlaces\": 1,\n                    \"prefix\": \"\\u20b9\"\n                },\n                {\n                    \"jsonName\": \"coordinate_lg\",\n                    \"type\": \"number\",\n                    \"aggFn\": \"COUNT\",\n                    \"fillLowestColor\": \"#866666\",\n                    \"label\": \"Tooltip Label\",\n                    \"decimalPlaces\": 3,\n                    \"prefix\": \"@\"\n                },\n                {\n                    \"jsonName\": \"Customer\",\n                    \"type\": \"string\"\n                },\n                {\n                    \"jsonName\": \"longitude\",\n                    \"type\": \"number\",\n                    \"aggFn\": \"MIN\",\n                    \"fillColor\": \"#f8b0y1\",\n                    \"fillLowestColor\": \"#99ff95\",\n                    \"label\": \"Tooltip Label\",\n                    \"decimalPlaces\": 1,\n                    \"prefix\": \"\\u20b9\"\n                },\n                {\n                    \"jsonName\": \"Demand\",\n                    \"type\": \"number\",\n                    \"fillLowestColor\": \"#99ff95\",\n                    \"label\": \"Tooltip Label\"\n                },\n                {\n                    \"jsonName\": \"Employee\",\n                    \"type\": \"string\"\n                },\n                {\n                    \"jsonName\": \"Generation\",\n                    \"type\": \"number\",\n                    \"aggFn\": \"SUM\",\n                    \"fillLowestColor\": \"#f8b0y1\",\n                    \"decimalPlaces\": 2\n                },\n                {\n                    \"jsonName\": \"Profit\",\n                    \"type\": \"number\",\n                    \"aggFn\": \"MIN\",\n                    \"label\": \"Tooltip Label\",\n                    \"decimalPlaces\": 2,\n                    \"prefix\": \"@\"\n                },\n                {\n                    \"jsonName\": \"Country\",\n                    \"type\": \"string\"\n                },\n                {\n                    \"jsonName\": \"coordinate_lt\",\n                    \"type\": \"number\",\n                    \"isYAxisValueVisible\": false,\n                    \"fillColor\": \"#1d3b7a\",\n                    \"fillHighestColor\": \"#f8b0y1\",\n                    \"fillLowestColor\": \"#f8b0y1\",\n                    \"decimalPlaces\": 1,\n                    \"prefix\": \"#\"\n                }\n            ],\n            \"params\": []\n        }\n    ],\n    \"chartLayout\": \"horizontal\",\n    \"attributes\": {\n        \"chartType\": \"Tree Map\",\n        \"sortOrder\": \"Asc\",\n        \"slider\": true,\n        \"saveImage\": true\n    },\n    \"chartName\": \"Chart Example 37\",\n    \"xAxis\": {\n        \"fields\": [\n            \"Customer\"\n        ]\n    },\n    \"yAxis\": {\n        \"fields\": [\n            \"Generation\"\n        ],\n        \"label\": \"Axis Label\",\n        \"nameLocation\": \"start\"\n    }\n}"
  },
  {
    "instruction": "Create a TimeLine Chart chart named 'Chart Example 38' plotting 'Price' against 'Category'. The data should be sorted in asc order and displayed using a vertical layout. The y-axis should be labeled as 'Axis Label' and positioned at 'center' with a name gap of 32 pixels. The column 'Price' should be aggregating using MIN function, filled with color #1d3b7a, tooltip should display 'Tooltip Label', values should be rounded to 2 decimal places, values should be prefixed with '₹'. The column 'Cost' should be highest values should be colored #99ff95, values should be rounded to 3 decimal places. The column 'coordinate_lg' should be aggregating using SUM function, y-axis values should be visible, highest values should be colored #1d3b7a, lowest values should be colored #99ff95, tooltip should display 'Tooltip Label', values should be prefixed with '@'. The column 'Generation' should be aggregating using MIN function, y-axis values should be hidden, tooltip should display 'Tooltip Label', values should be rounded to 2 decimal places, values should be prefixed with '₹'. The column 'Revenue' should be tooltip should display 'Tooltip Label', values should be rounded to 0 decimal places, values should be prefixed with '₹'.",
    "input": "{\"dataSources\":[{\"dataSourceId\":\"ds-6552\",\"queryKey\":\"API:+auto-task$$auto-task_68\",\"cols\":[{\"jsonName\":\"Price\",\"type\":\"number\"},{\"jsonName\":\"Category\",\"type\":\"string\"},{\"jsonName\":\"Cost\",\"type\":\"number\"},{\"jsonName\":\"coordinate_lg\",\"type\":\"number\"},{\"jsonName\":\"Generation\",\"type\":\"number\"},{\"jsonName\":\"Revenue\",\"type\":\"number\"},{\"jsonName\":\"Customer\",\"type\":\"string\"}],\"params\":[]}]}",
    "output": "{\n    \"dataSources\": [\n        {\n            \"dataSourceId\": \"ds-6552\",\n            \"queryKey\": \"API:+auto-task$$auto-task_68\",\n            \"cols\": [\n                {\n                    \"jsonName\": \"Price\",\n                    \"type\": \"number\",\n                    \"aggFn\": \"MIN\",\n                    \"fillColor\": \"#1d3b7a\",\n                    \"label\": \"Tooltip Label\",\n                    \"decimalPlaces\": 2,\n                    \"prefix\": \"\\u20b9\"\n                },\n                {\n                    \"jsonName\": \"Category\",\n                    \"type\": \"string\"\n                },\n                {\n                    \"jsonName\": \"Cost\",\n                    \"type\": \"number\",\n                    \"fillHighestColor\": \"#99ff95\",\n                    \"decimalPlaces\": 3\n                },\n                {\n                    \"jsonName\": \"coordinate_lg\",\n                    \"type\": \"number\",\n                    \"aggFn\": \"SUM\",\n                    \"isYAxisValueVisible\": true,\n                    \"fillHighestColor\": \"#1d3b7a\",\n                    \"fillLowestColor\": \"#99ff95\",\n                    \"label\": \"Tooltip Label\",\n                    \"prefix\": \"@\"\n                },\n                {\n                    \"jsonName\": \"Generation\",\n                    \"type\": \"number\",\n                    \"aggFn\": \"MIN\",\n                    \"isYAxisValueVisible\": false,\n                    \"label\": \"Tooltip Label\",\n                    \"decimalPlaces\": 2,\n                    \"prefix\": \"\\u20b9\"\n                },\n                {\n                    \"jsonName\": \"Revenue\",\n                    \"type\": \"number\",\n                    \"label\": \"Tooltip Label\",\n                    \"decimalPlaces\": 0,\n                    \"prefix\": \"\\u20b9\"\n                },\n                {\n                    \"jsonName\": \"Customer\",\n                    \"type\": \"string\"\n                }\n            ],\n            \"params\": []\n        }\n    ],\n    \"chartLayout\": \"vertical\",\n    \"attributes\": {\n        \"chartType\": \"TimeLine Chart\",\n        \"sortOrder\": \"Asc\",\n        \"slider\": true,\n        \"saveImage\": true\n},\n    \"chartName\": \"Chart Example 38\",\n    \"xAxis\": {\n        \"fields\": [\n            \"Category\"\n        ]\n    },\n    \"yAxis\": {\n        \"fields\": [\n            \"Price\"\n        ],\n        \"label\": \"Axis Label\",\n        \"nameLocation\": \"center\",\n        \"nameGap\": 32\n    }\n}"
  },
  {
    "instruction": "Create a Composed Chart chart named 'Chart Example 39' plotting 'Profit' as Line Chart against 'Customer'. The data should be sorted in asc order and displayed using a vertical layout. A secondary Y-axis is included, representing 'Sales'. The y-axis should be labeled as 'Axis Label' and positioned at 'center' The column 'Profit' should be filled with color #f8b0y1, values should be rounded to 1 decimal places, values should be prefixed with '@'. The column 'Sales' should be aggregating using COUNT function, lowest values should be colored #f8b0y1, values should be rounded to 1 decimal places, values should be prefixed with '*'. The column 'latitude' should be aggregating using AVG function, lowest values should be colored #f0f0f0, tooltip should display 'Tooltip Label', values should be rounded to 1 decimal places, values should be prefixed with '*'.",
    "input": "{\"dataSources\":[{\"dataSourceId\":\"ds-1794\",\"queryKey\":\"API:+jdbc$$dataService$$_98\",\"cols\":[{\"jsonName\":\"Profit\",\"type\":\"number\"},{\"jsonName\":\"Customer\",\"type\":\"string\"},{\"jsonName\":\"Sales\",\"type\":\"number\"},{\"jsonName\":\"latitude\",\"type\":\"number\"},{\"jsonName\":\"Category\",\"type\":\"string\"},{\"jsonName\":\"SubCategory\",\"type\":\"string\"},{\"jsonName\":\"Region\",\"type\":\"string\"}],\"params\":[]}]}",
    "output": "{\n    \"dataSources\": [\n        {\n            \"dataSourceId\": \"ds-1794\",\n            \"queryKey\": \"API:+jdbc$$dataService$$_98\",\n            \"cols\": [\n                {\n                    \"jsonName\": \"Profit\",\n                    \"type\": \"number\",\n                    \"composedChartType\": \"Line Chart\",\n                 \"fillColor\": \"#f8b0y1\",\n                    \"decimalPlaces\": 1,\n                    \"prefix\": \"@\"\n                },\n                {\n                    \"jsonName\": \"Customer\",\n                    \"type\": \"string\"\n                },\n                {\n                    \"jsonName\": \"Sales\",\n                    \"type\": \"number\",\n                   \"composedChartType\": \"Bar Chart\",\n                \"aggFn\": \"COUNT\",\n                    \"fillLowestColor\": \"#f8b0y1\",\n                    \"decimalPlaces\": 1,\n                    \"prefix\": \"*\"\n                },\n                {\n                    \"jsonName\": \"latitude\",\n                    \"type\": \"number\",\n                    \"aggFn\": \"AVG\",\n                    \"fillLowestColor\": \"#f0f0f0\",\n                    \"label\": \"Tooltip Label\",\n                    \"decimalPlaces\": 1,\n                    \"prefix\": \"*\"\n                },\n                {\n                    \"jsonName\": \"Category\",\n                    \"type\": \"string\"\n                },\n                {\n                    \"jsonName\": \"SubCategory\",\n                    \"type\": \"string\"\n                },\n                {\n                    \"jsonName\": \"Region\",\n                    \"type\": \"string\"\n                }\n            ],\n            \"params\": []\n        }\n    ],\n    \"chartLayout\": \"vertical\",\n    \"attributes\": {\n        \"chartType\": \"Composed Chart\",\n        \"sortOrder\": \"Asc\",\n        \"slider\": true,\n        \"saveImage\": true\n    },\n    \"chartName\": \"Chart Example 39\",\n    \"xAxis\": {\n        \"fields\": [\n            \"Customer\"\n        ]\n    },\n    \"yAxis\": {\n        \"fields\": [\n            \"Profit\"\n        ],\n        \"label\": \"Axis Label\",\n        \"nameLocation\": \"center\"\n    },\n    \"secondaryYAxis\": {\n        \"fields\": [\n            \"Sales\"\n        ]\n    }\n}"
  },
  {
    "instruction": "Create a Pie Chart chart named 'Chart Example 40' plotting 'Demand' against 'Category'. The data should be sorted in desc order and displayed using a vertical layout. The x-axis should be labeled as 'Axis Label' and positioned at 'center' The y-axis should be labeled as 'Axis Label'. Rotation should be 117 degree. The column 'Demand' should be aggregating using MIN function, y-axis values should be visible, highest values should be colored #1d3b7a, values should be prefixed with '#'. The column 'coordinate_lt' should be aggregating using MAX function, y-axis values should be visible, highest values should be colored #99ff95, tooltip should display 'Tooltip Label', values should be rounded to 1 decimal places, values should be prefixed with '@'. The column 'Discount' should be aggregating using AVG function, y-axis values should be hidden, filled with color #f0f0f0, lowest values should be colored #f0f0f0, values should be rounded to 2 decimal places, values should be prefixed with '₹'. The column 'latitude' should be aggregating using MAX function, lowest values should be colored #f8b0y1, tooltip should display 'Tooltip Label', values should be rounded to 3 decimal places, values should be prefixed with '@'.",
    "input": "{\"dataSources\":[{\"dataSourceId\":\"ds-1622\",\"queryKey\":\"API:+auto-task$$auto-task_74\",\"cols\":[{\"jsonName\":\"Demand\",\"type\":\"number\"},{\"jsonName\":\"Place\",\"type\":\"string\"},{\"jsonName\":\"SubCategory\",\"type\":\"string\"},{\"jsonName\":\"location\",\"type\":\"string\"},{\"jsonName\":\"Region\",\"type\":\"string\"},{\"jsonName\":\"Category\",\"type\":\"string\"},{\"jsonName\":\"Country\",\"type\":\"string\"},{\"jsonName\":\"coordinate_lt\",\"type\":\"number\"},{\"jsonName\":\"Discount\",\"type\":\"number\"},{\"jsonName\":\"latitude\",\"type\":\"number\"}],\"params\":[]}]}",
    "output": "{\n    \"dataSources\": [\n        {\n            \"dataSourceId\": \"ds-1622\",\n            \"queryKey\": \"API:+auto-task$$auto-task_74\",\n            \"cols\": [\n                {\n                    \"jsonName\": \"Demand\",\n                    \"type\": \"number\",\n                    \"aggFn\": \"MIN\",\n                    \"isYAxisValueVisible\": true,\n                    \"fillHighestColor\": \"#1d3b7a\",\n                    \"prefix\": \"#\"\n                },\n                {\n                    \"jsonName\": \"Place\",\n                    \"type\": \"string\"\n                },\n                {\n                    \"jsonName\": \"SubCategory\",\n                    \"type\": \"string\"\n                },\n                {\n                    \"jsonName\": \"location\",\n                    \"type\": \"string\"\n                },\n                {\n                    \"jsonName\": \"Region\",\n                    \"type\": \"string\"\n                },\n                {\n                    \"jsonName\": \"Category\",\n                    \"type\": \"string\"\n                },\n                {\n                    \"jsonName\": \"Country\",\n                    \"type\": \"string\"\n                },\n                {\n                    \"jsonName\": \"coordinate_lt\",\n                    \"type\": \"number\",\n                    \"aggFn\": \"MAX\",\n                    \"isYAxisValueVisible\": true,\n                    \"fillHighestColor\": \"#99ff95\",\n                    \"label\": \"Tooltip Label\",\n                    \"decimalPlaces\": 1,\n                    \"prefix\": \"@\"\n                },\n                {\n                    \"jsonName\": \"Discount\",\n                    \"type\": \"number\",\n                    \"aggFn\": \"AVG\",\n                    \"isYAxisValueVisible\": false,\n                    \"fillColor\": \"#f0f0f0\",\n                    \"fillLowestColor\": \"#f0f0f0\",\n                    \"decimalPlaces\": 2,\n                    \"prefix\": \"\\u20b9\"\n                },\n                {\n                    \"jsonName\": \"latitude\",\n                    \"type\": \"number\",\n                    \"aggFn\": \"MAX\",\n                    \"fillLowestColor\": \"#f8b0y1\",\n                    \"label\": \"Tooltip Label\",\n                    \"decimalPlaces\": 3,\n                    \"prefix\": \"@\"\n                }\n            ],\n            \"params\": []\n        }\n    ],\n    \"chartLayout\": \"vertical\",\n    \"attributes\": {\n        \"chartType\": \"Pie Chart\",\n        \"sortOrder\": \"Desc\",\n        \"slider\": true,\n        \"saveImage\": true,\n        \"chartSubType\": \"normal\",\n        \"rotation\": 117\n    },\n    \"chartName\": \"Chart Example 40\",\n    \"xAxis\": {\n        \"fields\": [\n            \"Category\"\n        ],\n        \"label\": \"Axis Label\",\n        \"nameLocation\": \"center\"\n    },\n    \"yAxis\": {\n        \"fields\": [\n            \"Demand\"\n        ],\n        \"label\": \"Axis Label\"\n    }\n}"
  },
  {
    "instruction": "Create a Area Chart chart named 'Chart Example 41' plotting 'Generation' against 'Customer'. The data should be sorted in asc order and displayed using a vertical layout. A secondary Y-axis is included, representing 'Revenue'. The x-axis should be labeled as 'Axis Label' and positioned at 'start' with a name gap of 41 pixels. The secondary Y-axis should be labeled as 'Axis Label' and positioned at 'start' The column 'Cost' should be filled with color #f0f0f0, lowest values should be colored #866666, tooltip should display 'Tooltip Label', values should be rounded to 1 decimal places, values should be suffixed with '%'. The column 'Mega_watt' should be y-axis values should be hidden, lowest values should be colored #99ff95, tooltip should display 'Tooltip Label', values should be rounded to 3 decimal places, values should be prefixed with '₹'. The column 'Generation' should be aggregating using MIN function, y-axis values should be hidden, filled with color #f8b0y1, tooltip should display 'Tooltip Label', values should be prefixed with '₹'. The column 'Revenue' should be aggregating using COUNT function, tooltip should display 'Tooltip Label', values should be prefixed with '#'. The column 'latitude' should be aggregating using AVG function, filled with color #866666, highest values should be colored #866666, lowest values should be colored #1d3b7a, tooltip should display 'Tooltip Label'.",
    "input": "{\"dataSources\":[{\"dataSourceId\":\"ds-3692\",\"queryKey\":\"API:+auto-task$$auto-task_4\",\"cols\":[{\"jsonName\":\"Cost\",\"type\":\"number\"},{\"jsonName\":\"Place\",\"type\":\"string\"},{\"jsonName\":\"Mega_watt\",\"type\":\"number\"},{\"jsonName\":\"Generation\",\"type\":\"number\"},{\"jsonName\":\"Revenue\",\"type\":\"number\"},{\"jsonName\":\"Customer\",\"type\":\"string\"},{\"jsonName\":\"latitude\",\"type\":\"number\"},{\"jsonName\":\"Region\",\"type\":\"string\"}],\"params\":[]}]}",
    "output": "{\n    \"dataSources\": [\n        {\n            \"dataSourceId\": \"ds-3692\",\n            \"queryKey\": \"API:+auto-task$$auto-task_4\",\n            \"cols\": [\n                {\n                    \"jsonName\": \"Cost\",\n                    \"type\": \"number\",\n                    \"fillColor\": \"#f0f0f0\",\n                    \"fillLowestColor\": \"#866666\",\n                    \"label\": \"Tooltip Label\",\n                    \"decimalPlaces\": 1,\n                    \"suffix\": \"%\"\n                },\n                {\n                    \"jsonName\": \"Place\",\n                    \"type\": \"string\"\n                },\n                {\n                    \"jsonName\": \"Mega_watt\",\n                    \"type\": \"number\",\n                    \"isYAxisValueVisible\": false,\n                    \"fillLowestColor\": \"#99ff95\",\n                    \"label\": \"Tooltip Label\",\n                    \"decimalPlaces\": 3,\n                    \"prefix\": \"\\u20b9\"\n                },\n                {\n                    \"jsonName\": \"Generation\",\n                    \"type\": \"number\",\n                    \"aggFn\": \"MIN\",\n                    \"isYAxisValueVisible\": false,\n                    \"fillColor\": \"#f8b0y1\",\n                    \"label\": \"Tooltip Label\",\n                    \"prefix\": \"\\u20b9\"\n                },\n                {\n                    \"jsonName\": \"Revenue\",\n                    \"type\": \"number\",\n                    \"aggFn\": \"COUNT\",\n                    \"label\": \"Tooltip Label\",\n                    \"prefix\": \"#\"\n                },\n                {\n                    \"jsonName\": \"Customer\",\n                    \"type\": \"string\"\n                },\n                {\n                    \"jsonName\": \"latitude\",\n                    \"type\": \"number\",\n                    \"aggFn\": \"AVG\",\n                    \"fillColor\": \"#866666\",\n                    \"fillHighestColor\": \"#866666\",\n                    \"fillLowestColor\": \"#1d3b7a\",\n                    \"label\": \"Tooltip Label\"\n                },\n                {\n                    \"jsonName\": \"Region\",\n                    \"type\": \"string\"\n                }\n            ],\n            \"params\": []\n        }\n    ],\n    \"chartLayout\": \"vertical\",\n    \"attributes\": {\n        \"chartType\": \"Area Chart\",\n        \"sortOrder\": \"Asc\",\n        \"slider\": true,\n        \"saveImage\": true\n    },\n    \"chartName\": \"Chart Example 41\",\n    \"xAxis\": {\n        \"fields\": [\n            \"Customer\"\n        ],\n        \"label\": \"Axis Label\",\n        \"nameLocation\": \"start\",\n        \"nameGap\": 41\n    },\n    \"yAxis\": {\n        \"fields\": [\n            \"Generation\"\n        ]\n    },\n    \"secondaryYAxis\": {\n        \"fields\": [\n            \"Revenue\"\n        ],\n        \"label\": \"Axis Label\",\n        \"nameLocation\": \"start\"\n    }\n}"
  },
  {
    "instruction": "Create a Gantt Chart chart has title 'Chart Example 42' and has fields 'start_date' & 'end_date' with 'SubCategory'. The data should be sorted in asc order and displayed using a horizontal layout. The x-axis should be labeled as 'Axis Label' The y-axis should be labeled as 'Axis Label' and positioned at 'start' with a name gap of 23 pixels. The column 'Price' should be filled with color #99ff95, tooltip should display 'Tooltip Label', values should be prefixed with '₹'. The column 'start_date' should be aggregating using COUNT function, y-axis values should be visible, lowest values should be colored #f8b0y1, values should be rounded to 2 decimal places, values should be suffixed with '%'. The column 'Revenue' should be aggregating using MIN function, lowest values should be colored #f0f0f0, tooltip should display 'Tooltip Label', values should be prefixed with '$'. The column 'longitude' should be highest values should be colored #f0f0f0, lowest values should be colored #99ff95, tooltip should display 'Tooltip Label', values should be rounded to 2 decimal places, values should be prefixed with '₹'. The column 'Cost' should be aggregating using COUNT function, filled with color #866666, values should be rounded to 3 decimal places, values should be suffixed with 'USD'. The column 'latitude' should be aggregating using AVG function, filled with color #1d3b7a, highest values should be colored #f8b0y1, lowest values should be colored #1d3b7a, tooltip should display 'Tooltip Label', values should be rounded to 1 decimal places, values should be prefixed with '@'.",
    "input": "{\"dataSources\":[{\"dataSourceId\":\"ds-5830\",\"queryKey\":\"API:+jdbc$$pmgr$$caps_35\",\"cols\":[{\"jsonName\":\"Category\",\"type\":\"string\"},{\"jsonName\":\"end_date\",\"type\":\"date\"},{\"jsonName\":\"Price\",\"type\":\"number\"},{\"jsonName\":\"start_date\",\"type\":\"date\"},{\"jsonName\":\"Revenue\",\"type\":\"number\"},{\"jsonName\":\"longitude\",\"type\":\"number\"},{\"jsonName\":\"SubCategory\",\"type\":\"string\"},{\"jsonName\":\"Cost\",\"type\":\"number\"},{\"jsonName\":\"latitude\",\"type\":\"number\"}],\"params\":[]}]}",
    "output": "{\n    \"dataSources\": [\n        {\n            \"dataSourceId\": \"ds-5830\",\n            \"queryKey\": \"API:+jdbc$$pmgr$$caps_35\",\n            \"cols\": [\n                {\n                    \"jsonName\": \"Category\",\n                    \"type\": \"string\"\n                },\n                {\n                    \"jsonName\": \"end_date\",\n                    \"type\": \"date\"\n                },\n                {\n                    \"jsonName\": \"Price\",\n                    \"type\": \"number\",\n                    \"fillColor\": \"#99ff95\",\n                    \"label\": \"Tooltip Label\",\n                    \"prefix\": \"\\u20b9\"\n                },\n                {\n                    \"jsonName\": \"start_date\",\n                    \"type\": \"date\",\n                    \"aggFn\": \"COUNT\",\n                    \"isYAxisValueVisible\": true,\n                    \"fillLowestColor\": \"#f8b0y1\",\n                    \"decimalPlaces\": 2,\n                    \"suffix\": \"%\"\n                },\n                {\n                    \"jsonName\": \"Revenue\",\n                    \"type\": \"number\",\n                    \"aggFn\": \"MIN\",\n                    \"fillLowestColor\": \"#f0f0f0\",\n                    \"label\": \"Tooltip Label\",\n                    \"prefix\": \"$\"\n                },\n                {\n                    \"jsonName\": \"longitude\",\n                    \"type\": \"number\",\n                    \"fillHighestColor\": \"#f0f0f0\",\n                    \"fillLowestColor\": \"#99ff95\",\n                    \"label\": \"Tooltip Label\",\n                    \"decimalPlaces\": 2,\n                    \"prefix\": \"\\u20b9\"\n                },\n                {\n                    \"jsonName\": \"SubCategory\",\n                    \"type\": \"string\"\n                },\n                {\n                    \"jsonName\": \"Cost\",\n                    \"type\": \"number\",\n                    \"aggFn\": \"COUNT\",\n                    \"fillColor\": \"#866666\",\n                    \"decimalPlaces\": 3,\n                    \"suffix\": \"USD\"\n                },\n                {\n                    \"jsonName\": \"latitude\",\n                    \"type\": \"number\",\n                    \"aggFn\": \"AVG\",\n                    \"fillColor\": \"#1d3b7a\",\n                    \"fillHighestColor\": \"#f8b0y1\",\n                    \"fillLowestColor\": \"#1d3b7a\",\n                    \"label\": \"Tooltip Label\",\n                    \"decimalPlaces\": 1,\n                    \"prefix\": \"@\"\n                }\n            ],\n            \"params\": []\n        }\n    ],\n    \"chartLayout\": \"horizontal\",\n    \"attributes\": {\n        \"chartType\": \"Gantt Chart\",\n        \"sortOrder\": \"Asc\",\n        \"slider\": true,\n        \"saveImage\": true\n    },\n    \"chartName\": \"Chart Example 42\",\n    \"xAxis\": {\n        \"fields\": [\n            \"SubCategory\"\n        ],\n        \"label\": \"Axis Label\"\n    },\n    \"yAxis\": {\n        \"fields\": [\n            \"start_date\"\n,     \"end_date\"\n   ],\n        \"label\": \"Axis Label\",\n        \"nameLocation\": \"start\",\n        \"nameGap\": 23\n    }\n}"
  },
  {
    "instruction": "Create a Bar Chart chart named 'Chart Example 43' plotting 'Demand' against 'SubCategory'. The data should be sorted in desc order and displayed using a horizontal layout. A secondary Y-axis is included, representing 'Price'. The x-axis should be labeled as 'Axis Label' and positioned at 'start' with a name gap of 38 pixels. The column 'Revenue' should be filled with color #99ff95, tooltip should display 'Tooltip Label', values should be rounded to 2 decimal places, values should be prefixed with '*'. The column 'coordinate_lt' should be aggregating using SUM function, filled with color #99ff95, highest values should be colored #866666, tooltip should display 'Tooltip Label', values should be rounded to 3 decimal places, values should be suffixed with 'MW'. The column 'Demand' should be aggregating using SUM function, filled with color #866666, highest values should be colored #1d3b7a, lowest values should be colored #f8b0y1, tooltip should display 'Tooltip Label', values should be rounded to 3 decimal places, values should be prefixed with '*'. The column 'Price' should be highest values should be colored #f0f0f0, lowest values should be colored #f0f0f0, values should be rounded to 1 decimal places, values should be prefixed with '#'.",
    "input": "{\"dataSources\":[{\"dataSourceId\":\"ds-4574\",\"queryKey\":\"API:+jdbc$$pmgr$$caps_58\",\"cols\":[{\"jsonName\":\"Order Date\",\"type\":\"date\"},{\"jsonName\":\"location\",\"type\":\"string\"},{\"jsonName\":\"Revenue\",\"type\":\"number\"},{\"jsonName\":\"SubCategory\",\"type\":\"string\"},{\"jsonName\":\"coordinate_lt\",\"type\":\"number\"},{\"jsonName\":\"Demand\",\"type\":\"number\"},{\"jsonName\":\"Customer\",\"type\":\"string\"},{\"jsonName\":\"Price\",\"type\":\"number\"},{\"jsonName\":\"Country\",\"type\":\"string\"}],\"params\":[]}]}",
    "output": "{\n    \"dataSources\": [\n        {\n            \"dataSourceId\": \"ds-4574\",\n            \"queryKey\": \"API:+jdbc$$pmgr$$caps_58\",\n            \"cols\": [\n                {\n                    \"jsonName\": \"Order Date\",\n                    \"type\": \"date\"\n                },\n                {\n                    \"jsonName\": \"location\",\n                    \"type\": \"string\"\n                },\n                {\n                    \"jsonName\": \"Revenue\",\n                    \"type\": \"number\",\n                    \"fillColor\": \"#99ff95\",\n                    \"label\": \"Tooltip Label\",\n                    \"decimalPlaces\": 2,\n                    \"prefix\": \"*\"\n                },\n                {\n                    \"jsonName\": \"SubCategory\",\n                    \"type\": \"string\"\n                },\n                {\n                    \"jsonName\": \"coordinate_lt\",\n                    \"type\": \"number\",\n                    \"aggFn\": \"SUM\",\n                    \"fillColor\": \"#99ff95\",\n                    \"fillHighestColor\": \"#866666\",\n                    \"label\": \"Tooltip Label\",\n                    \"decimalPlaces\": 3,\n                    \"suffix\": \"MW\"\n                },\n                {\n                    \"jsonName\": \"Demand\",\n                    \"type\": \"number\",\n                    \"aggFn\": \"SUM\",\n                    \"fillColor\": \"#866666\",\n                    \"fillHighestColor\": \"#1d3b7a\",\n                    \"fillLowestColor\": \"#f8b0y1\",\n                    \"label\": \"Tooltip Label\",\n                    \"decimalPlaces\": 3,\n                    \"prefix\": \"*\"\n                },\n                {\n                    \"jsonName\": \"Customer\",\n                    \"type\": \"string\"\n                },\n                {\n                    \"jsonName\": \"Price\",\n                    \"type\": \"number\",\n                    \"fillHighestColor\": \"#f0f0f0\",\n                    \"fillLowestColor\": \"#f0f0f0\",\n                    \"decimalPlaces\": 1,\n                    \"prefix\": \"#\"\n                },\n                {\n                    \"jsonName\": \"Country\",\n                    \"type\": \"string\"\n                }\n            ],\n            \"params\": []\n        }\n    ],\n    \"chartLayout\": \"horizontal\",\n    \"attributes\": {\n        \"chartType\": \"Bar Chart\",\n        \"sortOrder\": \"Desc\",\n        \"slider\": true,\n        \"saveImage\": true\n    },\n    \"chartName\": \"Chart Example 43\",\n    \"xAxis\": {\n        \"fields\": [\n            \"SubCategory\"\n        ],\n        \"label\": \"Axis Label\",\n        \"nameLocation\": \"start\",\n        \"nameGap\": 38\n    },\n    \"yAxis\": {\n        \"fields\": [\n            \"Demand\"\n        ]\n    },\n    \"secondaryYAxis\": {\n        \"fields\": [\n            \"Price\"\n        ]\n    }\n}"
  },
  {
    "instruction": "Create a Line Chart chart with legend as 'longitude' has name 'Chart Example 44' plotting 'Sales' against 'Place'. The data should be sorted in desc order and displayed using a vertical layout. The x-axis should be labeled as 'Axis Label' with a name gap of 23 pixels. The column 'coordinate_lt' should be aggregating using AVG function, y-axis values should be visible, lowest values should be colored #1d3b7a, tooltip should display 'Tooltip Label', values should be rounded to 0 decimal places, values should be prefixed with '$'. The column 'Sales' should be aggregating using SUM function, tooltip should display 'Tooltip Label', values should be prefixed with '@'. The column 'longitude' should be aggregating using MIN function, y-axis values should be visible, tooltip should display 'Tooltip Label', values should be rounded to 0 decimal places, values should be prefixed with '₹'.",
    "input": "{\"dataSources\":[{\"dataSourceId\":\"ds-3127\",\"queryKey\":\"API:+lookup$$lookup$$_73\",\"cols\":[{\"jsonName\":\"Region\",\"type\":\"string\"},{\"jsonName\":\"coordinate_lt\",\"type\":\"number\"},{\"jsonName\":\"Employee\",\"type\":\"string\"},{\"jsonName\":\"Sales\",\"type\":\"number\"},{\"jsonName\":\"longitude\",\"type\":\"number\"},{\"jsonName\":\"Place\",\"type\":\"string\"},{\"jsonName\":\"location\",\"type\":\"string\"}],\"params\":[]}]}",
    "output": "{\n    \"dataSources\": [\n        {\n            \"dataSourceId\": \"ds-3127\",\n            \"queryKey\": \"API:+lookup$$lookup$$_73\",\n            \"cols\": [\n                {\n                    \"jsonName\": \"Region\",\n                    \"type\": \"string\"\n                },\n                {\n                    \"jsonName\": \"coordinate_lt\",\n                    \"type\": \"number\",\n                    \"aggFn\": \"AVG\",\n                    \"isYAxisValueVisible\": true,\n                    \"fillLowestColor\": \"#1d3b7a\",\n                    \"label\": \"Tooltip Label\",\n                    \"decimalPlaces\": 0,\n                    \"prefix\": \"$\"\n                },\n                {\n                    \"jsonName\": \"Employee\",\n                    \"type\": \"string\"\n                },\n                {\n                    \"jsonName\": \"Sales\",\n                    \"type\": \"number\",\n                    \"aggFn\": \"SUM\",\n                    \"label\": \"Tooltip Label\",\n                    \"prefix\": \"@\"\n                },\n                {\n                    \"jsonName\": \"longitude\",\n                    \"type\": \"number\",\n                    \"aggFn\": \"MIN\",\n                    \"isYAxisValueVisible\": true,\n                    \"label\": \"Tooltip Label\",\n                    \"decimalPlaces\": 0,\n                    \"prefix\": \"\\u20b9\"\n                },\n                {\n                    \"jsonName\": \"Place\",\n                    \"type\": \"string\"\n                },\n                {\n                    \"jsonName\": \"location\",\n                    \"type\": \"string\"\n                }\n            ],\n            \"params\": []\n        }\n    ],\n    \"chartLayout\": \"vertical\",\n    \"attributes\": {\n        \"chartType\": \"Line Chart\",\n        \"sortOrder\": \"Desc\",\n        \"slider\": true,\n        \"saveImage\": true,\n        \"legend\": {\n            \"fields\": \"longitude\",\n            \"colors\": {}\n        }\n    },\n    \"chartName\": \"Chart Example 44\",\n    \"xAxis\": {\n        \"fields\": [\n            \"Place\"\n        ],\n        \"label\": \"Axis Label\",\n        \"nameGap\": 23\n    },\n    \"yAxis\": {\n        \"fields\": [\n            \"Sales\"\n        ]\n    }\n}"
  },
  {
    "instruction": "Create a Tree Map chart named 'Chart Example 45' plotting 'Cost' against 'Country'. The data should be sorted in asc order and displayed using a vertical layout. The y-axis should be labeled as 'Axis Label' with a name gap of 15 pixels. The column 'Mega_watt' should be y-axis values should be hidden, filled with color #99ff95, highest values should be colored #866666, lowest values should be colored #f0f0f0, tooltip should display 'Tooltip Label', values should be rounded to 2 decimal places, values should be prefixed with '@'. The column 'coordinate_lt' should be aggregating using MAX function, tooltip should display 'Tooltip Label', values should be suffixed with '%'. The column 'Profit' should be aggregating using MAX function, highest values should be colored #866666, lowest values should be colored #f0f0f0, values should be rounded to 0 decimal places. The column 'Cost' should be aggregating using MAX function, highest values should be colored #f8b0y1, lowest values should be colored #1d3b7a, values should be suffixed with 'p'.",
    "input": "{\"dataSources\":[{\"dataSourceId\":\"ds-5946\",\"queryKey\":\"API:+auto-task$$auto-task_80\",\"cols\":[{\"jsonName\":\"Mega_watt\",\"type\":\"number\"},{\"jsonName\":\"coordinate_lt\",\"type\":\"number\"},{\"jsonName\":\"Country\",\"type\":\"string\"},{\"jsonName\":\"Category\",\"type\":\"string\"},{\"jsonName\":\"Profit\",\"type\":\"number\"},{\"jsonName\":\"Order Date\",\"type\":\"date\"},{\"jsonName\":\"Cost\",\"type\":\"number\"},{\"jsonName\":\"Region\",\"type\":\"string\"}],\"params\":[]}]}",
    "output": "{\n    \"dataSources\": [\n        {\n            \"dataSourceId\": \"ds-5946\",\n            \"queryKey\": \"API:+auto-task$$auto-task_80\",\n            \"cols\": [\n                {\n                    \"jsonName\": \"Mega_watt\",\n                    \"type\": \"number\",\n                    \"isYAxisValueVisible\": false,\n                    \"fillColor\": \"#99ff95\",\n                    \"fillHighestColor\": \"#866666\",\n                    \"fillLowestColor\": \"#f0f0f0\",\n                    \"label\": \"Tooltip Label\",\n                    \"decimalPlaces\": 2,\n                    \"prefix\": \"@\"\n                },\n                {\n                    \"jsonName\": \"coordinate_lt\",\n                    \"type\": \"number\",\n                    \"aggFn\": \"MAX\",\n                    \"label\": \"Tooltip Label\",\n                    \"suffix\": \"%\"\n                },\n                {\n                    \"jsonName\": \"Country\",\n                    \"type\": \"string\"\n                },\n                {\n                    \"jsonName\": \"Category\",\n                    \"type\": \"string\"\n                },\n                {\n                    \"jsonName\": \"Profit\",\n                    \"type\": \"number\",\n                    \"aggFn\": \"MAX\",\n                    \"fillHighestColor\": \"#866666\",\n                    \"fillLowestColor\": \"#f0f0f0\",\n                    \"decimalPlaces\": 0\n                },\n                {\n                    \"jsonName\": \"Order Date\",\n                    \"type\": \"date\"\n                },\n                {\n                    \"jsonName\": \"Cost\",\n                    \"type\": \"number\",\n                    \"aggFn\": \"MAX\",\n                    \"fillHighestColor\": \"#f8b0y1\",\n                    \"fillLowestColor\": \"#1d3b7a\",\n                    \"suffix\": \"p\"\n                },\n                {\n                    \"jsonName\": \"Region\",\n                    \"type\": \"string\"\n                }\n            ],\n            \"params\": []\n        }\n    ],\n    \"chartLayout\": \"vertical\",\n    \"attributes\": {\n        \"chartType\": \"Tree Map\",\n        \"sortOrder\": \"Asc\",\n        \"slider\": true,\n        \"saveImage\": true\n},\n    \"chartName\": \"Chart Example 45\",\n    \"xAxis\": {\n        \"fields\": [\n            \"Country\"\n        ]\n    },\n    \"yAxis\": {\n        \"fields\": [\n            \"Cost\"\n        ],\n        \"label\": \"Axis Label\",\n        \"nameGap\": 15\n    }\n}"
  },
  {
    "instruction": "Create a TimeLine Chart chart named 'Chart Example 46' plotting 'Profit' against 'Order Date'. The data should be sorted in desc order and displayed using a vertical layout. The x-axis should be labeled as 'Axis Label' and positioned at 'center' The y-axis should be labeled as 'Axis Label' with a name gap of 24 pixels. The column 'coordinate_lg' should be aggregating using COUNT function, highest values should be colored #f8b0y1, values should be rounded to 0 decimal places, values should be prefixed with '₹'. The column 'longitude' should be aggregating using MAX function, filled with color #1d3b7a, tooltip should display 'Tooltip Label', values should be rounded to 3 decimal places. The column 'Generation' should be aggregating using MAX function, values should be rounded to 2 decimal places, values should be prefixed with '#'. The column 'Profit' should be aggregating using MIN function, highest values should be colored #99ff95, lowest values should be colored #f8b0y1, values should be rounded to 3 decimal places, values should be prefixed with '$'. The column 'latitude' should be highest values should be colored #f0f0f0, tooltip should display 'Tooltip Label', values should be suffixed with '%'.",
    "input": "{\"dataSources\":[{\"dataSourceId\":\"ds-1415\",\"queryKey\":\"API:+jdbc$$Oracle$$Energy_API_24\",\"cols\":[{\"jsonName\":\"coordinate_lg\",\"type\":\"number\"},{\"jsonName\":\"Order Date\",\"type\":\"date\"},{\"jsonName\":\"longitude\",\"type\":\"number\"},{\"jsonName\":\"Generation\",\"type\":\"number\"},{\"jsonName\":\"Profit\",\"type\":\"number\"},{\"jsonName\":\"latitude\",\"type\":\"number\"},{\"jsonName\":\"Place\",\"type\":\"string\"},{\"jsonName\":\"Employee\",\"type\":\"string\"}],\"params\":[]}]}",
    "output": "{\n    \"dataSources\": [\n        {\n            \"dataSourceId\": \"ds-1415\",\n            \"queryKey\": \"API:+jdbc$$Oracle$$Energy_API_24\",\n            \"cols\": [\n                {\n                    \"jsonName\": \"coordinate_lg\",\n                    \"type\": \"number\",\n                    \"aggFn\": \"COUNT\",\n                    \"fillHighestColor\": \"#f8b0y1\",\n                    \"decimalPlaces\": 0,\n                    \"prefix\": \"\\u20b9\"\n                },\n                {\n                    \"jsonName\": \"Order Date\",\n                    \"type\": \"date\"\n                },\n                {\n                    \"jsonName\": \"longitude\",\n                    \"type\": \"number\",\n                    \"aggFn\": \"MAX\",\n                    \"fillColor\": \"#1d3b7a\",\n                    \"label\": \"Tooltip Label\",\n                    \"decimalPlaces\": 3\n                },\n                {\n                    \"jsonName\": \"Generation\",\n                    \"type\": \"number\",\n                    \"aggFn\": \"MAX\",\n                    \"decimalPlaces\": 2,\n                    \"prefix\": \"#\"\n                },\n                {\n                    \"jsonName\": \"Profit\",\n                    \"type\": \"number\",\n                    \"aggFn\": \"MIN\",\n                    \"fillHighestColor\": \"#99ff95\",\n                    \"fillLowestColor\": \"#f8b0y1\",\n                    \"decimalPlaces\": 3,\n                    \"prefix\": \"$\"\n                },\n                {\n                    \"jsonName\": \"latitude\",\n                    \"type\": \"number\",\n                    \"fillHighestColor\": \"#f0f0f0\",\n                    \"label\": \"Tooltip Label\",\n                    \"suffix\": \"%\"\n                },\n                {\n                    \"jsonName\": \"Place\",\n                    \"type\": \"string\"\n                },\n                {\n                    \"jsonName\": \"Employee\",\n                    \"type\": \"string\"\n                }\n            ],\n            \"params\": []\n        }\n    ],\n    \"chartLayout\": \"vertical\",\n    \"attributes\": {\n        \"chartType\": \"TimeLine Chart\",\n        \"sortOrder\": \"Desc\",\n        \"slider\": true,\n        \"saveImage\": true\n},\n    \"chartName\": \"Chart Example 46\",\n    \"xAxis\": {\n        \"fields\": [\n            \"Order Date\"\n        ],\n        \"label\": \"Axis Label\",\n        \"nameLocation\": \"center\"\n    },\n    \"yAxis\": {\n        \"fields\": [\n            \"Profit\"\n        ],\n        \"label\": \"Axis Label\",\n        \"nameGap\": 24\n    }\n}"
  },
  {
    "instruction": "Create a Composed Chart chart named 'Chart Example 47' plotting 'Demand' against 'SubCategory'. The data should be sorted in desc order and displayed using a horizontal layout. A secondary Y-axis is included, representing 'Sales' as Bar Chart. The x-axis should be labeled as 'Axis Label' and positioned at 'center' with a name gap of 37 pixels. The secondary Y-axis should be labeled as 'Axis Label' with a name gap of 15 pixels. The column 'latitude' should be aggregating using MAX function, tooltip should display 'Tooltip Label', values should be rounded to 1 decimal places, values should be prefixed with '₹'. The column 'longitude' should be lowest values should be colored #866666, values should be rounded to 3 decimal places. The column 'Sales' should be aggregating using SUM function, tooltip should display 'Tooltip Label', values should be rounded to 2 decimal places. The column 'Mega_watt' should be aggregating using MAX function, highest values should be colored #f0f0f0, values should be rounded to 0 decimal places. The column 'Demand' should be aggregating using MIN function, filled with color #866666, lowest values should be colored #f0f0f0, values should be rounded to 0 decimal places, values should be suffixed with 'p'.",
    "input": "{\"dataSources\":[{\"dataSourceId\":\"ds-7876\",\"queryKey\":\"API:+auto-task$$auto-task_76\",\"cols\":[{\"jsonName\":\"Region\",\"type\":\"string\"},{\"jsonName\":\"Employee\",\"type\":\"string\"},{\"jsonName\":\"latitude\",\"type\":\"number\"},{\"jsonName\":\"longitude\",\"type\":\"number\"},{\"jsonName\":\"Sales\",\"type\":\"number\"},{\"jsonName\":\"Mega_watt\",\"type\":\"number\"},{\"jsonName\":\"Demand\",\"type\":\"number\"},{\"jsonName\":\"SubCategory\",\"type\":\"string\"},{\"jsonName\":\"location\",\"type\":\"string\"},{\"jsonName\":\"Category\",\"type\":\"string\"}],\"params\":[]}]}",
    "output": "{\n    \"dataSources\": [\n        {\n            \"dataSourceId\": \"ds-7876\",\n            \"queryKey\": \"API:+auto-task$$auto-task_76\",\n            \"cols\": [\n                {\n                    \"jsonName\": \"Region\",\n                    \"type\": \"string\"\n                },\n                {\n                    \"jsonName\": \"Employee\",\n                    \"type\": \"string\"\n                },\n                {\n                    \"jsonName\": \"latitude\",\n                    \"type\": \"number\",\n                    \"aggFn\": \"MAX\",\n                    \"label\": \"Tooltip Label\",\n                    \"decimalPlaces\": 1,\n                    \"prefix\": \"\\u20b9\"\n                },\n                {\n                    \"jsonName\": \"longitude\",\n                    \"type\": \"number\",\n                    \"fillLowestColor\": \"#866666\",\n                    \"decimalPlaces\": 3\n                },\n                {\n                    \"jsonName\": \"Sales\",\n                    \"type\": \"number\",\n                    \"composedChartType\": \"Bar Chart\",\n                 \"aggFn\": \"SUM\",\n                    \"label\": \"Tooltip Label\",\n                    \"decimalPlaces\": 2\n                },\n                {\n                    \"jsonName\": \"Mega_watt\",\n                    \"type\": \"number\",\n                    \"aggFn\": \"MAX\",\n                    \"fillHighestColor\": \"#f0f0f0\",\n                    \"decimalPlaces\": 0\n                },\n                {\n                    \"jsonName\": \"Demand\",\n                    \"type\": \"number\",\n                  \"composedChartType\": \"Bar Chart\",\n                 \"aggFn\": \"MIN\",\n                    \"fillColor\": \"#866666\",\n                    \"fillLowestColor\": \"#f0f0f0\",\n                    \"decimalPlaces\": 0,\n                    \"suffix\": \"p\"\n                },\n                {\n                    \"jsonName\": \"SubCategory\",\n                    \"type\": \"string\"\n                },\n                {\n                    \"jsonName\": \"location\",\n                    \"type\": \"string\"\n                },\n                {\n                    \"jsonName\": \"Category\",\n                    \"type\": \"string\"\n                }\n            ],\n            \"params\": []\n        }\n    ],\n    \"chartLayout\": \"horizontal\",\n    \"attributes\": {\n        \"chartType\": \"Composed Chart\",\n        \"sortOrder\": \"Desc\",\n        \"slider\": true,\n        \"saveImage\": true\n    },\n    \"chartName\": \"Chart Example 47\",\n    \"xAxis\": {\n        \"fields\": [\n            \"SubCategory\"\n        ],\n        \"label\": \"Axis Label\",\n        \"nameLocation\": \"center\",\n        \"nameGap\": 37\n    },\n    \"yAxis\": {\n        \"fields\": [\n            \"Demand\"\n        ]\n    },\n    \"secondaryYAxis\": {\n        \"fields\": [\n            \"Sales\"\n        ],\n        \"label\": \"Axis Label\",\n        \"nameGap\": 15\n    }\n}"
  },
  {
    "instruction": "Create a Geo Chart based on coordinates chart named 'Chart Example 48' plotting 'N/A' against 'N/A'. The data should be sorted in desc order and displayed using a vertical layout. The column 'latitude' should be aggregating using AVG function, filled with color #99ff95, highest values should be colored #f0f0f0, values should be rounded to 0 decimal places. The column 'Profit' should be aggregating using SUM function, filled with color #f8b0y1, values should be prefixed with '#'. The column 'Demand' should be aggregating using SUM function, lowest values should be colored #99ff95, tooltip should display 'Tooltip Label', values should be rounded to 2 decimal places, values should be suffixed with 'MW'. The column 'coordinate_lg' should be aggregating using MIN function, tooltip should display 'Tooltip Label', values should be prefixed with '$'.",
    "input": "{\"dataSources\":[{\"dataSourceId\":\"ds-3819\",\"queryKey\":\"API:+jdbc$$Oracle$$Energy_API_83\",\"cols\":[{\"jsonName\":\"Region\",\"type\":\"string\"},{\"jsonName\":\"SubCategory\",\"type\":\"string\"},{\"jsonName\":\"location\",\"type\":\"string\"},{\"jsonName\":\"Category\",\"type\":\"string\"},{\"jsonName\":\"latitude\",\"type\":\"number\"},{\"jsonName\":\"Profit\",\"type\":\"number\"},{\"jsonName\":\"Demand\",\"type\":\"number\"},{\"jsonName\":\"coordinate_lg\",\"type\":\"number\"}],\"params\":[]}]}",
    "output": "{\n    \"dataSources\": [\n        {\n            \"dataSourceId\": \"ds-3819\",\n            \"queryKey\": \"API:+jdbc$$Oracle$$Energy_API_83\",\n            \"cols\": [\n                {\n                    \"jsonName\": \"Region\",\n                    \"type\": \"string\"\n                },\n                {\n                    \"jsonName\": \"SubCategory\",\n                    \"type\": \"string\"\n                },\n                {\n                    \"jsonName\": \"location\",\n                    \"type\": \"string\"\n                },\n                {\n                    \"jsonName\": \"Category\",\n                    \"type\": \"string\"\n                },\n                {\n                    \"jsonName\": \"latitude\",\n                    \"type\": \"number\",\n                    \"aggFn\": \"AVG\",\n                    \"fillColor\": \"#99ff95\",\n                    \"fillHighestColor\": \"#f0f0f0\",\n                    \"decimalPlaces\": 0\n                },\n                {\n                    \"jsonName\": \"Profit\",\n                    \"type\": \"number\",\n                    \"aggFn\": \"SUM\",\n                    \"fillColor\": \"#f8b0y1\",\n                    \"prefix\": \"#\"\n                },\n                {\n                    \"jsonName\": \"Demand\",\n                    \"type\": \"number\",\n                    \"aggFn\": \"SUM\",\n                    \"fillLowestColor\": \"#99ff95\",\n                    \"label\": \"Tooltip Label\",\n                    \"decimalPlaces\": 2,\n                    \"suffix\": \"MW\"\n                },\n                {\n                    \"jsonName\": \"coordinate_lg\",\n                    \"type\": \"number\",\n                    \"aggFn\": \"MIN\",\n                    \"label\": \"Tooltip Label\",\n                    \"prefix\": \"$\"\n                }\n            ],\n            \"params\": []\n        }\n    ],\n    \"chartLayout\": \"vertical\",\n    \"attributes\": {\n        \"chartType\": \"Geo Chart\",\n        \"sortOrder\": \"Desc\",\n        \"slider\": true,\n        \"saveImage\": true,\n        \"chartSubType\": \"map\"\n    },\n    \"chartName\": \"Chart Example 48\",\n    \"xAxis\": {},\n    \"yAxis\": {},\n    \"longitude\": {\n        \"fields\": [\n            \"coordinate_lg\"\n        ]\n    },\n    \"latitude\": {\n        \"fields\": [\n            \"latitude\"\n        ]\n    },\n    \"values\": {\n        \"fields\": [\n            \"Demand\"\n        ]\n    }\n}"
  },
  {
    "instruction": "Create a TimeLine Chart chart named 'Chart Example 49' plotting 'Discount' against 'Order Date'. The data should be sorted in asc order and displayed using a vertical layout. The x-axis should be labeled as 'Axis Label' The column 'Discount' should be aggregating using COUNT function, y-axis values should be hidden, filled with color #f0f0f0, highest values should be colored #99ff95, lowest values should be colored #1d3b7a, values should be rounded to 1 decimal places, values should be prefixed with '*'. The column 'Mega_watt' should be aggregating using AVG function, filled with color #99ff95, lowest values should be colored #f0f0f0, values should be rounded to 0 decimal places. The column 'Demand' should be values should be rounded to 3 decimal places. The column 'Revenue' should be aggregating using MAX function, y-axis values should be visible, filled with color #f8b0y1, tooltip should display 'Tooltip Label', values should be prefixed with '$'. The column 'coordinate_lg' should be aggregating using COUNT function, filled with color #1d3b7a, lowest values should be colored #f0f0f0, values should be rounded to 2 decimal places.",
    "input": "{\"dataSources\":[{\"dataSourceId\":\"ds-3602\",\"queryKey\":\"API:+auto-task$$auto-task_80\",\"cols\":[{\"jsonName\":\"Region\",\"type\":\"string\"},{\"jsonName\":\"Order Date\",\"type\":\"date\"},{\"jsonName\":\"Discount\",\"type\":\"number\"},{\"jsonName\":\"SubCategory\",\"type\":\"string\"},{\"jsonName\":\"Mega_watt\",\"type\":\"number\"},{\"jsonName\":\"Place\",\"type\":\"string\"},{\"jsonName\":\"Demand\",\"type\":\"number\"},{\"jsonName\":\"Revenue\",\"type\":\"number\"},{\"jsonName\":\"coordinate_lg\",\"type\":\"number\"}],\"params\":[]}]}",
    "output": "{\n    \"dataSources\": [\n        {\n            \"dataSourceId\": \"ds-3602\",\n            \"queryKey\": \"API:+auto-task$$auto-task_80\",\n            \"cols\": [\n                {\n                    \"jsonName\": \"Region\",\n                    \"type\": \"string\"\n                },\n                {\n                    \"jsonName\": \"Order Date\",\n                    \"type\": \"date\"\n                },\n                {\n                    \"jsonName\": \"Discount\",\n                    \"type\": \"number\",\n                    \"aggFn\": \"COUNT\",\n                    \"isYAxisValueVisible\": false,\n                    \"fillColor\": \"#f0f0f0\",\n                    \"fillHighestColor\": \"#99ff95\",\n                    \"fillLowestColor\": \"#1d3b7a\",\n                    \"decimalPlaces\": 1,\n                    \"prefix\": \"*\"\n                },\n                {\n                    \"jsonName\": \"SubCategory\",\n                    \"type\": \"string\"\n                },\n                {\n                    \"jsonName\": \"Mega_watt\",\n                    \"type\": \"number\",\n                    \"aggFn\": \"AVG\",\n                    \"fillColor\": \"#99ff95\",\n                    \"fillLowestColor\": \"#f0f0f0\",\n                    \"decimalPlaces\": 0\n                },\n                {\n                    \"jsonName\": \"Place\",\n                    \"type\": \"string\"\n                },\n                {\n                    \"jsonName\": \"Demand\",\n                    \"type\": \"number\",\n                    \"decimalPlaces\": 3\n                },\n                {\n                    \"jsonName\": \"Revenue\",\n                    \"type\": \"number\",\n                    \"aggFn\": \"MAX\",\n                    \"isYAxisValueVisible\": true,\n                    \"fillColor\": \"#f8b0y1\",\n                    \"label\": \"Tooltip Label\",\n                    \"prefix\": \"$\"\n                },\n                {\n                    \"jsonName\": \"coordinate_lg\",\n                    \"type\": \"number\",\n                    \"aggFn\": \"COUNT\",\n                    \"fillColor\": \"#1d3b7a\",\n                    \"fillLowestColor\": \"#f0f0f0\",\n                    \"decimalPlaces\": 2\n                }\n            ],\n            \"params\": []\n        }\n    ],\n    \"chartLayout\": \"vertical\",\n    \"attributes\": {\n        \"chartType\": \"TimeLine Chart\",\n        \"sortOrder\": \"Asc\",\n        \"slider\": true,\n        \"saveImage\": true\n    },\n    \"chartName\": \"Chart Example 49\",\n    \"xAxis\": {\n        \"fields\": [\n            \"Order Date\"\n        ],\n        \"label\": \"Axis Label\"\n    },\n    \"yAxis\": {\n        \"fields\": [\n            \"Discount\"\n        ]\n    }\n}"
  },
  {
    "instruction": "Create a Line Chart chart named 'Chart Example 50' plotting 'Mega_watt' against 'Customer'. The data should be sorted in asc order and displayed using a horizontal layout. A secondary Y-axis is included, representing 'Revenue'. The y-axis should be labeled as 'Axis Label' The secondary Y-axis should be labeled as 'Axis Label' with a name gap of 43 pixels. The column 'Mega_watt' should be aggregating using COUNT function, highest values should be colored #1d3b7a, lowest values should be colored #99ff95, tooltip should display 'Tooltip Label', values should be rounded to 2 decimal places, values should be suffixed with 'USD'. The column 'coordinate_lg' should be highest values should be colored #1d3b7a, values should be rounded to 0 decimal places. The column 'latitude' should be aggregating using SUM function, filled with color #866666, highest values should be colored #866666, tooltip should display 'Tooltip Label', values should be rounded to 2 decimal places, values should be prefixed with '₹'. The column 'Revenue' should be aggregating using AVG function, values should be rounded to 0 decimal places. The column 'Profit' should be aggregating using MIN function, y-axis values should be visible, highest values should be colored #f8b0y1, values should be rounded to 0 decimal places, values should be prefixed with '$'. The column 'longitude' should be aggregating using AVG function, highest values should be colored #f8b0y1, lowest values should be colored #f0f0f0, tooltip should display 'Tooltip Label'. The column 'coordinate_lt' should be aggregating using AVG function, highest values should be colored #1d3b7a, values should be rounded to 2 decimal places.",
    "input": "{\"dataSources\":[{\"dataSourceId\":\"ds-5443\",\"queryKey\":\"API:+jdbc$$aws$$_67\",\"cols\":[{\"jsonName\":\"Mega_watt\",\"type\":\"number\"},{\"jsonName\":\"coordinate_lg\",\"type\":\"number\"},{\"jsonName\":\"latitude\",\"type\":\"number\"},{\"jsonName\":\"Revenue\",\"type\":\"number\"},{\"jsonName\":\"Customer\",\"type\":\"string\"},{\"jsonName\":\"Profit\",\"type\":\"number\"},{\"jsonName\":\"longitude\",\"type\":\"number\"},{\"jsonName\":\"SubCategory\",\"type\":\"string\"},{\"jsonName\":\"Category\",\"type\":\"string\"},{\"jsonName\":\"coordinate_lt\",\"type\":\"number\"}],\"params\":[]}]}",
    "output": "{\n    \"dataSources\": [\n        {\n            \"dataSourceId\": \"ds-5443\",\n            \"queryKey\": \"API:+jdbc$$aws$$_67\",\n            \"cols\": [\n                {\n                    \"jsonName\": \"Mega_watt\",\n                    \"type\": \"number\",\n                    \"aggFn\": \"COUNT\",\n                    \"fillHighestColor\": \"#1d3b7a\",\n                    \"fillLowestColor\": \"#99ff95\",\n                    \"label\": \"Tooltip Label\",\n                    \"decimalPlaces\": 2,\n                    \"suffix\": \"USD\"\n                },\n                {\n                    \"jsonName\": \"coordinate_lg\",\n                    \"type\": \"number\",\n                    \"fillHighestColor\": \"#1d3b7a\",\n                    \"decimalPlaces\": 0\n                },\n                {\n                    \"jsonName\": \"latitude\",\n                    \"type\": \"number\",\n                    \"aggFn\": \"SUM\",\n                    \"fillColor\": \"#866666\",\n                    \"fillHighestColor\": \"#866666\",\n                    \"label\": \"Tooltip Label\",\n                    \"decimalPlaces\": 2,\n                    \"prefix\": \"\\u20b9\"\n                },\n                {\n                    \"jsonName\": \"Revenue\",\n                    \"type\": \"number\",\n                    \"aggFn\": \"AVG\",\n                    \"decimalPlaces\": 0\n                },\n                {\n                    \"jsonName\": \"Customer\",\n                    \"type\": \"string\"\n                },\n                {\n                    \"jsonName\": \"Profit\",\n                    \"type\": \"number\",\n                    \"aggFn\": \"MIN\",\n                    \"isYAxisValueVisible\": true,\n                    \"fillHighestColor\": \"#f8b0y1\",\n                    \"decimalPlaces\": 0,\n                    \"prefix\": \"$\"\n                },\n                {\n                    \"jsonName\": \"longitude\",\n                    \"type\": \"number\",\n                    \"aggFn\": \"AVG\",\n                    \"fillHighestColor\": \"#f8b0y1\",\n                    \"fillLowestColor\": \"#f0f0f0\",\n                    \"label\": \"Tooltip Label\"\n                },\n                {\n                    \"jsonName\": \"SubCategory\",\n                    \"type\": \"string\"\n                },\n                {\n                    \"jsonName\": \"Category\",\n                    \"type\": \"string\"\n                },\n                {\n                    \"jsonName\": \"coordinate_lt\",\n                    \"type\": \"number\",\n                    \"aggFn\": \"AVG\",\n                    \"fillHighestColor\": \"#1d3b7a\",\n                    \"decimalPlaces\": 2\n                }\n            ],\n            \"params\": []\n        }\n    ],\n    \"chartLayout\": \"horizontal\",\n    \"attributes\": {\n        \"chartType\": \"Line Chart\",\n        \"sortOrder\": \"Asc\",\n        \"slider\": true,\n        \"saveImage\": true,\n        \"referenceLines\": [\n            {\n                \"referenceValueSource\": \"FIXED\",\n                \"referenceFor\": \"Revenue\",\n                \"referenceLabel\": \"Label Revenue\",\n                \"referenceLineColor\": \"#f8b0y1\",\n                \"referenceValue\": \"491\",\n                \"showValue\": false\n            }\n        ]\n    },\n    \"chartName\": \"Chart Example 50\",\n    \"xAxis\": {\n        \"fields\": [\n            \"Customer\"\n        ]\n    },\n    \"yAxis\": {\n        \"fields\": [\n            \"Mega_watt\"\n        ],\n        \"label\": \"Axis Label\"\n    },\n    \"secondaryYAxis\": {\n        \"fields\": [\n            \"Revenue\"\n        ],\n        \"label\": \"Axis Label\",\n        \"nameGap\": 43\n    }\n}"
  },
  {
    "instruction": "Create a Bar Chart chart named 'Chart Example 51' plotting 'Profit' against 'Region'. Legend 'Customer' field has to there. The data should be sorted in asc order and displayed using a horizontal layout. The x-axis should be labeled as 'Axis Label' and positioned at 'end' The column 'Mega_watt' should be aggregating using MAX function, highest values should be colored #866666, tooltip should display 'Tooltip Label', values should be rounded to 2 decimal places, values should be prefixed with '#'. The column 'coordinate_lg' should be aggregating using AVG function, lowest values should be colored #99ff95. The column 'Profit' should be aggregating using AVG function, highest values should be colored #f8b0y1, lowest values should be colored #1d3b7a, values should be rounded to 1 decimal places, values should be suffixed with 'MW'. The column 'Price' should be tooltip should display 'Tooltip Label', values should be rounded to 1 decimal places, values should be prefixed with '$'.",
    "input": "{\"dataSources\":[{\"dataSourceId\":\"ds-3095\",\"queryKey\":\"API:+jdbc$$dataService$$_4\",\"cols\":[{\"jsonName\":\"Mega_watt\",\"type\":\"number\"},{\"jsonName\":\"coordinate_lg\",\"type\":\"number\"},{\"jsonName\":\"SubCategory\",\"type\":\"string\"},{\"jsonName\":\"Profit\",\"type\":\"number\"},{\"jsonName\":\"Price\",\"type\":\"number\"},{\"jsonName\":\"Country\",\"type\":\"string\"},{\"jsonName\":\"Customer\",\"type\":\"string\"},{\"jsonName\":\"Region\",\"type\":\"string\"}],\"params\":[]}]}",
    "output": "{\n    \"dataSources\": [\n        {\n            \"dataSourceId\": \"ds-3095\",\n            \"queryKey\": \"API:+jdbc$$dataService$$_4\",\n            \"cols\": [\n                {\n                    \"jsonName\": \"Mega_watt\",\n                    \"type\": \"number\",\n                    \"aggFn\": \"MAX\",\n                    \"fillHighestColor\": \"#866666\",\n                    \"label\": \"Tooltip Label\",\n                    \"decimalPlaces\": 2,\n                    \"prefix\": \"#\"\n                },\n                {\n                    \"jsonName\": \"coordinate_lg\",\n                    \"type\": \"number\",\n                    \"aggFn\": \"AVG\",\n                    \"fillLowestColor\": \"#99ff95\"\n                },\n                {\n                    \"jsonName\": \"SubCategory\",\n                    \"type\": \"string\"\n                },\n                {\n                    \"jsonName\": \"Profit\",\n                    \"type\": \"number\",\n                    \"aggFn\": \"AVG\",\n                    \"fillHighestColor\": \"#f8b0y1\",\n                    \"fillLowestColor\": \"#1d3b7a\",\n                    \"decimalPlaces\": 1,\n                    \"suffix\": \"MW\"\n                },\n                {\n                    \"jsonName\": \"Price\",\n                    \"type\": \"number\",\n                    \"label\": \"Tooltip Label\",\n                    \"decimalPlaces\": 1,\n                    \"prefix\": \"$\"\n                },\n                {\n                    \"jsonName\": \"Country\",\n                    \"type\": \"string\"\n                },\n                {\n                    \"jsonName\": \"Customer\",\n                    \"type\": \"string\"\n                },\n                {\n                    \"jsonName\": \"Region\",\n                    \"type\": \"string\"\n                }\n            ],\n            \"params\": []\n        }\n    ],\n    \"chartLayout\": \"horizontal\",\n    \"attributes\": {\n        \"chartType\": \"Bar Chart\",\n        \"sortOrder\": \"Asc\",\n        \"slider\": true,\n        \"saveImage\": true,\n        \"legend\": {\n            \"fields\": \"Customer\",\n            \"colors\": {}\n        }\n    },\n    \"chartName\": \"Chart Example 51\",\n    \"xAxis\": {\n        \"fields\": [\n            \"Region\"\n        ],\n        \"label\": \"Axis Label\",\n        \"nameLocation\": \"end\"\n    },\n    \"yAxis\": {\n        \"fields\": [\n            \"Profit\"\n        ]\n    }\n}"
  },
  {
    "instruction": "Create a Line Chart chart named 'Chart Example 52' plotting 'Generation' against 'Country'. The data should be sorted in desc order and displayed using a vertical layout. A secondary Y-axis is included, representing 'Mega_watt'. The x-axis should be labeled as 'Axis Label' and positioned at 'start' with a name gap of 33 pixels. The y-axis should be labeled as 'Axis Label' with a name gap of 48 pixels. The column 'coordinate_lt' should be aggregating using AVG function, highest values should be colored #866666, values should be rounded to 0 decimal places, values should be suffixed with '%'. The column 'Mega_watt' should be aggregating using MIN function, y-axis values should be visible, filled with color #f0f0f0, highest values should be colored #866666, values should be rounded to 0 decimal places, values should be prefixed with '$'. The column 'latitude' should be aggregating using SUM function, lowest values should be colored #99ff95, values should be rounded to 3 decimal places. The column 'Generation' should be aggregating using AVG function, values should be rounded to 0 decimal places, values should be prefixed with '*'. The column 'Price' should be y-axis values should be hidden, filled with color #1d3b7a, lowest values should be colored #866666, tooltip should display 'Tooltip Label'.",
    "input": "{\"dataSources\":[{\"dataSourceId\":\"ds-1052\",\"queryKey\":\"API:+jdbc$$TEMP$$us_station_city_geo_data_31\",\"cols\":[{\"jsonName\":\"coordinate_lt\",\"type\":\"number\"},{\"jsonName\":\"Mega_watt\",\"type\":\"number\"},{\"jsonName\":\"location\",\"type\":\"string\"},{\"jsonName\":\"Order Date\",\"type\":\"date\"},{\"jsonName\":\"latitude\",\"type\":\"number\"},{\"jsonName\":\"Generation\",\"type\":\"number\"},{\"jsonName\":\"Price\",\"type\":\"number\"},{\"jsonName\":\"Country\",\"type\":\"string\"}],\"params\":[]}]}",
    "output": "{\n    \"dataSources\": [\n        {\n            \"dataSourceId\": \"ds-1052\",\n            \"queryKey\": \"API:+jdbc$$TEMP$$us_station_city_geo_data_31\",\n            \"cols\": [\n                {\n                    \"jsonName\": \"coordinate_lt\",\n                    \"type\": \"number\",\n                    \"aggFn\": \"AVG\",\n                    \"fillHighestColor\": \"#866666\",\n                    \"decimalPlaces\": 0,\n                    \"suffix\": \"%\"\n                },\n                {\n                    \"jsonName\": \"Mega_watt\",\n                    \"type\": \"number\",\n                    \"aggFn\": \"MIN\",\n                    \"isYAxisValueVisible\": true,\n                    \"fillColor\": \"#f0f0f0\",\n                    \"fillHighestColor\": \"#866666\",\n                    \"decimalPlaces\": 0,\n                    \"prefix\": \"$\"\n                },\n                {\n                    \"jsonName\": \"location\",\n                    \"type\": \"string\"\n                },\n                {\n                    \"jsonName\": \"Order Date\",\n                    \"type\": \"date\"\n                },\n                {\n                    \"jsonName\": \"latitude\",\n                    \"type\": \"number\",\n                    \"aggFn\": \"SUM\",\n                    \"fillLowestColor\": \"#99ff95\",\n                    \"decimalPlaces\": 3\n                },\n                {\n                    \"jsonName\": \"Generation\",\n                    \"type\": \"number\",\n                    \"aggFn\": \"AVG\",\n                    \"decimalPlaces\": 0,\n                    \"prefix\": \"*\"\n                },\n                {\n                    \"jsonName\": \"Price\",\n                    \"type\": \"number\",\n                    \"isYAxisValueVisible\": false,\n                    \"fillColor\": \"#1d3b7a\",\n                    \"fillLowestColor\": \"#866666\",\n                    \"label\": \"Tooltip Label\"\n                },\n                {\n                    \"jsonName\": \"Country\",\n                    \"type\": \"string\"\n                }\n            ],\n            \"params\": []\n        }\n    ],\n    \"chartLayout\": \"vertical\",\n    \"attributes\": {\n        \"chartType\": \"Line Chart\",\n        \"sortOrder\": \"Desc\",\n        \"slider\": true,\n        \"saveImage\": true\n    },\n    \"chartName\": \"Chart Example 52\",\n    \"xAxis\": {\n        \"fields\": [\n            \"Country\"\n        ],\n        \"label\": \"Axis Label\",\n        \"nameLocation\": \"start\",\n        \"nameGap\": 33\n    },\n    \"yAxis\": {\n        \"fields\": [\n            \"Generation\"\n        ],\n        \"label\": \"Axis Label\",\n        \"nameGap\": 48\n    },\n    \"secondaryYAxis\": {\n        \"fields\": [\n            \"Mega_watt\"\n        ]\n    }\n}"
  },
  {
    "instruction": "Create a Area Chart chart named 'Chart Example 53' plotting 'Price' against 'Region'. The data should be sorted in asc order and displayed using a vertical layout. The column 'Price' should be y-axis values should be hidden, highest values should be colored #866666, tooltip should display 'Tooltip Label', values should be rounded to 2 decimal places, values should be prefixed with '₹'. The column 'longitude' should be y-axis values should be hidden, tooltip should display 'Tooltip Label', values should be rounded to 0 decimal places, values should be suffixed with 'p'. The column 'Profit' should be y-axis values should be hidden, tooltip should display 'Tooltip Label', values should be rounded to 3 decimal places, values should be prefixed with '$'. The column 'latitude' should be filled with color #f0f0f0, values should be rounded to 1 decimal places, values should be prefixed with '#'. The column 'Discount' should be highest values should be colored #99ff95, lowest values should be colored #f8b0y1, tooltip should display 'Tooltip Label', values should be rounded to 3 decimal places. The column 'coordinate_lt' should be y-axis values should be visible, filled with color #1d3b7a, lowest values should be colored #1d3b7a, tooltip should display 'Tooltip Label', values should be rounded to 2 decimal places.",
    "input": "{\"dataSources\":[{\"dataSourceId\":\"ds-5697\",\"queryKey\":\"API:+auto-task$$auto_27\",\"cols\":[{\"jsonName\":\"Place\",\"type\":\"string\"},{\"jsonName\":\"Price\",\"type\":\"number\"},{\"jsonName\":\"Region\",\"type\":\"string\"},{\"jsonName\":\"longitude\",\"type\":\"number\"},{\"jsonName\":\"Profit\",\"type\":\"number\"},{\"jsonName\":\"latitude\",\"type\":\"number\"},{\"jsonName\":\"Discount\",\"type\":\"number\"},{\"jsonName\":\"coordinate_lt\",\"type\":\"number\"}],\"params\":[]}]}",
    "output": "{\n    \"dataSources\": [\n        {\n            \"dataSourceId\": \"ds-5697\",\n            \"queryKey\": \"API:+auto-task$$auto_27\",\n            \"cols\": [\n                {\n                    \"jsonName\": \"Place\",\n                    \"type\": \"string\"\n                },\n                {\n                    \"jsonName\": \"Price\",\n                    \"type\": \"number\",\n                    \"isYAxisValueVisible\": false,\n                    \"fillHighestColor\": \"#866666\",\n                    \"label\": \"Tooltip Label\",\n                    \"decimalPlaces\": 2,\n                    \"prefix\": \"\\u20b9\"\n                },\n                {\n                    \"jsonName\": \"Region\",\n                    \"type\": \"string\"\n                },\n                {\n                    \"jsonName\": \"longitude\",\n                    \"type\": \"number\",\n                    \"isYAxisValueVisible\": false,\n                    \"label\": \"Tooltip Label\",\n                    \"decimalPlaces\": 0,\n                    \"suffix\": \"p\"\n                },\n                {\n                    \"jsonName\": \"Profit\",\n                    \"type\": \"number\",\n                    \"isYAxisValueVisible\": false,\n                    \"label\": \"Tooltip Label\",\n                    \"decimalPlaces\": 3,\n                    \"prefix\": \"$\"\n                },\n                {\n                    \"jsonName\": \"latitude\",\n                    \"type\": \"number\",\n                    \"fillColor\": \"#f0f0f0\",\n                    \"decimalPlaces\": 1,\n                    \"prefix\": \"#\"\n                },\n                {\n                    \"jsonName\": \"Discount\",\n                    \"type\": \"number\",\n                    \"fillHighestColor\": \"#99ff95\",\n                    \"fillLowestColor\": \"#f8b0y1\",\n                    \"label\": \"Tooltip Label\",\n                    \"decimalPlaces\": 3\n                },\n                {\n                    \"jsonName\": \"coordinate_lt\",\n                    \"type\": \"number\",\n                    \"isYAxisValueVisible\": true,\n                    \"fillColor\": \"#1d3b7a\",\n                    \"fillLowestColor\": \"#1d3b7a\",\n                    \"label\": \"Tooltip Label\",\n                    \"decimalPlaces\": 2\n                }\n            ],\n            \"params\": []\n        }\n    ],\n    \"chartLayout\": \"vertical\",\n    \"attributes\": {\n        \"chartType\": \"Area Chart\",\n        \"sortOrder\": \"Asc\",\n        \"slider\": true,\n        \"saveImage\": true\n    },\n    \"chartName\": \"Chart Example 53\",\n    \"xAxis\": {\n        \"fields\": [\n            \"Region\"\n        ]\n    },\n    \"yAxis\": {\n        \"fields\": [\n            \"Price\"\n        ]\n    }\n}"
  },
  {
    "instruction": "Create a Bar Chart chart named 'Chart Example 54' plotting 'Profit' against 'SubCategory'. The data should be sorted in desc order and displayed using a vertical layout. The column 'latitude' should be aggregating using AVG function, lowest values should be colored #866666, tooltip should display 'Tooltip Label', values should be rounded to 3 decimal places, values should be prefixed with '$'. The column 'Profit' should be y-axis values should be visible, filled with color #f8b0y1, lowest values should be colored #866666, values should be rounded to 0 decimal places, values should be suffixed with 'p'. The column 'coordinate_lt' should be aggregating using MAX function, y-axis values should be hidden, tooltip should display 'Tooltip Label'.",
    "input": "{\"dataSources\":[{\"dataSourceId\":\"ds-8651\",\"queryKey\":\"API:+auto-task$$auto-task_72\",\"cols\":[{\"jsonName\":\"Customer\",\"type\":\"string\"},{\"jsonName\":\"Category\",\"type\":\"string\"},{\"jsonName\":\"Order Date\",\"type\":\"date\"},{\"jsonName\":\"latitude\",\"type\":\"number\"},{\"jsonName\":\"location\",\"type\":\"string\"},{\"jsonName\":\"SubCategory\",\"type\":\"string\"},{\"jsonName\":\"Profit\",\"type\":\"number\"},{\"jsonName\":\"coordinate_lt\",\"type\":\"number\"}],\"params\":[]}]}",
    "output": "{\n    \"dataSources\": [\n        {\n            \"dataSourceId\": \"ds-8651\",\n            \"queryKey\": \"API:+auto-task$$auto-task_72\",\n            \"cols\": [\n                {\n                    \"jsonName\": \"Customer\",\n                    \"type\": \"string\"\n                },\n                {\n                    \"jsonName\": \"Category\",\n                    \"type\": \"string\"\n                },\n                {\n                    \"jsonName\": \"Order Date\",\n                    \"type\": \"date\"\n                },\n                {\n                    \"jsonName\": \"latitude\",\n                    \"type\": \"number\",\n                    \"aggFn\": \"AVG\",\n                    \"fillLowestColor\": \"#866666\",\n                    \"label\": \"Tooltip Label\",\n                    \"decimalPlaces\": 3,\n                    \"prefix\": \"$\"\n                },\n                {\n                    \"jsonName\": \"location\",\n                    \"type\": \"string\"\n                },\n                {\n                    \"jsonName\": \"SubCategory\",\n                    \"type\": \"string\"\n                },\n                {\n                    \"jsonName\": \"Profit\",\n                    \"type\": \"number\",\n                    \"isYAxisValueVisible\": true,\n                    \"fillColor\": \"#f8b0y1\",\n                    \"fillLowestColor\": \"#866666\",\n                    \"decimalPlaces\": 0,\n                    \"suffix\": \"p\"\n                },\n                {\n                    \"jsonName\": \"coordinate_lt\",\n                    \"type\": \"number\",\n                    \"aggFn\": \"MAX\",\n                    \"isYAxisValueVisible\": false,\n                    \"label\": \"Tooltip Label\"\n                }\n            ],\n            \"params\": []\n        }\n    ],\n    \"chartLayout\": \"vertical\",\n    \"attributes\": {\n        \"chartType\": \"Bar Chart\",\n        \"sortOrder\": \"Desc\",\n        \"slider\": true,\n        \"saveImage\": true,\n        \"referenceLines\": [\n            {\n                \"referenceValueSource\": \"FIXED\",\n                \"referenceFor\": \"Profit\",\n                \"referenceLabel\": \"Label Profit\",\n                \"referenceLineColor\": \"#f8b0y1\",\n                \"referenceValue\": \"868\",\n                \"showValue\": true\n            }\n        ]\n    },\n    \"chartName\": \"Chart Example 54\",\n    \"xAxis\": {\n        \"fields\": [\n            \"SubCategory\"\n        ]\n    },\n    \"yAxis\": {\n        \"fields\": [\n            \"Profit\"\n        ]\n    }\n}"
  },
  {
    "instruction": "Create a Tree Map chart named 'Chart Example 55' plotting 'Generation' against 'Region'. The data should be sorted in asc order and displayed using a horizontal layout. The x-axis should be labeled as 'Axis Label' with a name gap of 12 pixels. The column 'Profit' should be values should be rounded to 3 decimal places. The column 'coordinate_lt' should be aggregating using COUNT function, filled with color #f8b0y1, lowest values should be colored #f0f0f0, values should be rounded to 1 decimal places, values should be suffixed with '%'. The column 'Discount' should be aggregating using AVG function, highest values should be colored #f0f0f0, tooltip should display 'Tooltip Label', values should be prefixed with '@'. The column 'Generation' should be aggregating using MIN function, y-axis values should be visible, tooltip should display 'Tooltip Label', values should be prefixed with '#'.",
    "input": "{\"dataSources\":[{\"dataSourceId\":\"ds-1685\",\"queryKey\":\"API:+jdbc$$pmgr$$caps_23\",\"cols\":[{\"jsonName\":\"Category\",\"type\":\"string\"},{\"jsonName\":\"Country\",\"type\":\"string\"},{\"jsonName\":\"Profit\",\"type\":\"number\"},{\"jsonName\":\"Customer\",\"type\":\"string\"},{\"jsonName\":\"coordinate_lt\",\"type\":\"number\"},{\"jsonName\":\"Region\",\"type\":\"string\"},{\"jsonName\":\"Discount\",\"type\":\"number\"},{\"jsonName\":\"SubCategory\",\"type\":\"string\"},{\"jsonName\":\"Generation\",\"type\":\"number\"}],\"params\":[]}]}",
    "output": "{\n    \"dataSources\": [\n        {\n            \"dataSourceId\": \"ds-1685\",\n            \"queryKey\": \"API:+jdbc$$pmgr$$caps_23\",\n            \"cols\": [\n                {\n                    \"jsonName\": \"Category\",\n                    \"type\": \"string\"\n                },\n                {\n                    \"jsonName\": \"Country\",\n                    \"type\": \"string\"\n                },\n                {\n                    \"jsonName\": \"Profit\",\n                    \"type\": \"number\",\n                    \"decimalPlaces\": 3\n                },\n                {\n                    \"jsonName\": \"Customer\",\n                    \"type\": \"string\"\n                },\n                {\n                    \"jsonName\": \"coordinate_lt\",\n                    \"type\": \"number\",\n                    \"aggFn\": \"COUNT\",\n                    \"fillColor\": \"#f8b0y1\",\n                    \"fillLowestColor\": \"#f0f0f0\",\n                    \"decimalPlaces\": 1,\n                    \"suffix\": \"%\"\n                },\n                {\n                    \"jsonName\": \"Region\",\n                    \"type\": \"string\"\n                },\n                {\n                    \"jsonName\": \"Discount\",\n                    \"type\": \"number\",\n                    \"aggFn\": \"AVG\",\n                    \"fillHighestColor\": \"#f0f0f0\",\n                    \"label\": \"Tooltip Label\",\n                    \"prefix\": \"@\"\n                },\n                {\n                    \"jsonName\": \"SubCategory\",\n                    \"type\": \"string\"\n                },\n                {\n                    \"jsonName\": \"Generation\",\n                    \"type\": \"number\",\n                    \"aggFn\": \"MIN\",\n                    \"isYAxisValueVisible\": true,\n                    \"label\": \"Tooltip Label\",\n                    \"prefix\": \"#\"\n                }\n            ],\n            \"params\": []\n        }\n    ],\n    \"chartLayout\": \"horizontal\",\n    \"attributes\": {\n        \"chartType\": \"Tree Map\",\n        \"sortOrder\": \"Asc\",\n        \"slider\": true,\n        \"saveImage\": true\n    },\n    \"chartName\": \"Chart Example 55\",\n    \"xAxis\": {\n        \"fields\": [\n            \"Region\"\n        ],\n        \"label\": \"Axis Label\",\n        \"nameGap\": 12\n    },\n    \"yAxis\": {\n        \"fields\": [\n            \"Generation\"\n        ]\n    }\n}"
  },
  {
    "instruction": "Create a Pie Chart chart named 'Chart Example 56' plotting 'Cost' against 'location'. The data should be sorted in desc order and displayed using a horizontal layout. The x-axis should be labeled as 'Axis Label' with a name gap of 11 pixels. It is rotated by 112 degree The column 'Discount' should be aggregating using MIN function, values should be rounded to 0 decimal places. The column 'Cost' should be values should be prefixed with '#'. The column 'Revenue' should be aggregating using MIN function, values should be rounded to 3 decimal places, values should be prefixed with '*'. The column 'Sales' should be filled with color #f8b0y1, values should be rounded to 0 decimal places, values should be prefixed with '@'.",
    "input": "{\"dataSources\":[{\"dataSourceId\":\"ds-4247\",\"queryKey\":\"API:+jdbc$$aws$$_59\",\"cols\":[{\"jsonName\":\"Employee\",\"type\":\"string\"},{\"jsonName\":\"Discount\",\"type\":\"number\"},{\"jsonName\":\"Cost\",\"type\":\"number\"},{\"jsonName\":\"Place\",\"type\":\"string\"},{\"jsonName\":\"Revenue\",\"type\":\"number\"},{\"jsonName\":\"Sales\",\"type\":\"number\"},{\"jsonName\":\"location\",\"type\":\"string\"}],\"params\":[]}]}",
    "output": "{\n    \"dataSources\": [\n        {\n            \"dataSourceId\": \"ds-4247\",\n            \"queryKey\": \"API:+jdbc$$aws$$_59\",\n            \"cols\": [\n                {\n                    \"jsonName\": \"Employee\",\n                    \"type\": \"string\"\n                },\n                {\n                    \"jsonName\": \"Discount\",\n                    \"type\": \"number\",\n                    \"aggFn\": \"MIN\",\n                    \"decimalPlaces\": 0\n                },\n                {\n                    \"jsonName\": \"Cost\",\n                    \"type\": \"number\",\n                    \"prefix\": \"#\"\n                },\n                {\n                    \"jsonName\": \"Place\",\n                    \"type\": \"string\"\n                },\n                {\n                    \"jsonName\": \"Revenue\",\n                    \"type\": \"number\",\n                    \"aggFn\": \"MIN\",\n                    \"decimalPlaces\": 3,\n                    \"prefix\": \"*\"\n                },\n                {\n                    \"jsonName\": \"Sales\",\n                    \"type\": \"number\",\n                    \"fillColor\": \"#f8b0y1\",\n                    \"decimalPlaces\": 0,\n                    \"prefix\": \"@\"\n                },\n                {\n                    \"jsonName\": \"location\",\n                    \"type\": \"string\"\n                }\n            ],\n            \"params\": []\n        }\n    ],\n    \"chartLayout\": \"horizontal\",\n    \"attributes\": {\n        \"chartType\": \"Pie Chart\",\n        \"sortOrder\": \"Desc\",\n        \"slider\": true,\n        \"saveImage\": true,\n        \"chartSubType\": \"normal\",\n        \"rotation\": 112\n},\n    \"chartName\": \"Chart Example 56\",\n    \"xAxis\": {\n        \"fields\": [\n            \"location\"\n        ],\n        \"label\": \"Axis Label\",\n        \"nameGap\": 11\n    },\n    \"yAxis\": {\n        \"fields\": [\n            \"Cost\"\n        ]\n    }\n}"
  },
  {
    "instruction": "Create a Composed Chart chart named 'Chart Example 58' plotting 'Mega_watt' against 'Category'. The data should be sorted in desc order and displayed using a vertical layout. The y-axis should be labeled as 'Axis Label' and positioned at 'center' The column 'coordinate_lg' should be aggregating using AVG function, filled with color #f0f0f0, tooltip should display 'Tooltip Label', values should be rounded to 3 decimal places, values should be prefixed with '@'. The column 'Mega_watt' should be aggregating using MIN function, y-axis values should be hidden, tooltip should display 'Tooltip Label', values should be rounded to 2 decimal places. The column 'Revenue' should be aggregating using AVG function, y-axis values should be hidden, highest values should be colored #f0f0f0, values should be suffixed with 'p'. The column 'Profit' should be highest values should be colored #f0f0f0, tooltip should display 'Tooltip Label', values should be suffixed with '%'. The column 'coordinate_lt' should be aggregating using AVG function, filled with color #99ff95, lowest values should be colored #99ff95, values should be rounded to 1 decimal places, values should be prefixed with '$'. The column 'Discount' should be tooltip should display 'Tooltip Label', values should be rounded to 3 decimal places, values should be suffixed with '%'.",
    "input": "{\"dataSources\":[{\"dataSourceId\":\"ds-5657\",\"queryKey\":\"API:+jdbc$$pmgr$$caps_70\",\"cols\":[{\"jsonName\":\"coordinate_lg\",\"type\":\"number\"},{\"jsonName\":\"Mega_watt\",\"type\":\"number\"},{\"jsonName\":\"Category\",\"type\":\"string\"},{\"jsonName\":\"Revenue\",\"type\":\"number\"},{\"jsonName\":\"Profit\",\"type\":\"number\"},{\"jsonName\":\"Employee\",\"type\":\"string\"},{\"jsonName\":\"coordinate_lt\",\"type\":\"number\"},{\"jsonName\":\"Discount\",\"type\":\"number\"},{\"jsonName\":\"Place\",\"type\":\"string\"}],\"params\":[]}]}",
    "output": "{\n    \"dataSources\": [\n        {\n            \"dataSourceId\": \"ds-5657\",\n            \"queryKey\": \"API:+jdbc$$pmgr$$caps_70\",\n            \"cols\": [\n                {\n                    \"jsonName\": \"coordinate_lg\",\n                    \"type\": \"number\",\n                    \"aggFn\": \"AVG\",\n                    \"fillColor\": \"#f0f0f0\",\n                    \"label\": \"Tooltip Label\",\n                    \"decimalPlaces\": 3,\n                    \"prefix\": \"@\"\n                },\n                {\n                    \"jsonName\": \"Mega_watt\",\n                    \"type\": \"number\",\n                    \"composedChartType\": \"Bar Chart\",\n                   \"aggFn\": \"MIN\",\n                    \"isYAxisValueVisible\": false,\n                    \"label\": \"Tooltip Label\",\n                    \"decimalPlaces\": 2\n                },\n                {\n                    \"jsonName\": \"Category\",\n                    \"type\": \"string\"\n                },\n                {\n                    \"jsonName\": \"Revenue\",\n                    \"type\": \"number\",\n                    \"aggFn\": \"AVG\",\n                    \"isYAxisValueVisible\": false,\n                    \"fillHighestColor\": \"#f0f0f0\",\n                    \"suffix\": \"p\"\n                },\n                {\n                    \"jsonName\": \"Profit\",\n                    \"type\": \"number\",\n                    \"fillHighestColor\": \"#f0f0f0\",\n                    \"label\": \"Tooltip Label\",\n                    \"suffix\": \"%\"\n                },\n                {\n                    \"jsonName\": \"Employee\",\n                    \"type\": \"string\"\n                },\n                {\n                    \"jsonName\": \"coordinate_lt\",\n                    \"type\": \"number\",\n                    \"aggFn\": \"AVG\",\n                    \"fillColor\": \"#99ff95\",\n                    \"fillLowestColor\": \"#99ff95\",\n                    \"decimalPlaces\": 1,\n                    \"prefix\": \"$\"\n                },\n                {\n                    \"jsonName\": \"Discount\",\n                    \"type\": \"number\",\n                    \"label\": \"Tooltip Label\",\n                    \"decimalPlaces\": 3,\n                    \"suffix\": \"%\"\n                },\n                {\n                    \"jsonName\": \"Place\",\n                    \"type\": \"string\"\n                }\n            ],\n            \"params\": []\n        }\n    ],\n    \"chartLayout\": \"vertical\",\n    \"attributes\": {\n        \"chartType\": \"Composed Chart\",\n        \"sortOrder\": \"Desc\",\n        \"slider\": true,\n        \"saveImage\": true\n    },\n    \"chartName\": \"Chart Example 58\",\n    \"xAxis\": {\n        \"fields\": [\n            \"Category\"\n        ]\n    },\n    \"yAxis\": {\n        \"fields\": [\n            \"Mega_watt\"\n        ],\n        \"label\": \"Axis Label\",\n        \"nameLocation\": \"center\"\n    }\n}"
  },
  {
    "instruction": "Create a Geo Chart chart named 'Chart Example 59' plotting 'N/A' against 'N/A'. The data should be sorted in desc order and displayed using a vertical layout. The column 'Demand' should be aggregating using COUNT function, values should be rounded to 3 decimal places, values should be suffixed with 'USD'. The column 'latitude' should be aggregating using COUNT function, highest values should be colored #866666, lowest values should be colored #f0f0f0, tooltip should display 'Tooltip Label', values should be prefixed with '$'. The column 'Sales' should be aggregating using MIN function, lowest values should be colored #f0f0f0, tooltip should display 'Tooltip Label', values should be rounded to 3 decimal places, values should be prefixed with '#'. The column 'coordinate_lg' should be aggregating using AVG function, filled with color #99ff95, lowest values should be colored #99ff95, tooltip should display 'Tooltip Label', values should be rounded to 3 decimal places, values should be suffixed with 'p'.",
    "input": "{\"dataSources\":[{\"dataSourceId\":\"ds-8179\",\"queryKey\":\"API:+jdbc$$TEMP$$us_station_city_geo_data_31\",\"cols\":[{\"jsonName\":\"Demand\",\"type\":\"number\"},{\"jsonName\":\"Category\",\"type\":\"string\"},{\"jsonName\":\"SubCategory\",\"type\":\"string\"},{\"jsonName\":\"latitude\",\"type\":\"number\"},{\"jsonName\":\"Place\",\"type\":\"string\"},{\"jsonName\":\"Country\",\"type\":\"string\"},{\"jsonName\":\"Employee\",\"type\":\"string\"},{\"jsonName\":\"location\",\"type\":\"string\"},{\"jsonName\":\"Sales\",\"type\":\"number\"},{\"jsonName\":\"coordinate_lg\",\"type\":\"number\"}],\"params\":[]}]}",
    "output": "{\n    \"dataSources\": [\n        {\n            \"dataSourceId\": \"ds-8179\",\n            \"queryKey\": \"API:+jdbc$$TEMP$$us_station_city_geo_data_31\",\n            \"cols\": [\n                {\n                    \"jsonName\": \"Demand\",\n                    \"type\": \"number\",\n                    \"aggFn\": \"COUNT\",\n                    \"decimalPlaces\": 3,\n                    \"suffix\": \"USD\"\n                },\n                {\n                    \"jsonName\": \"Category\",\n                    \"type\": \"string\"\n                },\n                {\n                    \"jsonName\": \"SubCategory\",\n                    \"type\": \"string\"\n                },\n                {\n                    \"jsonName\": \"latitude\",\n                    \"type\": \"number\",\n                    \"aggFn\": \"COUNT\",\n                    \"fillHighestColor\": \"#866666\",\n                    \"fillLowestColor\": \"#f0f0f0\",\n                    \"label\": \"Tooltip Label\",\n                    \"prefix\": \"$\"\n                },\n                {\n                    \"jsonName\": \"Place\",\n                    \"type\": \"string\"\n                },\n                {\n                    \"jsonName\": \"Country\",\n                    \"type\": \"string\"\n                },\n                {\n                    \"jsonName\": \"Employee\",\n                    \"type\": \"string\"\n                },\n                {\n                    \"jsonName\": \"location\",\n                    \"type\": \"string\"\n                },\n                {\n                    \"jsonName\": \"Sales\",\n                    \"type\": \"number\",\n                    \"aggFn\": \"MIN\",\n                    \"fillLowestColor\": \"#f0f0f0\",\n                    \"label\": \"Tooltip Label\",\n                    \"decimalPlaces\": 3,\n                    \"prefix\": \"#\"\n                },\n                {\n                    \"jsonName\": \"coordinate_lg\",\n                    \"type\": \"number\",\n                    \"aggFn\": \"AVG\",\n                    \"fillColor\": \"#99ff95\",\n                    \"fillLowestColor\": \"#99ff95\",\n                    \"label\": \"Tooltip Label\",\n                    \"decimalPlaces\": 3,\n                    \"suffix\": \"p\"\n                }\n            ],\n            \"params\": []\n        }\n    ],\n    \"chartLayout\": \"vertical\",\n    \"attributes\": {\n        \"chartType\": \"Geo Chart\",\n        \"sortOrder\": \"Desc\",\n        \"slider\": true,\n        \"saveImage\": true,\n        \"chartSubType\": \"map\"\n    },\n    \"chartName\": \"Chart Example 59\",\n    \"xAxis\": {},\n    \"yAxis\": {},\n    \"longitude\": {\n        \"fields\": [\n            \"coordinate_lg\"\n        ]\n    },\n    \"latitude\": {\n        \"fields\": [\n            \"latitude\"\n        ]\n    },\n    \"values\": {\n        \"fields\": [\n            \"Demand\"\n        ]\n    }\n}"
  },
  {
    "instruction": "Create a Scattered Chart chart named 'Chart Example 60' plotting 'Mega_watt' against 'SubCategory'. The data should be sorted in desc order and displayed using a horizontal layout. A Z-axis is also present, containing 'Price'. The y-axis should be labeled as 'Axis Label' and positioned at 'start' The column 'Price' should be aggregating using SUM function, filled with color #f8b0y1, values should be rounded to 2 decimal places, values should be prefixed with '*'. The column 'Cost' should be aggregating using COUNT function, lowest values should be colored #866666, tooltip should display 'Tooltip Label', values should be rounded to 3 decimal places, values should be prefixed with '@'. The column 'Mega_watt' should be highest values should be colored #f0f0f0, values should be prefixed with '@'. The column 'Generation' should be filled with color #99ff95, lowest values should be colored #866666, values should be suffixed with 'MW'. The column 'Revenue' should be aggregating using AVG function, y-axis values should be visible, tooltip should display 'Tooltip Label', values should be rounded to 1 decimal places, values should be prefixed with '@'.",
    "input": "{\"dataSources\":[{\"dataSourceId\":\"ds-2735\",\"queryKey\":\"API:+jdbc$$Oracle$$Energy_API_93\",\"cols\":[{\"jsonName\":\"Category\",\"type\":\"string\"},{\"jsonName\":\"location\",\"type\":\"string\"},{\"jsonName\":\"SubCategory\",\"type\":\"string\"},{\"jsonName\":\"Region\",\"type\":\"string\"},{\"jsonName\":\"Price\",\"type\":\"number\"},{\"jsonName\":\"Cost\",\"type\":\"number\"},{\"jsonName\":\"Mega_watt\",\"type\":\"number\"},{\"jsonName\":\"Generation\",\"type\":\"number\"},{\"jsonName\":\"Revenue\",\"type\":\"number\"}],\"params\":[]}]}",
    "output": "{\n    \"dataSources\": [\n        {\n            \"dataSourceId\": \"ds-2735\",\n            \"queryKey\": \"API:+jdbc$$Oracle$$Energy_API_93\",\n            \"cols\": [\n                {\n                    \"jsonName\": \"Category\",\n                    \"type\": \"string\"\n                },\n                {\n                    \"jsonName\": \"location\",\n                    \"type\": \"string\"\n                },\n                {\n                    \"jsonName\": \"SubCategory\",\n                    \"type\": \"string\"\n                },\n                {\n                    \"jsonName\": \"Region\",\n                    \"type\": \"string\"\n                },\n                {\n                    \"jsonName\": \"Price\",\n                    \"type\": \"number\",\n                    \"aggFn\": \"SUM\",\n                    \"fillColor\": \"#f8b0y1\",\n                    \"decimalPlaces\": 2,\n                    \"prefix\": \"*\"\n                },\n                {\n                    \"jsonName\": \"Cost\",\n                    \"type\": \"number\",\n                    \"aggFn\": \"COUNT\",\n                    \"fillLowestColor\": \"#866666\",\n                    \"label\": \"Tooltip Label\",\n                    \"decimalPlaces\": 3,\n                    \"prefix\": \"@\"\n                },\n                {\n                    \"jsonName\": \"Mega_watt\",\n                    \"type\": \"number\",\n                    \"fillHighestColor\": \"#f0f0f0\",\n                    \"prefix\": \"@\"\n                },\n                {\n                    \"jsonName\": \"Generation\",\n                    \"type\": \"number\",\n                    \"fillColor\": \"#99ff95\",\n                    \"fillLowestColor\": \"#866666\",\n                    \"suffix\": \"MW\"\n                },\n                {\n                    \"jsonName\": \"Revenue\",\n                    \"type\": \"number\",\n                    \"aggFn\": \"AVG\",\n                    \"isYAxisValueVisible\": true,\n                    \"label\": \"Tooltip Label\",\n                    \"decimalPlaces\": 1,\n                    \"prefix\": \"@\"\n                }\n            ],\n            \"params\": []\n        }\n    ],\n    \"chartLayout\": \"horizontal\",\n    \"attributes\": {\n        \"chartType\": \"Scattered Chart\",\n        \"sortOrder\": \"Desc\",\n        \"slider\": true,\n        \"saveImage\": true\n    },\n    \"chartName\": \"Chart Example 60\",\n    \"xAxis\": {\n        \"fields\": [\n            \"SubCategory\"\n        ]\n    },\n    \"yAxis\": {\n        \"fields\": [\n            \"Mega_watt\"\n        ],\n        \"label\": \"Axis Label\",\n        \"nameLocation\": \"start\"\n    },\n    \"zAxis\": {\n        \"fields\": [\n            \"Price\"\n        ]\n    }\n}"
  },
  {
    "instruction": "Create a Bar Chart chart named 'Chart Example 61' plotting 'Discount' against 'location'. The chart contains legend field 'Order Date'. The data should be sorted in asc order and displayed using a horizontal layout. The column 'coordinate_lt' should be highest values should be colored #f8b0y1, tooltip should display 'Tooltip Label', values should be rounded to 0 decimal places, values should be prefixed with '₹'. The column 'Discount' should be aggregating using MIN function, lowest values should be colored #99ff95, tooltip should display 'Tooltip Label', values should be prefixed with '*'. The column 'coordinate_lg' should be lowest values should be colored #f0f0f0, tooltip should display 'Tooltip Label', values should be rounded to 0 decimal places, values should be prefixed with '#'. The column 'Sales' should be aggregating using AVG function, tooltip should display 'Tooltip Label'. The column 'latitude' should be y-axis values should be visible, highest values should be colored #866666, lowest values should be colored #99ff95, values should be rounded to 1 decimal places, values should be suffixed with 'MW'.",
    "input": "{\"dataSources\":[{\"dataSourceId\":\"ds-4491\",\"queryKey\":\"API:+jdbc$$dataService$$_99\",\"cols\":[{\"jsonName\":\"location\",\"type\":\"string\"},{\"jsonName\":\"Region\",\"type\":\"string\"},{\"jsonName\":\"coordinate_lt\",\"type\":\"number\"},{\"jsonName\":\"Discount\",\"type\":\"number\"},{\"jsonName\":\"Country\",\"type\":\"string\"},{\"jsonName\":\"Order Date\",\"type\":\"date\"},{\"jsonName\":\"coordinate_lg\",\"type\":\"number\"},{\"jsonName\":\"Sales\",\"type\":\"number\"},{\"jsonName\":\"latitude\",\"type\":\"number\"}],\"params\":[]}]}",
    "output": "{\n    \"dataSources\": [\n        {\n            \"dataSourceId\": \"ds-4491\",\n            \"queryKey\": \"API:+jdbc$$dataService$$_99\",\n            \"cols\": [\n                {\n                    \"jsonName\": \"location\",\n                    \"type\": \"string\"\n                },\n                {\n                    \"jsonName\": \"Region\",\n                    \"type\": \"string\"\n                },\n                {\n                    \"jsonName\": \"coordinate_lt\",\n                    \"type\": \"number\",\n                    \"fillHighestColor\": \"#f8b0y1\",\n                    \"label\": \"Tooltip Label\",\n                    \"decimalPlaces\": 0,\n                    \"prefix\": \"\\u20b9\"\n                },\n                {\n                    \"jsonName\": \"Discount\",\n                    \"type\": \"number\",\n                    \"aggFn\": \"MIN\",\n                    \"fillLowestColor\": \"#99ff95\",\n                    \"label\": \"Tooltip Label\",\n                    \"prefix\": \"*\"\n                },\n                {\n                    \"jsonName\": \"Country\",\n                    \"type\": \"string\"\n                },\n                {\n                    \"jsonName\": \"Order Date\",\n                    \"type\": \"date\"\n                },\n                {\n                    \"jsonName\": \"coordinate_lg\",\n                    \"type\": \"number\",\n                    \"fillLowestColor\": \"#f0f0f0\",\n                    \"label\": \"Tooltip Label\",\n                    \"decimalPlaces\": 0,\n                    \"prefix\": \"#\"\n                },\n                {\n                    \"jsonName\": \"Sales\",\n                    \"type\": \"number\",\n                    \"aggFn\": \"AVG\",\n                    \"label\": \"Tooltip Label\"\n                },\n                {\n                    \"jsonName\": \"latitude\",\n                    \"type\": \"number\",\n                    \"isYAxisValueVisible\": true,\n                    \"fillHighestColor\": \"#866666\",\n                    \"fillLowestColor\": \"#99ff95\",\n                    \"decimalPlaces\": 1,\n                    \"suffix\": \"MW\"\n                }\n            ],\n            \"params\": []\n        }\n    ],\n    \"chartLayout\": \"horizontal\",\n    \"attributes\": {\n        \"chartType\": \"Bar Chart\",\n        \"sortOrder\": \"Asc\",\n        \"slider\": true,\n        \"saveImage\": true,\n        \"legend\": {\n            \"fields\": \"Order Date\",\n            \"colors\": {}\n        }\n    },\n    \"chartName\": \"Chart Example 61\",\n    \"xAxis\": {\n        \"fields\": [\n            \"location\"\n        ]\n    },\n    \"yAxis\": {\n        \"fields\": [\n            \"Discount\"\n        ]\n    }\n}"
  },
  {
    "instruction": "Create a Nightingale Pie Chart chart named 'Chart Example 62' plotting 'Price' against 'location'. The data should be sorted in desc order and displayed using a vertical layout. The y-axis should be labeled as 'Axis Label'. 259 degree rotated. The column 'Profit' should be aggregating using COUNT function, tooltip should display 'Tooltip Label', values should be rounded to 3 decimal places, values should be suffixed with 'USD'. The column 'Generation' should be filled with color #99ff95, lowest values should be colored #f0f0f0, tooltip should display 'Tooltip Label', values should be rounded to 3 decimal places, values should be prefixed with '₹'. The column 'Price' should be aggregating using SUM function, filled with color #1d3b7a.",
    "input": "{\"dataSources\":[{\"dataSourceId\":\"ds-4501\",\"queryKey\":\"API:+jdbc$$dataService$$_58\",\"cols\":[{\"jsonName\":\"Profit\",\"type\":\"number\"},{\"jsonName\":\"location\",\"type\":\"string\"},{\"jsonName\":\"Generation\",\"type\":\"number\"},{\"jsonName\":\"Place\",\"type\":\"string\"},{\"jsonName\":\"Region\",\"type\":\"string\"},{\"jsonName\":\"Price\",\"type\":\"number\"},{\"jsonName\":\"Employee\",\"type\":\"string\"}],\"params\":[]}]}",
    "output": "{\n    \"dataSources\": [\n        {\n            \"dataSourceId\": \"ds-4501\",\n            \"queryKey\": \"API:+jdbc$$dataService$$_58\",\n            \"cols\": [\n                {\n                    \"jsonName\": \"Profit\",\n                    \"type\": \"number\",\n                    \"aggFn\": \"COUNT\",\n                    \"label\": \"Tooltip Label\",\n                    \"decimalPlaces\": 3,\n                    \"suffix\": \"USD\"\n                },\n                {\n                    \"jsonName\": \"location\",\n                    \"type\": \"string\"\n                },\n                {\n                    \"jsonName\": \"Generation\",\n                    \"type\": \"number\",\n                    \"fillColor\": \"#99ff95\",\n                    \"fillLowestColor\": \"#f0f0f0\",\n                    \"label\": \"Tooltip Label\",\n                    \"decimalPlaces\": 3,\n                    \"prefix\": \"\\u20b9\"\n                },\n                {\n                    \"jsonName\": \"Place\",\n                    \"type\": \"string\"\n                },\n                {\n                    \"jsonName\": \"Region\",\n                    \"type\": \"string\"\n                },\n                {\n                    \"jsonName\": \"Price\",\n                    \"type\": \"number\",\n                    \"aggFn\": \"SUM\",\n                    \"fillColor\": \"#1d3b7a\"\n                },\n                {\n                    \"jsonName\": \"Employee\",\n                    \"type\": \"string\"\n                }\n            ],\n            \"params\": []\n        }\n    ],\n    \"chartLayout\": \"vertical\",\n    \"attributes\": {\n        \"chartType\": \"Pie Chart\",\n        \"sortOrder\": \"Desc\",\n        \"slider\": true,\n        \"saveImage\": true,\n        \"chartSubType\": \"nightingale\",\n        \"rotation\": 259\n    },\n    \"chartName\": \"Chart Example 62\",\n    \"xAxis\": {\n        \"fields\": [\n            \"location\"\n        ]\n    },\n    \"yAxis\": {\n        \"fields\": [\n            \"Price\"\n        ],\n        \"label\": \"Axis Label\"\n    }\n}"
  },
  {
    "instruction": "Create a Tree Map chart named 'Chart Example 63' plotting 'Discount' against 'SubCategory'. The data should be sorted in desc order and displayed using a vertical layout. The column 'Discount' should be aggregating using AVG function, lowest values should be colored #f0f0f0, values should be rounded to 0 decimal places, values should be suffixed with 'p'. The column 'Generation' should be aggregating using MIN function, lowest values should be colored #f8b0y1, tooltip should display 'Tooltip Label', values should be rounded to 1 decimal places, values should be prefixed with '*'. The column 'Revenue' should be aggregating using MIN function, highest values should be colored #1d3b7a, tooltip should display 'Tooltip Label', values should be suffixed with '%'. The column 'Mega_watt' should be lowest values should be colored #1d3b7a, values should be rounded to 2 decimal places, values should be prefixed with '#'. The column 'Profit' should be aggregating using SUM function, y-axis values should be visible, values should be prefixed with '₹'. The column 'Demand' should be filled with color #1d3b7a, lowest values should be colored #866666, tooltip should display 'Tooltip Label'. The column 'longitude' should be aggregating using MIN function, tooltip should display 'Tooltip Label', values should be rounded to 0 decimal places.",
    "input": "{\"dataSources\":[{\"dataSourceId\":\"ds-7333\",\"queryKey\":\"API:+jdbc$$dataService$$_61\",\"cols\":[{\"jsonName\":\"Discount\",\"type\":\"number\"},{\"jsonName\":\"Generation\",\"type\":\"number\"},{\"jsonName\":\"Order Date\",\"type\":\"date\"},{\"jsonName\":\"Revenue\",\"type\":\"number\"},{\"jsonName\":\"Mega_watt\",\"type\":\"number\"},{\"jsonName\":\"Profit\",\"type\":\"number\"},{\"jsonName\":\"Region\",\"type\":\"string\"},{\"jsonName\":\"Demand\",\"type\":\"number\"},{\"jsonName\":\"longitude\",\"type\":\"number\"},{\"jsonName\":\"SubCategory\",\"type\":\"string\"}],\"params\":[]}]}",
    "output": "{\n    \"dataSources\": [\n        {\n            \"dataSourceId\": \"ds-7333\",\n            \"queryKey\": \"API:+jdbc$$dataService$$_61\",\n            \"cols\": [\n                {\n                    \"jsonName\": \"Discount\",\n                    \"type\": \"number\",\n                    \"aggFn\": \"AVG\",\n                    \"fillLowestColor\": \"#f0f0f0\",\n                    \"decimalPlaces\": 0,\n                    \"suffix\": \"p\"\n                },\n                {\n                    \"jsonName\": \"Generation\",\n                    \"type\": \"number\",\n                    \"aggFn\": \"MIN\",\n                    \"fillLowestColor\": \"#f8b0y1\",\n                    \"label\": \"Tooltip Label\",\n                    \"decimalPlaces\": 1,\n                    \"prefix\": \"*\"\n                },\n                {\n                    \"jsonName\": \"Order Date\",\n                    \"type\": \"date\"\n                },\n                {\n                    \"jsonName\": \"Revenue\",\n                    \"type\": \"number\",\n                    \"aggFn\": \"MIN\",\n                    \"fillHighestColor\": \"#1d3b7a\",\n                    \"label\": \"Tooltip Label\",\n                    \"suffix\": \"%\"\n                },\n                {\n                    \"jsonName\": \"Mega_watt\",\n                    \"type\": \"number\",\n                    \"fillLowestColor\": \"#1d3b7a\",\n                    \"decimalPlaces\": 2,\n                    \"prefix\": \"#\"\n                },\n                {\n                    \"jsonName\": \"Profit\",\n                    \"type\": \"number\",\n                    \"aggFn\": \"SUM\",\n                    \"isYAxisValueVisible\": true,\n                    \"prefix\": \"\\u20b9\"\n                },\n                {\n                    \"jsonName\": \"Region\",\n                    \"type\": \"string\"\n                },\n                {\n                    \"jsonName\": \"Demand\",\n                    \"type\": \"number\",\n                    \"fillColor\": \"#1d3b7a\",\n                    \"fillLowestColor\": \"#866666\",\n                    \"label\": \"Tooltip Label\"\n                },\n                {\n                    \"jsonName\": \"longitude\",\n                    \"type\": \"number\",\n                    \"aggFn\": \"MIN\",\n                    \"label\": \"Tooltip Label\",\n                    \"decimalPlaces\": 0\n                },\n                {\n                    \"jsonName\": \"SubCategory\",\n                    \"type\": \"string\"\n                }\n            ],\n            \"params\": []\n        }\n    ],\n    \"chartLayout\": \"vertical\",\n    \"attributes\": {\n        \"chartType\": \"Tree Map\",\n        \"sortOrder\": \"Desc\",\n        \"slider\": true,\n        \"saveImage\": true\n    },\n    \"chartName\": \"Chart Example 63\",\n    \"xAxis\": {\n        \"fields\": [\n            \"SubCategory\"\n        ]\n    },\n    \"yAxis\": {\n        \"fields\": [\n            \"Discount\"\n        ]\n    }\n}"
  },
  {
    "instruction": "Create a Composed Chart chart named 'Chart Example 64' plotting 'Cost' against 'Region'. 'Cost' should be displayed as Line Chart. The data should be sorted in desc order and displayed using a horizontal layout. A secondary Y-axis is included, representing 'Mega_watt' as Line Chart. The x-axis should be labeled as 'Axis Label' with a name gap of 10 pixels. The y-axis should be labeled as 'Axis Label' and positioned at 'center' The secondary Y-axis should be labeled as 'Axis Label' The column 'Sales' should be y-axis values should be hidden, tooltip should display 'Tooltip Label', values should be rounded to 1 decimal places, values should be prefixed with '$'. The column 'Generation' should be aggregating using MAX function, tooltip should display 'Tooltip Label', values should be suffixed with '%'. The column 'Cost' should be highest values should be colored #1d3b7a, lowest values should be colored #99ff95, values should be prefixed with '@'. The column 'longitude' should be tooltip should display 'Tooltip Label', values should be rounded to 1 decimal places. The column 'latitude' should be y-axis values should be visible, values should be rounded to 3 decimal places, values should be prefixed with '*'. The column 'Mega_watt' should be filled with color #1d3b7a, tooltip should display 'Tooltip Label', values should be prefixed with '@'.",
    "input": "{\"dataSources\":[{\"dataSourceId\":\"ds-2226\",\"queryKey\":\"API:+jdbc$$TEMP$$us_station_city_geo_data_65\",\"cols\":[{\"jsonName\":\"Sales\",\"type\":\"number\"},{\"jsonName\":\"Place\",\"type\":\"string\"},{\"jsonName\":\"Generation\",\"type\":\"number\"},{\"jsonName\":\"Cost\",\"type\":\"number\"},{\"jsonName\":\"longitude\",\"type\":\"number\"},{\"jsonName\":\"latitude\",\"type\":\"number\"},{\"jsonName\":\"Mega_watt\",\"type\":\"number\"},{\"jsonName\":\"SubCategory\",\"type\":\"string\"},{\"jsonName\":\"Region\",\"type\":\"string\"},{\"jsonName\":\"Employee\",\"type\":\"string\"}],\"params\":[]}]}",
    "output": "{\n    \"dataSources\": [\n        {\n            \"dataSourceId\": \"ds-2226\",\n            \"queryKey\": \"API:+jdbc$$TEMP$$us_station_city_geo_data_65\",\n            \"cols\": [\n                {\n                    \"jsonName\": \"Sales\",\n                    \"type\": \"number\",\n                    \"isYAxisValueVisible\": false,\n                    \"label\": \"Tooltip Label\",\n                    \"decimalPlaces\": 1,\n                    \"prefix\": \"$\"\n                },\n                {\n                    \"jsonName\": \"Place\",\n                    \"type\": \"string\"\n                },\n                {\n                    \"jsonName\": \"Generation\",\n                    \"type\": \"number\",\n                    \"aggFn\": \"MAX\",\n                    \"label\": \"Tooltip Label\",\n                    \"suffix\": \"%\"\n                },\n                {\n                    \"jsonName\": \"Cost\",\n                    \"type\": \"number\",\n                    \"composedChartType\": \"Line Chart\",\n                    \"fillHighestColor\": \"#1d3b7a\",\n                    \"fillLowestColor\": \"#99ff95\",\n                    \"prefix\": \"@\"\n                },\n                {\n                    \"jsonName\": \"longitude\",\n                    \"type\": \"number\",\n                    \"label\": \"Tooltip Label\",\n                    \"decimalPlaces\": 1\n                },\n                {\n                    \"jsonName\": \"latitude\",\n                    \"type\": \"number\",\n                    \"isYAxisValueVisible\": true,\n                    \"decimalPlaces\": 3,\n                    \"prefix\": \"*\"\n                },\n                {\n                    \"jsonName\": \"Mega_watt\",\n                    \"type\": \"number\",\n                    \"composedChartType\": \"Line Chart\",\n                        \"fillColor\": \"#1d3b7a\",\n                    \"label\": \"Tooltip Label\",\n                    \"prefix\": \"@\"\n                },\n                {\n                    \"jsonName\": \"SubCategory\",\n                    \"type\": \"string\"\n                },\n                {\n                    \"jsonName\": \"Region\",\n                    \"type\": \"string\"\n                },\n                {\n                    \"jsonName\": \"Employee\",\n                    \"type\": \"string\"\n                }\n            ],\n            \"params\": []\n        }\n    ],\n    \"chartLayout\": \"horizontal\",\n    \"attributes\": {\n        \"chartType\": \"Composed Chart\",\n        \"sortOrder\": \"Desc\",\n        \"slider\": true,\n        \"saveImage\": true\n    },\n    \"chartName\": \"Chart Example 64\",\n    \"xAxis\": {\n        \"fields\": [\n            \"Region\"\n        ],\n        \"label\": \"Axis Label\",\n        \"nameGap\": 10\n    },\n    \"yAxis\": {\n        \"fields\": [\n            \"Cost\"\n        ],\n        \"label\": \"Axis Label\",\n        \"nameLocation\": \"center\"\n    },\n    \"secondaryYAxis\": {\n        \"fields\": [\n            \"Mega_watt\"\n        ],\n        \"label\": \"Axis Label\"\n    }\n}"
  },
  {
    "instruction": "Create a Geo Chart with location based not based on coordinates type chart named 'Chart Example 65' plotting 'N/A' against 'N/A'. The data should be sorted in desc order and displayed using a vertical layout. The column 'Price' should be aggregating using COUNT function. The column 'Demand' should be filled with color #1d3b7a, tooltip should display 'Tooltip Label', values should be rounded to 1 decimal places, values should be prefixed with '@'. The column 'Sales' should be aggregating using AVG function, lowest values should be colored #866666, values should be prefixed with '@'.",
    "input": "{\"dataSources\":[{\"dataSourceId\":\"ds-9883\",\"queryKey\":\"API:+auto-task$$auto_58\",\"cols\":[{\"jsonName\":\"Employee\",\"type\":\"string\"},{\"jsonName\":\"Region\",\"type\":\"string\"},{\"jsonName\":\"Place\",\"type\":\"string\"},{\"jsonName\":\"Order Date\",\"type\":\"date\"},{\"jsonName\":\"Price\",\"type\":\"number\"},{\"jsonName\":\"Demand\",\"type\":\"number\"},{\"jsonName\":\"Sales\",\"type\":\"number\"}],\"params\":[]}]}",
    "output": "{\n    \"dataSources\": [\n        {\n            \"dataSourceId\": \"ds-9883\",\n            \"queryKey\": \"API:+auto-task$$auto_58\",\n            \"cols\": [\n                {\n                    \"jsonName\": \"Employee\",\n                    \"type\": \"string\"\n                },\n                {\n                    \"jsonName\": \"Region\",\n                    \"type\": \"string\"\n                },\n                {\n                    \"jsonName\": \"Place\",\n                    \"type\": \"string\"\n                },\n                {\n                    \"jsonName\": \"Order Date\",\n                    \"type\": \"date\"\n                },\n                {\n                    \"jsonName\": \"Price\",\n                    \"type\": \"number\",\n                    \"aggFn\": \"COUNT\"\n                },\n                {\n                    \"jsonName\": \"Demand\",\n                    \"type\": \"number\",\n                    \"fillColor\": \"#1d3b7a\",\n                    \"label\": \"Tooltip Label\",\n                    \"decimalPlaces\": 1,\n                    \"prefix\": \"@\"\n                },\n                {\n                    \"jsonName\": \"Sales\",\n                    \"type\": \"number\",\n                    \"aggFn\": \"AVG\",\n                    \"fillLowestColor\": \"#866666\",\n                    \"prefix\": \"@\"\n                }\n            ],\n            \"params\": []\n        }\n    ],\n    \"chartLayout\": \"vertical\",\n    \"attributes\": {\n        \"chartType\": \"Geo Chart\",\n        \"sortOrder\": \"Desc\",\n        \"slider\": true,\n        \"saveImage\": true,\n        \"chartSubType\": \"filledMap\"\n    },\n    \"chartName\": \"Chart Example 65\",\n    \"xAxis\": {},\n    \"yAxis\": {},\n    \"location\": {\n        \"fields\": [\n            \"Region\"\n        ]\n    },\n    \"values\": {\n        \"fields\": [\n            \"Demand\"\n        ]\n    }\n}"
  },
  {
    "instruction": "Create a TimeLine Chart chart named 'Chart Example 66' plotting 'Generation' against 'Order Date'. The data should be sorted in desc order and displayed using a vertical layout. The x-axis should be labeled as 'Axis Label' and positioned at 'end' The y-axis should be labeled as 'Axis Label' and positioned at 'end' The column 'Generation' should be aggregating using MAX function, filled with color #1d3b7a, highest values should be colored #1d3b7a, values should be rounded to 1 decimal places, values should be prefixed with '*'. The column 'latitude' should be y-axis values should be hidden, filled with color #f0f0f0, highest values should be colored #f8b0y1, tooltip should display 'Tooltip Label', values should be prefixed with '#'. The column 'Revenue' should be aggregating using AVG function, lowest values should be colored #99ff95, tooltip should display 'Tooltip Label', values should be rounded to 2 decimal places. The column 'Cost' should be aggregating using AVG function, tooltip should display 'Tooltip Label'. The column 'Price' should be aggregating using COUNT function, filled with color #f8b0y1, highest values should be colored #866666, tooltip should display 'Tooltip Label', values should be rounded to 3 decimal places.",
    "input": "{\"dataSources\":[{\"dataSourceId\":\"ds-5143\",\"queryKey\":\"API:+jdbc$$aws$$_57\",\"cols\":[{\"jsonName\":\"Generation\",\"type\":\"number\"},{\"jsonName\":\"latitude\",\"type\":\"number\"},{\"jsonName\":\"Revenue\",\"type\":\"number\"},{\"jsonName\":\"Place\",\"type\":\"string\"},{\"jsonName\":\"Cost\",\"type\":\"number\"},{\"jsonName\":\"Price\",\"type\":\"number\"},{\"jsonName\":\"Order Date\",\"type\":\"date\"},{\"jsonName\":\"SubCategory\",\"type\":\"string\"}],\"params\":[]}]}",
    "output": "{\n    \"dataSources\": [\n        {\n            \"dataSourceId\": \"ds-5143\",\n            \"queryKey\": \"API:+jdbc$$aws$$_57\",\n            \"cols\": [\n                {\n                    \"jsonName\": \"Generation\",\n                    \"type\": \"number\",\n                    \"aggFn\": \"MAX\",\n                    \"fillColor\": \"#1d3b7a\",\n                    \"fillHighestColor\": \"#1d3b7a\",\n                    \"decimalPlaces\": 1,\n                    \"prefix\": \"*\"\n                },\n                {\n                    \"jsonName\": \"latitude\",\n                    \"type\": \"number\",\n                    \"isYAxisValueVisible\": false,\n                    \"fillColor\": \"#f0f0f0\",\n                    \"fillHighestColor\": \"#f8b0y1\",\n                    \"label\": \"Tooltip Label\",\n                    \"prefix\": \"#\"\n                },\n                {\n                    \"jsonName\": \"Revenue\",\n                    \"type\": \"number\",\n                    \"aggFn\": \"AVG\",\n                    \"fillLowestColor\": \"#99ff95\",\n                    \"label\": \"Tooltip Label\",\n                    \"decimalPlaces\": 2\n                },\n                {\n                    \"jsonName\": \"Place\",\n                    \"type\": \"string\"\n                },\n                {\n                    \"jsonName\": \"Cost\",\n                    \"type\": \"number\",\n                    \"aggFn\": \"AVG\",\n                    \"label\": \"Tooltip Label\"\n                },\n                {\n                    \"jsonName\": \"Price\",\n                    \"type\": \"number\",\n                    \"aggFn\": \"COUNT\",\n                    \"fillColor\": \"#f8b0y1\",\n                    \"fillHighestColor\": \"#866666\",\n                    \"label\": \"Tooltip Label\",\n                    \"decimalPlaces\": 3\n                },\n                {\n                    \"jsonName\": \"Order Date\",\n                    \"type\": \"date\"\n                },\n                {\n                    \"jsonName\": \"SubCategory\",\n                    \"type\": \"string\"\n                }\n            ],\n            \"params\": []\n        }\n    ],\n    \"chartLayout\": \"vertical\",\n    \"attributes\": {\n        \"chartType\": \"TimeLine Chart\",\n        \"sortOrder\": \"Desc\",\n        \"slider\": true,\n        \"saveImage\": true\n},\n    \"chartName\": \"Chart Example 66\",\n    \"xAxis\": {\n        \"fields\": [\n            \"Order Date\"\n        ],\n        \"label\": \"Axis Label\",\n        \"nameLocation\": \"end\"\n    },\n    \"yAxis\": {\n        \"fields\": [\n            \"Generation\"\n        ],\n        \"label\": \"Axis Label\",\n        \"nameLocation\": \"end\"\n    }\n}"
  },
  {
    "instruction": "Create a Scattered Chart chart named 'Chart Example 67' plotting 'Cost' against 'Country'. The data should be sorted in desc order and displayed using a horizontal layout. A Z-axis is also present, containing 'Profit'. The x-axis should be labeled as 'Axis Label' and positioned at 'start' with a name gap of 38 pixels. The column 'Profit' should be tooltip should display 'Tooltip Label', values should be rounded to 0 decimal places, values should be prefixed with '*'. The column 'longitude' should be filled with color #f0f0f0, tooltip should display 'Tooltip Label', values should be rounded to 2 decimal places. The column 'Cost' should be aggregating using MIN function, tooltip should display 'Tooltip Label', values should be suffixed with '%'. The column 'Generation' should be tooltip should display 'Tooltip Label', values should be rounded to 0 decimal places, values should be prefixed with '$'. The column 'latitude' should be aggregating using COUNT function, tooltip should display 'Tooltip Label', values should be rounded to 0 decimal places, values should be suffixed with '%'.",
    "input": "{\"dataSources\":[{\"dataSourceId\":\"ds-6692\",\"queryKey\":\"API:+auto-task$$auto-task_22\",\"cols\":[{\"jsonName\":\"Country\",\"type\":\"string\"},{\"jsonName\":\"Profit\",\"type\":\"number\"},{\"jsonName\":\"Employee\",\"type\":\"string\"},{\"jsonName\":\"longitude\",\"type\":\"number\"},{\"jsonName\":\"Region\",\"type\":\"string\"},{\"jsonName\":\"Cost\",\"type\":\"number\"},{\"jsonName\":\"Generation\",\"type\":\"number\"},{\"jsonName\":\"latitude\",\"type\":\"number\"},{\"jsonName\":\"location\",\"type\":\"string\"}],\"params\":[]}]}",
    "output": "{\n    \"dataSources\": [\n        {\n            \"dataSourceId\": \"ds-6692\",\n            \"queryKey\": \"API:+auto-task$$auto-task_22\",\n            \"cols\": [\n                {\n                    \"jsonName\": \"Country\",\n                    \"type\": \"string\"\n                },\n                {\n                    \"jsonName\": \"Profit\",\n                    \"type\": \"number\",\n                    \"label\": \"Tooltip Label\",\n                    \"decimalPlaces\": 0,\n                    \"prefix\": \"*\"\n                },\n                {\n                    \"jsonName\": \"Employee\",\n                    \"type\": \"string\"\n                },\n                {\n                    \"jsonName\": \"longitude\",\n                    \"type\": \"number\",\n                    \"fillColor\": \"#f0f0f0\",\n                    \"label\": \"Tooltip Label\",\n                    \"decimalPlaces\": 2\n                },\n                {\n                    \"jsonName\": \"Region\",\n                    \"type\": \"string\"\n                },\n                {\n                    \"jsonName\": \"Cost\",\n                    \"type\": \"number\",\n                    \"aggFn\": \"MIN\",\n                    \"label\": \"Tooltip Label\",\n                    \"suffix\": \"%\"\n                },\n                {\n                    \"jsonName\": \"Generation\",\n                    \"type\": \"number\",\n                    \"label\": \"Tooltip Label\",\n                    \"decimalPlaces\": 0,\n                    \"prefix\": \"$\"\n                },\n                {\n                    \"jsonName\": \"latitude\",\n                    \"type\": \"number\",\n                    \"aggFn\": \"COUNT\",\n                    \"label\": \"Tooltip Label\",\n                    \"decimalPlaces\": 0,\n                    \"suffix\": \"%\"\n                },\n                {\n                    \"jsonName\": \"location\",\n                    \"type\": \"string\"\n                }\n            ],\n            \"params\": []\n        }\n    ],\n    \"chartLayout\": \"horizontal\",\n    \"attributes\": {\n        \"chartType\": \"Scattered Chart\",\n        \"sortOrder\": \"Desc\",\n        \"slider\": true,\n        \"saveImage\": true\n},\n    \"chartName\": \"Chart Example 67\",\n    \"xAxis\": {\n        \"fields\": [\n            \"Country\"\n        ],\n        \"label\": \"Axis Label\",\n        \"nameLocation\": \"start\",\n        \"nameGap\": 38\n    },\n    \"yAxis\": {\n        \"fields\": [\n            \"Cost\"\n        ]\n    },\n    \"zAxis\": {\n        \"fields\": [\n            \"Profit\"\n        ]\n    }\n}"
  },
  {
    "instruction": "Create a Composed Chart chart named 'Chart Example 69' plotting 'Revenue' against 'Category'. 'Revenue' should be Pie Chart. The data should be sorted in desc order and displayed using a vertical layout. The column 'Revenue' should be aggregating using MAX function, y-axis values should be visible, filled with color #f8b0y1, tooltip should display 'Tooltip Label', values should be rounded to 2 decimal places, values should be prefixed with '₹'. The column 'coordinate_lg' should be aggregating using MAX function, y-axis values should be hidden, filled with color #1d3b7a, tooltip should display 'Tooltip Label', values should be rounded to 2 decimal places, values should be prefixed with '*'. The column 'latitude' should be aggregating using MAX function, lowest values should be colored #99ff95, tooltip should display 'Tooltip Label', values should be rounded to 2 decimal places. The column 'Cost' should be y-axis values should be hidden, filled with color #866666, tooltip should display 'Tooltip Label', values should be rounded to 2 decimal places, values should be suffixed with '%'. The column 'Discount' should be aggregating using SUM function, values should be prefixed with '*'.",
    "input": "{\"dataSources\":[{\"dataSourceId\":\"ds-2196\",\"queryKey\":\"API:+jdbc$$pmgr$$caps_2\",\"cols\":[{\"jsonName\":\"Revenue\",\"type\":\"number\"},{\"jsonName\":\"Category\",\"type\":\"string\"},{\"jsonName\":\"Country\",\"type\":\"string\"},{\"jsonName\":\"coordinate_lg\",\"type\":\"number\"},{\"jsonName\":\"latitude\",\"type\":\"number\"},{\"jsonName\":\"Cost\",\"type\":\"number\"},{\"jsonName\":\"Order Date\",\"type\":\"date\"},{\"jsonName\":\"Discount\",\"type\":\"number\"},{\"jsonName\":\"SubCategory\",\"type\":\"string\"}],\"params\":[]}]}",
    "output": "{\n    \"dataSources\": [\n        {\n            \"dataSourceId\": \"ds-2196\",\n            \"queryKey\": \"API:+jdbc$$pmgr$$caps_2\",\n            \"cols\": [\n                {\n                    \"jsonName\": \"Revenue\",\n                    \"type\": \"number\",\n                    \"composedChartType\": \"Bar Chart\",\n                 \"aggFn\": \"MAX\",\n                    \"isYAxisValueVisible\": true,\n                    \"fillColor\": \"#f8b0y1\",\n                    \"label\": \"Tooltip Label\",\n                    \"decimalPlaces\": 2,\n                    \"prefix\": \"\\u20b9\"\n                },\n                {\n                    \"jsonName\": \"Category\",\n                    \"type\": \"string\"\n                },\n                {\n                    \"jsonName\": \"Country\",\n                    \"type\": \"string\"\n                },\n                {\n                    \"jsonName\": \"coordinate_lg\",\n                    \"type\": \"number\",\n                    \"aggFn\": \"MAX\",\n                    \"isYAxisValueVisible\": false,\n                    \"fillColor\": \"#1d3b7a\",\n                    \"label\": \"Tooltip Label\",\n                    \"decimalPlaces\": 2,\n                    \"prefix\": \"*\"\n                },\n                {\n                    \"jsonName\": \"latitude\",\n                    \"type\": \"number\",\n                    \"aggFn\": \"MAX\",\n                    \"fillLowestColor\": \"#99ff95\",\n                    \"label\": \"Tooltip Label\",\n                    \"decimalPlaces\": 2\n                },\n                {\n                    \"jsonName\": \"Cost\",\n                    \"type\": \"number\",\n                    \"isYAxisValueVisible\": false,\n                    \"fillColor\": \"#866666\",\n                    \"label\": \"Tooltip Label\",\n                    \"decimalPlaces\": 2,\n                    \"suffix\": \"%\"\n                },\n                {\n                    \"jsonName\": \"Order Date\",\n                    \"type\": \"date\"\n                },\n                {\n                    \"jsonName\": \"Discount\",\n                    \"type\": \"number\",\n                    \"aggFn\": \"SUM\",\n                    \"prefix\": \"*\"\n                },\n                {\n                    \"jsonName\": \"SubCategory\",\n                    \"type\": \"string\"\n                }\n            ],\n            \"params\": []\n        }\n    ],\n    \"chartLayout\": \"vertical\",\n    \"attributes\": {\n        \"chartType\": \"Composed Chart\",\n        \"sortOrder\": \"Desc\",\n        \"slider\": true,\n        \"saveImage\": true\n    },\n    \"chartName\": \"Chart Example 69\",\n    \"xAxis\": {\n        \"fields\": [\n            \"Category\"\n        ]\n    },\n    \"yAxis\": {\n        \"fields\": [\n            \"Revenue\"\n        ]\n    }\n}"
  },
  {
    "instruction": "Create a Gantt Chart chart named 'Chart Example 70' which has 'Departure_date' & 'Arrival_date' on y Axis and 'location' on x Axis. The data should be sorted in asc order and displayed using a horizontal layout. The y-axis should be labeled as 'Axis Label' The column 'Departure_date' should be filled with color #f8b0y1, highest values should be colored #99ff95, tooltip should display 'Tooltip Label', values should be rounded to 2 decimal places. The column 'Revenue' should be y-axis values should be hidden, lowest values should be colored #f0f0f0, tooltip should display 'Tooltip Label', values should be rounded to 2 decimal places. The column 'Arrival_date' should be values should be rounded to 1 decimal places, values should be prefixed with '$'. The column 'latitude' should be aggregating using COUNT function, tooltip should display 'Tooltip Label', values should be rounded to 3 decimal places, values should be prefixed with '*'. The column 'Mega_watt' should be aggregating using MIN function, highest values should be colored #866666, tooltip should display 'Tooltip Label', values should be rounded to 3 decimal places, values should be prefixed with '*'.",
    "input": "{\"dataSources\":[{\"dataSourceId\":\"ds-8610\",\"queryKey\":\"API:+jdbc$$aws$$_44\",\"cols\":[{\"jsonName\":\"Departure_date\",\"type\":\"date\"},{\"jsonName\":\"location\",\"type\":\"string\"},{\"jsonName\":\"Revenue\",\"type\":\"number\"},{\"jsonName\":\"Arrival_date\",\"type\":\"date\"},{\"jsonName\":\"latitude\",\"type\":\"number\"},{\"jsonName\":\"Mega_watt\",\"type\":\"number\"},{\"jsonName\":\"Country\",\"type\":\"string\"}],\"params\":[]}]}",
    "output": "{\n    \"dataSources\": [\n        {\n            \"dataSourceId\": \"ds-8610\",\n            \"queryKey\": \"API:+jdbc$$aws$$_44\",\n            \"cols\": [\n                {\n                    \"jsonName\": \"Departure_date\",\n                    \"type\": \"date\",\n                    \"fillColor\": \"#f8b0y1\",\n                    \"fillHighestColor\": \"#99ff95\",\n                    \"label\": \"Tooltip Label\",\n                    \"decimalPlaces\": 2\n                },\n                {\n                    \"jsonName\": \"location\",\n                    \"type\": \"string\"\n                },\n                {\n                    \"jsonName\": \"Revenue\",\n                    \"type\": \"number\",\n                    \"isYAxisValueVisible\": false,\n                    \"fillLowestColor\": \"#f0f0f0\",\n                    \"label\": \"Tooltip Label\",\n                    \"decimalPlaces\": 2\n                },\n                {\n                    \"jsonName\": \"Arrival_date\",\n                    \"type\": \"date\",\n                    \"decimalPlaces\": 1,\n                    \"prefix\": \"$\"\n                },\n                {\n                    \"jsonName\": \"latitude\",\n                    \"type\": \"number\",\n                    \"aggFn\": \"COUNT\",\n                    \"label\": \"Tooltip Label\",\n                    \"decimalPlaces\": 3,\n                    \"prefix\": \"*\"\n                },\n                {\n                    \"jsonName\": \"Mega_watt\",\n                    \"type\": \"number\",\n                    \"aggFn\": \"MIN\",\n                    \"fillHighestColor\": \"#866666\",\n                    \"label\": \"Tooltip Label\",\n                    \"decimalPlaces\": 3,\n                    \"prefix\": \"*\"\n                },\n                {\n                    \"jsonName\": \"Country\",\n                    \"type\": \"string\"\n                }\n            ],\n            \"params\": []\n        }\n    ],\n    \"chartLayout\": \"horizontal\",\n    \"attributes\": {\n        \"chartType\": \"Gantt Chart\",\n        \"sortOrder\": \"Asc\",\n        \"slider\": true,\n        \"saveImage\": true\n    },\n    \"chartName\": \"Chart Example 70\",\n    \"xAxis\": {\n        \"fields\": [\n            \"location\"\n        ]\n    },\n    \"yAxis\": {\n        \"fields\": [\n            \"Departure_date\"\n,    \"Arrival_date\"\n     ],\n        \"label\": \"Axis Label\"\n    }\n}"
  },
  {
    "instruction": "Create a Scattered Chart chart named 'Chart Example 71' plotting 'Mega_watt' against 'Category'. The data should be sorted in asc order and displayed using a horizontal layout. A Z-axis is also present, containing 'Price'. The y-axis should be labeled as 'Axis Label' The column 'Cost' should be aggregating using SUM function, highest values should be colored #866666, values should be rounded to 1 decimal places. The column 'Price' should be aggregating using COUNT function, lowest values should be colored #f8b0y1, tooltip should display 'Tooltip Label', values should be rounded to 2 decimal places, values should be prefixed with '*'. The column 'Revenue' should be aggregating using COUNT function, tooltip should display 'Tooltip Label', values should be rounded to 2 decimal places. The column 'Sales' should be aggregating using MAX function, tooltip should display 'Tooltip Label', values should be rounded to 1 decimal places, values should be prefixed with '#'. The column 'Mega_watt' should be aggregating using MAX function, tooltip should display 'Tooltip Label', values should be rounded to 3 decimal places, values should be prefixed with '@'.",
    "input": "{\"dataSources\":[{\"dataSourceId\":\"ds-9516\",\"queryKey\":\"API:+auto-task$$auto-task_7\",\"cols\":[{\"jsonName\":\"Cost\",\"type\":\"number\"},{\"jsonName\":\"Category\",\"type\":\"string\"},{\"jsonName\":\"Order Date\",\"type\":\"date\"},{\"jsonName\":\"Price\",\"type\":\"number\"},{\"jsonName\":\"Revenue\",\"type\":\"number\"},{\"jsonName\":\"SubCategory\",\"type\":\"string\"},{\"jsonName\":\"Sales\",\"type\":\"number\"},{\"jsonName\":\"Mega_watt\",\"type\":\"number\"}],\"params\":[]}]}",
    "output": "{\n    \"dataSources\": [\n        {\n            \"dataSourceId\": \"ds-9516\",\n            \"queryKey\": \"API:+auto-task$$auto-task_7\",\n            \"cols\": [\n                {\n                    \"jsonName\": \"Cost\",\n                    \"type\": \"number\",\n                    \"aggFn\": \"SUM\",\n                    \"fillHighestColor\": \"#866666\",\n                    \"decimalPlaces\": 1\n                },\n                {\n                    \"jsonName\": \"Category\",\n                    \"type\": \"string\"\n                },\n                {\n                    \"jsonName\": \"Order Date\",\n                    \"type\": \"date\"\n                },\n                {\n                    \"jsonName\": \"Price\",\n                    \"type\": \"number\",\n                    \"aggFn\": \"COUNT\",\n                    \"fillLowestColor\": \"#f8b0y1\",\n                    \"label\": \"Tooltip Label\",\n                    \"decimalPlaces\": 2,\n                    \"prefix\": \"*\"\n                },\n                {\n                    \"jsonName\": \"Revenue\",\n                    \"type\": \"number\",\n                    \"aggFn\": \"COUNT\",\n                    \"label\": \"Tooltip Label\",\n                    \"decimalPlaces\": 2\n                },\n                {\n                    \"jsonName\": \"SubCategory\",\n                    \"type\": \"string\"\n                },\n                {\n                    \"jsonName\": \"Sales\",\n                    \"type\": \"number\",\n                    \"aggFn\": \"MAX\",\n                    \"label\": \"Tooltip Label\",\n                    \"decimalPlaces\": 1,\n                    \"prefix\": \"#\"\n                },\n                {\n                    \"jsonName\": \"Mega_watt\",\n                    \"type\": \"number\",\n                    \"aggFn\": \"MAX\",\n                    \"label\": \"Tooltip Label\",\n                    \"decimalPlaces\": 3,\n                    \"prefix\": \"@\"\n                }\n            ],\n            \"params\": []\n        }\n    ],\n    \"chartLayout\": \"horizontal\",\n    \"attributes\": {\n        \"chartType\": \"Scattered Chart\",\n        \"sortOrder\": \"Asc\",\n        \"slider\": true,\n        \"saveImage\": true\n},\n    \"chartName\": \"Chart Example 71\",\n    \"xAxis\": {\n        \"fields\": [\n            \"Category\"\n        ]\n    },\n    \"yAxis\": {\n        \"fields\": [\n            \"Mega_watt\"\n        ],\n        \"label\": \"Axis Label\"\n    },\n    \"zAxis\": {\n        \"fields\": [\n            \"Price\"\n        ]\n    }\n}"
  },
  {
    "instruction": "Create a Scattered Chart chart named 'Chart Example 72' plotting 'Generation' against 'Country'. The data should be sorted in asc order and displayed using a horizontal layout. A Z-axis is also present, containing 'Sales'. The x-axis should be labeled as 'Axis Label' with a name gap of 43 pixels. The y-axis should be labeled as 'Axis Label' with a name gap of 40 pixels. The column 'Generation' should be aggregating using MAX function, highest values should be colored #99ff95, values should be rounded to 1 decimal places, values should be prefixed with '*'. The column 'Sales' should be filled with color #866666, tooltip should display 'Tooltip Label', values should be prefixed with '$'. The column 'longitude' should be aggregating using MIN function, lowest values should be colored #866666, values should be rounded to 3 decimal places, values should be prefixed with '#'. The column 'latitude' should be filled with color #1d3b7a, tooltip should display 'Tooltip Label', values should be rounded to 1 decimal places, values should be prefixed with '$'.",
    "input": "{\"dataSources\":[{\"dataSourceId\":\"ds-1714\",\"queryKey\":\"API:+auto-task$$auto-task_40\",\"cols\":[{\"jsonName\":\"Generation\",\"type\":\"number\"},{\"jsonName\":\"Sales\",\"type\":\"number\"},{\"jsonName\":\"Country\",\"type\":\"string\"},{\"jsonName\":\"longitude\",\"type\":\"number\"},{\"jsonName\":\"Order Date\",\"type\":\"date\"},{\"jsonName\":\"latitude\",\"type\":\"number\"},{\"jsonName\":\"Place\",\"type\":\"string\"}],\"params\":[]}]}",
    "output": "{\n    \"dataSources\": [\n        {\n            \"dataSourceId\": \"ds-1714\",\n            \"queryKey\": \"API:+auto-task$$auto-task_40\",\n            \"cols\": [\n                {\n                    \"jsonName\": \"Generation\",\n                    \"type\": \"number\",\n                    \"aggFn\": \"MAX\",\n                    \"fillHighestColor\": \"#99ff95\",\n                    \"decimalPlaces\": 1,\n                    \"prefix\": \"*\"\n                },\n                {\n                    \"jsonName\": \"Sales\",\n                    \"type\": \"number\",\n                    \"fillColor\": \"#866666\",\n                    \"label\": \"Tooltip Label\",\n                    \"prefix\": \"$\"\n                },\n                {\n                    \"jsonName\": \"Country\",\n                    \"type\": \"string\"\n                },\n                {\n                    \"jsonName\": \"longitude\",\n                    \"type\": \"number\",\n                    \"aggFn\": \"MIN\",\n                    \"fillLowestColor\": \"#866666\",\n                    \"decimalPlaces\": 3,\n                    \"prefix\": \"#\"\n                },\n                {\n                    \"jsonName\": \"Order Date\",\n                    \"type\": \"date\"\n                },\n                {\n                    \"jsonName\": \"latitude\",\n                    \"type\": \"number\",\n                    \"fillColor\": \"#1d3b7a\",\n                    \"label\": \"Tooltip Label\",\n                    \"decimalPlaces\": 1,\n                    \"prefix\": \"$\"\n                },\n                {\n                    \"jsonName\": \"Place\",\n                    \"type\": \"string\"\n                }\n            ],\n            \"params\": []\n        }\n    ],\n    \"chartLayout\": \"horizontal\",\n    \"attributes\": {\n        \"chartType\": \"Scattered Chart\",\n        \"sortOrder\": \"Asc\",\n        \"slider\": true,\n        \"saveImage\": true\n}\n    },\n    \"chartName\": \"Chart Example 72\",\n    \"xAxis\": {\n        \"fields\": [\n            \"Country\"\n        ],\n        \"label\": \"Axis Label\",\n        \"nameGap\": 43\n    },\n    \"yAxis\": {\n        \"fields\": [\n            \"Generation\"\n        ],\n        \"label\": \"Axis Label\",\n        \"nameGap\": 40\n    },\n    \"zAxis\": {\n        \"fields\": [\n            \"Sales\"\n        ]\n    }\n}"
  },
  {
    "instruction": "Create a Line Chart chart named 'Chart Example 73' plotting 'Generation' against 'Customer' with 'Sales' as legend. The data should be sorted in asc order and displayed using a horizontal layout. The x-axis should be labeled as 'Axis Label' with a name gap of 18 pixels. The column 'Generation' should be y-axis values should be visible, lowest values should be colored #f8b0y1, values should be rounded to 3 decimal places, values should be prefixed with '₹'. The column 'Discount' should be lowest values should be colored #f0f0f0, values should be rounded to 2 decimal places, values should be prefixed with '*'. The column 'Sales' should be aggregating using MIN function, highest values should be colored #866666, values should be prefixed with '@'. The column 'coordinate_lg' should be aggregating using AVG function, filled with color #866666, lowest values should be colored #866666, values should be rounded to 1 decimal places. The column 'Profit' should be aggregating using MIN function, filled with color #1d3b7a, values should be rounded to 2 decimal places, values should be prefixed with '*'.",
    "input": "{\"dataSources\":[{\"dataSourceId\":\"ds-8637\",\"queryKey\":\"API:+jdbc$$Oracle$$Energy_API_51\",\"cols\":[{\"jsonName\":\"Generation\",\"type\":\"number\"},{\"jsonName\":\"Discount\",\"type\":\"number\"},{\"jsonName\":\"location\",\"type\":\"string\"},{\"jsonName\":\"Sales\",\"type\":\"number\"},{\"jsonName\":\"coordinate_lg\",\"type\":\"number\"},{\"jsonName\":\"Customer\",\"type\":\"string\"},{\"jsonName\":\"Profit\",\"type\":\"number\"},{\"jsonName\":\"Place\",\"type\":\"string\"}],\"params\":[]}]}",
    "output": "{\n    \"dataSources\": [\n        {\n            \"dataSourceId\": \"ds-8637\",\n            \"queryKey\": \"API:+jdbc$$Oracle$$Energy_API_51\",\n            \"cols\": [\n                {\n                    \"jsonName\": \"Generation\",\n                    \"type\": \"number\",\n                    \"isYAxisValueVisible\": true,\n                    \"fillLowestColor\": \"#f8b0y1\",\n                    \"decimalPlaces\": 3,\n                    \"prefix\": \"\\u20b9\"\n                },\n                {\n                    \"jsonName\": \"Discount\",\n                    \"type\": \"number\",\n                    \"fillLowestColor\": \"#f0f0f0\",\n                    \"decimalPlaces\": 2,\n                    \"prefix\": \"*\"\n                },\n                {\n                    \"jsonName\": \"location\",\n                    \"type\": \"string\"\n                },\n                {\n                    \"jsonName\": \"Sales\",\n                    \"type\": \"number\",\n                    \"aggFn\": \"MIN\",\n                    \"fillHighestColor\": \"#866666\",\n                    \"prefix\": \"@\"\n                },\n                {\n                    \"jsonName\": \"coordinate_lg\",\n                    \"type\": \"number\",\n                    \"aggFn\": \"AVG\",\n                    \"fillColor\": \"#866666\",\n                    \"fillLowestColor\": \"#866666\",\n                    \"decimalPlaces\": 1\n                },\n                {\n                    \"jsonName\": \"Customer\",\n                    \"type\": \"string\"\n                },\n                {\n                    \"jsonName\": \"Profit\",\n                    \"type\": \"number\",\n                    \"aggFn\": \"MIN\",\n                    \"fillColor\": \"#1d3b7a\",\n                    \"decimalPlaces\": 2,\n                    \"prefix\": \"*\"\n                },\n                {\n                    \"jsonName\": \"Place\",\n                    \"type\": \"string\"\n                }\n            ],\n            \"params\": []\n        }\n    ],\n    \"chartLayout\": \"horizontal\",\n    \"attributes\": {\n        \"chartType\": \"Line Chart\",\n        \"sortOrder\": \"Asc\",\n        \"slider\": true,\n        \"saveImage\": true,\n        \"legend\": {\n            \"fields\": \"Sales\",\n            \"colors\": {}\n        }\n    },\n    \"chartName\": \"Chart Example 73\",\n    \"xAxis\": {\n        \"fields\": [\n            \"Customer\"\n        ],\n        \"label\": \"Axis Label\",\n        \"nameGap\": 18\n    },\n    \"yAxis\": {\n        \"fields\": [\n            \"Generation\"\n        ]\n    }\n}"
  },
  {
    "instruction": "Create a Tree Map chart named 'Chart Example 74' plotting 'Cost' against 'location'. The data should be sorted in desc order and displayed using a vertical layout. The x-axis should be labeled as 'Axis Label' The y-axis should be labeled as 'Axis Label' with a name gap of 45 pixels. The column 'Generation' should be aggregating using AVG function, y-axis values should be visible, lowest values should be colored #866666, values should be prefixed with '₹'. The column 'latitude' should be aggregating using AVG function, highest values should be colored #1d3b7a, lowest values should be colored #866666, values should be rounded to 1 decimal places, values should be prefixed with '@'. The column 'coordinate_lg' should be aggregating using MIN function, filled with color #f0f0f0, lowest values should be colored #99ff95, tooltip should display 'Tooltip Label', values should be rounded to 1 decimal places, values should be prefixed with '@'. The column 'Cost' should be aggregating using SUM function, highest values should be colored #f0f0f0, lowest values should be colored #866666, tooltip should display 'Tooltip Label', values should be rounded to 0 decimal places, values should be prefixed with '$'.",
    "input": "{\"dataSources\":[{\"dataSourceId\":\"ds-3681\",\"queryKey\":\"API:+auto-task$$auto_12\",\"cols\":[{\"jsonName\":\"Order Date\",\"type\":\"date\"},{\"jsonName\":\"Generation\",\"type\":\"number\"},{\"jsonName\":\"Country\",\"type\":\"string\"},{\"jsonName\":\"location\",\"type\":\"string\"},{\"jsonName\":\"latitude\",\"type\":\"number\"},{\"jsonName\":\"Employee\",\"type\":\"string\"},{\"jsonName\":\"coordinate_lg\",\"type\":\"number\"},{\"jsonName\":\"Cost\",\"type\":\"number\"}],\"params\":[]}]}",
    "output": "{\n    \"dataSources\": [\n        {\n            \"dataSourceId\": \"ds-3681\",\n            \"queryKey\": \"API:+auto-task$$auto_12\",\n            \"cols\": [\n                {\n                    \"jsonName\": \"Order Date\",\n                    \"type\": \"date\"\n                },\n                {\n                    \"jsonName\": \"Generation\",\n                    \"type\": \"number\",\n                    \"aggFn\": \"AVG\",\n                    \"isYAxisValueVisible\": true,\n                    \"fillLowestColor\": \"#866666\",\n                    \"prefix\": \"\\u20b9\"\n                },\n                {\n                    \"jsonName\": \"Country\",\n                    \"type\": \"string\"\n                },\n                {\n                    \"jsonName\": \"location\",\n                    \"type\": \"string\"\n                },\n                {\n                    \"jsonName\": \"latitude\",\n                    \"type\": \"number\",\n                    \"aggFn\": \"AVG\",\n                    \"fillHighestColor\": \"#1d3b7a\",\n                    \"fillLowestColor\": \"#866666\",\n                    \"decimalPlaces\": 1,\n                    \"prefix\": \"@\"\n                },\n                {\n                    \"jsonName\": \"Employee\",\n                    \"type\": \"string\"\n                },\n                {\n                    \"jsonName\": \"coordinate_lg\",\n                    \"type\": \"number\",\n                    \"aggFn\": \"MIN\",\n                    \"fillColor\": \"#f0f0f0\",\n                    \"fillLowestColor\": \"#99ff95\",\n                    \"label\": \"Tooltip Label\",\n                    \"decimalPlaces\": 1,\n                    \"prefix\": \"@\"\n                },\n                {\n                    \"jsonName\": \"Cost\",\n                    \"type\": \"number\",\n                    \"aggFn\": \"SUM\",\n                    \"fillHighestColor\": \"#f0f0f0\",\n                    \"fillLowestColor\": \"#866666\",\n                    \"label\": \"Tooltip Label\",\n                    \"decimalPlaces\": 0,\n                    \"prefix\": \"$\"\n                }\n            ],\n            \"params\": []\n        }\n    ],\n    \"chartLayout\": \"vertical\",\n    \"attributes\": {\n        \"chartType\": \"Tree Map\",\n        \"sortOrder\": \"Desc\",\n        \"slider\": true,\n        \"saveImage\": true\n    },\n    \"chartName\": \"Chart Example 74\",\n    \"xAxis\": {\n        \"fields\": [\n            \"location\"\n        ],\n        \"label\": \"Axis Label\"\n    },\n    \"yAxis\": {\n        \"fields\": [\n            \"Cost\"\n        ],\n        \"label\": \"Axis Label\",\n        \"nameGap\": 45\n    }\n}"
  },
  {
    "instruction": "Create a TimeLine Chart chart named 'Chart Example 75' plotting 'Revenue' against 'Category'. The data should be sorted in desc order and displayed using a vertical layout. The column 'Profit' should be aggregating using COUNT function, lowest values should be colored #99ff95, values should be rounded to 1 decimal places, values should be prefixed with '#'. The column 'Revenue' should be values should be prefixed with '#'. The column 'latitude' should be aggregating using AVG function, lowest values should be colored #1d3b7a, tooltip should display 'Tooltip Label', values should be rounded to 0 decimal places, values should be prefixed with '#'.",
    "input": "{\"dataSources\":[{\"dataSourceId\":\"ds-9237\",\"queryKey\":\"API:+jdbc$$aws$$_83\",\"cols\":[{\"jsonName\":\"Profit\",\"type\":\"number\"},{\"jsonName\":\"Revenue\",\"type\":\"number\"},{\"jsonName\":\"Country\",\"type\":\"string\"},{\"jsonName\":\"latitude\",\"type\":\"number\"},{\"jsonName\":\"Category\",\"type\":\"string\"},{\"jsonName\":\"Customer\",\"type\":\"string\"},{\"jsonName\":\"SubCategory\",\"type\":\"string\"}],\"params\":[]}]}",
    "output": "{\n    \"dataSources\": [\n        {\n            \"dataSourceId\": \"ds-9237\",\n            \"queryKey\": \"API:+jdbc$$aws$$_83\",\n            \"cols\": [\n                {\n                    \"jsonName\": \"Profit\",\n                    \"type\": \"number\",\n                    \"aggFn\": \"COUNT\",\n                    \"fillLowestColor\": \"#99ff95\",\n                    \"decimalPlaces\": 1,\n                    \"prefix\": \"#\"\n                },\n                {\n                    \"jsonName\": \"Revenue\",\n                    \"type\": \"number\",\n                    \"prefix\": \"#\"\n                },\n                {\n                    \"jsonName\": \"Country\",\n                    \"type\": \"string\"\n                },\n                {\n                    \"jsonName\": \"latitude\",\n                    \"type\": \"number\",\n                    \"aggFn\": \"AVG\",\n                    \"fillLowestColor\": \"#1d3b7a\",\n                    \"label\": \"Tooltip Label\",\n                    \"decimalPlaces\": 0,\n                    \"prefix\": \"#\"\n                },\n                {\n                    \"jsonName\": \"Category\",\n                    \"type\": \"string\"\n                },\n                {\n                    \"jsonName\": \"Customer\",\n                    \"type\": \"string\"\n                },\n                {\n                    \"jsonName\": \"SubCategory\",\n                    \"type\": \"string\"\n                }\n            ],\n            \"params\": []\n        }\n    ],\n    \"chartLayout\": \"vertical\",\n    \"attributes\": {\n        \"chartType\": \"TimeLine Chart\",\n        \"sortOrder\": \"Desc\",\n        \"slider\": true,\n        \"saveImage\": true\n    },\n    \"chartName\": \"Chart Example 75\",\n    \"xAxis\": {\n        \"fields\": [\n            \"Category\"\n        ]\n    },\n    \"yAxis\": {\n        \"fields\": [\n            \"Revenue\"\n        ]\n    }\n}"
  },
  {
    "instruction": "Create a Composed Chart chart named 'Chart Example 76' plotting 'Generation' should be Line Chart against 'Region'. The data should be sorted in desc order and displayed using a vertical layout. A secondary Y-axis is included, representing 'Cost' as a Geo Chart. The column 'Revenue' should be filled with color #99ff95, tooltip should display 'Tooltip Label', values should be rounded to 1 decimal places, values should be prefixed with '*'. The column 'coordinate_lg' should be aggregating using AVG function, tooltip should display 'Tooltip Label', values should be rounded to 2 decimal places, values should be suffixed with 'USD'. The column 'Generation' should be lowest values should be colored #1d3b7a, tooltip should display 'Tooltip Label', values should be rounded to 3 decimal places, values should be prefixed with '₹'. The column 'coordinate_lt' should be aggregating using AVG function, filled with color #866666, values should be rounded to 2 decimal places, values should be prefixed with '*'. The column 'Cost' should be aggregating using MAX function, lowest values should be colored #866666, tooltip should display 'Tooltip Label', values should be prefixed with '@'. The column 'longitude' should be aggregating using MIN function, y-axis values should be hidden, values should be suffixed with 'p'.",
    "input": "{\"dataSources\":[{\"dataSourceId\":\"ds-8864\",\"queryKey\":\"API:+jdbc$$TEMP$$us_station_city_geo_data_91\",\"cols\":[{\"jsonName\":\"Region\",\"type\":\"string\"},{\"jsonName\":\"Revenue\",\"type\":\"number\"},{\"jsonName\":\"coordinate_lg\",\"type\":\"number\"},{\"jsonName\":\"Generation\",\"type\":\"number\"},{\"jsonName\":\"coordinate_lt\",\"type\":\"number\"},{\"jsonName\":\"Employee\",\"type\":\"string\"},{\"jsonName\":\"Cost\",\"type\":\"number\"},{\"jsonName\":\"longitude\",\"type\":\"number\"},{\"jsonName\":\"SubCategory\",\"type\":\"string\"}],\"params\":[]}]}",
    "output": "{\n    \"dataSources\": [\n        {\n            \"dataSourceId\": \"ds-8864\",\n            \"queryKey\": \"API:+jdbc$$TEMP$$us_station_city_geo_data_91\",\n            \"cols\": [\n                {\n                    \"jsonName\": \"Region\",\n                    \"type\": \"string\"\n                },\n                {\n                    \"jsonName\": \"Revenue\",\n                    \"type\": \"number\",\n                    \"fillColor\": \"#99ff95\",\n                    \"label\": \"Tooltip Label\",\n                    \"decimalPlaces\": 1,\n                    \"prefix\": \"*\"\n                },\n                {\n                    \"jsonName\": \"coordinate_lg\",\n                    \"type\": \"number\",\n                    \"aggFn\": \"AVG\",\n                    \"label\": \"Tooltip Label\",\n                    \"decimalPlaces\": 2,\n                    \"suffix\": \"USD\"\n                },\n                {\n                    \"jsonName\": \"Generation\",\n                    \"type\": \"number\",\n                   \"composedChartType\": \"Line Chart\",\n                      \"fillLowestColor\": \"#1d3b7a\",\n                    \"label\": \"Tooltip Label\",\n                    \"decimalPlaces\": 3,\n                    \"prefix\": \"\\u20b9\"\n                },\n                {\n                    \"jsonName\": \"coordinate_lt\",\n                    \"type\": \"number\",\n                    \"aggFn\": \"AVG\",\n                    \"fillColor\": \"#866666\",\n                    \"decimalPlaces\": 2,\n                    \"prefix\": \"*\"\n                },\n                {\n                    \"jsonName\": \"Employee\",\n                    \"type\": \"string\"\n                },\n                {\n                    \"jsonName\": \"Cost\",\n                    \"type\": \"number\",\n                    \"composedChartType\": \"Bar Chart\",\n             \"aggFn\": \"MAX\",\n                    \"fillLowestColor\": \"#866666\",\n                    \"label\": \"Tooltip Label\",\n                    \"prefix\": \"@\"\n                },\n                {\n                    \"jsonName\": \"longitude\",\n                    \"type\": \"number\",\n                    \"aggFn\": \"MIN\",\n                    \"isYAxisValueVisible\": false,\n                    \"suffix\": \"p\"\n                },\n                {\n                    \"jsonName\": \"SubCategory\",\n                    \"type\": \"string\"\n                }\n            ],\n            \"params\": []\n        }\n    ],\n    \"chartLayout\": \"vertical\",\n    \"attributes\": {\n        \"chartType\": \"Composed Chart\",\n        \"sortOrder\": \"Desc\",\n        \"slider\": true,\n        \"saveImage\": true\n    },\n    \"chartName\": \"Chart Example 76\",\n    \"xAxis\": {\n        \"fields\": [\n            \"Region\"\n        ]\n    },\n    \"yAxis\": {\n        \"fields\": [\n            \"Generation\"\n        ]\n    },\n    \"secondaryYAxis\": {\n        \"fields\": [\n            \"Cost\"\n        ]\n    }\n}"
  },
  {
    "instruction": "Create a Line Chart chart named 'Chart Example 77' plotting 'Discount' against 'Country'. The data should be sorted in desc order and displayed using a horizontal layout. A secondary Y-axis is included, representing 'Demand'. The y-axis should be labeled as 'Axis Label' and positioned at 'start' with a name gap of 39 pixels. The column 'Generation' should be aggregating using AVG function, values should be rounded to 0 decimal places, values should be suffixed with 'USD'. The column 'coordinate_lt' should be lowest values should be colored #1d3b7a, tooltip should display 'Tooltip Label', values should be suffixed with '%'. The column 'Cost' should be aggregating using COUNT function, lowest values should be colored #866666, values should be rounded to 0 decimal places, values should be prefixed with '*'. The column 'Demand' should be aggregating using COUNT function, y-axis values should be hidden, filled with color #99ff95, highest values should be colored #f0f0f0, lowest values should be colored #f8b0y1, tooltip should display 'Tooltip Label', values should be rounded to 0 decimal places, values should be prefixed with '₹'. The column 'Price' should be lowest values should be colored #f8b0y1, tooltip should display 'Tooltip Label', values should be rounded to 1 decimal places. The column 'coordinate_lg' should be aggregating using COUNT function, filled with color #f0f0f0, highest values should be colored #99ff95, lowest values should be colored #1d3b7a, tooltip should display 'Tooltip Label', values should be rounded to 3 decimal places, values should be prefixed with '*'. The column 'Discount' should be aggregating using AVG function, lowest values should be colored #1d3b7a, values should be suffixed with 'USD'.",
    "input": "{\"dataSources\":[{\"dataSourceId\":\"ds-5867\",\"queryKey\":\"API:+auto-task$$auto_39\",\"cols\":[{\"jsonName\":\"Generation\",\"type\":\"number\"},{\"jsonName\":\"coordinate_lt\",\"type\":\"number\"},{\"jsonName\":\"Country\",\"type\":\"string\"},{\"jsonName\":\"Cost\",\"type\":\"number\"},{\"jsonName\":\"Demand\",\"type\":\"number\"},{\"jsonName\":\"Price\",\"type\":\"number\"},{\"jsonName\":\"coordinate_lg\",\"type\":\"number\"},{\"jsonName\":\"Discount\",\"type\":\"number\"}],\"params\":[]}]}",
    "output": "{\n    \"dataSources\": [\n        {\n            \"dataSourceId\": \"ds-5867\",\n            \"queryKey\": \"API:+auto-task$$auto_39\",\n            \"cols\": [\n                {\n                    \"jsonName\": \"Generation\",\n                    \"type\": \"number\",\n                    \"aggFn\": \"AVG\",\n                    \"decimalPlaces\": 0,\n                    \"suffix\": \"USD\"\n                },\n                {\n                    \"jsonName\": \"coordinate_lt\",\n                    \"type\": \"number\",\n                    \"fillLowestColor\": \"#1d3b7a\",\n                    \"label\": \"Tooltip Label\",\n                    \"suffix\": \"%\"\n                },\n                {\n                    \"jsonName\": \"Country\",\n                    \"type\": \"string\"\n                },\n                {\n                    \"jsonName\": \"Cost\",\n                    \"type\": \"number\",\n                    \"aggFn\": \"COUNT\",\n                    \"fillLowestColor\": \"#866666\",\n                    \"decimalPlaces\": 0,\n                    \"prefix\": \"*\"\n                },\n                {\n                    \"jsonName\": \"Demand\",\n                    \"type\": \"number\",\n                    \"aggFn\": \"COUNT\",\n                    \"isYAxisValueVisible\": false,\n                    \"fillColor\": \"#99ff95\",\n                    \"fillHighestColor\": \"#f0f0f0\",\n                    \"fillLowestColor\": \"#f8b0y1\",\n                    \"label\": \"Tooltip Label\",\n                    \"decimalPlaces\": 0,\n                    \"prefix\": \"\\u20b9\"\n                },\n                {\n                    \"jsonName\": \"Price\",\n                    \"type\": \"number\",\n                    \"fillLowestColor\": \"#f8b0y1\",\n                    \"label\": \"Tooltip Label\",\n                    \"decimalPlaces\": 1\n                },\n                {\n                    \"jsonName\": \"coordinate_lg\",\n                    \"type\": \"number\",\n                    \"aggFn\": \"COUNT\",\n                    \"fillColor\": \"#f0f0f0\",\n                    \"fillHighestColor\": \"#99ff95\",\n                    \"fillLowestColor\": \"#1d3b7a\",\n                    \"label\": \"Tooltip Label\",\n                    \"decimalPlaces\": 3,\n                    \"prefix\": \"*\"\n                },\n                {\n                    \"jsonName\": \"Discount\",\n                    \"type\": \"number\",\n                    \"aggFn\": \"AVG\",\n                    \"fillLowestColor\": \"#1d3b7a\",\n                    \"suffix\": \"USD\"\n                }\n            ],\n            \"params\": []\n        }\n    ],\n    \"chartLayout\": \"horizontal\",\n    \"attributes\": {\n        \"chartType\": \"Line Chart\",\n        \"sortOrder\": \"Desc\",\n        \"slider\": true,\n        \"saveImage\": true,\n        \"referenceLines\": [\n            {\n                \"referenceValueSource\": \"COMPUTED\",\n                \"referenceFor\": \"Price\",\n                \"referenceLabel\": \"Label Price\",\n                \"referenceLineColor\": \"#f0f0f0\",\n                \"referenceValue\": \"MEDIAN\",\n                \"showValue\": false\n            }\n        ]\n    },\n    \"chartName\": \"Chart Example 77\",\n    \"xAxis\": {\n        \"fields\": [\n            \"Country\"\n        ]\n    },\n    \"yAxis\": {\n        \"fields\": [\n            \"Discount\"\n        ],\n        \"label\": \"Axis Label\",\n        \"nameLocation\": \"start\",\n        \"nameGap\": 39\n    },\n    \"secondaryYAxis\": {\n        \"fields\": [\n            \"Demand\"\n        ]\n    }\n}"
  },
  {
    "instruction": "Create a Polar Pie Chart chart named 'Chart Example 78' plotting 'Price' against 'Order Date'. The data should be sorted in desc order and displayed using a horizontal layout. The y-axis should be labeled as 'Axis Label' and positioned at 'start' with a name gap of 32 pixels. Rotation is by 163 degree. The column 'Mega_watt' should be y-axis values should be hidden, filled with color #f8b0y1, values should be prefixed with '*'. The column 'coordinate_lg' should be aggregating using MIN function, highest values should be colored #866666, tooltip should display 'Tooltip Label', values should be rounded to 1 decimal places. The column 'Sales' should be aggregating using MAX function, filled with color #866666, values should be prefixed with '*'. The column 'Cost' should be aggregating using AVG function, values should be suffixed with '%'. The column 'Discount' should be aggregating using AVG function, highest values should be colored #1d3b7a, tooltip should display 'Tooltip Label', values should be rounded to 3 decimal places, values should be prefixed with '$'. The column 'Price' should be aggregating using SUM function, y-axis values should be hidden, filled with color #866666, highest values should be colored #f0f0f0, tooltip should display 'Tooltip Label', values should be rounded to 2 decimal places, values should be prefixed with '#'. The column 'coordinate_lt' should be aggregating using AVG function, filled with color #f0f0f0, lowest values should be colored #99ff95, values should be rounded to 1 decimal places, values should be prefixed with '@'.",
    "input": "{\"dataSources\":[{\"dataSourceId\":\"ds-8788\",\"queryKey\":\"API:+jdbc$$dataService$$_49\",\"cols\":[{\"jsonName\":\"Mega_watt\",\"type\":\"number\"},{\"jsonName\":\"coordinate_lg\",\"type\":\"number\"},{\"jsonName\":\"Sales\",\"type\":\"number\"},{\"jsonName\":\"Place\",\"type\":\"string\"},{\"jsonName\":\"Cost\",\"type\":\"number\"},{\"jsonName\":\"Discount\",\"type\":\"number\"},{\"jsonName\":\"Price\",\"type\":\"number\"},{\"jsonName\":\"Order Date\",\"type\":\"date\"},{\"jsonName\":\"coordinate_lt\",\"type\":\"number\"}],\"params\":[]}]}",
    "output": "{\n    \"dataSources\": [\n        {\n            \"dataSourceId\": \"ds-8788\",\n            \"queryKey\": \"API:+jdbc$$dataService$$_49\",\n            \"cols\": [\n                {\n                    \"jsonName\": \"Mega_watt\",\n                    \"type\": \"number\",\n                    \"isYAxisValueVisible\": false,\n                    \"fillColor\": \"#f8b0y1\",\n                    \"prefix\": \"*\"\n                },\n                {\n                    \"jsonName\": \"coordinate_lg\",\n                    \"type\": \"number\",\n                    \"aggFn\": \"MIN\",\n                    \"fillHighestColor\": \"#866666\",\n                    \"label\": \"Tooltip Label\",\n                    \"decimalPlaces\": 1\n                },\n                {\n                    \"jsonName\": \"Sales\",\n                    \"type\": \"number\",\n                    \"aggFn\": \"MAX\",\n                    \"fillColor\": \"#866666\",\n                    \"prefix\": \"*\"\n                },\n                {\n                    \"jsonName\": \"Place\",\n                    \"type\": \"string\"\n                },\n                {\n                    \"jsonName\": \"Cost\",\n                    \"type\": \"number\",\n                    \"aggFn\": \"AVG\",\n                    \"suffix\": \"%\"\n                },\n                {\n                    \"jsonName\": \"Discount\",\n                    \"type\": \"number\",\n                    \"aggFn\": \"AVG\",\n                    \"fillHighestColor\": \"#1d3b7a\",\n                    \"label\": \"Tooltip Label\",\n                    \"decimalPlaces\": 3,\n                    \"prefix\": \"$\"\n                },\n                {\n                    \"jsonName\": \"Price\",\n                    \"type\": \"number\",\n                    \"aggFn\": \"SUM\",\n                    \"isYAxisValueVisible\": false,\n                    \"fillColor\": \"#866666\",\n                    \"fillHighestColor\": \"#f0f0f0\",\n                    \"label\": \"Tooltip Label\",\n                    \"decimalPlaces\": 2,\n                    \"prefix\": \"#\"\n                },\n                {\n                    \"jsonName\": \"Order Date\",\n                    \"type\": \"date\"\n                },\n                {\n                    \"jsonName\": \"coordinate_lt\",\n                    \"type\": \"number\",\n                    \"aggFn\": \"AVG\",\n                    \"fillColor\": \"#f0f0f0\",\n                    \"fillLowestColor\": \"#99ff95\",\n                    \"decimalPlaces\": 1,\n                    \"prefix\": \"@\"\n                }\n            ],\n            \"params\": []\n        }\n    ],\n    \"chartLayout\": \"horizontal\",\n    \"attributes\": {\n        \"chartType\": \"Pie Chart\",\n        \"sortOrder\": \"Desc\",\n        \"slider\": true,\n        \"saveImage\": true,\n        \"chartSubType\": \"nightingale\",\n        \"rotation\": 163\n},\n    \"chartName\": \"Chart Example 78\",\n    \"xAxis\": {\n        \"fields\": [\n            \"Order Date\"\n        ]\n    },\n    \"yAxis\": {\n        \"fields\": [\n            \"Price\"\n        ],\n        \"label\": \"Axis Label\",\n        \"nameLocation\": \"start\",\n        \"nameGap\": 32\n    }\n}"
  },
  {
    "instruction": "Create a Line Chart chart named 'Chart Example 79' plotting 'Mega_watt' against 'Customer'. The data should be sorted in asc order and displayed using a horizontal layout. A secondary Y-axis is included, representing 'Profit'. The x-axis should be labeled as 'Axis Label' The y-axis should be labeled as 'Axis Label' and positioned at 'start' with a name gap of 29 pixels. The column 'Profit' should be aggregating using AVG function, filled with color #1d3b7a, highest values should be colored #f8b0y1, tooltip should display 'Tooltip Label', values should be prefixed with '₹'. The column 'longitude' should be highest values should be colored #99ff95, values should be rounded to 0 decimal places, values should be prefixed with '@'. The column 'Price' should be aggregating using MIN function, lowest values should be colored #f8b0y1, values should be prefixed with '@'. The column 'Mega_watt' should be aggregating using MAX function, y-axis values should be hidden, filled with color #99ff95. The column 'Generation' should be aggregating using AVG function, highest values should be colored #f8b0y1, tooltip should display 'Tooltip Label', values should be prefixed with '₹'. The column 'latitude' should be aggregating using MAX function, filled with color #f8b0y1, highest values should be colored #f0f0f0, lowest values should be colored #f8b0y1, values should be prefixed with '₹'.",
    "input": "{\"dataSources\":[{\"dataSourceId\":\"ds-1561\",\"queryKey\":\"API:+jdbc$$TEMP$$us_station_city_geo_data_82\",\"cols\":[{\"jsonName\":\"Profit\",\"type\":\"number\"},{\"jsonName\":\"longitude\",\"type\":\"number\"},{\"jsonName\":\"Order Date\",\"type\":\"date\"},{\"jsonName\":\"Price\",\"type\":\"number\"},{\"jsonName\":\"Mega_watt\",\"type\":\"number\"},{\"jsonName\":\"Generation\",\"type\":\"number\"},{\"jsonName\":\"Customer\",\"type\":\"string\"},{\"jsonName\":\"latitude\",\"type\":\"number\"},{\"jsonName\":\"Category\",\"type\":\"string\"},{\"jsonName\":\"Region\",\"type\":\"string\"}],\"params\":[]}]}",
    "output": "{\n    \"dataSources\": [\n        {\n            \"dataSourceId\": \"ds-1561\",\n            \"queryKey\": \"API:+jdbc$$TEMP$$us_station_city_geo_data_82\",\n            \"cols\": [\n                {\n                    \"jsonName\": \"Profit\",\n                    \"type\": \"number\",\n                    \"aggFn\": \"AVG\",\n                    \"fillColor\": \"#1d3b7a\",\n                    \"fillHighestColor\": \"#f8b0y1\",\n                    \"label\": \"Tooltip Label\",\n                    \"prefix\": \"\\u20b9\"\n                },\n                {\n                    \"jsonName\": \"longitude\",\n                    \"type\": \"number\",\n                    \"fillHighestColor\": \"#99ff95\",\n                    \"decimalPlaces\": 0,\n                    \"prefix\": \"@\"\n                },\n                {\n                    \"jsonName\": \"Order Date\",\n                    \"type\": \"date\"\n                },\n                {\n                    \"jsonName\": \"Price\",\n                    \"type\": \"number\",\n                    \"aggFn\": \"MIN\",\n                    \"fillLowestColor\": \"#f8b0y1\",\n                    \"prefix\": \"@\"\n                },\n                {\n                    \"jsonName\": \"Mega_watt\",\n                    \"type\": \"number\",\n                    \"aggFn\": \"MAX\",\n                    \"isYAxisValueVisible\": false,\n                    \"fillColor\": \"#99ff95\"\n                },\n                {\n                    \"jsonName\": \"Generation\",\n                    \"type\": \"number\",\n                    \"aggFn\": \"AVG\",\n                    \"fillHighestColor\": \"#f8b0y1\",\n                    \"label\": \"Tooltip Label\",\n                    \"prefix\": \"\\u20b9\"\n                },\n                {\n                    \"jsonName\": \"Customer\",\n                    \"type\": \"string\"\n                },\n                {\n                    \"jsonName\": \"latitude\",\n                    \"type\": \"number\",\n                    \"aggFn\": \"MAX\",\n                    \"fillColor\": \"#f8b0y1\",\n                    \"fillHighestColor\": \"#f0f0f0\",\n                    \"fillLowestColor\": \"#f8b0y1\",\n                    \"prefix\": \"\\u20b9\"\n                },\n                {\n                    \"jsonName\": \"Category\",\n                    \"type\": \"string\"\n                },\n                {\n                    \"jsonName\": \"Region\",\n                    \"type\": \"string\"\n                }\n            ],\n            \"params\": []\n        }\n    ],\n    \"chartLayout\": \"horizontal\",\n    \"attributes\": {\n        \"chartType\": \"Line Chart\",\n        \"sortOrder\": \"Asc\",\n        \"slider\": true,\n        \"saveImage\": true\n    },\n    \"chartName\": \"Chart Example 79\",\n    \"xAxis\": {\n        \"fields\": [\n            \"Customer\"\n        ],\n        \"label\": \"Axis Label\"\n    },\n    \"yAxis\": {\n        \"fields\": [\n            \"Mega_watt\"\n        ],\n        \"label\": \"Axis Label\",\n        \"nameLocation\": \"start\",\n        \"nameGap\": 29\n    },\n    \"secondaryYAxis\": {\n        \"fields\": [\n            \"Profit\"\n        ]\n    }\n}"
  },
  {
    "instruction": "Create a Bar Chart chart named 'Chart Example 80' plotting 'Mega_watt' against 'Region'. The data should be sorted in desc order and displayed using a vertical layout. A secondary Y-axis is included, representing 'Demand'. The y-axis should be labeled as 'Axis Label' and positioned at 'end' The column 'Sales' should be filled with color #99ff95, highest values should be colored #99ff95, tooltip should display 'Tooltip Label', values should be prefixed with '@'. The column 'Revenue' should be highest values should be colored #99ff95, tooltip should display 'Tooltip Label', values should be rounded to 3 decimal places. The column 'longitude' should be aggregating using MAX function, filled with color #f0f0f0, highest values should be colored #f0f0f0, lowest values should be colored #866666, values should be prefixed with '*'. The column 'Mega_watt' should be aggregating using SUM function, values should be rounded to 0 decimal places, values should be prefixed with '*'. The column 'Demand' should be highest values should be colored #1d3b7a, values should be rounded to 3 decimal places, values should be prefixed with '@'. The column 'Cost' should be aggregating using SUM function, y-axis values should be hidden, filled with color #f0f0f0, lowest values should be colored #f8b0y1, tooltip should display 'Tooltip Label', values should be prefixed with '$'.",
    "input": "{\"dataSources\":[{\"dataSourceId\":\"ds-4257\",\"queryKey\":\"API:+auto-task$$auto_20\",\"cols\":[{\"jsonName\":\"Sales\",\"type\":\"number\"},{\"jsonName\":\"SubCategory\",\"type\":\"string\"},{\"jsonName\":\"Revenue\",\"type\":\"number\"},{\"jsonName\":\"Region\",\"type\":\"string\"},{\"jsonName\":\"longitude\",\"type\":\"number\"},{\"jsonName\":\"Place\",\"type\":\"string\"},{\"jsonName\":\"Mega_watt\",\"type\":\"number\"},{\"jsonName\":\"Demand\",\"type\":\"number\"},{\"jsonName\":\"Cost\",\"type\":\"number\"}],\"params\":[]}]}",
    "output": "{\n    \"dataSources\": [\n        {\n            \"dataSourceId\": \"ds-4257\",\n            \"queryKey\": \"API:+auto-task$$auto_20\",\n            \"cols\": [\n                {\n                    \"jsonName\": \"Sales\",\n                    \"type\": \"number\",\n                    \"fillColor\": \"#99ff95\",\n                    \"fillHighestColor\": \"#99ff95\",\n                    \"label\": \"Tooltip Label\",\n                    \"prefix\": \"@\"\n                },\n                {\n                    \"jsonName\": \"SubCategory\",\n                    \"type\": \"string\"\n                },\n                {\n                    \"jsonName\": \"Revenue\",\n                    \"type\": \"number\",\n                    \"fillHighestColor\": \"#99ff95\",\n                    \"label\": \"Tooltip Label\",\n                    \"decimalPlaces\": 3\n                },\n                {\n                    \"jsonName\": \"Region\",\n                    \"type\": \"string\"\n                },\n                {\n                    \"jsonName\": \"longitude\",\n                    \"type\": \"number\",\n                    \"aggFn\": \"MAX\",\n                    \"fillColor\": \"#f0f0f0\",\n                    \"fillHighestColor\": \"#f0f0f0\",\n                    \"fillLowestColor\": \"#866666\",\n                    \"prefix\": \"*\"\n                },\n                {\n                    \"jsonName\": \"Place\",\n                    \"type\": \"string\"\n                },\n                {\n                    \"jsonName\": \"Mega_watt\",\n                    \"type\": \"number\",\n                    \"aggFn\": \"SUM\",\n                    \"decimalPlaces\": 0,\n                    \"prefix\": \"*\"\n                },\n                {\n                    \"jsonName\": \"Demand\",\n                    \"type\": \"number\",\n                    \"fillHighestColor\": \"#1d3b7a\",\n                    \"decimalPlaces\": 3,\n                    \"prefix\": \"@\"\n                },\n                {\n                    \"jsonName\": \"Cost\",\n                    \"type\": \"number\",\n                    \"aggFn\": \"SUM\",\n                    \"isYAxisValueVisible\": false,\n                    \"fillColor\": \"#f0f0f0\",\n                    \"fillLowestColor\": \"#f8b0y1\",\n                    \"label\": \"Tooltip Label\",\n                    \"prefix\": \"$\"\n                }\n            ],\n            \"params\": []\n        }\n    ],\n    \"chartLayout\": \"vertical\",\n    \"attributes\": {\n        \"chartType\": \"Bar Chart\",\n        \"sortOrder\": \"Desc\",\n        \"slider\": true,\n        \"saveImage\": true\n    },\n    \"chartName\": \"Chart Example 80\",\n    \"xAxis\": {\n        \"fields\": [\n            \"Region\"\n        ]\n    },\n    \"yAxis\": {\n        \"fields\": [\n            \"Mega_watt\"\n        ],\n        \"label\": \"Axis Label\",\n        \"nameLocation\": \"end\"\n    },\n    \"secondaryYAxis\": {\n        \"fields\": [\n            \"Demand\"\n        ]\n    }\n}"
  },
  {
    "instruction": "Create a Bar Chart chart named 'Chart Example 81' plotting 'Profit' against 'SubCategory' with legends field as 'coordinate_lg'. The data should be sorted in desc order and displayed using a horizontal layout. The x-axis should be labeled as 'Axis Label' and positioned at 'center' with a name gap of 12 pixels. The y-axis should be labeled as 'Axis Label' and positioned at 'center' with a name gap of 13 pixels. The column 'Profit' should be tooltip should display 'Tooltip Label', values should be prefixed with '*'. The column 'longitude' should be aggregating using SUM function, values should be rounded to 0 decimal places, values should be prefixed with '@'. The column 'coordinate_lg' should be aggregating using MAX function, y-axis values should be visible, lowest values should be colored #866666, tooltip should display 'Tooltip Label', values should be rounded to 3 decimal places, values should be prefixed with '@'. The column 'Sales' should be values should be rounded to 0 decimal places, values should be suffixed with 'MW'. The column 'Generation' should be highest values should be colored #f0f0f0, lowest values should be colored #f8b0y1, values should be prefixed with '#'. The column 'coordinate_lt' should be y-axis values should be hidden, lowest values should be colored #866666, tooltip should display 'Tooltip Label', values should be rounded to 1 decimal places, values should be prefixed with '*'.",
    "input": "{\"dataSources\":[{\"dataSourceId\":\"ds-5479\",\"queryKey\":\"API:+jdbc$$TEMP$$us_station_city_geo_data_27\",\"cols\":[{\"jsonName\":\"Profit\",\"type\":\"number\"},{\"jsonName\":\"longitude\",\"type\":\"number\"},{\"jsonName\":\"coordinate_lg\",\"type\":\"number\"},{\"jsonName\":\"SubCategory\",\"type\":\"string\"},{\"jsonName\":\"Sales\",\"type\":\"number\"},{\"jsonName\":\"Generation\",\"type\":\"number\"},{\"jsonName\":\"coordinate_lt\",\"type\":\"number\"},{\"jsonName\":\"Order Date\",\"type\":\"date\"}],\"params\":[]}]}",
    "output": "{\n    \"dataSources\": [\n        {\n            \"dataSourceId\": \"ds-5479\",\n            \"queryKey\": \"API:+jdbc$$TEMP$$us_station_city_geo_data_27\",\n            \"cols\": [\n                {\n                    \"jsonName\": \"Profit\",\n                    \"type\": \"number\",\n                    \"label\": \"Tooltip Label\",\n                    \"prefix\": \"*\"\n                },\n                {\n                    \"jsonName\": \"longitude\",\n                    \"type\": \"number\",\n                    \"aggFn\": \"SUM\",\n                    \"decimalPlaces\": 0,\n                    \"prefix\": \"@\"\n                },\n                {\n                    \"jsonName\": \"coordinate_lg\",\n                    \"type\": \"number\",\n                    \"aggFn\": \"MAX\",\n                    \"isYAxisValueVisible\": true,\n                    \"fillLowestColor\": \"#866666\",\n                    \"label\": \"Tooltip Label\",\n                    \"decimalPlaces\": 3,\n                    \"prefix\": \"@\"\n                },\n                {\n                    \"jsonName\": \"SubCategory\",\n                    \"type\": \"string\"\n                },\n                {\n                    \"jsonName\": \"Sales\",\n                    \"type\": \"number\",\n                    \"decimalPlaces\": 0,\n                    \"suffix\": \"MW\"\n                },\n                {\n                    \"jsonName\": \"Generation\",\n                    \"type\": \"number\",\n                    \"fillHighestColor\": \"#f0f0f0\",\n                    \"fillLowestColor\": \"#f8b0y1\",\n                    \"prefix\": \"#\"\n                },\n                {\n                    \"jsonName\": \"coordinate_lt\",\n                    \"type\": \"number\",\n                    \"isYAxisValueVisible\": false,\n                    \"fillLowestColor\": \"#866666\",\n                    \"label\": \"Tooltip Label\",\n                    \"decimalPlaces\": 1,\n                    \"prefix\": \"*\"\n                },\n                {\n                    \"jsonName\": \"Order Date\",\n                    \"type\": \"date\"\n                }\n            ],\n            \"params\": []\n        }\n    ],\n    \"chartLayout\": \"horizontal\",\n    \"attributes\": {\n        \"chartType\": \"Bar Chart\",\n        \"sortOrder\": \"Desc\",\n        \"slider\": true,\n        \"saveImage\": true,\n        \"legend\": {\n            \"fields\": \"coordinate_lg\",\n            \"colors\": {}\n        }\n    },\n    \"chartName\": \"Chart Example 81\",\n    \"xAxis\": {\n        \"fields\": [\n            \"SubCategory\"\n        ],\n        \"label\": \"Axis Label\",\n        \"nameLocation\": \"center\",\n        \"nameGap\": 12\n    },\n    \"yAxis\": {\n        \"fields\": [\n            \"Profit\"\n        ],\n        \"label\": \"Axis Label\",\n        \"nameLocation\": \"center\",\n        \"nameGap\": 13\n    }\n}"
  },
  {
    "instruction": "Create a Tree Map chart named 'Chart Example 82' plotting 'Mega_watt' against 'Country'. The data should be sorted in desc order and displayed using a horizontal layout. The x-axis should be labeled as 'Axis Label' and positioned at 'start' The column 'Cost' should be highest values should be colored #f8b0y1, tooltip should display 'Tooltip Label', values should be rounded to 3 decimal places, values should be prefixed with '₹'. The column 'coordinate_lg' should be highest values should be colored #1d3b7a, values should be prefixed with '@'. The column 'Generation' should be aggregating using MAX function, lowest values should be colored #866666, values should be prefixed with '$'. The column 'Sales' should be aggregating using AVG function, y-axis values should be hidden, highest values should be colored #1d3b7a, values should be prefixed with '#'. The column 'Mega_watt' should be highest values should be colored #866666, lowest values should be colored #f8b0y1, values should be rounded to 2 decimal places, values should be prefixed with '#'.",
    "input": "{\"dataSources\":[{\"dataSourceId\":\"ds-3522\",\"queryKey\":\"API:+auto-task$$auto_22\",\"cols\":[{\"jsonName\":\"Cost\",\"type\":\"number\"},{\"jsonName\":\"Country\",\"type\":\"string\"},{\"jsonName\":\"location\",\"type\":\"string\"},{\"jsonName\":\"coordinate_lg\",\"type\":\"number\"},{\"jsonName\":\"Generation\",\"type\":\"number\"},{\"jsonName\":\"Sales\",\"type\":\"number\"},{\"jsonName\":\"Employee\",\"type\":\"string\"},{\"jsonName\":\"Place\",\"type\":\"string\"},{\"jsonName\":\"Mega_watt\",\"type\":\"number\"}],\"params\":[]}]}",
    "output": "{\n    \"dataSources\": [\n        {\n            \"dataSourceId\": \"ds-3522\",\n            \"queryKey\": \"API:+auto-task$$auto_22\",\n            \"cols\": [\n                {\n                    \"jsonName\": \"Cost\",\n                    \"type\": \"number\",\n                    \"fillHighestColor\": \"#f8b0y1\",\n                    \"label\": \"Tooltip Label\",\n                    \"decimalPlaces\": 3,\n                    \"prefix\": \"\\u20b9\"\n                },\n                {\n                    \"jsonName\": \"Country\",\n                    \"type\": \"string\"\n                },\n                {\n                    \"jsonName\": \"location\",\n                    \"type\": \"string\"\n                },\n                {\n                    \"jsonName\": \"coordinate_lg\",\n                    \"type\": \"number\",\n                    \"fillHighestColor\": \"#1d3b7a\",\n                    \"prefix\": \"@\"\n                },\n                {\n                    \"jsonName\": \"Generation\",\n                    \"type\": \"number\",\n                    \"aggFn\": \"MAX\",\n                    \"fillLowestColor\": \"#866666\",\n                    \"prefix\": \"$\"\n                },\n                {\n                    \"jsonName\": \"Sales\",\n                    \"type\": \"number\",\n                    \"aggFn\": \"AVG\",\n                    \"isYAxisValueVisible\": false,\n                    \"fillHighestColor\": \"#1d3b7a\",\n                    \"prefix\": \"#\"\n                },\n                {\n                    \"jsonName\": \"Employee\",\n                    \"type\": \"string\"\n                },\n                {\n                    \"jsonName\": \"Place\",\n                    \"type\": \"string\"\n                },\n                {\n                    \"jsonName\": \"Mega_watt\",\n                    \"type\": \"number\",\n                    \"fillHighestColor\": \"#866666\",\n                    \"fillLowestColor\": \"#f8b0y1\",\n                    \"decimalPlaces\": 2,\n                    \"prefix\": \"#\"\n                }\n            ],\n            \"params\": []\n        }\n    ],\n    \"chartLayout\": \"horizontal\",\n    \"attributes\": {\n        \"chartType\": \"Tree Map\",\n        \"sortOrder\": \"Desc\",\n        \"slider\": true,\n        \"saveImage\": true\n    },\n    \"chartName\": \"Chart Example 82\",\n    \"xAxis\": {\n        \"fields\": [\n            \"Country\"\n        ],\n        \"label\": \"Axis Label\",\n        \"nameLocation\": \"start\"\n    },\n    \"yAxis\": {\n        \"fields\": [\n            \"Mega_watt\"\n        ]\n    }\n}"
  },
  {
    "instruction": "Create a Pie Chart chart with subtype nightingale and named 'Chart Example 83' plotting 'Demand' against 'Employee'. The data should be sorted in desc order and displayed using a vertical layout. Chart is 360 degree rotated. The column 'Demand' should be aggregating using COUNT function, highest values should be colored #1d3b7a, tooltip should display 'Tooltip Label', values should be rounded to 1 decimal places, values should be suffixed with 'p'. The column 'Cost' should be y-axis values should be hidden, filled with color #1d3b7a, highest values should be colored #f8b0y1, lowest values should be colored #866666, tooltip should display 'Tooltip Label', values should be prefixed with '#'. The column 'Price' should be filled with color #f8b0y1, values should be rounded to 1 decimal places, values should be prefixed with '*'. The column 'Mega_watt' should be aggregating using COUNT function, filled with color #f8b0y1, values should be prefixed with '#'. The column 'Generation' should be aggregating using MAX function, y-axis values should be visible, highest values should be colored #99ff95, lowest values should be colored #f0f0f0, values should be rounded to 0 decimal places.",
    "input": "{\"dataSources\":[{\"dataSourceId\":\"ds-9713\",\"queryKey\":\"API:+lookup$$lookup$$_57\",\"cols\":[{\"jsonName\":\"Demand\",\"type\":\"number\"},{\"jsonName\":\"Region\",\"type\":\"string\"},{\"jsonName\":\"Cost\",\"type\":\"number\"},{\"jsonName\":\"Price\",\"type\":\"number\"},{\"jsonName\":\"SubCategory\",\"type\":\"string\"},{\"jsonName\":\"Mega_watt\",\"type\":\"number\"},{\"jsonName\":\"Generation\",\"type\":\"number\"},{\"jsonName\":\"Employee\",\"type\":\"string\"},{\"jsonName\":\"location\",\"type\":\"string\"}],\"params\":[]}]}",
    "output": "{\n    \"dataSources\": [\n        {\n            \"dataSourceId\": \"ds-9713\",\n            \"queryKey\": \"API:+lookup$$lookup$$_57\",\n            \"cols\": [\n                {\n                    \"jsonName\": \"Demand\",\n                    \"type\": \"number\",\n                    \"aggFn\": \"COUNT\",\n                    \"fillHighestColor\": \"#1d3b7a\",\n                    \"label\": \"Tooltip Label\",\n                    \"decimalPlaces\": 1,\n                    \"suffix\": \"p\"\n                },\n                {\n                    \"jsonName\": \"Region\",\n                    \"type\": \"string\"\n                },\n                {\n                    \"jsonName\": \"Cost\",\n                    \"type\": \"number\",\n                    \"isYAxisValueVisible\": false,\n                    \"fillColor\": \"#1d3b7a\",\n                    \"fillHighestColor\": \"#f8b0y1\",\n                    \"fillLowestColor\": \"#866666\",\n                    \"label\": \"Tooltip Label\",\n                    \"prefix\": \"#\"\n                },\n                {\n                    \"jsonName\": \"Price\",\n                    \"type\": \"number\",\n                    \"fillColor\": \"#f8b0y1\",\n                    \"decimalPlaces\": 1,\n                    \"prefix\": \"*\"\n                },\n                {\n                    \"jsonName\": \"SubCategory\",\n                    \"type\": \"string\"\n                },\n                {\n                    \"jsonName\": \"Mega_watt\",\n                    \"type\": \"number\",\n                    \"aggFn\": \"COUNT\",\n                    \"fillColor\": \"#f8b0y1\",\n                    \"prefix\": \"#\"\n                },\n                {\n                    \"jsonName\": \"Generation\",\n                    \"type\": \"number\",\n                    \"aggFn\": \"MAX\",\n                    \"isYAxisValueVisible\": true,\n                    \"fillHighestColor\": \"#99ff95\",\n                    \"fillLowestColor\": \"#f0f0f0\",\n                    \"decimalPlaces\": 0\n                },\n                {\n                    \"jsonName\": \"Employee\",\n                    \"type\": \"string\"\n                },\n                {\n                    \"jsonName\": \"location\",\n                    \"type\": \"string\"\n                }\n            ],\n            \"params\": []\n        }\n    ],\n    \"chartLayout\": \"vertical\",\n    \"attributes\": {\n        \"chartType\": \"Pie Chart\",\n        \"sortOrder\": \"Desc\",\n        \"slider\": true,\n        \"saveImage\": true,\n        \"chartSubType\": \"nightingale\",\n        \"rotation\": 360\n},\n    \"chartName\": \"Chart Example 83\",\n    \"xAxis\": {\n        \"fields\": [\n            \"Employee\"\n        ]\n    },\n    \"yAxis\": {\n        \"fields\": [\n            \"Demand\"\n        ]\n    }\n}"
  },
  {
    "instruction": "Create a Tree Map chart named 'Chart Example 85' plotting 'Generation' against 'Category'. The data should be sorted in asc order and displayed using a vertical layout. The x-axis should be labeled as 'Axis Label' The y-axis should be labeled as 'Axis Label' The column 'Discount' should be aggregating using MAX function, filled with color #f8b0y1, tooltip should display 'Tooltip Label', values should be prefixed with '#'. The column 'latitude' should be aggregating using COUNT function, highest values should be colored #f0f0f0, tooltip should display 'Tooltip Label', values should be rounded to 2 decimal places, values should be prefixed with '₹'. The column 'longitude' should be lowest values should be colored #f8b0y1, tooltip should display 'Tooltip Label', values should be suffixed with 'MW'. The column 'Profit' should be filled with color #99ff95, tooltip should display 'Tooltip Label', values should be rounded to 2 decimal places, values should be prefixed with '#'. The column 'coordinate_lg' should be lowest values should be colored #866666, tooltip should display 'Tooltip Label', values should be rounded to 1 decimal places. The column 'Sales' should be aggregating using COUNT function, highest values should be colored #f0f0f0, tooltip should display 'Tooltip Label', values should be rounded to 2 decimal places. The column 'Generation' should be aggregating using MIN function, lowest values should be colored #f8b0y1, values should be prefixed with '$'.",
    "input": "{\"dataSources\":[{\"dataSourceId\":\"ds-5052\",\"queryKey\":\"API:+jdbc$$pmgr$$caps_46\",\"cols\":[{\"jsonName\":\"Discount\",\"type\":\"number\"},{\"jsonName\":\"latitude\",\"type\":\"number\"},{\"jsonName\":\"longitude\",\"type\":\"number\"},{\"jsonName\":\"Customer\",\"type\":\"string\"},{\"jsonName\":\"Region\",\"type\":\"string\"},{\"jsonName\":\"Profit\",\"type\":\"number\"},{\"jsonName\":\"coordinate_lg\",\"type\":\"number\"},{\"jsonName\":\"Sales\",\"type\":\"number\"},{\"jsonName\":\"Generation\",\"type\":\"number\"},{\"jsonName\":\"Category\",\"type\":\"string\"}],\"params\":[]}]}",
    "output": "{\n    \"dataSources\": [\n        {\n            \"dataSourceId\": \"ds-5052\",\n            \"queryKey\": \"API:+jdbc$$pmgr$$caps_46\",\n            \"cols\": [\n                {\n                    \"jsonName\": \"Discount\",\n                    \"type\": \"number\",\n                    \"aggFn\": \"MAX\",\n                    \"fillColor\": \"#f8b0y1\",\n                    \"label\": \"Tooltip Label\",\n                    \"prefix\": \"#\"\n                },\n                {\n                    \"jsonName\": \"latitude\",\n                    \"type\": \"number\",\n                    \"aggFn\": \"COUNT\",\n                    \"fillHighestColor\": \"#f0f0f0\",\n                    \"label\": \"Tooltip Label\",\n                    \"decimalPlaces\": 2,\n                    \"prefix\": \"\\u20b9\"\n                },\n                {\n                    \"jsonName\": \"longitude\",\n                    \"type\": \"number\",\n                    \"fillLowestColor\": \"#f8b0y1\",\n                    \"label\": \"Tooltip Label\",\n                    \"suffix\": \"MW\"\n                },\n                {\n                    \"jsonName\": \"Customer\",\n                    \"type\": \"string\"\n                },\n                {\n                    \"jsonName\": \"Region\",\n                    \"type\": \"string\"\n                },\n                {\n                    \"jsonName\": \"Profit\",\n                    \"type\": \"number\",\n                    \"fillColor\": \"#99ff95\",\n                    \"label\": \"Tooltip Label\",\n                    \"decimalPlaces\": 2,\n                    \"prefix\": \"#\"\n                },\n                {\n                    \"jsonName\": \"coordinate_lg\",\n                    \"type\": \"number\",\n                    \"fillLowestColor\": \"#866666\",\n                    \"label\": \"Tooltip Label\",\n                    \"decimalPlaces\": 1\n                },\n                {\n                    \"jsonName\": \"Sales\",\n                    \"type\": \"number\",\n                    \"aggFn\": \"COUNT\",\n                    \"fillHighestColor\": \"#f0f0f0\",\n                    \"label\": \"Tooltip Label\",\n                    \"decimalPlaces\": 2\n                },\n                {\n                    \"jsonName\": \"Generation\",\n                    \"type\": \"number\",\n                    \"aggFn\": \"MIN\",\n                    \"fillLowestColor\": \"#f8b0y1\",\n                    \"prefix\": \"$\"\n                },\n                {\n                    \"jsonName\": \"Category\",\n                    \"type\": \"string\"\n                }\n            ],\n            \"params\": []\n        }\n    ],\n    \"chartLayout\": \"vertical\",\n    \"attributes\": {\n        \"chartType\": \"Tree Map\",\n        \"sortOrder\": \"Asc\",\n        \"slider\": true,\n        \"saveImage\": true\n    },\n    \"chartName\": \"Chart Example 85\",\n    \"xAxis\": {\n        \"fields\": [\n            \"Category\"\n        ],\n        \"label\": \"Axis Label\"\n    },\n    \"yAxis\": {\n        \"fields\": [\n            \"Generation\"\n        ],\n        \"label\": \"Axis Label\"\n    }\n}"
  },
  {
    "instruction": "Create a Pie Chart chart named 'Chart Example 86' plotting 'Discount' against 'Place'. The data should be sorted in asc order and displayed using a horizontal layout. The x-axis should be labeled as 'Axis Label' and positioned at 'end'. Rotation is 33 degree & subtype is nightingale. The column 'Discount' should be aggregating using COUNT function, y-axis values should be visible, filled with color #866666, tooltip should display 'Tooltip Label', values should be prefixed with '₹'. The column 'Cost' should be aggregating using COUNT function, lowest values should be colored #f8b0y1, values should be rounded to 0 decimal places, values should be suffixed with 'p'. The column 'Generation' should be values should be rounded to 0 decimal places, values should be suffixed with 'USD'. The column 'latitude' should be aggregating using COUNT function, highest values should be colored #866666, tooltip should display 'Tooltip Label', values should be rounded to 0 decimal places, values should be prefixed with '#'.",
    "input": "{\"dataSources\":[{\"dataSourceId\":\"ds-8395\",\"queryKey\":\"API:+jdbc$$Oracle$$Energy_API_10\",\"cols\":[{\"jsonName\":\"Place\",\"type\":\"string\"},{\"jsonName\":\"SubCategory\",\"type\":\"string\"},{\"jsonName\":\"Employee\",\"type\":\"string\"},{\"jsonName\":\"Discount\",\"type\":\"number\"},{\"jsonName\":\"Cost\",\"type\":\"number\"},{\"jsonName\":\"Generation\",\"type\":\"number\"},{\"jsonName\":\"Order Date\",\"type\":\"date\"},{\"jsonName\":\"latitude\",\"type\":\"number\"}],\"params\":[]}]}",
    "output": "{\n    \"dataSources\": [\n        {\n            \"dataSourceId\": \"ds-8395\",\n            \"queryKey\": \"API:+jdbc$$Oracle$$Energy_API_10\",\n            \"cols\": [\n                {\n                    \"jsonName\": \"Place\",\n                    \"type\": \"string\"\n                },\n                {\n                    \"jsonName\": \"SubCategory\",\n                    \"type\": \"string\"\n                },\n                {\n                    \"jsonName\": \"Employee\",\n                    \"type\": \"string\"\n                },\n                {\n                    \"jsonName\": \"Discount\",\n                    \"type\": \"number\",\n                    \"aggFn\": \"COUNT\",\n                    \"isYAxisValueVisible\": true,\n                    \"fillColor\": \"#866666\",\n                    \"label\": \"Tooltip Label\",\n                    \"prefix\": \"\\u20b9\"\n                },\n                {\n                    \"jsonName\": \"Cost\",\n                    \"type\": \"number\",\n                    \"aggFn\": \"COUNT\",\n                    \"fillLowestColor\": \"#f8b0y1\",\n                    \"decimalPlaces\": 0,\n                    \"suffix\": \"p\"\n                },\n                {\n                    \"jsonName\": \"Generation\",\n                    \"type\": \"number\",\n                    \"decimalPlaces\": 0,\n                    \"suffix\": \"USD\"\n                },\n                {\n                    \"jsonName\": \"Order Date\",\n                    \"type\": \"date\"\n                },\n                {\n                    \"jsonName\": \"latitude\",\n                    \"type\": \"number\",\n                    \"aggFn\": \"COUNT\",\n                    \"fillHighestColor\": \"#866666\",\n                    \"label\": \"Tooltip Label\",\n                    \"decimalPlaces\": 0,\n                    \"prefix\": \"#\"\n                }\n            ],\n            \"params\": []\n        }\n    ],\n    \"chartLayout\": \"horizontal\",\n    \"attributes\": {\n        \"chartType\": \"Pie Chart\",\n        \"sortOrder\": \"Asc\",\n        \"slider\": true,\n        \"saveImage\": true,\n        \"chartSubType\": \"nightingale\",\n        \"rotation\": 33\n    },\n    \"chartName\": \"Chart Example 86\",\n    \"xAxis\": {\n        \"fields\": [\n            \"Place\"\n        ],\n        \"label\": \"Axis Label\",\n        \"nameLocation\": \"end\"\n    },\n    \"yAxis\": {\n        \"fields\": [\n            \"Discount\"\n        ]\n    }\n}"
  },
  {
    "instruction": "Create a Line Chart chart named 'Chart Example 87' plotting 'Generation' against 'SubCategory'. The data should be sorted in desc order and displayed using a horizontal layout. A secondary Y-axis is included, representing 'Revenue'. The y-axis should be labeled as 'Axis Label' with a name gap of 44 pixels. The column 'latitude' should be aggregating using AVG function, filled with color #1d3b7a, highest values should be colored #866666, lowest values should be colored #1d3b7a, tooltip should display 'Tooltip Label', values should be rounded to 1 decimal places. The column 'Revenue' should be aggregating using COUNT function, filled with color #99ff95, highest values should be colored #866666, tooltip should display 'Tooltip Label', values should be rounded to 1 decimal places, values should be prefixed with '#'. The column 'Generation' should be aggregating using COUNT function, lowest values should be colored #1d3b7a, values should be rounded to 2 decimal places. The column 'longitude' should be filled with color #f0f0f0, lowest values should be colored #99ff95, tooltip should display 'Tooltip Label', values should be rounded to 0 decimal places, values should be prefixed with '@'.",
    "input": "{\"dataSources\":[{\"dataSourceId\":\"ds-5909\",\"queryKey\":\"API:+auto-task$$auto_96\",\"cols\":[{\"jsonName\":\"latitude\",\"type\":\"number\"},{\"jsonName\":\"SubCategory\",\"type\":\"string\"},{\"jsonName\":\"Revenue\",\"type\":\"number\"},{\"jsonName\":\"Place\",\"type\":\"string\"},{\"jsonName\":\"Customer\",\"type\":\"string\"},{\"jsonName\":\"Generation\",\"type\":\"number\"},{\"jsonName\":\"Country\",\"type\":\"string\"},{\"jsonName\":\"longitude\",\"type\":\"number\"}],\"params\":[]}]}",
    "output": "{\n    \"dataSources\": [\n        {\n            \"dataSourceId\": \"ds-5909\",\n            \"queryKey\": \"API:+auto-task$$auto_96\",\n            \"cols\": [\n                {\n                    \"jsonName\": \"latitude\",\n                    \"type\": \"number\",\n                    \"aggFn\": \"AVG\",\n                    \"fillColor\": \"#1d3b7a\",\n                    \"fillHighestColor\": \"#866666\",\n                    \"fillLowestColor\": \"#1d3b7a\",\n                    \"label\": \"Tooltip Label\",\n                    \"decimalPlaces\": 1\n                },\n                {\n                    \"jsonName\": \"SubCategory\",\n                    \"type\": \"string\"\n                },\n                {\n                    \"jsonName\": \"Revenue\",\n                    \"type\": \"number\",\n                    \"aggFn\": \"COUNT\",\n                    \"fillColor\": \"#99ff95\",\n                    \"fillHighestColor\": \"#866666\",\n                    \"label\": \"Tooltip Label\",\n                    \"decimalPlaces\": 1,\n                    \"prefix\": \"#\"\n                },\n                {\n                    \"jsonName\": \"Place\",\n                    \"type\": \"string\"\n                },\n                {\n                    \"jsonName\": \"Customer\",\n                    \"type\": \"string\"\n                },\n                {\n                    \"jsonName\": \"Generation\",\n                    \"type\": \"number\",\n                    \"aggFn\": \"COUNT\",\n                    \"fillLowestColor\": \"#1d3b7a\",\n                    \"decimalPlaces\": 2\n                },\n                {\n                    \"jsonName\": \"Country\",\n                    \"type\": \"string\"\n                },\n                {\n                    \"jsonName\": \"longitude\",\n                    \"type\": \"number\",\n                    \"fillColor\": \"#f0f0f0\",\n                    \"fillLowestColor\": \"#99ff95\",\n                    \"label\": \"Tooltip Label\",\n                    \"decimalPlaces\": 0,\n                    \"prefix\": \"@\"\n                }\n            ],\n            \"params\": []\n        }\n    ],\n    \"chartLayout\": \"horizontal\",\n    \"attributes\": {\n        \"chartType\": \"Line Chart\",\n        \"sortOrder\": \"Desc\",\n        \"slider\": true,\n        \"saveImage\": true\n    },\n    \"chartName\": \"Chart Example 87\",\n    \"xAxis\": {\n        \"fields\": [\n            \"SubCategory\"\n        ]\n    },\n    \"yAxis\": {\n        \"fields\": [\n            \"Generation\"\n        ],\n        \"label\": \"Axis Label\",\n        \"nameGap\": 44\n    },\n    \"secondaryYAxis\": {\n        \"fields\": [\n            \"Revenue\"\n        ]\n    }\n}"
  },
  {
    "instruction": "Create a Scattered Chart chart named 'Chart Example 88' plotting 'Discount' against 'SubCategory'. The data should be sorted in asc order and displayed using a vertical layout. A Z-axis is also present, containing 'Price'. The x-axis should be labeled as 'Axis Label' The column 'Mega_watt' should be aggregating using COUNT function, y-axis values should be hidden, highest values should be colored #866666, lowest values should be colored #866666, values should be rounded to 2 decimal places, values should be prefixed with '#'. The column 'coordinate_lg' should be aggregating using SUM function, values should be prefixed with '$'. The column 'Price' should be aggregating using COUNT function, lowest values should be colored #866666, values should be rounded to 1 decimal places, values should be suffixed with 'MW'. The column 'Discount' should be aggregating using AVG function, lowest values should be colored #1d3b7a, tooltip should display 'Tooltip Label', values should be rounded to 0 decimal places, values should be prefixed with '@'.",
    "input": "{\"dataSources\":[{\"dataSourceId\":\"ds-7844\",\"queryKey\":\"API:+jdbc$$dataService$$_60\",\"cols\":[{\"jsonName\":\"SubCategory\",\"type\":\"string\"},{\"jsonName\":\"Order Date\",\"type\":\"date\"},{\"jsonName\":\"Category\",\"type\":\"string\"},{\"jsonName\":\"Country\",\"type\":\"string\"},{\"jsonName\":\"Mega_watt\",\"type\":\"number\"},{\"jsonName\":\"coordinate_lg\",\"type\":\"number\"},{\"jsonName\":\"Price\",\"type\":\"number\"},{\"jsonName\":\"Discount\",\"type\":\"number\"}],\"params\":[]}]}",
    "output": "{\n    \"dataSources\": [\n        {\n            \"dataSourceId\": \"ds-7844\",\n            \"queryKey\": \"API:+jdbc$$dataService$$_60\",\n            \"cols\": [\n                {\n                    \"jsonName\": \"SubCategory\",\n                    \"type\": \"string\"\n                },\n                {\n                    \"jsonName\": \"Order Date\",\n                    \"type\": \"date\"\n                },\n                {\n                    \"jsonName\": \"Category\",\n                    \"type\": \"string\"\n                },\n                {\n                    \"jsonName\": \"Country\",\n                    \"type\": \"string\"\n                },\n                {\n                    \"jsonName\": \"Mega_watt\",\n                    \"type\": \"number\",\n                    \"aggFn\": \"COUNT\",\n                    \"isYAxisValueVisible\": false,\n                    \"fillHighestColor\": \"#866666\",\n                    \"fillLowestColor\": \"#866666\",\n                    \"decimalPlaces\": 2,\n                    \"prefix\": \"#\"\n                },\n                {\n                    \"jsonName\": \"coordinate_lg\",\n                    \"type\": \"number\",\n                    \"aggFn\": \"SUM\",\n                    \"prefix\": \"$\"\n                },\n                {\n                    \"jsonName\": \"Price\",\n                    \"type\": \"number\",\n                    \"aggFn\": \"COUNT\",\n                    \"fillLowestColor\": \"#866666\",\n                    \"decimalPlaces\": 1,\n                    \"suffix\": \"MW\"\n                },\n                {\n                    \"jsonName\": \"Discount\",\n                    \"type\": \"number\",\n                    \"aggFn\": \"AVG\",\n                    \"fillLowestColor\": \"#1d3b7a\",\n                    \"label\": \"Tooltip Label\",\n                    \"decimalPlaces\": 0,\n                    \"prefix\": \"@\"\n                }\n            ],\n            \"params\": []\n        }\n    ],\n    \"chartLayout\": \"vertical\",\n    \"attributes\": {\n        \"chartType\": \"Scattered Chart\",\n        \"sortOrder\": \"Asc\",\n        \"slider\": true,\n        \"saveImage\": true\n}\n    },\n    \"chartName\": \"Chart Example 88\",\n    \"xAxis\": {\n        \"fields\": [\n            \"SubCategory\"\n        ],\n        \"label\": \"Axis Label\"\n    },\n    \"yAxis\": {\n        \"fields\": [\n            \"Discount\"\n        ]\n    },\n    \"zAxis\": {\n        \"fields\": [\n            \"Price\"\n        ]\n    }\n}"
  },
  {
    "instruction": "Create a Pie Chart chart named 'Chart Example 89' plotting 'Generation' against 'Category' rotated by 222 degree and viewed as nightingale. The data should be sorted in desc order and displayed using a vertical layout. The column 'Revenue' should be aggregating using MAX function, values should be suffixed with '%'. The column 'latitude' should be aggregating using AVG function, y-axis values should be hidden, tooltip should display 'Tooltip Label', values should be prefixed with '@'. The column 'Generation' should be aggregating using MAX function, filled with color #99ff95, lowest values should be colored #1d3b7a.",
    "input": "{\"dataSources\":[{\"dataSourceId\":\"ds-2130\",\"queryKey\":\"API:+jdbc$$aws$$_99\",\"cols\":[{\"jsonName\":\"Revenue\",\"type\":\"number\"},{\"jsonName\":\"Place\",\"type\":\"string\"},{\"jsonName\":\"Category\",\"type\":\"string\"},{\"jsonName\":\"latitude\",\"type\":\"number\"},{\"jsonName\":\"Employee\",\"type\":\"string\"},{\"jsonName\":\"Generation\",\"type\":\"number\"},{\"jsonName\":\"Customer\",\"type\":\"string\"},{\"jsonName\":\"location\",\"type\":\"string\"}],\"params\":[]}]}",
    "output": "{\n    \"dataSources\": [\n        {\n            \"dataSourceId\": \"ds-2130\",\n            \"queryKey\": \"API:+jdbc$$aws$$_99\",\n            \"cols\": [\n                {\n                    \"jsonName\": \"Revenue\",\n                    \"type\": \"number\",\n                    \"aggFn\": \"MAX\",\n                    \"suffix\": \"%\"\n                },\n                {\n                    \"jsonName\": \"Place\",\n                    \"type\": \"string\"\n                },\n                {\n                    \"jsonName\": \"Category\",\n                    \"type\": \"string\"\n                },\n                {\n                    \"jsonName\": \"latitude\",\n                    \"type\": \"number\",\n                    \"aggFn\": \"AVG\",\n                    \"isYAxisValueVisible\": false,\n                    \"label\": \"Tooltip Label\",\n                    \"prefix\": \"@\"\n                },\n                {\n                    \"jsonName\": \"Employee\",\n                    \"type\": \"string\"\n                },\n                {\n                    \"jsonName\": \"Generation\",\n                    \"type\": \"number\",\n                    \"aggFn\": \"MAX\",\n                    \"fillColor\": \"#99ff95\",\n                    \"fillLowestColor\": \"#1d3b7a\"\n                },\n                {\n                    \"jsonName\": \"Customer\",\n                    \"type\": \"string\"\n                },\n                {\n                    \"jsonName\": \"location\",\n                    \"type\": \"string\"\n                }\n            ],\n            \"params\": []\n        }\n    ],\n    \"chartLayout\": \"vertical\",\n    \"attributes\": {\n        \"chartType\": \"Pie Chart\",\n        \"sortOrder\": \"Desc\",\n        \"slider\": true,\n        \"saveImage\": true,\n        \"chartSubType\": \"nightingale\",\n        \"rotation\": 222\n    },\n    \"chartName\": \"Chart Example 89\",\n    \"xAxis\": {\n        \"fields\": [\n            \"Category\"\n        ]\n    },\n    \"yAxis\": {\n        \"fields\": [\n            \"Generation\"\n        ]\n    }\n}"
  },
  {
    "instruction": "Create a Gantt Chart chart named 'Chart Example 90' plotting 'startDate' and 'endDate' with 'Place'. The data should be sorted in asc order and displayed using a horizontal layout. The x-axis should be labeled as 'Axis Label' and positioned at 'end' The column 'Demand' should be aggregating using SUM function, lowest values should be colored #f0f0f0, tooltip should display 'Tooltip Label', values should be prefixed with '#'. The column 'Revenue' should be aggregating using MIN function, tooltip should display 'Tooltip Label', values should be rounded to 0 decimal places, values should be suffixed with 'USD'. The column 'Discount' should be values should be rounded to 0 decimal places, values should be prefixed with '$'.",
    "input": "{\"dataSources\":[{\"dataSourceId\":\"ds-8975\",\"queryKey\":\"API:+jdbc$$aws$$_99\",\"cols\":[{\"jsonName\":\"startDate\",\"type\":\"date\"},{\"jsonName\":\"endDate\",\"type\":\"date\"},{\"jsonName\":\"Demand\",\"type\":\"number\"},{\"jsonName\":\"Revenue\",\"type\":\"number\"},{\"jsonName\":\"Country\",\"type\":\"string\"},{\"jsonName\":\"Discount\",\"type\":\"number\"},{\"jsonName\":\"Place\",\"type\":\"string\"},{\"jsonName\":\"Category\",\"type\":\"string\"}],\"params\":[]}]}",
    "output": "{\n    \"dataSources\": [\n        {\n            \"dataSourceId\": \"ds-8975\",\n            \"queryKey\": \"API:+jdbc$$aws$$_99\",\n            \"cols\": [\n                {\n                    \"jsonName\": \"startDate\",\n                    \"type\": \"date\"\n                },\n                {\n                    \"jsonName\": \"endDate\",\n                    \"type\": \"date\"\n                },\n                {\n                    \"jsonName\": \"Demand\",\n                    \"type\": \"number\",\n                    \"aggFn\": \"SUM\",\n                    \"fillLowestColor\": \"#f0f0f0\",\n                    \"label\": \"Tooltip Label\",\n                    \"prefix\": \"#\"\n                },\n                {\n                    \"jsonName\": \"Revenue\",\n                    \"type\": \"number\",\n                    \"aggFn\": \"MIN\",\n                    \"label\": \"Tooltip Label\",\n                    \"decimalPlaces\": 0,\n                    \"suffix\": \"USD\"\n                },\n                {\n                    \"jsonName\": \"Country\",\n                    \"type\": \"string\"\n                },\n                {\n                    \"jsonName\": \"Discount\",\n                    \"type\": \"number\",\n                    \"decimalPlaces\": 0,\n                    \"prefix\": \"$\"\n                },\n                {\n                    \"jsonName\": \"Place\",\n                    \"type\": \"string\"\n                },\n                {\n                    \"jsonName\": \"Category\",\n                    \"type\": \"string\"\n                }\n            ],\n            \"params\": []\n        }\n    ],\n    \"chartLayout\": \"horizontal\",\n    \"attributes\": {\n        \"chartType\": \"Gantt Chart\",\n        \"sortOrder\": \"Asc\",\n        \"slider\": true,\n        \"saveImage\": true\n    },\n    \"chartName\": \"Chart Example 90\",\n    \"xAxis\": {\n        \"fields\": [\n            \"Place\"\n        ],\n        \"label\": \"Axis Label\",\n        \"nameLocation\": \"end\"\n    },\n    \"yAxis\": {\n        \"fields\": [\n            \"startDate\"\n,   \"endDate\"\n        ]\n    }\n}"
  },
  {
    "instruction": "Create a Composed Chart chart named 'Chart Example 91' plotting 'Generation' against 'Place'. The data should be sorted in asc order and displayed using a vertical layout. A secondary Y-axis is included, representing 'Cost'. 'Cost' and 'Generation' both are Bar Charts. The column 'Price' should be aggregating using AVG function, lowest values should be colored #f0f0f0, values should be rounded to 1 decimal places, values should be prefixed with '@'. The column 'longitude' should be aggregating using SUM function, y-axis values should be visible, highest values should be colored #99ff95, tooltip should display 'Tooltip Label', values should be rounded to 1 decimal places. The column 'Cost' should be aggregating using SUM function, lowest values should be colored #f8b0y1. The column 'Revenue' should be aggregating using MIN function, filled with color #99ff95, highest values should be colored #99ff95, values should be rounded to 2 decimal places. The column 'Sales' should be filled with color #f8b0y1, highest values should be colored #99ff95, values should be rounded to 2 decimal places, values should be suffixed with 'USD'. The column 'Generation' should be aggregating using COUNT function, highest values should be colored #866666, lowest values should be colored #866666, values should be rounded to 3 decimal places, values should be prefixed with '@'.",
    "input": "{\"dataSources\":[{\"dataSourceId\":\"ds-7072\",\"queryKey\":\"API:+jdbc$$aws$$_93\",\"cols\":[{\"jsonName\":\"Price\",\"type\":\"number\"},{\"jsonName\":\"Order Date\",\"type\":\"date\"},{\"jsonName\":\"longitude\",\"type\":\"number\"},{\"jsonName\":\"Place\",\"type\":\"string\"},{\"jsonName\":\"Cost\",\"type\":\"number\"},{\"jsonName\":\"Revenue\",\"type\":\"number\"},{\"jsonName\":\"Sales\",\"type\":\"number\"},{\"jsonName\":\"SubCategory\",\"type\":\"string\"},{\"jsonName\":\"Generation\",\"type\":\"number\"},{\"jsonName\":\"Customer\",\"type\":\"string\"}],\"params\":[]}]}",
    "output": "{\n    \"dataSources\": [\n        {\n            \"dataSourceId\": \"ds-7072\",\n            \"queryKey\": \"API:+jdbc$$aws$$_93\",\n            \"cols\": [\n                {\n                    \"jsonName\": \"Price\",\n                    \"type\": \"number\",\n                    \"aggFn\": \"AVG\",\n                    \"fillLowestColor\": \"#f0f0f0\",\n                    \"decimalPlaces\": 1,\n                    \"prefix\": \"@\"\n                },\n                {\n                    \"jsonName\": \"Order Date\",\n                    \"type\": \"date\"\n                },\n                {\n                    \"jsonName\": \"longitude\",\n                    \"type\": \"number\",\n                    \"aggFn\": \"SUM\",\n                    \"isYAxisValueVisible\": true,\n                    \"fillHighestColor\": \"#99ff95\",\n                    \"label\": \"Tooltip Label\",\n                    \"decimalPlaces\": 1\n                },\n                {\n                    \"jsonName\": \"Place\",\n                    \"type\": \"string\"\n                },\n                {\n                    \"jsonName\": \"Cost\",\n                    \"type\": \"number\",\n                    \"composedChartType\": \"Bar Chart\",\n                   \"aggFn\": \"SUM\",\n                    \"fillLowestColor\": \"#f8b0y1\"\n                },\n                {\n                    \"jsonName\": \"Revenue\",\n                    \"type\": \"number\",\n                    \"aggFn\": \"MIN\",\n                    \"fillColor\": \"#99ff95\",\n                    \"fillHighestColor\": \"#99ff95\",\n                    \"decimalPlaces\": 2\n                },\n                {\n                    \"jsonName\": \"Sales\",\n                    \"type\": \"number\",\n                    \"fillColor\": \"#f8b0y1\",\n                    \"fillHighestColor\": \"#99ff95\",\n                    \"decimalPlaces\": 2,\n                    \"suffix\": \"USD\"\n                },\n                {\n                    \"jsonName\": \"SubCategory\",\n                    \"type\": \"string\"\n                },\n                {\n                    \"jsonName\": \"Generation\",\n                    \"type\": \"number\",\n                    \"composedChartType\": \"Bar Chart\",\n                     \"aggFn\": \"COUNT\",\n                    \"fillHighestColor\": \"#866666\",\n                    \"fillLowestColor\": \"#866666\",\n                    \"decimalPlaces\": 3,\n                    \"prefix\": \"@\"\n                },\n                {\n                    \"jsonName\": \"Customer\",\n                    \"type\": \"string\"\n                }\n            ],\n            \"params\": []\n        }\n    ],\n    \"chartLayout\": \"vertical\",\n    \"attributes\": {\n        \"chartType\": \"Composed Chart\",\n        \"sortOrder\": \"Asc\",\n        \"slider\": true,\n        \"saveImage\": true\n    },\n    \"chartName\": \"Chart Example 91\",\n    \"xAxis\": {\n        \"fields\": [\n            \"Place\"\n        ]\n    },\n    \"yAxis\": {\n        \"fields\": [\n            \"Generation\"\n        ]\n    },\n    \"secondaryYAxis\": {\n        \"fields\": [\n            \"Cost\"\n        ]\n    }\n}"
  },
  {
    "instruction": "Create a Tree Map chart named 'Chart Example 92' plotting 'Profit' against 'SubCategory'. The data should be sorted in asc order and displayed using a horizontal layout. The x-axis should be labeled as 'Axis Label' The y-axis should be labeled as 'Axis Label' with a name gap of 25 pixels. The column 'Cost' should be aggregating using SUM function, lowest values should be colored #866666, tooltip should display 'Tooltip Label', values should be rounded to 3 decimal places, values should be prefixed with '@'. The column 'Profit' should be aggregating using MAX function, values should be rounded to 2 decimal places, values should be prefixed with '@'. The column 'longitude' should be aggregating using MIN function, y-axis values should be visible, tooltip should display 'Tooltip Label', values should be rounded to 1 decimal places, values should be prefixed with '*'. The column 'Generation' should be highest values should be colored #99ff95, tooltip should display 'Tooltip Label', values should be rounded to 3 decimal places. The column 'coordinate_lt' should be aggregating using AVG function, tooltip should display 'Tooltip Label', values should be rounded to 1 decimal places, values should be prefixed with '#'.",
    "input": "{\"dataSources\":[{\"dataSourceId\":\"ds-5061\",\"queryKey\":\"API:+auto-task$$auto-task_42\",\"cols\":[{\"jsonName\":\"Employee\",\"type\":\"string\"},{\"jsonName\":\"Cost\",\"type\":\"number\"},{\"jsonName\":\"Profit\",\"type\":\"number\"},{\"jsonName\":\"longitude\",\"type\":\"number\"},{\"jsonName\":\"Customer\",\"type\":\"string\"},{\"jsonName\":\"Place\",\"type\":\"string\"},{\"jsonName\":\"Generation\",\"type\":\"number\"},{\"jsonName\":\"coordinate_lt\",\"type\":\"number\"},{\"jsonName\":\"location\",\"type\":\"string\"},{\"jsonName\":\"SubCategory\",\"type\":\"string\"}],\"params\":[]}]}",
    "output": "{\n    \"dataSources\": [\n        {\n            \"dataSourceId\": \"ds-5061\",\n            \"queryKey\": \"API:+auto-task$$auto-task_42\",\n            \"cols\": [\n                {\n                    \"jsonName\": \"Employee\",\n                    \"type\": \"string\"\n                },\n                {\n                    \"jsonName\": \"Cost\",\n                    \"type\": \"number\",\n                    \"aggFn\": \"SUM\",\n                    \"fillLowestColor\": \"#866666\",\n                    \"label\": \"Tooltip Label\",\n                    \"decimalPlaces\": 3,\n                    \"prefix\": \"@\"\n                },\n                {\n                    \"jsonName\": \"Profit\",\n                    \"type\": \"number\",\n                    \"aggFn\": \"MAX\",\n                    \"decimalPlaces\": 2,\n                    \"prefix\": \"@\"\n                },\n                {\n                    \"jsonName\": \"longitude\",\n                    \"type\": \"number\",\n                    \"aggFn\": \"MIN\",\n                    \"isYAxisValueVisible\": true,\n                    \"label\": \"Tooltip Label\",\n                    \"decimalPlaces\": 1,\n                    \"prefix\": \"*\"\n                },\n                {\n                    \"jsonName\": \"Customer\",\n                    \"type\": \"string\"\n                },\n                {\n                    \"jsonName\": \"Place\",\n                    \"type\": \"string\"\n                },\n                {\n                    \"jsonName\": \"Generation\",\n                    \"type\": \"number\",\n                    \"fillHighestColor\": \"#99ff95\",\n                    \"label\": \"Tooltip Label\",\n                    \"decimalPlaces\": 3\n                },\n                {\n                    \"jsonName\": \"coordinate_lt\",\n                    \"type\": \"number\",\n                    \"aggFn\": \"AVG\",\n                    \"label\": \"Tooltip Label\",\n                    \"decimalPlaces\": 1,\n                    \"prefix\": \"#\"\n                },\n                {\n                    \"jsonName\": \"location\",\n                    \"type\": \"string\"\n                },\n                {\n                    \"jsonName\": \"SubCategory\",\n                    \"type\": \"string\"\n                }\n            ],\n            \"params\": []\n        }\n    ],\n    \"chartLayout\": \"horizontal\",\n    \"attributes\": {\n        \"chartType\": \"Tree Map\",\n        \"sortOrder\": \"Asc\",\n        \"slider\": true,\n        \"saveImage\": true\n    },\n    \"chartName\": \"Chart Example 92\",\n    \"xAxis\": {\n        \"fields\": [\n            \"SubCategory\"\n        ],\n        \"label\": \"Axis Label\"\n    },\n    \"yAxis\": {\n        \"fields\": [\n            \"Profit\"\n        ],\n        \"label\": \"Axis Label\",\n        \"nameGap\": 25\n    }\n}"
  },
  {
    "instruction": "Create a Scattered Chart chart named 'Chart Example 93' plotting 'Profit' against 'SubCategory'. The data should be sorted in desc order and displayed using a vertical layout. A Z-axis is also present, containing 'Generation'. The column 'latitude' should be aggregating using AVG function, filled with color #99ff95, values should be rounded to 2 decimal places, values should be prefixed with '@'. The column 'Profit' should be lowest values should be colored #f8b0y1, tooltip should display 'Tooltip Label', values should be prefixed with '*'. The column 'Cost' should be filled with color #866666, highest values should be colored #99ff95, lowest values should be colored #866666, tooltip should display 'Tooltip Label', values should be rounded to 2 decimal places, values should be prefixed with '₹'. The column 'Demand' should be aggregating using COUNT function, y-axis values should be hidden, highest values should be colored #f0f0f0, tooltip should display 'Tooltip Label', values should be prefixed with '#'. The column 'coordinate_lg' should be aggregating using AVG function, lowest values should be colored #99ff95, values should be suffixed with 'p'. The column 'Generation' should be aggregating using SUM function, y-axis values should be hidden, filled with color #99ff95, highest values should be colored #f0f0f0, values should be rounded to 0 decimal places.",
    "input": "{\"dataSources\":[{\"dataSourceId\":\"ds-6951\",\"queryKey\":\"API:+jdbc$$pmgr$$caps_32\",\"cols\":[{\"jsonName\":\"Customer\",\"type\":\"string\"},{\"jsonName\":\"Order Date\",\"type\":\"date\"},{\"jsonName\":\"latitude\",\"type\":\"number\"},{\"jsonName\":\"Profit\",\"type\":\"number\"},{\"jsonName\":\"Cost\",\"type\":\"number\"},{\"jsonName\":\"Demand\",\"type\":\"number\"},{\"jsonName\":\"coordinate_lg\",\"type\":\"number\"},{\"jsonName\":\"Category\",\"type\":\"string\"},{\"jsonName\":\"SubCategory\",\"type\":\"string\"},{\"jsonName\":\"Generation\",\"type\":\"number\"}],\"params\":[]}]}",
    "output": "{\n    \"dataSources\": [\n        {\n            \"dataSourceId\": \"ds-6951\",\n            \"queryKey\": \"API:+jdbc$$pmgr$$caps_32\",\n            \"cols\": [\n                {\n                    \"jsonName\": \"Customer\",\n                    \"type\": \"string\"\n                },\n                {\n                    \"jsonName\": \"Order Date\",\n                    \"type\": \"date\"\n                },\n                {\n                    \"jsonName\": \"latitude\",\n                    \"type\": \"number\",\n                    \"aggFn\": \"AVG\",\n                    \"fillColor\": \"#99ff95\",\n                    \"decimalPlaces\": 2,\n                    \"prefix\": \"@\"\n                },\n                {\n                    \"jsonName\": \"Profit\",\n                    \"type\": \"number\",\n                    \"fillLowestColor\": \"#f8b0y1\",\n                    \"label\": \"Tooltip Label\",\n                    \"prefix\": \"*\"\n                },\n                {\n                    \"jsonName\": \"Cost\",\n                    \"type\": \"number\",\n                    \"fillColor\": \"#866666\",\n                    \"fillHighestColor\": \"#99ff95\",\n                    \"fillLowestColor\": \"#866666\",\n                    \"label\": \"Tooltip Label\",\n                    \"decimalPlaces\": 2,\n                    \"prefix\": \"\\u20b9\"\n                },\n                {\n                    \"jsonName\": \"Demand\",\n                    \"type\": \"number\",\n                    \"aggFn\": \"COUNT\",\n                    \"isYAxisValueVisible\": false,\n                    \"fillHighestColor\": \"#f0f0f0\",\n                    \"label\": \"Tooltip Label\",\n                    \"prefix\": \"#\"\n                },\n                {\n                    \"jsonName\": \"coordinate_lg\",\n                    \"type\": \"number\",\n                    \"aggFn\": \"AVG\",\n                    \"fillLowestColor\": \"#99ff95\",\n                    \"suffix\": \"p\"\n                },\n                {\n                    \"jsonName\": \"Category\",\n                    \"type\": \"string\"\n                },\n                {\n                    \"jsonName\": \"SubCategory\",\n                    \"type\": \"string\"\n                },\n                {\n                    \"jsonName\": \"Generation\",\n                    \"type\": \"number\",\n                    \"aggFn\": \"SUM\",\n                    \"isYAxisValueVisible\": false,\n                    \"fillColor\": \"#99ff95\",\n                    \"fillHighestColor\": \"#f0f0f0\",\n                    \"decimalPlaces\": 0\n                }\n            ],\n            \"params\": []\n        }\n    ],\n    \"chartLayout\": \"vertical\",\n    \"attributes\": {\n        \"chartType\": \"Scattered Chart\",\n        \"sortOrder\": \"Desc\",\n        \"slider\": true,\n        \"saveImage\": true\n}\n    },\n    \"chartName\": \"Chart Example 93\",\n    \"xAxis\": {\n        \"fields\": [\n            \"SubCategory\"\n        ]\n    },\n    \"yAxis\": {\n        \"fields\": [\n            \"Profit\"\n        ]\n    },\n    \"zAxis\": {\n        \"fields\": [\n            \"Generation\"\n        ]\n    }\n}"
  },
  {
    "instruction": "Create a Line Chart chart named 'Chart Example 94' plotting 'Sales' against 'Place' with 'Region' as legend. The data should be sorted in asc order and displayed using a vertical layout. The x-axis should be labeled as 'Axis Label' and positioned at 'start' The y-axis should be labeled as 'Axis Label' and positioned at 'end' The column 'Discount' should be aggregating using SUM function, filled with color #f0f0f0, highest values should be colored #99ff95, lowest values should be colored #1d3b7a, tooltip should display 'Tooltip Label', values should be rounded to 0 decimal places, values should be prefixed with '*'. The column 'Sales' should be aggregating using MIN function, y-axis values should be visible, tooltip should display 'Tooltip Label', values should be rounded to 3 decimal places, values should be suffixed with 'USD'. The column 'coordinate_lt' should be aggregating using COUNT function, y-axis values should be visible, filled with color #f0f0f0, highest values should be colored #866666, lowest values should be colored #f8b0y1, values should be rounded to 0 decimal places, values should be suffixed with 'p'. The column 'coordinate_lg' should be filled with color #f0f0f0, values should be rounded to 2 decimal places, values should be suffixed with 'p'.",
    "input": "{\"dataSources\":[{\"dataSourceId\":\"ds-3387\",\"queryKey\":\"API:+lookup$$lookup$$_30\",\"cols\":[{\"jsonName\":\"Discount\",\"type\":\"number\"},{\"jsonName\":\"Category\",\"type\":\"string\"},{\"jsonName\":\"Sales\",\"type\":\"number\"},{\"jsonName\":\"coordinate_lt\",\"type\":\"number\"},{\"jsonName\":\"Region\",\"type\":\"string\"},{\"jsonName\":\"coordinate_lg\",\"type\":\"number\"},{\"jsonName\":\"Place\",\"type\":\"string\"},{\"jsonName\":\"Customer\",\"type\":\"string\"}],\"params\":[]}]}",
    "output": "{\n    \"dataSources\": [\n        {\n            \"dataSourceId\": \"ds-3387\",\n            \"queryKey\": \"API:+lookup$$lookup$$_30\",\n            \"cols\": [\n                {\n                    \"jsonName\": \"Discount\",\n                    \"type\": \"number\",\n                    \"aggFn\": \"SUM\",\n                    \"fillColor\": \"#f0f0f0\",\n                    \"fillHighestColor\": \"#99ff95\",\n                    \"fillLowestColor\": \"#1d3b7a\",\n                    \"label\": \"Tooltip Label\",\n                    \"decimalPlaces\": 0,\n                    \"prefix\": \"*\"\n                },\n                {\n                    \"jsonName\": \"Category\",\n                    \"type\": \"string\"\n                },\n                {\n                    \"jsonName\": \"Sales\",\n                    \"type\": \"number\",\n                    \"aggFn\": \"MIN\",\n                    \"isYAxisValueVisible\": true,\n                    \"label\": \"Tooltip Label\",\n                    \"decimalPlaces\": 3,\n                    \"suffix\": \"USD\"\n                },\n                {\n                    \"jsonName\": \"coordinate_lt\",\n                    \"type\": \"number\",\n                    \"aggFn\": \"COUNT\",\n                    \"isYAxisValueVisible\": true,\n                    \"fillColor\": \"#f0f0f0\",\n                    \"fillHighestColor\": \"#866666\",\n                    \"fillLowestColor\": \"#f8b0y1\",\n                    \"decimalPlaces\": 0,\n                    \"suffix\": \"p\"\n                },\n                {\n                    \"jsonName\": \"Region\",\n                    \"type\": \"string\"\n                },\n                {\n                    \"jsonName\": \"coordinate_lg\",\n                    \"type\": \"number\",\n                    \"fillColor\": \"#f0f0f0\",\n                    \"decimalPlaces\": 2,\n                    \"suffix\": \"p\"\n                },\n                {\n                    \"jsonName\": \"Place\",\n                    \"type\": \"string\"\n                },\n                {\n                    \"jsonName\": \"Customer\",\n                    \"type\": \"string\"\n                }\n            ],\n            \"params\": []\n        }\n    ],\n    \"chartLayout\": \"vertical\",\n    \"attributes\": {\n        \"chartType\": \"Line Chart\",\n        \"sortOrder\": \"Asc\",\n        \"slider\": true,\n        \"saveImage\": true,\n        \"legend\": {\n            \"fields\": \"Region\",\n            \"colors\": {}\n        }\n    },\n    \"chartName\": \"Chart Example 94\",\n    \"xAxis\": {\n        \"fields\": [\n            \"Place\"\n        ],\n        \"label\": \"Axis Label\",\n        \"nameLocation\": \"start\"\n    },\n    \"yAxis\": {\n        \"fields\": [\n            \"Sales\"\n        ],\n        \"label\": \"Axis Label\",\n        \"nameLocation\": \"end\"\n    }\n}"
  },
  {
    "instruction": "Create a Composed Chart chart named 'Chart Example 95' plotting 'Sales' as Line Chart against 'Category'. The data should be sorted in asc order and displayed using a vertical layout. The y-axis should be labeled as 'Axis Label' The column 'Sales' should be aggregating using MAX function, highest values should be colored #f8b0y1, values should be rounded to 1 decimal places, values should be suffixed with 'p'. The column 'Price' should be aggregating using AVG function, filled with color #f8b0y1, tooltip should display 'Tooltip Label', values should be rounded to 3 decimal places, values should be prefixed with '$'. The column 'coordinate_lg' should be aggregating using COUNT function, y-axis values should be hidden, filled with color #99ff95, values should be rounded to 0 decimal places, values should be prefixed with '$'.",
    "input": "{\"dataSources\":[{\"dataSourceId\":\"ds-9739\",\"queryKey\":\"API:+jdbc$$aws$$_88\",\"cols\":[{\"jsonName\":\"Customer\",\"type\":\"string\"},{\"jsonName\":\"Sales\",\"type\":\"number\"},{\"jsonName\":\"Employee\",\"type\":\"string\"},{\"jsonName\":\"Price\",\"type\":\"number\"},{\"jsonName\":\"coordinate_lg\",\"type\":\"number\"},{\"jsonName\":\"SubCategory\",\"type\":\"string\"},{\"jsonName\":\"Category\",\"type\":\"string\"},{\"jsonName\":\"Place\",\"type\":\"string\"},{\"jsonName\":\"Region\",\"type\":\"string\"}],\"params\":[]}]}",
    "output": "{\n    \"dataSources\": [\n        {\n            \"dataSourceId\": \"ds-9739\",\n            \"queryKey\": \"API:+jdbc$$aws$$_88\",\n            \"cols\": [\n                {\n                    \"jsonName\": \"Customer\",\n                    \"type\": \"string\"\n                },\n                {\n                    \"jsonName\": \"Sales\",\n                    \"type\": \"number\",\n                    \"composedChartType\": \"Line Chart\",\n                 \"aggFn\": \"MAX\",\n                    \"fillHighestColor\": \"#f8b0y1\",\n                    \"decimalPlaces\": 1,\n                    \"suffix\": \"p\"\n                },\n                {\n                    \"jsonName\": \"Employee\",\n                    \"type\": \"string\"\n                },\n                {\n                    \"jsonName\": \"Price\",\n                    \"type\": \"number\",\n                    \"aggFn\": \"AVG\",\n                    \"fillColor\": \"#f8b0y1\",\n                    \"label\": \"Tooltip Label\",\n                    \"decimalPlaces\": 3,\n                    \"prefix\": \"$\"\n                },\n                {\n                    \"jsonName\": \"coordinate_lg\",\n                    \"type\": \"number\",\n                    \"aggFn\": \"COUNT\",\n                    \"isYAxisValueVisible\": false,\n                    \"fillColor\": \"#99ff95\",\n                    \"decimalPlaces\": 0,\n                    \"prefix\": \"$\"\n                },\n                {\n                    \"jsonName\": \"SubCategory\",\n                    \"type\": \"string\"\n                },\n                {\n                    \"jsonName\": \"Category\",\n                    \"type\": \"string\"\n                },\n                {\n                    \"jsonName\": \"Place\",\n                    \"type\": \"string\"\n                },\n                {\n                    \"jsonName\": \"Region\",\n                    \"type\": \"string\"\n                }\n            ],\n            \"params\": []\n        }\n    ],\n    \"chartLayout\": \"vertical\",\n    \"attributes\": {\n        \"chartType\": \"Composed Chart\",\n        \"sortOrder\": \"Asc\",\n        \"slider\": true,\n        \"saveImage\": true\n    },\n    \"chartName\": \"Chart Example 95\",\n    \"xAxis\": {\n        \"fields\": [\n            \"Category\"\n        ]\n    },\n    \"yAxis\": {\n        \"fields\": [\n            \"Sales\"\n        ],\n        \"label\": \"Axis Label\"\n    }\n}"
  },
  {
    "instruction": "Create a Area Chart chart named 'Chart Example 96' plotting 'Revenue' against 'Country'. The data should be sorted in asc order and displayed using a horizontal layout. A secondary Y-axis is included, representing 'Generation'. The x-axis should be labeled as 'Axis Label' The secondary Y-axis should be labeled as 'Axis Label' and positioned at 'center' with a name gap of 10 pixels. The column 'coordinate_lt' should be aggregating using MIN function, highest values should be colored #99ff95, tooltip should display 'Tooltip Label', values should be rounded to 2 decimal places, values should be prefixed with '₹'. The column 'longitude' should be lowest values should be colored #866666, tooltip should display 'Tooltip Label', values should be suffixed with 'MW'. The column 'coordinate_lg' should be highest values should be colored #99ff95, lowest values should be colored #f8b0y1, values should be rounded to 3 decimal places, values should be prefixed with '#'. The column 'Generation' should be lowest values should be colored #1d3b7a, values should be rounded to 0 decimal places, values should be prefixed with '₹'. The column 'Revenue' should be lowest values should be colored #f0f0f0, tooltip should display 'Tooltip Label', values should be rounded to 0 decimal places, values should be prefixed with '₹'. The column 'Profit' should be aggregating using MIN function, filled with color #99ff95, tooltip should display 'Tooltip Label', values should be rounded to 1 decimal places, values should be prefixed with '$'. The column 'latitude' should be highest values should be colored #866666, values should be rounded to 2 decimal places, values should be prefixed with '₹'.",
    "input": "{\"dataSources\":[{\"dataSourceId\":\"ds-6886\",\"queryKey\":\"API:+lookup$$lookup$$_78\",\"cols\":[{\"jsonName\":\"coordinate_lt\",\"type\":\"number\"},{\"jsonName\":\"longitude\",\"type\":\"number\"},{\"jsonName\":\"coordinate_lg\",\"type\":\"number\"},{\"jsonName\":\"Generation\",\"type\":\"number\"},{\"jsonName\":\"Revenue\",\"type\":\"number\"},{\"jsonName\":\"Profit\",\"type\":\"number\"},{\"jsonName\":\"Country\",\"type\":\"string\"},{\"jsonName\":\"latitude\",\"type\":\"number\"},{\"jsonName\":\"Order Date\",\"type\":\"date\"}],\"params\":[]}]}",
    "output": "{\n    \"dataSources\": [\n        {\n            \"dataSourceId\": \"ds-6886\",\n            \"queryKey\": \"API:+lookup$$lookup$$_78\",\n            \"cols\": [\n                {\n                    \"jsonName\": \"coordinate_lt\",\n                    \"type\": \"number\",\n                    \"aggFn\": \"MIN\",\n                    \"fillHighestColor\": \"#99ff95\",\n                    \"label\": \"Tooltip Label\",\n                    \"decimalPlaces\": 2,\n                    \"prefix\": \"\\u20b9\"\n                },\n                {\n                    \"jsonName\": \"longitude\",\n                    \"type\": \"number\",\n                    \"fillLowestColor\": \"#866666\",\n                    \"label\": \"Tooltip Label\",\n                    \"suffix\": \"MW\"\n                },\n                {\n                    \"jsonName\": \"coordinate_lg\",\n                    \"type\": \"number\",\n                    \"fillHighestColor\": \"#99ff95\",\n                    \"fillLowestColor\": \"#f8b0y1\",\n                    \"decimalPlaces\": 3,\n                    \"prefix\": \"#\"\n                },\n                {\n                    \"jsonName\": \"Generation\",\n                    \"type\": \"number\",\n                    \"fillLowestColor\": \"#1d3b7a\",\n                    \"decimalPlaces\": 0,\n                    \"prefix\": \"\\u20b9\"\n                },\n                {\n                    \"jsonName\": \"Revenue\",\n                    \"type\": \"number\",\n                    \"fillLowestColor\": \"#f0f0f0\",\n                    \"label\": \"Tooltip Label\",\n                    \"decimalPlaces\": 0,\n                    \"prefix\": \"\\u20b9\"\n                },\n                {\n                    \"jsonName\": \"Profit\",\n                    \"type\": \"number\",\n                    \"aggFn\": \"MIN\",\n                    \"fillColor\": \"#99ff95\",\n                    \"label\": \"Tooltip Label\",\n                    \"decimalPlaces\": 1,\n                    \"prefix\": \"$\"\n                },\n                {\n                    \"jsonName\": \"Country\",\n                    \"type\": \"string\"\n                },\n                {\n                    \"jsonName\": \"latitude\",\n                    \"type\": \"number\",\n                    \"fillHighestColor\": \"#866666\",\n                    \"decimalPlaces\": 2,\n                    \"prefix\": \"\\u20b9\"\n                },\n                {\n                    \"jsonName\": \"Order Date\",\n                    \"type\": \"date\"\n                }\n            ],\n            \"params\": []\n        }\n    ],\n    \"chartLayout\": \"horizontal\",\n    \"attributes\": {\n        \"chartType\": \"Area Chart\",\n        \"sortOrder\": \"Asc\",\n        \"slider\": true,\n        \"saveImage\": true\n    },\n    \"chartName\": \"Chart Example 96\",\n    \"xAxis\": {\n        \"fields\": [\n            \"Country\"\n        ],\n        \"label\": \"Axis Label\"\n    },\n    \"yAxis\": {\n        \"fields\": [\n            \"Revenue\"\n        ]\n    },\n    \"secondaryYAxis\": {\n        \"fields\": [\n            \"Generation\"\n        ],\n        \"label\": \"Axis Label\",\n        \"nameLocation\": \"center\",\n        \"nameGap\": 10\n    }\n}"
  },
  {
    "instruction": "Create a Area Chart chart named 'Chart Example 97' plotting 'Revenue' against 'location' and 'Discount' legends. The data should be sorted in desc order and displayed using a vertical layout. The y-axis should be labeled as 'Axis Label' with a name gap of 32 pixels. The column 'Price' should be aggregating using MIN function, y-axis values should be hidden, filled with color #f0f0f0, values should be rounded to 2 decimal places, values should be prefixed with '#'. The column 'Profit' should be aggregating using COUNT function, y-axis values should be hidden, tooltip should display 'Tooltip Label', values should be suffixed with 'MW'. The column 'Discount' should be aggregating using MAX function, y-axis values should be visible, filled with color #99ff95, tooltip should display 'Tooltip Label', values should be prefixed with '$'. The column 'Revenue' should be aggregating using AVG function, y-axis values should be hidden, filled with color #f0f0f0, highest values should be colored #99ff95, lowest values should be colored #f8b0y1, values should be suffixed with '%'. The column 'coordinate_lt' should be aggregating using AVG function, highest values should be colored #99ff95, lowest values should be colored #f0f0f0, values should be rounded to 0 decimal places, values should be suffixed with 'USD'.",
    "input": "{\"dataSources\":[{\"dataSourceId\":\"ds-6798\",\"queryKey\":\"API:+jdbc$$TEMP$$us_station_city_geo_data_15\",\"cols\":[{\"jsonName\":\"Price\",\"type\":\"number\"},{\"jsonName\":\"Profit\",\"type\":\"number\"},{\"jsonName\":\"location\",\"type\":\"string\"},{\"jsonName\":\"Discount\",\"type\":\"number\"},{\"jsonName\":\"Revenue\",\"type\":\"number\"},{\"jsonName\":\"Place\",\"type\":\"string\"},{\"jsonName\":\"coordinate_lt\",\"type\":\"number\"},{\"jsonName\":\"Category\",\"type\":\"string\"}],\"params\":[]}]}",
    "output": "{\n    \"dataSources\": [\n        {\n            \"dataSourceId\": \"ds-6798\",\n            \"queryKey\": \"API:+jdbc$$TEMP$$us_station_city_geo_data_15\",\n            \"cols\": [\n                {\n                    \"jsonName\": \"Price\",\n                    \"type\": \"number\",\n                    \"aggFn\": \"MIN\",\n                    \"isYAxisValueVisible\": false,\n                    \"fillColor\": \"#f0f0f0\",\n                    \"decimalPlaces\": 2,\n                    \"prefix\": \"#\"\n                },\n                {\n                    \"jsonName\": \"Profit\",\n                    \"type\": \"number\",\n                    \"aggFn\": \"COUNT\",\n                    \"isYAxisValueVisible\": false,\n                    \"label\": \"Tooltip Label\",\n                    \"suffix\": \"MW\"\n                },\n                {\n                    \"jsonName\": \"location\",\n                    \"type\": \"string\"\n                },\n                {\n                    \"jsonName\": \"Discount\",\n                    \"type\": \"number\",\n                    \"aggFn\": \"MAX\",\n                    \"isYAxisValueVisible\": true,\n                    \"fillColor\": \"#99ff95\",\n                    \"label\": \"Tooltip Label\",\n                    \"prefix\": \"$\"\n                },\n                {\n                    \"jsonName\": \"Revenue\",\n                    \"type\": \"number\",\n                    \"aggFn\": \"AVG\",\n                    \"isYAxisValueVisible\": false,\n                    \"fillColor\": \"#f0f0f0\",\n                    \"fillHighestColor\": \"#99ff95\",\n                    \"fillLowestColor\": \"#f8b0y1\",\n                    \"suffix\": \"%\"\n                },\n                {\n                    \"jsonName\": \"Place\",\n                    \"type\": \"string\"\n                },\n                {\n                    \"jsonName\": \"coordinate_lt\",\n                    \"type\": \"number\",\n                    \"aggFn\": \"AVG\",\n                    \"fillHighestColor\": \"#99ff95\",\n                    \"fillLowestColor\": \"#f0f0f0\",\n                    \"decimalPlaces\": 0,\n                    \"suffix\": \"USD\"\n                },\n                {\n                    \"jsonName\": \"Category\",\n                    \"type\": \"string\"\n                }\n            ],\n            \"params\": []\n        }\n    ],\n    \"chartLayout\": \"vertical\",\n    \"attributes\": {\n        \"chartType\": \"Area Chart\",\n        \"sortOrder\": \"Desc\",\n        \"slider\": true,\n        \"saveImage\": true,\n        \"legend\": {\n            \"fields\": \"Discount\",\n            \"colors\": {}\n        }\n    },\n    \"chartName\": \"Chart Example 97\",\n    \"xAxis\": {\n        \"fields\": [\n            \"location\"\n        ]\n    },\n    \"yAxis\": {\n        \"fields\": [\n            \"Revenue\"\n        ],\n        \"label\": \"Axis Label\",\n        \"nameGap\": 32\n    }\n}"
  },
  {
    "instruction": "Create a Line Chart chart named 'Chart Example 98' plotting 'Revenue' against 'Category'. The data should be sorted in asc order and displayed using a horizontal layout. The column 'Revenue' should be aggregating using SUM function, y-axis values should be hidden, filled with color #f8b0y1, lowest values should be colored #f0f0f0, tooltip should display 'Tooltip Label'. The column 'Generation' should be aggregating using COUNT function, tooltip should display 'Tooltip Label', values should be rounded to 1 decimal places, values should be suffixed with 'MW'.",
    "input": "{\"dataSources\":[{\"dataSourceId\":\"ds-8740\",\"queryKey\":\"API:+jdbc$$dataService$$_94\",\"cols\":[{\"jsonName\":\"Customer\",\"type\":\"string\"},{\"jsonName\":\"Revenue\",\"type\":\"number\"},{\"jsonName\":\"Category\",\"type\":\"string\"},{\"jsonName\":\"Generation\",\"type\":\"number\"},{\"jsonName\":\"Country\",\"type\":\"string\"},{\"jsonName\":\"SubCategory\",\"type\":\"string\"},{\"jsonName\":\"Place\",\"type\":\"string\"}],\"params\":[]}]}",
    "output": "{\n    \"dataSources\": [\n        {\n            \"dataSourceId\": \"ds-8740\",\n            \"queryKey\": \"API:+jdbc$$dataService$$_94\",\n            \"cols\": [\n                {\n                    \"jsonName\": \"Customer\",\n                    \"type\": \"string\"\n                },\n                {\n                    \"jsonName\": \"Revenue\",\n                    \"type\": \"number\",\n                    \"aggFn\": \"SUM\",\n                    \"isYAxisValueVisible\": false,\n                    \"fillColor\": \"#f8b0y1\",\n                    \"fillLowestColor\": \"#f0f0f0\",\n                    \"label\": \"Tooltip Label\"\n                },\n                {\n                    \"jsonName\": \"Category\",\n                    \"type\": \"string\"\n                },\n                {\n                    \"jsonName\": \"Generation\",\n                    \"type\": \"number\",\n                    \"aggFn\": \"COUNT\",\n                    \"label\": \"Tooltip Label\",\n                    \"decimalPlaces\": 1,\n                    \"suffix\": \"MW\"\n                },\n                {\n                    \"jsonName\": \"Country\",\n                    \"type\": \"string\"\n                },\n                {\n                    \"jsonName\": \"SubCategory\",\n                    \"type\": \"string\"\n                },\n                {\n                    \"jsonName\": \"Place\",\n                    \"type\": \"string\"\n                }\n            ],\n            \"params\": []\n        }\n    ],\n    \"chartLayout\": \"horizontal\",\n    \"attributes\": {\n        \"chartType\": \"Line Chart\",\n        \"sortOrder\": \"Asc\",\n        \"slider\": true,\n        \"saveImage\": true,\n        \"referenceLines\": [\n            {\n                \"referenceValueSource\": \"FIXED\",\n                \"referenceFor\": \"Revenue\",\n                \"referenceLabel\": \"Label Revenue\",\n                \"referenceLineColor\": \"#99ff95\",\n                \"referenceValue\": \"702\",\n                \"showValue\": false\n            }\n        ]\n    },\n    \"chartName\": \"Chart Example 98\",\n    \"xAxis\": {\n        \"fields\": [\n            \"Category\"\n        ]\n    },\n    \"yAxis\": {\n        \"fields\": [\n            \"Revenue\"\n        ]\n    }\n}"
  },
  {
    "instruction": "Create a TimeLine Chart chart named 'Chart Example 99' plotting 'Revenue' against 'Customer'. The data should be sorted in desc order and displayed using a vertical layout. The column 'coordinate_lt' should be lowest values should be colored #1d3b7a. The column 'coordinate_lg' should be aggregating using MAX function, highest values should be colored #1d3b7a, values should be prefixed with '*'. The column 'Revenue' should be aggregating using SUM function, filled with color #f8b0y1, lowest values should be colored #f0f0f0, tooltip should display 'Tooltip Label', values should be prefixed with '@'. The column 'Sales' should be aggregating using AVG function, lowest values should be colored #866666, values should be rounded to 0 decimal places.",
    "input": "{\"dataSources\":[{\"dataSourceId\":\"ds-9042\",\"queryKey\":\"API:+jdbc$$TEMP$$us_station_city_geo_data_57\",\"cols\":[{\"jsonName\":\"Customer\",\"type\":\"string\"},{\"jsonName\":\"coordinate_lt\",\"type\":\"number\"},{\"jsonName\":\"coordinate_lg\",\"type\":\"number\"},{\"jsonName\":\"Country\",\"type\":\"string\"},{\"jsonName\":\"Revenue\",\"type\":\"number\"},{\"jsonName\":\"Order Date\",\"type\":\"date\"},{\"jsonName\":\"Sales\",\"type\":\"number\"},{\"jsonName\":\"Place\",\"type\":\"string\"},{\"jsonName\":\"SubCategory\",\"type\":\"string\"}],\"params\":[]}]}",
    "output": "{\n    \"dataSources\": [\n        {\n            \"dataSourceId\": \"ds-9042\",\n            \"queryKey\": \"API:+jdbc$$TEMP$$us_station_city_geo_data_57\",\n            \"cols\": [\n                {\n                    \"jsonName\": \"Customer\",\n                    \"type\": \"string\"\n                },\n                {\n                    \"jsonName\": \"coordinate_lt\",\n                    \"type\": \"number\",\n                    \"fillLowestColor\": \"#1d3b7a\"\n                },\n                {\n                    \"jsonName\": \"coordinate_lg\",\n                    \"type\": \"number\",\n                    \"aggFn\": \"MAX\",\n                    \"fillHighestColor\": \"#1d3b7a\",\n                    \"prefix\": \"*\"\n                },\n                {\n                    \"jsonName\": \"Country\",\n                    \"type\": \"string\"\n                },\n                {\n                    \"jsonName\": \"Revenue\",\n                    \"type\": \"number\",\n                    \"aggFn\": \"SUM\",\n                    \"fillColor\": \"#f8b0y1\",\n                    \"fillLowestColor\": \"#f0f0f0\",\n                    \"label\": \"Tooltip Label\",\n                    \"prefix\": \"@\"\n                },\n                {\n                    \"jsonName\": \"Order Date\",\n                    \"type\": \"date\"\n                },\n                {\n                    \"jsonName\": \"Sales\",\n                    \"type\": \"number\",\n                    \"aggFn\": \"AVG\",\n                    \"fillLowestColor\": \"#866666\",\n                    \"decimalPlaces\": 0\n                },\n                {\n                    \"jsonName\": \"Place\",\n                    \"type\": \"string\"\n                },\n                {\n                    \"jsonName\": \"SubCategory\",\n                    \"type\": \"string\"\n                }\n            ],\n            \"params\": []\n        }\n    ],\n    \"chartLayout\": \"vertical\",\n    \"attributes\": {\n        \"chartType\": \"TimeLine Chart\",\n        \"sortOrder\": \"Desc\",\n        \"slider\": true,\n        \"saveImage\": true\n}\n    },\n    \"chartName\": \"Chart Example 99\",\n    \"xAxis\": {\n        \"fields\": [\n            \"Customer\"\n        ]\n    },\n    \"yAxis\": {\n        \"fields\": [\n            \"Revenue\"\n        ]\n    }\n}"
  },
  {
    "instruction": "Give me bar chart Units sold by Sales person in ascending order, label Units axis to \"Sold Units\" where it's position should be at start of axis, show maximum of sold units by Sales Person fill with white color and add 'Rupees' at the end of values and give title Sales Chart to it.",
    "input": "{ \"dataSources\": [ { \"dataSourceId\": \"2f344f20-663e-4428-8e9a-bee6797fc0f5\", \"queryKey\": \"API:+lookup$$lookup$$Chocolate_Sales\", \"cols\": [ { \"jsonName\": \"Sales Person\", \"type\": \"string\" }, { \"jsonName\": \"Geography\", \"type\": \"string\" }, { \"jsonName\": \"Product\", \"type\": \"string\" }, { \"jsonName\": \"Amount\", \"type\": \"number\" }, { \"jsonName\": \"Units\", \"type\": \"number\", } ], \"params\": [] } ]}",
    "output": "{ \"dataSources\": [ { \"dataSourceId\": \"2f344f20-663e-4428-8e9a-bee6797fc0f5\", \"queryKey\": \"API:+lookup$$lookup$$Chocolate_Sales\", \"cols\": [ { \"jsonName\": \"Sales Person\", \"type\": \"string\" }, { \"jsonName\": \"Geography\", \"type\": \"string\" }, { \"jsonName\": \"Product\", \"type\": \"string\" }, { \"jsonName\": \"Amount\", \"type\": \"number\" }, { \"jsonName\": \"Units\", \"type\": \"number\", \"aggFn\": \"MAX\", \"fillColor\": \"#FFFFFF\", \"suffix\": \"Rupees\" } ], \"params\": [] } ], \"chartLayout\": \"vertical\", \"attributes\": { \"chartType\": \"Bar Chart\", \"sortOrder\": \"Asc\", \"slider\": true, \"saveImage\": true, }, \"chartName\": \"Sales Chart\", \"xAxis\": { \"fields\": [ \"Sales Person\" ], }, \"yAxis\": { \"fields\": [ \"Units\" ], \"nameLocation\": \"start\", \"label\": \"Sold Units\", \"nameGap\": \"50\" } } "
  },
  {
    "instruction": "Create a bar chart showing the total units sold by each Sales Person in ascending order, with the x-axis labeled \"Sales\" and the y-axis labeled \"Uniiiit.\" The highest, lowest, and default bars should be colored differently, values should have a \"$\" prefix with one decimal place, and tooltips should have light blue text on a dark blue background. Allow sliding through data, enable image saving, and set the chart title to \"Temppp\".",
    "input": "{ \"dataSources\": [ { \"dataSourceId\": \"2f344f20-663e-4428-8e9a-bee6797fc0f5\", \"queryKey\": \"API:+lookup$$lookup$$Chocolate_Sales\", \"cols\": [ { \"jsonName\": \"Sales Person\", \"type\": \"string\" }, { \"jsonName\": \"Geography\", \"type\": \"string\" }, { \"jsonName\": \"Product\", \"type\": \"string\" }, { \"jsonName\": \"Amount\", \"type\": \"number\" }, { \"jsonName\": \"Units\", \"type\": \"number\", } ], \"params\": [] } ]}",
    "output": "{\n    \"dataSources\": [\n        {\n            \"dataSourceId\": \"2f344f20-663e-4428-8e9a-bee6797fc0f5\",\n            \"queryKey\": \"API:+lookup$$lookup$$Chocolate_Sales\",\n            \"cols\": [\n                {\n                    \"jsonName\": \"Sales Person\",\n                    \"type\": \"string\"\n                },\n                {\n                    \"jsonName\": \"Geography\",\n                    \"type\": \"string\"\n                },\n                {\n                    \"jsonName\": \"Product\",\n                    \"type\": \"string\"\n                },\n                {\n                    \"jsonName\": \"Amount\",\n                    \"type\": \"number\"\n                },\n                {\n                    \"jsonName\": \"Units\",\n                    \"type\": \"number\"\n                }\n            ],\n            \"params\": []\n        }\n    ],\n    \"chartLayout\": \"vertical\",\n    \"attributes\": {\n        \"chartType\": \"Bar Chart\",\n        \"sortOrder\": \"Asc\",\n        \"slider\": true,\n        \"saveImage\": true,\n        \"tooltipTextColor\": \"#1fe0f0\",\n        \"tooltipBgColor\": \"#13175a\"\n    },\n    \"chartName\": \"Temppp\",\n    \"xAxis\": {\n        \"fields\": [\n            \"Sales Person\"\n        ],\n        \"label\": \"Sales\",\n        \"nameLocation\": \"start\",\n        \"nameGap\": \"22\"\n    },\n    \"yAxis\": {\n        \"fields\": [\n            \"Units\"\n        ],\n        \"label\": \"Uniiiit\",\n        \"nameGap\": \"50\"\n    }\n}"
  },
  {
    "instruction": "Generate a bar chart showing units sold by each sales person and Set the chart name to \"Sales Data\".",
    "input": "{ \"dataSources\": [ { \"dataSourceId\": \"2f344f20-663e-4428-8e9a-bee6797fc0f5\", \"queryKey\": \"API:+lookup$$lookup$$Chocolate_Sales\", \"cols\": [ { \"jsonName\": \"Sales Person\", \"type\": \"string\" }, { \"jsonName\": \"Geography\", \"type\": \"string\" }, { \"jsonName\": \"Product\", \"type\": \"string\" }, { \"jsonName\": \"Amount\", \"type\": \"number\" }, { \"jsonName\": \"Units\", \"type\": \"number\", } ], \"params\": [] } ]}",
    "output": "{ \"dataSources\": [ { \"dataSourceId\": \"2f344f20-663e-4428-8e9a-bee6797fc0f5\", \"queryKey\": \"API:+lookup$$lookup$$Chocolate_Sales\", \"cols\": [ { \"jsonName\": \"Sales Person\", \"type\": \"string\" }, { \"jsonName\": \"Geography\", \"type\": \"string\" }, { \"jsonName\": \"Product\", \"type\": \"string\" }, { \"jsonName\": \"Amount\", \"type\": \"number\" }, { \"jsonName\": \"Units\", \"type\": \"number\", } ], \"params\": [] } ], \"chartLayout\": \"vertical\", \"attributes\": { \"chartType\": \"Bar Chart\", \"sortOrder\": \"Asc\", \"slider\": true, \"saveImage\": true, }, \"chartName\": \"Sales Data\", \"xAxis\": { \"fields\": [ \"Sales Person\" ], }, \"yAxis\": { \"fields\": [ \"Units\" ], } } "
  },
  {
    "instruction": "Create a composed chart with a bar chart for units sold and a line chart for amount, grouped by sales person. Display values with a \"$\" prefix for amount and a \"p\" suffix for units. Enable sliding through data, allow image saving, and set the chart title to \"Composed Checker\"",
    "input": "{ \"dataSources\": [ { \"dataSourceId\": \"d2e0b533-82e9-437e-9a3f-cda0ca85da76\", \"queryKey\": \"API:+lookup$$lookup$$Chocolate_Sales\", \"cols\": [ { \"jsonName\": \"Sales Person\", \"type\": \"string\" }, { \"jsonName\": \"Geography\", \"type\": \"string\" }, { \"jsonName\": \"Product\", \"type\": \"string\" }, { \"jsonName\": \"Amount\", \"type\": \"number\"}, { \"jsonName\": \"Units\", \"type\": \"number\" } ], \"params\": [] } ]}",
    "output": "{ \"dataSources\": [ { \"dataSourceId\": \"d2e0b533-82e9-437e-9a3f-cda0ca85da76\", \"queryKey\": \"API:+lookup$$lookup$$Chocolate_Sales\", \"cols\": [ { \"jsonName\": \"Sales Person\", \"type\": \"string\" }, { \"jsonName\": \"Geography\", \"type\": \"string\" }, { \"jsonName\": \"Product\", \"type\": \"string\" }, { \"jsonName\": \"Amount\", \"type\": \"number\", \"composedChartType\": \"Line Chart\", \"prefix\": \"$\" }, { \"jsonName\": \"Units\", \"type\": \"number\", \"composedChartType\": \"Bar Chart\", \"suffix\": \"p\" } ], \"params\": [] } ], \"xAxis\": { \"fields\": [ \"Sales Person\" ] }, \"yAxis\": { \"fields\": [ \"Units\", \"Amount\" ] }, \"chartLayout\": \"vertical\", \"attributes\": { \"chartType\": \"Composed Chart\", \"sortOrder\": \"Asc\", \"slider\": true, \"saveImage\": true, }, \"chartName\": \"Composed Checker\", } "
  },
  {
    "instruction": "Design a composed chart that visualizes the amount as a bar chart and units as a line chart for each sales person. The secondary y-axis should be labeled \"Unit Displayed,\" and the tooltip label for amount should be \"Amounts\", naming it \"Unit Sold By Person\"",
    "input": "{ \"dataSources\": [ { \"dataSourceId\": \"d2e0b533-82e9-437e-9a3f-cda0ca85da76\", \"queryKey\": \"API:+lookup$$lookup$$Chocolate_Sales\", \"cols\": [ { \"jsonName\": \"Sales Person\", \"type\": \"string\" }, { \"jsonName\": \"Geography\", \"type\": \"string\" }, { \"jsonName\": \"Product\", \"type\": \"string\" }, { \"jsonName\": \"Amount\", \"type\": \"number\"}, { \"jsonName\": \"Units\", \"type\": \"number\" } ], \"params\": [] } ]}",
    "output": "{ \"dataSources\": [ { \"dataSourceId\": \"d2e0b533-82e9-437e-9a3f-cda0ca85da76\", \"queryKey\": \"API:+lookup$$lookup$$Chocolate_Sales\", \"cols\": [ { \"jsonName\": \"Sales Person\", \"type\": \"string\" }, { \"jsonName\": \"Geography\", \"type\": \"string\" }, { \"jsonName\": \"Product\", \"type\": \"string\" }, { \"jsonName\": \"Amount\", \"type\": \"number\", \"composedChartType\": \"Bar Chart\", \"label\": \"Amount in Tooltip\", }, { \"jsonName\": \"Units\", \"type\": \"number\", \"composedChartType\": \"Line Chart\", } ], \"params\": [] } ], \"xAxis\": { \"fields\": [ \"Sales Person\" ] }, \"yAxis\": { \"fields\": [ \"Amount\" ] }, \"secondaryYAxis\": { \"fields\": [ \"Units\" ], label: \"Unit Displayed\", }, \"chartLayout\": \"vertical\", \"attributes\": { \"chartType\": \"Composed Chart\", \"sortOrder\": \"Asc\", \"slider\": true, \"saveImage\": true, }, \"chartName\": \"Unit Sold By Person\", } "
  },
  {
    "instruction": "Create a bar chart that displays unit costs over time, grouping data by order date in yearly format. Name the chart \"Date Grouping Checker.\".",
    "input": "{ \"dataSources\": [ { \"dataSourceId\": \"0d10c58e-ae71-423a-9e5f-9bcdf928141a\", \"queryKey\": \"API:+jdbc$$aws$$sales_data\", \"cols\": [ { \"jsonName\": \"region\", \"type\": \"String\" }, { \"jsonName\": \"country\", \"type\": \"String\" }, { \"jsonName\": \"itemType\", \"type\": \"String\" }, { \"jsonName\": \"salesChannel\", \"type\": \"String\" }, { \"jsonName\": \"ordePriority\", \"type\": \"String\" }, { \"jsonName\": \"orderDate\", \"type\": \"Date\" }, { \"jsonName\": \"orderId\", \"type\": \"Number\" }, { \"jsonName\": \"shipDate\", \"type\": \"Date\" }, { \"jsonName\": \"unitsSold\", \"type\": \"Number\" }, { \"jsonName\": \"unitPrice\", \"type\": \"Number\" }, { \"jsonName\": \"unitCost\", \"type\": \"Number\" }, { \"jsonName\": \"totalRevenue\", \"type\": \"Number\" }, { \"jsonName\": \"totalCost\", \"type\": \"Number\" }, { \"jsonName\": \"totalProfit\", \"type\": \"Number\" } ], \"params\": [] } ]}",
    "output": "{ \"dataSources\": [ { \"dataSourceId\": \"0d10c58e-ae71-423a-9e5f-9bcdf928141a\", \"queryKey\": \"API:+jdbc$$aws$$sales_data\", \"cols\": [ { \"jsonName\": \"region\", \"type\": \"String\" }, { \"jsonName\": \"country\", \"type\": \"String\" }, { \"jsonName\": \"itemType\", \"type\": \"String\" }, { \"jsonName\": \"salesChannel\", \"type\": \"String\" }, { \"jsonName\": \"ordePriority\", \"type\": \"String\" }, { \"jsonName\": \"orderDate\", \"type\": \"Date\" }, { \"jsonName\": \"orderId\", \"type\": \"Number\" }, { \"jsonName\": \"shipDate\", \"type\": \"Date\" }, { \"jsonName\": \"unitsSold\", \"type\": \"Number\" }, { \"jsonName\": \"unitPrice\", \"type\": \"Number\" }, { \"jsonName\": \"unitCost\", \"type\": \"Number\", \"aggFn\": \"COUNT\" }, { \"jsonName\": \"totalRevenue\", \"type\": \"Number\" }, { \"jsonName\": \"totalCost\", \"type\": \"Number\" }, { \"jsonName\": \"totalProfit\", \"type\": \"Number\" } ], \"params\": [] } ], \"xAxis\": { \"fields\": [ \"orderDate\" ], \"dateDisplayFormat\": \"YYYY\" }, \"yAxis\": { \"fields\": [ \"unitCost\" ] }, \"chartLayout\": \"vertical\", \"attributes\": { \"chartType\": \"Bar Chart\", \"sortOrder\": \"Asc\", \"slider\": true, \"saveImage\": true, }, \"chartName\": \"Date Grouping Checker\", } "
  },
  {
    "instruction": "Generate a geo chart displaying station counts in California and Texas, using longitude and latitude for positioning. Color California in green and Texas in orange. Set the chart sub type to a map, and title it \"Geo Checker\".",
    "input": "{ \"dataSources\": [ { \"dataSourceId\": \"c1366774-dace-4c33-904f-c9855255a7ef\", \"queryKey\": \"API:+jdbc$$dataService$$ecwt_noaa_station\", \"cols\": [ { \"jsonName\": \"usaf\", \"type\": \"String\" }, { \"jsonName\": \"wban\", \"type\": \"String\" }, { \"jsonName\": \"station\", \"type\": \"String\", \"aggFn\": \"COUNT\" }, { \"jsonName\": \"country\", \"type\": \"String\" }, { \"jsonName\": \"state\", \"type\": \"String\" }, { \"jsonName\": \"icao\", \"type\": \"String\" }, { \"jsonName\": \"longitude\", \"type\": \"Number\" }, { \"jsonName\": \"latitude\", \"type\": \"Number\" }, { \"jsonName\": \"elevation\", \"type\": \"Number\" }, { \"jsonName\": \"dataBegin\", \"type\": \"Date\" }, { \"jsonName\": \"dataEnd\", \"type\": \"Date\" } ], \"params\": [ { \"jsonName\": \"state\", \"type\": \"in_set\", \"value\": \"\" } ] } ]}",
    "output": "{\n    \"dataSources\": [\n        {\n            \"dataSourceId\": \"c1366774-dace-4c33-904f-c9855255a7ef\",\n            \"queryKey\": \"API:+jdbc$$dataService$$ecwt_noaa_station\",\n            \"cols\": [\n                {\n                    \"jsonName\": \"usaf\",\n                    \"type\": \"String\"\n                },\n                {\n                    \"jsonName\": \"wban\",\n                    \"type\": \"String\"\n                },\n                {\n                    \"jsonName\": \"station\",\n                    \"type\": \"String\"\n                },\n                {\n                    \"jsonName\": \"country\",\n                    \"type\": \"String\"\n                },\n                {\n                    \"jsonName\": \"state\",\n                    \"type\": \"String\"\n                },\n                {\n                    \"jsonName\": \"icao\",\n                    \"type\": \"String\"\n                },\n                {\n                    \"jsonName\": \"longitude\",\n                    \"type\": \"Number\"\n                },\n                {\n                    \"jsonName\": \"latitude\",\n                    \"type\": \"Number\"\n                },\n                {\n                    \"jsonName\": \"elevation\",\n                    \"type\": \"Number\"\n                },\n                {\n                    \"jsonName\": \"dataBegin\",\n                    \"type\": \"Date\"\n                },\n                {\n                    \"jsonName\": \"dataEnd\",\n                    \"type\": \"Date\"\n                }\n            ],\n            \"params\": [\n                {\n                    \"jsonName\": \"state\",\n                    \"type\": \"in_set\",\n                    \"value\": \"California,Texas\"\n                }\n            ]\n        }\n    ],\n    \"chartLayout\": \"vertical\",\n    \"attributes\": {\n        \"chartType\": \"Geo Chart\",\n        \"sortOrder\": \"Asc\",\n        \"chartSubType\": \"map\",\n        \"geoColors\": {\n            \"field\": \"state\",\n            \"colors\": {\n                \"California\": \"#9cdd0e\",\n                \"Texas\": \"#d4a014\"\n            }\n        }\n    },\n    \"chartName\": \"Geo Checker\",\n    \"longitude\": {\n        \"fields\": [\n            \"longitude\"\n        ]\n    },\n    \"latitude\": {\n        \"fields\": [\n            \"latitude\"\n        ]\n    },\n    \"geoValue\": {\n        \"fields\": [\n            \"station\"\n        ]\n    },\n    \"geoField\": {},\n    \"xAxis\": {},\n    \"yAxis\": {},\n    \"secondaryYAxis\": {}\n}"
  },
  {
    "instruction": "Create a filled geo chart displaying the number of stations in California and Texas, using state names as locations. Arrange the data in descending order and set the chart title to \"Geo Checker\".",
    "input": "{ \"dataSources\": [ { \"dataSourceId\": \"c1366774-dace-4c33-904f-c9855255a7ef\", \"queryKey\": \"API:+jdbc$$dataService$$ecwt_noaa_station\", \"cols\": [ { \"jsonName\": \"usaf\", \"type\": \"String\" }, { \"jsonName\": \"wban\", \"type\": \"String\" }, { \"jsonName\": \"station\", \"type\": \"String\", \"aggFn\": \"COUNT\" }, { \"jsonName\": \"country\", \"type\": \"String\" }, { \"jsonName\": \"state\", \"type\": \"String\" }, { \"jsonName\": \"icao\", \"type\": \"String\" }, { \"jsonName\": \"longitude\", \"type\": \"Number\" }, { \"jsonName\": \"latitude\", \"type\": \"Number\" }, { \"jsonName\": \"elevation\", \"type\": \"Number\" }, { \"jsonName\": \"dataBegin\", \"type\": \"Date\" }, { \"jsonName\": \"dataEnd\", \"type\": \"Date\" } ], \"params\": [ { \"jsonName\": \"state\", \"type\": \"in_set\", \"value\": \"\" } ] } ]}",
    "output": "{ \"dataSources\": [ { \"dataSourceId\": \"c1366774-dace-4c33-904f-c9855255a7ef\", \"queryKey\": \"API:+jdbc$$dataService$$ecwt_noaa_station\", \"cols\": [ { \"jsonName\": \"usaf\", \"type\": \"String\" }, { \"jsonName\": \"wban\", \"type\": \"String\" }, { \"jsonName\": \"station\", \"type\": \"String\", \"aggFn\": \"COUNT\" }, { \"jsonName\": \"country\", \"type\": \"String\" }, { \"jsonName\": \"state\", \"type\": \"String\" }, { \"jsonName\": \"icao\", \"type\": \"String\" }, { \"jsonName\": \"longitude\", \"type\": \"Number\" }, { \"jsonName\": \"latitude\", \"type\": \"Number\" }, { \"jsonName\": \"elevation\", \"type\": \"Number\" }, { \"jsonName\": \"dataBegin\", \"type\": \"Date\" }, { \"jsonName\": \"dataEnd\", \"type\": \"Date\" } ], \"params\": [ { \"jsonName\": \"state\", \"type\": \"in_set\", \"value\": \"California,Texas\" } ] } ], \"chartLayout\": \"vertical\", \"attributes\": { \"chartType\": \"Geo Chart\", \"sortOrder\": \"Desc\", \"chartSubType\": \"filledMap\", }, \"chartName\": \"Geo Checker\", \"geoValue\": { \"fields\": [ \"station\" ] }, \"location\": { \"fields\": [ \"state\" ] }, \"geoField\": {}, \"xAxis\": {}, \"yAxis\": {}, \"secondaryYAxis\": {} }  "
  },
  {
    "instruction": "Generate a Gantt chart displaying tasks based on start and end dates. Use labels on the x-axis and mark milestones with a red flag at the end date. Set tooltips to show the name field and apply custom colors for different task types. Enable automatic y-axis margin adjustment and title the chart \"gantt chart - 2\".",
    "input": "{ \"dataSources\": [ { \"dataSourceId\": \"d6d59abc-852a-470c-99d8-a53b7411ed20\", \"queryKey\": \"API:+auto-task$$auto-task$$gantt-test-data-api\", \"cols\": [ { \"jsonName\": \"unitname\", \"type\": \"String\" }, { \"jsonName\": \"maintenanceName\", \"type\": \"String\" }, { \"jsonName\": \"label\", \"type\": \"String\" }, { \"jsonName\": \"startDate\", \"type\": \"Date\" }, { \"jsonName\": \"endDate\", \"type\": \"Date\" }, { \"jsonName\": \"seqNo\", \"type\": \"Number\" }, { \"jsonName\": \"name\", \"type\": \"String\" }, { \"jsonName\": \"color\", \"type\": \"String\" } ], \"params\": [] } ]}",
    "output": "{ \"dataSources\": [ { \"dataSourceId\": \"d6d59abc-852a-470c-99d8-a53b7411ed20\", \"queryKey\": \"API:+auto-task$$auto-task$$gantt-test-data-api\", \"cols\": [ { \"jsonName\": \"unitname\", \"type\": \"String\" }, { \"jsonName\": \"maintenanceName\", \"type\": \"String\" }, { \"jsonName\": \"label\", \"type\": \"String\" }, { \"jsonName\": \"startDate\", \"type\": \"Date\" }, { \"jsonName\": \"endDate\", \"type\": \"Date\" }, { \"jsonName\": \"seqNo\", \"type\": \"Number\" }, { \"jsonName\": \"name\", \"type\": \"String\" }, { \"jsonName\": \"color\", \"type\": \"String\" } ], \"params\": [] } ], \"xAxis\": { \"fields\": [ \"label\" ], }, \"yAxis\": { \"fields\": [ \"startDate\", \"endDate\" ], \"endMileStone\": \"endDate\", \"mileStoneIcon\": \"redFlag\" }, \"chartLayout\": \"vertical\", \"attributes\": { \"chartType\": \"Gantt Chart\", \"sortOrder\": \"Asc\", \"autoYMargin\": true, \"tooltipField\": \"@name \", \"fieldColor\": { \"field\": \"name\", \"colors\": { \"NEXT INSPECTION\": \"\", \"PLANNED OUTAGE\": \"\" } } }, \"chartName\": \"gantt chart - 2\", \"compositeDataSource\": \"\", \"secondaryYAxis\": {} } "
  },
  {
    "instruction": "Create a bar chart showing units on the y-axis and end dates on the x-axis, formatted by year with drill-down options for quarter, month, and date. Include profit as a secondary y-axis. Name the chart \"drill down chart\".",
    "input": "{ \"dataSources\": [{\"dataSourceId\": \"195d1b50-154c-41ef-99ce-8797b081435d\", \"queryKey\": \"API:+auto-task$$auto-task$$date-fields-api\", \"cols\": [{  \"jsonName\": \"name\", \"type\": \"string\"},{\"jsonName\": \"age\", \"type\": \"number\" },{\"jsonName\": \"id\", \"type\": \"number\"},{\"jsonName\": \"start\", \"type\": \"date\"},{\"jsonName\": \"end\", \"type\": \"date\"},{\"jsonName\": \"unit\",\"type\": \"number\" },{\"jsonName\": \"profit\",\"type\":\"number\"}],\"params\": []}]}",
    "output": "{\n    \"dataSources\": [\n        {\n            \"dataSourceId\": \"195d1b50-154c-41ef-99ce-8797b081435d\",\n            \"queryKey\": \"API:+auto-task$$auto-task$$date-fields-api\",\n            \"cols\": [\n                {\n                    \"jsonName\": \"name\",\n                    \"type\": \"string\"\n                },\n                {\n                    \"jsonName\": \"age\",\n                    \"type\": \"number\"\n                },\n                {\n                    \"jsonName\": \"id\",\n                    \"type\": \"number\"\n                },\n                {\n                    \"jsonName\": \"start\",\n                    \"type\": \"date\"\n                },\n                {\n                    \"jsonName\": \"end\",\n                    \"type\": \"date\"\n                },\n                {\n                    \"jsonName\": \"unit\",\n                    \"type\": \"number\"\n                },\n                {\n                    \"jsonName\": \"profit\",\n                    \"type\": \"number\"\n                }\n            ],\n            \"params\": []\n        }\n    ],\n    \"xAxis\": {\n        \"fields\": [\n            \"end\"\n        ],\n        \"dateDisplayFormat\": \"YYYY\",\n        \"drillDownBy\": [\n            \"quarter\",\n            \"month\",\n            \"date\"\n        ]\n    },\n    \"yAxis\": {\n        \"fields\": [\n            \"unit\"\n        ]\n    },\n    \"chartLayout\": \"vertical\",\n    \"attributes\": {\n        \"chartType\": \"Bar Chart\",\n        \"sortOrder\": \"Asc\"\n    },\n    \"chartName\": \"drill down chart\",\n    \"compositeDataSource\": \"\",\n    \"secondaryYAxis\": {\n        \"fields\": [\n            \"profit\"\n        ]\n    }\n}"
  },
  {
    "instruction": "Generate a stacked bar chart displaying sales amount for each sales person, categorized by geography with a color legend. Name the chart \"Legend Checker\".",
    "input": "{ \"dataSources\": [ { \"dataSourceId\": \"7d195dff-e36b-4a14-8c21-96aa21391583\", \"queryKey\": \"API:+lookup$$lookup$$Chocolate_Sales\", \"cols\": [ { \"jsonName\": \"Sales Person\", \"type\": \"string\" }, { \"jsonName\": \"Geography\", \"type\": \"string\" }, { \"jsonName\": \"Product\", \"type\": \"string\" }, { \"jsonName\": \"Amount\", \"type\": \"number\" }, { \"jsonName\": \"Units\", \"type\": \"number\" } ], \"params\": [] } ]}",
    "output": "{ \"dataSources\": [ { \"dataSourceId\": \"7d195dff-e36b-4a14-8c21-96aa21391583\", \"queryKey\": \"API:+lookup$$lookup$$Chocolate_Sales\", \"cols\": [ { \"jsonName\": \"Sales Person\", \"type\": \"string\" }, { \"jsonName\": \"Geography\", \"type\": \"string\" }, { \"jsonName\": \"Product\", \"type\": \"string\" }, { \"jsonName\": \"Amount\", \"type\": \"number\" }, { \"jsonName\": \"Units\", \"type\": \"number\" } ], \"params\": [] } ], \"xAxis\": { \"fields\": [ \"Sales Person\" ] }, \"yAxis\": { \"fields\": [ \"Amount\" ] }, \"chartLayout\": \"vertical\", \"attributes\": { \"chartType\": \"Bar Chart\", \"sortOrder\": \"Asc\", \"slider\": true, \"saveImage\": true, \"legend\": { \"field\": \"Geography\", \"colors\": { \"New Zealand\": \"\", \"USA\": \"\", \"Canada\": \"\", \"UK\": \"\", \"Australia\": \"\", \"India\": \"\" } }, \"stacked\": true }, \"chartName\": \"Legend Checker\", } "
  },
  {
    "instruction": "Create a bar chart to show sales amount per salesperson, categorized by geography with a legend. Sort the data in descending order, enable a slider, and don't allow image saving. Name the chart \"Legend Checker\".",
    "input": "{ \"dataSources\": [ { \"dataSourceId\": \"7d195dff-e36b-4a14-8c21-96aa21391583\", \"queryKey\": \"API:+lookup$$lookup$$Chocolate_Sales\", \"cols\": [ { \"jsonName\": \"Sales Person\", \"type\": \"string\" }, { \"jsonName\": \"Geography\", \"type\": \"string\" }, { \"jsonName\": \"Product\", \"type\": \"string\" }, { \"jsonName\": \"Amount\", \"type\": \"number\" }, { \"jsonName\": \"Units\", \"type\": \"number\" } ], \"params\": [] } ]}",
    "output": "{ \"dataSources\": [ { \"dataSourceId\": \"7d195dff-e36b-4a14-8c21-96aa21391583\", \"queryKey\": \"API:+lookup$$lookup$$Chocolate_Sales\", \"cols\": [ { \"jsonName\": \"Sales Person\", \"type\": \"string\" }, { \"jsonName\": \"Geography\", \"type\": \"string\" }, { \"jsonName\": \"Product\", \"type\": \"string\" }, { \"jsonName\": \"Amount\", \"type\": \"number\" }, { \"jsonName\": \"Units\", \"type\": \"number\" } ], \"params\": [] } ], \"xAxis\": { \"fields\": [ \"Sales Person\" ] }, \"yAxis\": { \"fields\": [ \"Amount\" ] }, \"chartLayout\": \"vertical\", \"attributes\": { \"chartType\": \"Bar Chart\", \"sortOrder\": \"Desc\", \"slider\": true, \"saveImage\": false, \"legend\": { \"field\": \"Geography\", \"colors\": { \"New Zealand\": \"\", \"USA\": \"\", \"Canada\": \"\", \"UK\": \"\", \"Australia\": \"\", \"India\": \"\" } }, }, \"chartName\": \"Legend Checker\", } "
  },
  {
    "instruction": "Generate a line chart to display official values over transaction hours. Give the chart title: \"Line Checker\".",
    "input": "{ \"dataSources\": [ { \"dataSourceId\": \"e744696c-bf86-4c97-9f6f-cef61501bb15\", \"queryKey\": \"API:+lookup$$lookup$$test_data\", \"cols\": [ { \"jsonName\": \"Entityname\", \"type\": \"string\" }, { \"jsonName\": \"Entity\", \"type\": \"string\" }, { \"jsonName\": \"Transdate\", \"type\": \"string\" }, { \"jsonName\": \"Transhour\", \"type\": \"number\" }, { \"jsonName\": \"Official\", \"type\": \"number\" }, { \"jsonName\": \"Pjm\", \"type\": \"number\" } ], \"params\": [] } ]}",
    "output": "{ \"dataSources\": [ { \"dataSourceId\": \"e744696c-bf86-4c97-9f6f-cef61501bb15\", \"queryKey\": \"API:+lookup$$lookup$$test_data\", \"cols\": [ { \"jsonName\": \"Entityname\", \"type\": \"string\" }, { \"jsonName\": \"Entity\", \"type\": \"string\" }, { \"jsonName\": \"Transdate\", \"type\": \"string\" }, { \"jsonName\": \"Transhour\", \"type\": \"number\" }, { \"jsonName\": \"Official\", \"type\": \"number\" }, { \"jsonName\": \"Pjm\", \"type\": \"number\" } ], \"params\": [] } ], \"xAxis\": { \"fields\": [ \"Transhour\" ] }, \"yAxis\": { \"fields\": [ \"Official\" ] }, \"chartLayout\": \"vertical\", \"attributes\": { \"chartType\": \"Line Chart\", \"sortOrder\": \"Asc\", \"slider\": true, \"saveImage\": true, }, \"chartName\": \"Line checker\", } "
  },
  {
    "instruction": "Create a horizontal line chart showing the minimum official values across transaction hours. The tooltip should have white text on a blue background. Name the chart \"Line Checker\".",
    "input": "{ \"dataSources\": [ { \"dataSourceId\": \"e744696c-bf86-4c97-9f6f-cef61501bb15\", \"queryKey\": \"API:+lookup$$lookup$$test_data\", \"cols\": [ { \"jsonName\": \"Entityname\", \"type\": \"string\" }, { \"jsonName\": \"Entity\", \"type\": \"string\" }, { \"jsonName\": \"Transdate\", \"type\": \"string\" }, { \"jsonName\": \"Transhour\", \"type\": \"number\" }, { \"jsonName\": \"Official\", \"type\": \"number\" }, { \"jsonName\": \"Pjm\", \"type\": \"number\" } ], \"params\": [] } ]}",
    "output": "{ \"dataSources\": [ { \"dataSourceId\": \"e744696c-bf86-4c97-9f6f-cef61501bb15\", \"queryKey\": \"API:+lookup$$lookup$$test_data\", \"cols\": [ { \"jsonName\": \"Entityname\", \"type\": \"string\" }, { \"jsonName\": \"Entity\", \"type\": \"string\" }, { \"jsonName\": \"Transdate\", \"type\": \"string\" }, { \"jsonName\": \"Transhour\", \"type\": \"number\" }, { \"jsonName\": \"Official\", \"type\": \"number\", \"aggFn\": \"MIN\", \"decimal\": \"1\" }, { \"jsonName\": \"Pjm\", \"type\": \"number\" } ], \"params\": [] } ], \"xAxis\": { \"fields\": [ \"Transhour\" ] }, \"yAxis\": { \"fields\": [ \"Official\" ] }, \"chartLayout\": \"horizontal\", \"attributes\": { \"chartType\": \"Line Chart\", \"sortOrder\": \"Desc\", \"slider\": true, \"saveImage\": true, \"tooltipTextColor\": \"#FFFFFF\", \"tooltipBgColor\": \"#0000FF\" }, \"chartName\": \"Line checker\", }  "
  },
  {
    "instruction": "Generate a vertical line chart to visualize official data over different transaction hours. The x-axis represents hours, while the y-axis displays official values, with an additional secondary y-axis for Pjm values. The official data line should be red, with the highest values in orange and lowest in gray. Chart should be named as \"Line Checker\".",
    "input": "{ \"dataSources\": [ { \"dataSourceId\": \"e744696c-bf86-4c97-9f6f-cef61501bb15\", \"queryKey\": \"API:+lookup$$lookup$$test_data\", \"cols\": [ { \"jsonName\": \"Entityname\", \"type\": \"string\" }, { \"jsonName\": \"Entity\", \"type\": \"string\" }, { \"jsonName\": \"Transdate\", \"type\": \"string\" }, { \"jsonName\": \"Transhour\", \"type\": \"number\" }, { \"jsonName\": \"Official\", \"type\": \"number\" }, { \"jsonName\": \"Pjm\", \"type\": \"number\" } ], \"params\": [] } ]}",
    "output": "{ \"dataSources\": [ { \"dataSourceId\": \"e744696c-bf86-4c97-9f6f-cef61501bb15\", \"queryKey\": \"API:+lookup$$lookup$$test_data\", \"cols\": [ { \"jsonName\": \"Entityname\", \"type\": \"string\" }, { \"jsonName\": \"Entity\", \"type\": \"string\" }, { \"jsonName\": \"Transdate\", \"type\": \"string\" }, { \"jsonName\": \"Transhour\", \"type\": \"number\" }, { \"jsonName\": \"Official\", \"type\": \"number\", \"isYAxisValueVisible\": true, \"label\": \"Official Data\", \"fillColor\": \"#FF0000\", \"fillHighestColor\": \"#FFA500\", \"fillLowestColor\": \"#D3D3D3\" }, { \"jsonName\": \"Pjm\", \"type\": \"number\" } ], \"params\": [] } ], \"xAxis\": { \"fields\": [ \"Transhour\" ], label: \"Hours\" }, \"yAxis\": { \"fields\": [ \"Official\" ] }, \"secondaryYAxis\": { \"fields\": [ \"Pjm\" ] }, \"chartLayout\": \"vertical\", \"attributes\": { \"chartType\": \"Line Chart\", \"sortOrder\": \"Asc\", \"slider\": true, \"saveImage\": true, }, \"chartName\": \"Line checker\", } "
  },
  {
    "instruction": "Create a pie chart to display the total units sold across different geographical regions. The x-axis represents geography, while the y-axis shows the units sold. Ensure that the chart includes percentage labels for each segment. Name this chart \"Pie Checker\".",
    "input": "{ \"dataSources\": [ { \"dataSourceId\": \"9875f4fa-b22e-4ea8-9e38-32b0ff8905d6\", \"queryKey\": \"API:+lookup$$lookup$$Chocolate_Sales\", \"cols\": [ { \"jsonName\": \"Sales Person\", \"type\": \"string\" }, { \"jsonName\": \"Geography\", \"type\": \"string\" }, { \"jsonName\": \"Product\", \"type\": \"string\" }, { \"jsonName\": \"Amount\", \"type\": \"number\" }, { \"jsonName\": \"Units\", \"type\": \"number\" } ], \"params\": [] } ]}",
    "output": "{ \"dataSources\": [ { \"dataSourceId\": \"9875f4fa-b22e-4ea8-9e38-32b0ff8905d6\", \"queryKey\": \"API:+lookup$$lookup$$Chocolate_Sales\", \"cols\": [ { \"jsonName\": \"Sales Person\", \"type\": \"string\" }, { \"jsonName\": \"Geography\", \"type\": \"string\" }, { \"jsonName\": \"Product\", \"type\": \"string\" }, { \"jsonName\": \"Amount\", \"type\": \"number\" }, { \"jsonName\": \"Units\", \"type\": \"number\" } ], \"params\": [] } ], \"xAxis\": { \"fields\": [ \"Geography\" ] }, \"yAxis\": { \"fields\": [ \"Units\" ] }, \"chartLayout\": \"vertical\", \"attributes\": { \"chartType\": \"Pie Chart\", \"sortOrder\": \"Asc\", \"showPercentage\": true }, \"chartName\": \"Pie Checker\", } "
  },
  {
    "instruction": "Create a doughnut chart to visualize units sold across different geographies. The x-axis represents geographical locations, while the y-axis corresponds to units sold. Ensure the chart includes a 29-degree rotation for better visibility. Each geography should have a distinct color, and the chart should be named \"Pie Checker\".",
    "input": "{ \"dataSources\": [ { \"dataSourceId\": \"9875f4fa-b22e-4ea8-9e38-32b0ff8905d6\", \"queryKey\": \"API:+lookup$$lookup$$Chocolate_Sales\", \"cols\": [ { \"jsonName\": \"Sales Person\", \"type\": \"string\" }, { \"jsonName\": \"Geography\", \"type\": \"string\" }, { \"jsonName\": \"Product\", \"type\": \"string\" }, { \"jsonName\": \"Amount\", \"type\": \"number\" }, { \"jsonName\": \"Units\", \"type\": \"number\" } ], \"params\": [] } ]}",
    "output": "{ \"dataSources\": [ { \"dataSourceId\": \"9875f4fa-b22e-4ea8-9e38-32b0ff8905d6\", \"queryKey\": \"API:+lookup$$lookup$$Chocolate_Sales\", \"cols\": [ { \"jsonName\": \"Sales Person\", \"type\": \"string\" }, { \"jsonName\": \"Geography\", \"type\": \"string\" }, { \"jsonName\": \"Product\", \"type\": \"string\" }, { \"jsonName\": \"Amount\", \"type\": \"number\" }, { \"jsonName\": \"Units\", \"type\": \"number\" } ], \"params\": [] } ], \"xAxis\": { \"fields\": [ \"Geography\" ] }, \"yAxis\": { \"fields\": [ \"Units\" ] }, \"chartLayout\": \"vertical\", \"attributes\": { \"chartType\": \"Pie Chart\", \"sortOrder\": \"Asc\", \"fieldColor\": { \"field\": \"Geography\", \"colors\": { \"New Zealand\": \"\", \"USA\": \"\", \"Canada\": \"\", \"UK\": \"\", \"Australia\": \"\", \"India\": \"\" } }, \"rotation\": 29, \"chartSubType\": \"doughnut\", }, \"chartName\": \"Pie Checker\" } "
  },
  {
    "instruction": "Create a line chart showing units sold across different regions. The x-axis represents geography, and the y-axis shows units. Add reference lines for max amount, median units, and average units, with only the average value displayed. Name it \"Reference Line Checker\".",
    "input": "{\n    \"dataSources\": [\n        {\n            \"dataSourceId\": \"613ead61-a88d-4eb6-a310-3a3d9afa0ea8\",\n            \"queryKey\": \"API:+lookup$$lookup$$Chocolate_Sales\",\n            \"cols\": [\n                {\n                    \"jsonName\": \"Sales Person\",\n                    \"type\": \"string\"\n                },\n                {\n                    \"jsonName\": \"Geography\",\n                    \"type\": \"string\"\n                },\n                {\n                    \"jsonName\": \"Product\",\n                    \"type\": \"string\"\n                },\n                {\n                    \"jsonName\": \"Amount\",\n                    \"type\": \"number\"\n                },\n                {\n                    \"jsonName\": \"Units\",\n                    \"type\": \"number\"\n                }\n            ],\n            \"params\": []\n        }\n    ]}",
    "output": "{\n    \"dataSources\": [\n        {\n            \"dataSourceId\": \"613ead61-a88d-4eb6-a310-3a3d9afa0ea8\",\n            \"queryKey\": \"API:+lookup$$lookup$$Chocolate_Sales\",\n            \"cols\": [\n                {\n                    \"jsonName\": \"Sales Person\",\n                    \"type\": \"string\"\n                },\n                {\n                    \"jsonName\": \"Geography\",\n                    \"type\": \"string\"\n                },\n                {\n                    \"jsonName\": \"Product\",\n                    \"type\": \"string\"\n                },\n                {\n                    \"jsonName\": \"Amount\",\n                    \"type\": \"number\"\n                },\n                {\n                    \"jsonName\": \"Units\",\n                    \"type\": \"number\"\n                }\n            ],\n            \"params\": []\n        }\n    ],\n    \"xAxis\": {\n        \"fields\": [\n            \"Geography\"\n        ]\n    },\n    \"yAxis\": {\n        \"fields\": [\n            \"Units\"\n        ]\n    },\n    \"chartLayout\": \"vertical\",\n    \"attributes\": {\n        \"chartType\": \"Line Chart\",\n        \"sortOrder\": \"Asc\",\n        \"referenceLines\": [\n            {\n                \"referenceFor\": \"Units\",\n                \"referenceLabel\": \"Amount Ref for Unit\",\n                \"showValue\": false,\n                \"referenceValueSource\": \"COMPUTED\",\n                \"referenceValue\": \"MAX\",\n                \"referenceLineColor\": \"#82da2b\",\n                \"referencefield\": \"Amount\"\n            },\n            {\n                \"referenceFor\": \"Units\",\n                \"referenceLabel\": \"Unit Median\",\n                \"showValue\": false,\n                \"referenceValueSource\": \"COMPUTED\",\n                \"referenceValue\": \"MEDIAN\",\n                \"referenceLineColor\": \"#e57427\",\n                \"referencefield\": \"Units\"\n            },\n            {\n                \"referenceFor\": \"Units\",\n                \"referenceLabel\": \"Unit Average\",\n                \"showValue\": true,\n                \"referenceValueSource\": \"COMPUTED\",\n                \"referenceValue\": \"AVG\",\n                \"referenceLineColor\": \"#c010ff\",\n                \"referencefield\": \"Units\"\n            }\n        ]\n    },\n    \"chartName\": \"Reference Line Checker\",\n    \"compositeDataSource\": \"\"\n}"
  },
  {
    "instruction": "Create a scatter chart to visualize the relationship between salespersons and geographical regions. The size of the points should reflect the number of units sold. Name the chart \"Scatter Checker\".",
    "input": "\n    \"dataSources\": [\n        {\n            \"dataSourceId\": \"2fcc2dab-b478-4359-b040-52a962bee8e1\",\n            \"queryKey\": \"API:+lookup$$lookup$$Chocolate_Sales\",\n            \"cols\": [\n                {\n                    \"jsonName\": \"Sales Person\",\n                    \"type\": \"string\"\n                },\n                {\n                    \"jsonName\": \"Geography\",\n                    \"type\": \"string\"\n                },\n                {\n                    \"jsonName\": \"Product\",\n                    \"type\": \"string\"\n                },\n                {\n                    \"jsonName\": \"Amount\",\n                    \"type\": \"number\"\n                },\n                {\n                    \"jsonName\": \"Units\",\n                    \"type\": \"number\"\n                }\n            ],\n            \"params\": []\n        }\n    ]}",
    "output": "{\n    \"dataSources\": [\n        {\n            \"dataSourceId\": \"2fcc2dab-b478-4359-b040-52a962bee8e1\",\n            \"queryKey\": \"API:+lookup$$lookup$$Chocolate_Sales\",\n            \"cols\": [\n                {\n                    \"jsonName\": \"Sales Person\",\n                    \"type\": \"string\"\n                },\n                {\n                    \"jsonName\": \"Geography\",\n                    \"type\": \"string\"\n                },\n                {\n                    \"jsonName\": \"Product\",\n                    \"type\": \"string\"\n                },\n                {\n                    \"jsonName\": \"Amount\",\n                    \"type\": \"number\"\n                },\n                {\n                    \"jsonName\": \"Units\",\n                    \"type\": \"number\"\n                }\n            ],\n            \"params\": []\n        }\n    ],\n    \"xAxis\": {\n        \"fields\": [\n            \"Sales Person\"\n        ]\n    },\n    \"yAxis\": {\n        \"fields\": [\n            \"Geography\"\n        ]\n    },\n    \"chartLayout\": \"vertical\",\n    \"attributes\": {\n        \"chartType\": \"Scattered Chart\",\n        \"sortOrder\": \"Asc\"\n    },\n    \"chartName\": \"Scatter Checker\",\n    \"compositeDataSource\": \"\",\n    \"zAxis\": {\n        \"fields\": [\n            \"Units\"\n        ]\n    }\n}"
  },
  {
    "instruction": "Generate a Tree Map chart to display the distribution of units sold across different geographies. The x-axis should represent the regions, while the y-axis corresponds to the number of units sold. Ensure the tooltip text is light blue on a dark background. Name the chart \"Tree Map Checker\".",
    "input": "{\n    \"dataSources\": [\n        {\n            \"dataSourceId\": \"5f150dc6-fa33-4f05-8323-1db6c849fb30\",\n            \"queryKey\": \"API:+lookup$$lookup$$Chocolate_Sales\",\n            \"cols\": [\n                {\n                    \"jsonName\": \"Sales Person\",\n                    \"type\": \"string\"\n                },\n                {\n                    \"jsonName\": \"Geography\",\n                    \"type\": \"string\"\n                },\n                {\n                    \"jsonName\": \"Product\",\n                    \"type\": \"string\"\n                },\n                {\n                    \"jsonName\": \"Amount\",\n                    \"type\": \"number\"\n                },\n                {\n                    \"jsonName\": \"Units\",\n                    \"type\": \"number\"\n                }\n            ],\n            \"params\": []\n        }\n    ]}",
    "output": "{\n    \"dataSources\": [\n        {\n            \"dataSourceId\": \"5f150dc6-fa33-4f05-8323-1db6c849fb30\",\n            \"queryKey\": \"API:+lookup$$lookup$$Chocolate_Sales\",\n            \"cols\": [\n                {\n                    \"jsonName\": \"Sales Person\",\n                    \"type\": \"string\"\n                },\n                {\n                    \"jsonName\": \"Geography\",\n                    \"type\": \"string\"\n                },\n                {\n                    \"jsonName\": \"Product\",\n                    \"type\": \"string\"\n                },\n                {\n                    \"jsonName\": \"Amount\",\n                    \"type\": \"number\"\n                },\n                {\n                    \"jsonName\": \"Units\",\n                    \"type\": \"number\"\n                }\n            ],\n            \"params\": []\n        }\n    ],\n    \"xAxis\": {\n        \"fields\": [\n            \"Geography\"\n        ]\n    },\n    \"yAxis\": {\n        \"fields\": [\n            \"Units\"\n        ]\n    },\n    \"chartLayout\": \"vertical\",\n    \"attributes\": {\n        \"chartType\": \"Tree Map\",\n        \"sortOrder\": \"Asc\",\n        \"tooltipTextColor\": \"#5acfe2\",\n        \"tooltipBgColor\": \"#0e3f56\"\n    },\n    \"chartName\": \"Tree Map Checker\"\n}"
  },
  {
    "instruction": "Create a Timeline Chart to visualize the maintenance schedule for different units. The x-axis should display unit names, while the y-axis represents the start and end dates of each task. Name the chart \"timeline chart - 1\".",
    "input": "{\n    \"dataSources\": [\n        {\n            \"dataSourceId\": \"224ef989-22b6-487f-a679-de520b50f027\",\n            \"queryKey\": \"API:+auto-task$$auto-task$$gantt-test-data-api\",\n            \"cols\": [\n                {\n                    \"jsonName\": \"unitname\",\n                    \"type\": \"String\"\n                },\n                {\n                    \"jsonName\": \"maintenanceName\",\n                    \"type\": \"String\"\n                },\n                {\n                    \"jsonName\": \"label\",\n                    \"type\": \"String\"\n                },\n                {\n                    \"jsonName\": \"startDate\",\n                    \"type\": \"Date\"\n                },\n                {\n                    \"jsonName\": \"endDate\",\n                    \"type\": \"Date\"\n                },\n                {\n                    \"jsonName\": \"seqNo\",\n                    \"type\": \"Number\"\n                },\n                {\n                    \"jsonName\": \"name\",\n                    \"type\": \"String\"\n                },\n                {\n                    \"jsonName\": \"color\",\n                    \"type\": \"String\"\n                }\n            ],\n            \"params\": []\n        }\n    ]}",
    "output": "{\n    \"dataSources\": [\n        {\n            \"dataSourceId\": \"224ef989-22b6-487f-a679-de520b50f027\",\n            \"queryKey\": \"API:+auto-task$$auto-task$$gantt-test-data-api\",\n            \"cols\": [\n                {\n                    \"jsonName\": \"unitname\",\n                    \"type\": \"String\"\n                },\n                {\n                    \"jsonName\": \"maintenanceName\",\n                    \"type\": \"String\"\n                },\n                {\n                    \"jsonName\": \"label\",\n                    \"type\": \"String\"\n                },\n                {\n                    \"jsonName\": \"startDate\",\n                    \"type\": \"Date\"\n                },\n                {\n                    \"jsonName\": \"endDate\",\n                    \"type\": \"Date\"\n                },\n                {\n                    \"jsonName\": \"seqNo\",\n                    \"type\": \"Number\"\n                },\n                {\n                    \"jsonName\": \"name\",\n                    \"type\": \"String\"\n                },\n                {\n                    \"jsonName\": \"color\",\n                    \"type\": \"String\"\n                }\n            ],\n            \"params\": []\n        }\n    ],\n    \"xAxis\": {\n        \"fields\": [\n            \"unitname\"\n        ]\n    },\n    \"yAxis\": {\n        \"fields\": [\n            \"startDate\",\n            \"endDate\"\n        ]\n    },\n    \"chartLayout\": \"vertical\",\n    \"attributes\": {\n        \"chartType\": \"TimeLine Chart\",\n        \"sortOrder\": \"Asc\"\n    },\n    \"chartName\": \"timeline chart - 1\",\n    \"compositeDataSource\": \"\",\n    \"secondaryYAxis\": {}\n}"
  },
  {
    "instruction": "\"Pie Chart\" with polar area diagram for cap1 group by capabilityid.",
    "input": "{\"dataSources\":[{\"dataSourceId\":\"92b03f88-84fd-484e-80a4-a1e809d90455\",\"queryKey\":\"API:+jdbc$$pmgr$$caps\",\"cols\":[{\"jsonName\":\"unitid\",\"type\":\"string\"},{\"jsonName\":\"capabilityid\",\"type\":\"string\"},{\"jsonName\":\"effectivedate\",\"type\":\"date\"},{\"jsonName\":\"cap1\",\"type\":\"number\"},{\"jsonName\":\"cap2\",\"type\":\"number\"},{\"jsonName\":\"cap3\",\"type\":\"number\"},{\"jsonName\":\"cap4\",\"type\":\"number\"},{\"jsonName\":\"cap5\",\"type\":\"number\"},{\"jsonName\":\"cap6\",\"type\":\"number\"},{\"jsonName\":\"cap7\",\"type\":\"number\"},{\"jsonName\":\"cap8\",\"type\":\"number\"},{\"jsonName\":\"cap9\",\"type\":\"number\"},{\"jsonName\":\"cap10\",\"type\":\"number\"},{\"jsonName\":\"cap11\",\"type\":\"number\"},{\"jsonName\":\"cap12\",\"type\":\"number\"},{\"jsonName\":\"documentIds\",\"type\":\"string\"},{\"jsonName\":\"comments\",\"type\":\"string\"},{\"jsonName\":\"modifier\",\"type\":\"string\"},{\"jsonName\":\"modifieddate\",\"type\":\"date\"},{\"jsonName\":\"workflowId\",\"type\":\"string\"},{\"jsonName\":\"integTransId\",\"type\":\"string\"}],\"params\":[]}]}",
    "output": "{\"dataSources\":[{\"dataSourceId\":\"92b03f88-84fd-484e-80a4-a1e809d90455\",\"queryKey\":\"API:+jdbc$$pmgr$$caps\",\"cols\":[{\"jsonName\":\"unitid\",\"type\":\"string\"},{\"jsonName\":\"capabilityid\",\"type\":\"string\"},{\"jsonName\":\"effectivedate\",\"type\":\"date\"},{\"jsonName\":\"cap1\",\"type\":\"number\"},{\"jsonName\":\"cap2\",\"type\":\"number\"},{\"jsonName\":\"cap3\",\"type\":\"number\"},{\"jsonName\":\"cap4\",\"type\":\"number\"},{\"jsonName\":\"cap5\",\"type\":\"number\"},{\"jsonName\":\"cap6\",\"type\":\"number\"},{\"jsonName\":\"cap7\",\"type\":\"number\"},{\"jsonName\":\"cap8\",\"type\":\"number\"},{\"jsonName\":\"cap9\",\"type\":\"number\"},{\"jsonName\":\"cap10\",\"type\":\"number\"},{\"jsonName\":\"cap11\",\"type\":\"number\"},{\"jsonName\":\"cap12\",\"type\":\"number\"},{\"jsonName\":\"documentIds\",\"type\":\"string\"},{\"jsonName\":\"comments\",\"type\":\"string\"},{\"jsonName\":\"modifier\",\"type\":\"string\"},{\"jsonName\":\"modifieddate\",\"type\":\"date\"},{\"jsonName\":\"workflowId\",\"type\":\"string\"},{\"jsonName\":\"integTransId\",\"type\":\"string\"}],\"params\":[]}],\"xAxis\":{\"fields\":[\"capabilityid\"]},\"yAxis\":{\"fields\":[\"cap1\"]},\"chartLayout\":\"vertical\",\"attributes\":{\"chartType\":\"Pie Chart\",\"sortOrder\":\"Asc\",\"rotation\":0,\"chartSubType\":\"nightingale\"},\"chartName\":\"Pie Chart\",\"compositeDataSource\":\"\"}"
  },
  {
    "instruction": "Add gantt chart, x-axis should be name and y-axis should be start and end.",
    "input": "{\"dataSources\":[{\"dataSourceId\":\"31ffbb88-0053-4e71-b14e-1dbf7e21cd4a\",\"queryKey\":\"API:+auto-task$$auto-task$$timeline-json-api\",\"cols\":[{\"jsonName\":\"name\",\"type\":\"string\"},{\"jsonName\":\"age\",\"type\":\"number\"},{\"jsonName\":\"id\",\"type\":\"number\"},{\"jsonName\":\"start\",\"type\":\"date\"},{\"jsonName\":\"end\",\"type\":\"date\"}],\"params\":[]}]}",
    "output": "{\"dataSources\":[{\"dataSourceId\":\"31ffbb88-0053-4e71-b14e-1dbf7e21cd4a\",\"queryKey\":\"API:+auto-task$$auto-task$$timeline-json-api\",\"cols\":[{\"jsonName\":\"name\",\"type\":\"string\"},{\"jsonName\":\"age\",\"type\":\"number\"},{\"jsonName\":\"id\",\"type\":\"number\"},{\"jsonName\":\"start\",\"type\":\"date\"},{\"jsonName\":\"end\",\"type\":\"date\"}],\"params\":[]}],\"chartLayout\":\"vertical\",\"chartName\":\"Gantt Chart\",\"xAxis\":{\"fields\":[\"name\"]},\"yAxis\":{\"fields\":[\"start\",\"end\"]},\"attributes\":{\"chartType\":\"Gantt Chart\",\"sortOrder\":\"Asc\"},\"compositeDataSource\":\"\"}"
  },
  {
    "instruction": "If possible add combine chart of line and bar. On xaxis show TEMPERATURE (Bin) and on yaxis show FREQUENCY (Frequency).Also add secondary yaxis for PERCENTILE (Cumulative %) show in #e66405 color. I would like to name it Histogram ECWT",
    "input": "{\"dataSources\":[{\"dataSourceId\":\"883de1ba-8459-4459-bde3-eb9ced4c03d0\",\"queryKey\":\"API:+auto-task$$auto-task$$NOAA-Histogram-Data-api\",\"cols\":[{\"jsonName\":\"START_DATE\",\"type\":\"string\"},{\"jsonName\":\"END_DATE\",\"type\":\"string\"},{\"jsonName\":\"STATION\",\"type\":\"number\"},{\"jsonName\":\"TEMPERATURE\",\"type\":\"number\"},{\"jsonName\":\"FREQUENCY\",\"type\":\"number\"},{\"jsonName\":\"C_FREQUENCY\",\"type\":\"number\"},{\"jsonName\":\"DATA_SIZE\",\"type\":\"number\"},{\"jsonName\":\"PERCENTILE\",\"type\":\"number\",\"fillColor\":\"#e66405\",\"composedChartType\":\"Line Chart\"}],\"params\":[{\"jsonName\":\"station\",\"type\":\"string\",\"value\":\"72353013967\"},{\"jsonName\":\"start_date\",\"type\":\"string\",\"value\":\"10/31/2012\"},{\"jsonName\":\"end_date\",\"type\":\"string\",\"value\":\"03/01/2022\"}]}]}",
    "output": "{\"dataSources\":[{\"dataSourceId\":\"883de1ba-8459-4459-bde3-eb9ced4c03d0\",\"queryKey\":\"API:+auto-task$$auto-task$$NOAA-Histogram-Data-api\",\"cols\":[{\"jsonName\":\"START_DATE\",\"type\":\"string\"},{\"jsonName\":\"END_DATE\",\"type\":\"string\"},{\"jsonName\":\"STATION\",\"type\":\"number\"},{\"jsonName\":\"TEMPERATURE\",\"type\":\"number\"},{\"jsonName\":\"FREQUENCY\",\"type\":\"number\"},{\"jsonName\":\"C_FREQUENCY\",\"type\":\"number\"},{\"jsonName\":\"DATA_SIZE\",\"type\":\"number\"},{\"jsonName\":\"PERCENTILE\",\"type\":\"number\",\"fillColor\":\"#e66405\",\"composedChartType\":\"Line Chart\"}],\"params\":[{\"jsonName\":\"station\",\"type\":\"string\",\"value\":\"72353013967\"},{\"jsonName\":\"start_date\",\"type\":\"string\",\"value\":\"10/31/2012\"},{\"jsonName\":\"end_date\",\"type\":\"string\",\"value\":\"03/01/2022\"}]}],\"xAxis\":{\"fields\":[\"TEMPERATURE\"],\"label\":\"Bin\"},\"yAxis\":{\"fields\":[\"FREQUENCY\"],\"label\":\"Frequency\"},\"chartLayout\":\"vertical\",\"attributes\":{\"chartType\":\"Composed Chart\",\"sortOrder\":\"Asc\"},\"chartName\":\"Histogram ECWT\",\"compositeDataSource\":\"\",\"secondaryYAxis\":{\"fields\":[\"PERCENTILE\"],\"label\":\"Cumulative %\"}}"
  },
  {
    "instruction": "Energy_TotalCn_Barchart (Bar chart) day on x and globalActivePower and globalReactivePower on y both should be group by sum and show in different colors.",
    "input": "{\"dataSources\":[{\"dataSourceId\":\"00bfb278-f853-4584-a576-623e91ea81b6\",\"queryKey\":\"API:+jdbc$$Oracle$$Energy_API\",\"cols\":[{\"jsonName\":\"year\",\"type\":\"Number\"},{\"jsonName\":\"month\",\"type\":\"Number\"},{\"jsonName\":\"day\",\"type\":\"Number\"},{\"jsonName\":\"timestamp\",\"type\":\"Date\"},{\"jsonName\":\"voltage\",\"type\":\"Number\"},{\"jsonName\":\"globalIntensity\",\"type\":\"Number\"},{\"jsonName\":\"globalActivePower\",\"type\":\"Number\",\"aggFn\":\"SUM\",\"label\":\"\",\"numberFormat\":\"Regular\",\"fillColor\":\"#1b8585\"},{\"jsonName\":\"globalReactivePower\",\"type\":\"Number\",\"aggFn\":\"SUM\",\"label\":\"\",\"numberFormat\":\"Regular\",\"fillColor\":\"#afffff\"},{\"jsonName\":\"powerFactor\",\"type\":\"Number\"},{\"jsonName\":\"activeEnergy\",\"type\":\"Number\"},{\"jsonName\":\"subMetering1\",\"type\":\"Number\"},{\"jsonName\":\"subMetering2\",\"type\":\"Number\"},{\"jsonName\":\"subMetering3\",\"type\":\"Number\"}],\"params\":[{\"jsonName\":\"Startdate\",\"type\":\"DATE\",\"value\":\"2007-05-01T00:00:00+05:30\"},{\"jsonName\":\"Enddate\",\"type\":\"DATE\",\"value\":\"2007-05-17T00:00:00+05:30\"}]}]}",
    "output": "{\"dataSources\":[{\"dataSourceId\":\"00bfb278-f853-4584-a576-623e91ea81b6\",\"queryKey\":\"API:+jdbc$$Oracle$$Energy_API\",\"cols\":[{\"jsonName\":\"year\",\"type\":\"Number\"},{\"jsonName\":\"month\",\"type\":\"Number\"},{\"jsonName\":\"day\",\"type\":\"Number\"},{\"jsonName\":\"timestamp\",\"type\":\"Date\"},{\"jsonName\":\"voltage\",\"type\":\"Number\"},{\"jsonName\":\"globalIntensity\",\"type\":\"Number\"},{\"jsonName\":\"globalActivePower\",\"type\":\"Number\",\"aggFn\":\"SUM\",\"label\":\"\",\"numberFormat\":\"Regular\",\"fillColor\":\"#1b8585\"},{\"jsonName\":\"globalReactivePower\",\"type\":\"Number\",\"aggFn\":\"SUM\",\"label\":\"\",\"numberFormat\":\"Regular\",\"fillColor\":\"#afffff\"},{\"jsonName\":\"powerFactor\",\"type\":\"Number\"},{\"jsonName\":\"activeEnergy\",\"type\":\"Number\"},{\"jsonName\":\"subMetering1\",\"type\":\"Number\"},{\"jsonName\":\"subMetering2\",\"type\":\"Number\"},{\"jsonName\":\"subMetering3\",\"type\":\"Number\"}],\"params\":[{\"jsonName\":\"Startdate\",\"type\":\"DATE\",\"value\":\"2007-05-01T00:00:00+05:30\"},{\"jsonName\":\"Enddate\",\"type\":\"DATE\",\"value\":\"2007-05-17T00:00:00+05:30\"}]}],\"chartLayout\":\"vertical\",\"chartName\":\"Energy_TotalCn_Barchart\",\"xAxis\":{\"fields\":[\"day\"]},\"yAxis\":{\"fields\":[\"globalActivePower\",\"globalReactivePower\"]},\"attributes\":{\"chartType\":\"Bar Chart\",\"sortOrder\":\"Asc\"},\"compositeDataSource\":\"\"}"
  },
  {
    "instruction": "Energy_SM_Barchart chart day by subMetering1, subMetering2 and subMetering3 and show in light cyan,bright cyan and teal colors respectively.",
    "input": "{\"dataSources\":[{\"dataSourceId\":\"bb9377dd-1103-45d3-a5ab-27a1a17411df\",\"queryKey\":\"API:+jdbc$$Oracle$$Energy_API\",\"cols\":[{\"jsonName\":\"year\",\"type\":\"Number\"},{\"jsonName\":\"month\",\"type\":\"Number\"},{\"jsonName\":\"day\",\"type\":\"Number\"},{\"jsonName\":\"timestamp\",\"type\":\"Date\"},{\"jsonName\":\"voltage\",\"type\":\"Number\"},{\"jsonName\":\"globalIntensity\",\"type\":\"Number\"},{\"jsonName\":\"globalActivePower\",\"type\":\"Number\"},{\"jsonName\":\"globalReactivePower\",\"type\":\"Number\"},{\"jsonName\":\"powerFactor\",\"type\":\"Number\"},{\"jsonName\":\"activeEnergy\",\"type\":\"Number\"},{\"jsonName\":\"subMetering1\",\"type\":\"Number\",\"aggFn\":\"SUM\",\"label\":\"\",\"numberFormat\":\"Regular\",\"fillColor\":\"#afffff\"},{\"jsonName\":\"subMetering2\",\"type\":\"Number\",\"aggFn\":\"SUM\",\"label\":\"\",\"numberFormat\":\"Regular\",\"fillColor\":\"#24dbdb\"},{\"jsonName\":\"subMetering3\",\"type\":\"Number\",\"aggFn\":\"SUM\",\"label\":\"\",\"numberFormat\":\"Regular\",\"fillColor\":\"#1b8585\"}],\"params\":[{\"jsonName\":\"Startdate\",\"type\":\"DATE\",\"value\":\"2007-05-01T00:00:00+05:30\"},{\"jsonName\":\"Enddate\",\"type\":\"DATE\",\"value\":\"2007-05-16T00:00:00+05:30\"}]}]}",
    "output": "{\"dataSources\":[{\"dataSourceId\":\"bb9377dd-1103-45d3-a5ab-27a1a17411df\",\"queryKey\":\"API:+jdbc$$Oracle$$Energy_API\",\"cols\":[{\"jsonName\":\"year\",\"type\":\"Number\"},{\"jsonName\":\"month\",\"type\":\"Number\"},{\"jsonName\":\"day\",\"type\":\"Number\"},{\"jsonName\":\"timestamp\",\"type\":\"Date\"},{\"jsonName\":\"voltage\",\"type\":\"Number\"},{\"jsonName\":\"globalIntensity\",\"type\":\"Number\"},{\"jsonName\":\"globalActivePower\",\"type\":\"Number\"},{\"jsonName\":\"globalReactivePower\",\"type\":\"Number\"},{\"jsonName\":\"powerFactor\",\"type\":\"Number\"},{\"jsonName\":\"activeEnergy\",\"type\":\"Number\"},{\"jsonName\":\"subMetering1\",\"type\":\"Number\",\"aggFn\":\"SUM\",\"label\":\"\",\"numberFormat\":\"Regular\",\"fillColor\":\"#afffff\"},{\"jsonName\":\"subMetering2\",\"type\":\"Number\",\"aggFn\":\"SUM\",\"label\":\"\",\"numberFormat\":\"Regular\",\"fillColor\":\"#24dbdb\"},{\"jsonName\":\"subMetering3\",\"type\":\"Number\",\"aggFn\":\"SUM\",\"label\":\"\",\"numberFormat\":\"Regular\",\"fillColor\":\"#1b8585\"}],\"params\":[{\"jsonName\":\"Startdate\",\"type\":\"DATE\",\"value\":\"2007-05-01T00:00:00+05:30\"},{\"jsonName\":\"Enddate\",\"type\":\"DATE\",\"value\":\"2007-05-16T00:00:00+05:30\"}]}],\"chartLayout\":\"vertical\",\"chartName\":\"Energy_SM_Barchart\",\"xAxis\":{\"fields\":[\"day\"]},\"yAxis\":{\"fields\":[\"subMetering3\",\"subMetering2\",\"subMetering1\"]},\"attributes\":{\"chartType\":\"Bar Chart\",\"sortOrder\":\"Asc\"},\"compositeDataSource\":\"\"}"
  },
  {
    "instruction": "Energy_AE_linechart line chart with given name x-axis:day and y-axis:activeEnergy avg with Deep Sea Green color.",
    "input": "{\"dataSources\":[{\"dataSourceId\":\"131243fa-0180-45a3-b601-bd296e1fcf5e\",\"queryKey\":\"API:+jdbc$$Oracle$$Energy_API\",\"cols\":[{\"jsonName\":\"year\",\"type\":\"Number\"},{\"jsonName\":\"month\",\"type\":\"Number\",\"aggFn\":\"SUM\",\"label\":\"\",\"numberFormat\":\"Regular\",\"fillColor\":\"#F4D03F\"},{\"jsonName\":\"day\",\"type\":\"Number\",\"aggFn\":\"SUM\",\"label\":\"\",\"numberFormat\":\"Regular\",\"fillColor\":\"#0000ff\"},{\"jsonName\":\"timestamp\",\"type\":\"Date\"},{\"jsonName\":\"voltage\",\"type\":\"Number\"},{\"jsonName\":\"globalIntensity\",\"type\":\"Number\"},{\"jsonName\":\"globalActivePower\",\"type\":\"Number\"},{\"jsonName\":\"globalReactivePower\",\"type\":\"Number\",\"aggFn\":\"SUM\",\"label\":\"\",\"numberFormat\":\"Regular\",\"fillColor\":\"#0000ff\"},{\"jsonName\":\"powerFactor\",\"type\":\"Number\"},{\"jsonName\":\"activeEnergy\",\"type\":\"Number\",\"aggFn\":\"AVG\",\"label\":\"\",\"numberFormat\":\"Regular\",\"fillColor\":\"#1b8585\"},{\"jsonName\":\"subMetering1\",\"type\":\"Number\"},{\"jsonName\":\"subMetering2\",\"type\":\"Number\"},{\"jsonName\":\"subMetering3\",\"type\":\"Number\"}],\"params\":[{\"jsonName\":\"Startdate\",\"type\":\"DATE\",\"value\":\"2007-05-01T00:00:00+05:30\"},{\"jsonName\":\"Enddate\",\"type\":\"DATE\",\"value\":\"2007-05-16T00:00:00+05:30\"}]}]}",
    "output": "{\"dataSources\":[{\"dataSourceId\":\"131243fa-0180-45a3-b601-bd296e1fcf5e\",\"queryKey\":\"API:+jdbc$$Oracle$$Energy_API\",\"cols\":[{\"jsonName\":\"year\",\"type\":\"Number\"},{\"jsonName\":\"month\",\"type\":\"Number\",\"aggFn\":\"SUM\",\"label\":\"\",\"numberFormat\":\"Regular\",\"fillColor\":\"#F4D03F\"},{\"jsonName\":\"day\",\"type\":\"Number\",\"aggFn\":\"SUM\",\"label\":\"\",\"numberFormat\":\"Regular\",\"fillColor\":\"#0000ff\"},{\"jsonName\":\"timestamp\",\"type\":\"Date\"},{\"jsonName\":\"voltage\",\"type\":\"Number\"},{\"jsonName\":\"globalIntensity\",\"type\":\"Number\"},{\"jsonName\":\"globalActivePower\",\"type\":\"Number\"},{\"jsonName\":\"globalReactivePower\",\"type\":\"Number\",\"aggFn\":\"SUM\",\"label\":\"\",\"numberFormat\":\"Regular\",\"fillColor\":\"#0000ff\"},{\"jsonName\":\"powerFactor\",\"type\":\"Number\"},{\"jsonName\":\"activeEnergy\",\"type\":\"Number\",\"aggFn\":\"AVG\",\"label\":\"\",\"numberFormat\":\"Regular\",\"fillColor\":\"#1b8585\"},{\"jsonName\":\"subMetering1\",\"type\":\"Number\"},{\"jsonName\":\"subMetering2\",\"type\":\"Number\"},{\"jsonName\":\"subMetering3\",\"type\":\"Number\"}],\"params\":[{\"jsonName\":\"Startdate\",\"type\":\"DATE\",\"value\":\"2007-05-01T00:00:00+05:30\"},{\"jsonName\":\"Enddate\",\"type\":\"DATE\",\"value\":\"2007-05-16T00:00:00+05:30\"}]}],\"chartLayout\":\"vertical\",\"chartName\":\"Energy_AE_linechart\",\"xAxis\":{\"fields\":[\"day\"]},\"yAxis\":{\"fields\":[\"activeEnergy\"]},\"attributes\":{\"chartType\":\"Line Chart\",\"sortOrder\":\"Asc\"},\"compositeDataSource\":\"\"}"
  },
  {
    "instruction": "Energy_PF_linechart x-axis day and y-axis:powerFactor avg with some good color.",
    "input": "{\"dataSources\":[{\"dataSourceId\":\"1c258399-fda3-4eeb-b2be-48fdbaf82986\",\"queryKey\":\"API:+jdbc$$Oracle$$Energy_API\",\"cols\":[{\"jsonName\":\"year\",\"type\":\"Number\"},{\"jsonName\":\"month\",\"type\":\"Number\"},{\"jsonName\":\"day\",\"type\":\"Number\"},{\"jsonName\":\"timestamp\",\"type\":\"Date\"},{\"jsonName\":\"voltage\",\"type\":\"Number\"},{\"jsonName\":\"globalIntensity\",\"type\":\"Number\"},{\"jsonName\":\"globalActivePower\",\"type\":\"Number\"},{\"jsonName\":\"globalReactivePower\",\"type\":\"Number\"},{\"jsonName\":\"powerFactor\",\"type\":\"Number\",\"aggFn\":\"AVG\",\"label\":\"\",\"numberFormat\":\"Regular\",\"fillColor\":\"#1b8585\"},{\"jsonName\":\"activeEnergy\",\"type\":\"Number\"},{\"jsonName\":\"subMetering1\",\"type\":\"Number\"},{\"jsonName\":\"subMetering2\",\"type\":\"Number\"},{\"jsonName\":\"subMetering3\",\"type\":\"Number\"}],\"params\":[{\"jsonName\":\"Startdate\",\"type\":\"DATE\",\"value\":\"2007-05-01T00:00:00+05:30\"},{\"jsonName\":\"Enddate\",\"type\":\"DATE\",\"value\":\"2007-05-17T00:00:00+05:30\"}]}]}",
    "output": "{\"dataSources\":[{\"dataSourceId\":\"1c258399-fda3-4eeb-b2be-48fdbaf82986\",\"queryKey\":\"API:+jdbc$$Oracle$$Energy_API\",\"cols\":[{\"jsonName\":\"year\",\"type\":\"Number\"},{\"jsonName\":\"month\",\"type\":\"Number\"},{\"jsonName\":\"day\",\"type\":\"Number\"},{\"jsonName\":\"timestamp\",\"type\":\"Date\"},{\"jsonName\":\"voltage\",\"type\":\"Number\"},{\"jsonName\":\"globalIntensity\",\"type\":\"Number\"},{\"jsonName\":\"globalActivePower\",\"type\":\"Number\"},{\"jsonName\":\"globalReactivePower\",\"type\":\"Number\"},{\"jsonName\":\"powerFactor\",\"type\":\"Number\",\"aggFn\":\"AVG\",\"label\":\"\",\"numberFormat\":\"Regular\",\"fillColor\":\"#1b8585\"},{\"jsonName\":\"activeEnergy\",\"type\":\"Number\"},{\"jsonName\":\"subMetering1\",\"type\":\"Number\"},{\"jsonName\":\"subMetering2\",\"type\":\"Number\"},{\"jsonName\":\"subMetering3\",\"type\":\"Number\"}],\"params\":[{\"jsonName\":\"Startdate\",\"type\":\"DATE\",\"value\":\"2007-05-01T00:00:00+05:30\"},{\"jsonName\":\"Enddate\",\"type\":\"DATE\",\"value\":\"2007-05-17T00:00:00+05:30\"}]}],\"chartLayout\":\"vertical\",\"chartName\":\"Energy_PF_linechart\",\"xAxis\":{\"fields\":[\"day\"]},\"yAxis\":{\"fields\":[\"powerFactor\"]},\"attributes\":{\"chartType\":\"Line Chart\",\"sortOrder\":\"Asc\"},\"compositeDataSource\":\"\"}"
  },
  {
    "instruction": "Stacked Pie chart to show cap1,cap2,cap5,cap6,cap7,cap8,cap11,cap12 values by capabilityid use can name it Cap New Pie.",
    "input": "{\"dataSources\":[{\"dataSourceId\":\"65f75388-5912-416f-8ac7-6fcb1ed08356\",\"queryKey\":\"API:+jdbc$$pmgr$$caps\",\"cols\":[{\"jsonName\":\"unitid\",\"type\":\"String\"},{\"jsonName\":\"capabilityid\",\"type\":\"String\"},{\"jsonName\":\"effectivedate\",\"type\":\"Date\"},{\"jsonName\":\"cap1\",\"type\":\"Number\"},{\"jsonName\":\"cap2\",\"type\":\"Number\"},{\"jsonName\":\"cap3\",\"type\":\"Number\"},{\"jsonName\":\"cap4\",\"type\":\"Number\"},{\"jsonName\":\"cap5\",\"type\":\"Number\"},{\"jsonName\":\"cap6\",\"type\":\"Number\"},{\"jsonName\":\"cap7\",\"type\":\"Number\"},{\"jsonName\":\"cap8\",\"type\":\"Number\"},{\"jsonName\":\"cap9\",\"type\":\"Number\"},{\"jsonName\":\"cap10\",\"type\":\"Number\"},{\"jsonName\":\"cap11\",\"type\":\"Number\"},{\"jsonName\":\"cap12\",\"type\":\"Number\"},{\"jsonName\":\"documentIds\",\"type\":\"String\"},{\"jsonName\":\"comments\",\"type\":\"String\"},{\"jsonName\":\"modifier\",\"type\":\"String\"},{\"jsonName\":\"modifieddate\",\"type\":\"Date\"},{\"jsonName\":\"workflowId\",\"type\":\"String\"},{\"jsonName\":\"integTransId\",\"type\":\"String\"}],\"params\":[]}]}",
    "output": "{\"dataSources\":[{\"dataSourceId\":\"65f75388-5912-416f-8ac7-6fcb1ed08356\",\"queryKey\":\"API:+jdbc$$pmgr$$caps\",\"cols\":[{\"jsonName\":\"unitid\",\"type\":\"String\"},{\"jsonName\":\"capabilityid\",\"type\":\"String\"},{\"jsonName\":\"effectivedate\",\"type\":\"Date\"},{\"jsonName\":\"cap1\",\"type\":\"Number\"},{\"jsonName\":\"cap2\",\"type\":\"Number\"},{\"jsonName\":\"cap3\",\"type\":\"Number\"},{\"jsonName\":\"cap4\",\"type\":\"Number\"},{\"jsonName\":\"cap5\",\"type\":\"Number\"},{\"jsonName\":\"cap6\",\"type\":\"Number\"},{\"jsonName\":\"cap7\",\"type\":\"Number\"},{\"jsonName\":\"cap8\",\"type\":\"Number\"},{\"jsonName\":\"cap9\",\"type\":\"Number\"},{\"jsonName\":\"cap10\",\"type\":\"Number\"},{\"jsonName\":\"cap11\",\"type\":\"Number\"},{\"jsonName\":\"cap12\",\"type\":\"Number\"},{\"jsonName\":\"documentIds\",\"type\":\"String\"},{\"jsonName\":\"comments\",\"type\":\"String\"},{\"jsonName\":\"modifier\",\"type\":\"String\"},{\"jsonName\":\"modifieddate\",\"type\":\"Date\"},{\"jsonName\":\"workflowId\",\"type\":\"String\"},{\"jsonName\":\"integTransId\",\"type\":\"String\"}],\"params\":[]}],\"chartLayout\":\"vertical\",\"chartName\":\"Cap New Pie\",\"xAxis\":{\"fields\":[\"capabilityid\"]},\"yAxis\":{\"fields\":[\"cap1\",\"cap2\",\"cap11\",\"cap12\",\"cap5\",\"cap7\",\"cap6\",\"cap8\"]},\"attributes\":{\"chartType\":\"Stacked Pie Chart\",\"sortOrder\":\"Asc\"},\"compositeDataSource\":\"\"}"
  },
  {
    "instruction": "Area Chart (Energy_Hours_Chart) timestamp on x with 24 hour format to show globalActivePower and globalReactivePower.",
    "input": "{\"dataSources\":[{\"dataSourceId\":\"8b986e55-28d6-458a-8c70-f3fbf6086d04\",\"queryKey\":\"API:+jdbc$$Oracle$$Energy_API\",\"cols\":[{\"jsonName\":\"year\",\"type\":\"Number\"},{\"jsonName\":\"month\",\"type\":\"Number\"},{\"jsonName\":\"day\",\"type\":\"Number\"},{\"jsonName\":\"timestamp\",\"type\":\"Date\"},{\"jsonName\":\"voltage\",\"type\":\"Number\"},{\"jsonName\":\"globalIntensity\",\"type\":\"Number\"},{\"jsonName\":\"globalActivePower\",\"type\":\"Number\",\"aggFn\":\"SUM\",\"label\":\"\",\"numberFormat\":\"Regular\",\"fillColor\":\"#bdffff\"},{\"jsonName\":\"globalReactivePower\",\"type\":\"Number\",\"aggFn\":\"SUM\",\"label\":\"\",\"numberFormat\":\"Regular\",\"fillColor\":\"#1b8585\"},{\"jsonName\":\"powerFactor\",\"type\":\"Number\"},{\"jsonName\":\"activeEnergy\",\"type\":\"Number\"},{\"jsonName\":\"subMetering1\",\"type\":\"Number\"},{\"jsonName\":\"subMetering2\",\"type\":\"Number\"},{\"jsonName\":\"subMetering3\",\"type\":\"Number\"}],\"params\":[{\"jsonName\":\"Startdate\",\"type\":\"DATE\",\"value\":\"2007-03-01T00:00:00+05:30\"},{\"jsonName\":\"Enddate\",\"type\":\"DATE\",\"value\":\"2007-03-31T00:00:00+05:30\"}]}]}",
    "output": "{\"dataSources\":[{\"dataSourceId\":\"8b986e55-28d6-458a-8c70-f3fbf6086d04\",\"queryKey\":\"API:+jdbc$$Oracle$$Energy_API\",\"cols\":[{\"jsonName\":\"year\",\"type\":\"Number\"},{\"jsonName\":\"month\",\"type\":\"Number\"},{\"jsonName\":\"day\",\"type\":\"Number\"},{\"jsonName\":\"timestamp\",\"type\":\"Date\"},{\"jsonName\":\"voltage\",\"type\":\"Number\"},{\"jsonName\":\"globalIntensity\",\"type\":\"Number\"},{\"jsonName\":\"globalActivePower\",\"type\":\"Number\",\"aggFn\":\"SUM\",\"label\":\"\",\"numberFormat\":\"Regular\",\"fillColor\":\"#bdffff\"},{\"jsonName\":\"globalReactivePower\",\"type\":\"Number\",\"aggFn\":\"SUM\",\"label\":\"\",\"numberFormat\":\"Regular\",\"fillColor\":\"#1b8585\"},{\"jsonName\":\"powerFactor\",\"type\":\"Number\"},{\"jsonName\":\"activeEnergy\",\"type\":\"Number\"},{\"jsonName\":\"subMetering1\",\"type\":\"Number\"},{\"jsonName\":\"subMetering2\",\"type\":\"Number\"},{\"jsonName\":\"subMetering3\",\"type\":\"Number\"}],\"params\":[{\"jsonName\":\"Startdate\",\"type\":\"DATE\",\"value\":\"2007-03-01T00:00:00+05:30\"},{\"jsonName\":\"Enddate\",\"type\":\"DATE\",\"value\":\"2007-03-31T00:00:00+05:30\"}]}],\"chartLayout\":\"vertical\",\"chartName\":\"Energy_Hours_Chart\",\"xAxis\":{\"fields\":[\"timestamp\"],\"dateDisplayFormat\":\"HH\"},\"yAxis\":{\"fields\":[\"globalActivePower\",\"globalReactivePower\"]},\"attributes\":{\"chartType\":\"Area Chart\",\"sortOrder\":\"Asc\"},\"compositeDataSource\":\"\"}"
  },
  {
    "instruction": "My first bar chart for testing capabilityid on x-axis and cap2 on y-axis and cap10 on another y-axis with default values.",
    "input": "{\"dataSources\":[{\"dataSourceId\":\"6ca470fd-ace9-4db1-bc4d-6208c097a2aa\",\"queryKey\":\"API:+jdbc$$pmgr$$caps\",\"cols\":[{\"jsonName\":\"unitid\",\"type\":\"String\"},{\"jsonName\":\"capabilityid\",\"type\":\"String\"},{\"jsonName\":\"effectivedate\",\"type\":\"Date\"},{\"jsonName\":\"cap1\",\"type\":\"Number\"},{\"jsonName\":\"cap2\",\"type\":\"Number\"},{\"jsonName\":\"cap3\",\"type\":\"Number\"},{\"jsonName\":\"cap4\",\"type\":\"Number\"},{\"jsonName\":\"cap5\",\"type\":\"Number\"},{\"jsonName\":\"cap6\",\"type\":\"Number\"},{\"jsonName\":\"cap7\",\"type\":\"Number\"},{\"jsonName\":\"cap8\",\"type\":\"Number\"},{\"jsonName\":\"cap9\",\"type\":\"Number\"},{\"jsonName\":\"cap10\",\"type\":\"Number\"},{\"jsonName\":\"cap11\",\"type\":\"Number\"},{\"jsonName\":\"cap12\",\"type\":\"Number\"},{\"jsonName\":\"documentIds\",\"type\":\"String\"},{\"jsonName\":\"comments\",\"type\":\"String\"},{\"jsonName\":\"modifier\",\"type\":\"String\"},{\"jsonName\":\"modifieddate\",\"type\":\"Date\"},{\"jsonName\":\"workflowId\",\"type\":\"String\"},{\"jsonName\":\"integTransId\",\"type\":\"String\"}],\"params\":[]}]}",
    "output": "{\"dataSources\":[{\"dataSourceId\":\"6ca470fd-ace9-4db1-bc4d-6208c097a2aa\",\"queryKey\":\"API:+jdbc$$pmgr$$caps\",\"cols\":[{\"jsonName\":\"unitid\",\"type\":\"String\"},{\"jsonName\":\"capabilityid\",\"type\":\"String\"},{\"jsonName\":\"effectivedate\",\"type\":\"Date\"},{\"jsonName\":\"cap1\",\"type\":\"Number\"},{\"jsonName\":\"cap2\",\"type\":\"Number\"},{\"jsonName\":\"cap3\",\"type\":\"Number\"},{\"jsonName\":\"cap4\",\"type\":\"Number\"},{\"jsonName\":\"cap5\",\"type\":\"Number\"},{\"jsonName\":\"cap6\",\"type\":\"Number\"},{\"jsonName\":\"cap7\",\"type\":\"Number\"},{\"jsonName\":\"cap8\",\"type\":\"Number\"},{\"jsonName\":\"cap9\",\"type\":\"Number\"},{\"jsonName\":\"cap10\",\"type\":\"Number\"},{\"jsonName\":\"cap11\",\"type\":\"Number\"},{\"jsonName\":\"cap12\",\"type\":\"Number\"},{\"jsonName\":\"documentIds\",\"type\":\"String\"},{\"jsonName\":\"comments\",\"type\":\"String\"},{\"jsonName\":\"modifier\",\"type\":\"String\"},{\"jsonName\":\"modifieddate\",\"type\":\"Date\"},{\"jsonName\":\"workflowId\",\"type\":\"String\"},{\"jsonName\":\"integTransId\",\"type\":\"String\"}],\"params\":[]}],\"xAxis\":{\"fields\":[\"capabilityid\"]},\"yAxis\":{\"fields\":[\"cap1\"]},\"chartLayout\":\"vertical\",\"attributes\":{\"chartType\":\"Bar Chart\",\"sortOrder\":\"Asc\"},\"chartName\":\"First Bar Chart\",\"compositeDataSource\":\"\",\"secondaryYAxis\":{\"fields\":[\"cap10\"]}}"
  },
  {
    "instruction": "Test for Bar chart with date format MM/YYYY on effectivedate (x) , cap1 (y) name it something like First Chart with Date.",
    "input": "{\"dataSources\":[{\"dataSourceId\":\"6ca470fd-ace9-4db1-bc4d-6208c097a2aa\",\"queryKey\":\"API:+jdbc$$pmgr$$caps\",\"cols\":[{\"jsonName\":\"unitid\",\"type\":\"String\"},{\"jsonName\":\"capabilityid\",\"type\":\"String\"},{\"jsonName\":\"effectivedate\",\"type\":\"Date\"},{\"jsonName\":\"cap1\",\"type\":\"Number\"},{\"jsonName\":\"cap2\",\"type\":\"Number\"},{\"jsonName\":\"cap3\",\"type\":\"Number\"},{\"jsonName\":\"cap4\",\"type\":\"Number\"},{\"jsonName\":\"cap5\",\"type\":\"Number\"},{\"jsonName\":\"cap6\",\"type\":\"Number\"},{\"jsonName\":\"cap7\",\"type\":\"Number\"},{\"jsonName\":\"cap8\",\"type\":\"Number\"},{\"jsonName\":\"cap9\",\"type\":\"Number\"},{\"jsonName\":\"cap10\",\"type\":\"Number\"},{\"jsonName\":\"cap11\",\"type\":\"Number\"},{\"jsonName\":\"cap12\",\"type\":\"Number\"},{\"jsonName\":\"documentIds\",\"type\":\"String\"},{\"jsonName\":\"comments\",\"type\":\"String\"},{\"jsonName\":\"modifier\",\"type\":\"String\"},{\"jsonName\":\"modifieddate\",\"type\":\"Date\"},{\"jsonName\":\"workflowId\",\"type\":\"String\"},{\"jsonName\":\"integTransId\",\"type\":\"String\"}],\"params\":[]}]}",
    "output": "{\"dataSources\":[{\"dataSourceId\":\"6ca470fd-ace9-4db1-bc4d-6208c097a2aa\",\"queryKey\":\"API:+jdbc$$pmgr$$caps\",\"cols\":[{\"jsonName\":\"unitid\",\"type\":\"String\"},{\"jsonName\":\"capabilityid\",\"type\":\"String\"},{\"jsonName\":\"effectivedate\",\"type\":\"Date\"},{\"jsonName\":\"cap1\",\"type\":\"Number\"},{\"jsonName\":\"cap2\",\"type\":\"Number\"},{\"jsonName\":\"cap3\",\"type\":\"Number\"},{\"jsonName\":\"cap4\",\"type\":\"Number\"},{\"jsonName\":\"cap5\",\"type\":\"Number\"},{\"jsonName\":\"cap6\",\"type\":\"Number\"},{\"jsonName\":\"cap7\",\"type\":\"Number\"},{\"jsonName\":\"cap8\",\"type\":\"Number\"},{\"jsonName\":\"cap9\",\"type\":\"Number\"},{\"jsonName\":\"cap10\",\"type\":\"Number\"},{\"jsonName\":\"cap11\",\"type\":\"Number\"},{\"jsonName\":\"cap12\",\"type\":\"Number\"},{\"jsonName\":\"documentIds\",\"type\":\"String\"},{\"jsonName\":\"comments\",\"type\":\"String\"},{\"jsonName\":\"modifier\",\"type\":\"String\"},{\"jsonName\":\"modifieddate\",\"type\":\"Date\"},{\"jsonName\":\"workflowId\",\"type\":\"String\"},{\"jsonName\":\"integTransId\",\"type\":\"String\"}],\"params\":[]}],\"xAxis\":{\"fields\":[\"effectivedate\"],\"dateDisplayFormat\":\"MM/YYYY\"},\"yAxis\":{\"fields\":[\"cap1\"]},\"chartLayout\":\"vertical\",\"attributes\":{\"chartType\":\"Bar Chart\",\"sortOrder\":\"Asc\"},\"chartName\":\"First Chart with Date\",\"compositeDataSource\":\"\",\"secondaryYAxis\":{\"fields\":[]}}"
  },
  {
    "instruction": "Gantt chart with name Timeline chart for age.",
    "input": "{\"dataSources\":[{\"dataSourceId\":\"528f3754-d50d-42b7-bff1-974fe7b9eebc\",\"queryKey\":\"API:+auto-task$$auto-task$$test-helper-timeline-api\",\"cols\":[{\"jsonName\":\"name\",\"type\":\"string\"},{\"jsonName\":\"age\",\"type\":\"number\"},{\"jsonName\":\"id\",\"type\":\"number\"},{\"jsonName\":\"start\",\"type\":\"date\"},{\"jsonName\":\"end\",\"type\":\"date\"}],\"params\":[]}]}",
    "output": "{\"dataSources\":[{\"dataSourceId\":\"528f3754-d50d-42b7-bff1-974fe7b9eebc\",\"queryKey\":\"API:+auto-task$$auto-task$$test-helper-timeline-api\",\"cols\":[{\"jsonName\":\"name\",\"type\":\"string\"},{\"jsonName\":\"age\",\"type\":\"number\"},{\"jsonName\":\"id\",\"type\":\"number\"},{\"jsonName\":\"start\",\"type\":\"date\"},{\"jsonName\":\"end\",\"type\":\"date\"}],\"params\":[]}],\"xAxis\":{\"fields\":[\"age\"]},\"yAxis\":{\"fields\":[\"start\",\"end\"]},\"chartLayout\":\"vertical\",\"attributes\":{\"chartType\":\"Gantt Chart\",\"sortOrder\":\"Asc\"},\"chartName\":\"Timeline Chart\",\"compositeDataSource\":\"\",\"secondaryYAxis\":{}}"
  },
  {
    "instruction": "Legend bar chart name it Legends Bar capabiltiyid on x field and cap1 to cap5 on y field make cap1 is going to be the only legend field with other default fields.",
    "input": "{\"dataSources\":[{\"dataSourceId\":\"b37b4f38-9488-4e3a-9db0-1d965b88a098\",\"queryKey\":\"API:+jdbc$$pmgr$$caps-20\",\"cols\":[{\"jsonName\":\"unitid\",\"type\":\"string\"},{\"jsonName\":\"capabilityid\",\"type\":\"string\"},{\"jsonName\":\"effectivedate\",\"type\":\"date\"},{\"jsonName\":\"cap1\",\"type\":\"number\"},{\"jsonName\":\"cap2\",\"type\":\"number\"},{\"jsonName\":\"cap3\",\"type\":\"number\"},{\"jsonName\":\"cap4\",\"type\":\"number\"},{\"jsonName\":\"cap5\",\"type\":\"number\"},{\"jsonName\":\"cap6\",\"type\":\"number\"},{\"jsonName\":\"cap7\",\"type\":\"number\"},{\"jsonName\":\"cap8\",\"type\":\"number\"},{\"jsonName\":\"cap9\",\"type\":\"number\"},{\"jsonName\":\"cap10\",\"type\":\"number\"},{\"jsonName\":\"cap11\",\"type\":\"number\"},{\"jsonName\":\"cap12\",\"type\":\"number\"},{\"jsonName\":\"documentIds\",\"type\":\"string\"},{\"jsonName\":\"comments\",\"type\":\"string\"},{\"jsonName\":\"modifier\",\"type\":\"string\"},{\"jsonName\":\"modifieddate\",\"type\":\"date\"},{\"jsonName\":\"workflowId\",\"type\":\"string\"},{\"jsonName\":\"integTransId\",\"type\":\"string\"}],\"params\":[]}]}",
    "output": "{\"dataSources\":[{\"dataSourceId\":\"b37b4f38-9488-4e3a-9db0-1d965b88a098\",\"queryKey\":\"API:+jdbc$$pmgr$$caps-20\",\"cols\":[{\"jsonName\":\"unitid\",\"type\":\"string\"},{\"jsonName\":\"capabilityid\",\"type\":\"string\"},{\"jsonName\":\"effectivedate\",\"type\":\"date\"},{\"jsonName\":\"cap1\",\"type\":\"number\"},{\"jsonName\":\"cap2\",\"type\":\"number\"},{\"jsonName\":\"cap3\",\"type\":\"number\"},{\"jsonName\":\"cap4\",\"type\":\"number\"},{\"jsonName\":\"cap5\",\"type\":\"number\"},{\"jsonName\":\"cap6\",\"type\":\"number\"},{\"jsonName\":\"cap7\",\"type\":\"number\"},{\"jsonName\":\"cap8\",\"type\":\"number\"},{\"jsonName\":\"cap9\",\"type\":\"number\"},{\"jsonName\":\"cap10\",\"type\":\"number\"},{\"jsonName\":\"cap11\",\"type\":\"number\"},{\"jsonName\":\"cap12\",\"type\":\"number\"},{\"jsonName\":\"documentIds\",\"type\":\"string\"},{\"jsonName\":\"comments\",\"type\":\"string\"},{\"jsonName\":\"modifier\",\"type\":\"string\"},{\"jsonName\":\"modifieddate\",\"type\":\"date\"},{\"jsonName\":\"workflowId\",\"type\":\"string\"},{\"jsonName\":\"integTransId\",\"type\":\"string\"}],\"params\":[]}],\"chartLayout\":\"vertical\",\"attributes\":{\"chartType\":\"Bar Chart\",\"sortOrder\":\"Asc\",\"legend\":{\"field\":\"cap1\",\"colors\":{\"66\":\"\",\"73\":\"\",\"75\":\"\",\"151\":\"\",\"175\":\"\",\"500\":\"\",\"597\":\"\",\"600\":\"\",\"900\":\"\",\"1084\":\"\",\"1320\":\"\"}}},\"chartName\":\"Legends Bar\",\"compositeDataSource\":\"\",\"xAxis\":{\"fields\":[\"capabilityid\"]},\"yAxis\":{\"fields\":[\"cap2\",\"cap3\",\"cap5\",\"cap1\",\"cap4\"]}}"
  },
  {
    "instruction": "Geo chart with city as geo value,stateName as location, lat as latitude and lng as longitude. name it GEO Map.",
    "input": "{\"dataSources\":[{\"dataSourceId\":\"e298aca2-bac5-470c-b630-220bb19336eb\",\"queryKey\":\"API:+jdbc$$TEMP$$us_station_city_geo_data\",\"cols\":[{\"jsonName\":\"city\",\"type\":\"string\",\"aggFn\":\"COUNT\"},{\"jsonName\":\"cityAscii\",\"type\":\"string\"},{\"jsonName\":\"stateId\",\"type\":\"string\"},{\"jsonName\":\"stateName\",\"type\":\"string\"},{\"jsonName\":\"countyFips\",\"type\":\"string\"},{\"jsonName\":\"countyName\",\"type\":\"string\"},{\"jsonName\":\"lat\",\"type\":\"number\"},{\"jsonName\":\"lng\",\"type\":\"number\"},{\"jsonName\":\"population\",\"type\":\"number\"},{\"jsonName\":\"density\",\"type\":\"number\"},{\"jsonName\":\"source\",\"type\":\"string\"},{\"jsonName\":\"military\",\"type\":\"string\"},{\"jsonName\":\"incorporated\",\"type\":\"string\"},{\"jsonName\":\"timezone\",\"type\":\"string\"},{\"jsonName\":\"ranking\",\"type\":\"number\"},{\"jsonName\":\"zips\",\"type\":\"string\"},{\"jsonName\":\"id\",\"type\":\"number\"}],\"params\":[{\"jsonName\":\"State\",\"type\":\"in_set\",\"value\":\"NJ,AK\"}]}]}",
    "output": "{\"dataSources\":[{\"dataSourceId\":\"e298aca2-bac5-470c-b630-220bb19336eb\",\"queryKey\":\"API:+jdbc$$TEMP$$us_station_city_geo_data\",\"cols\":[{\"jsonName\":\"city\",\"type\":\"string\",\"aggFn\":\"COUNT\"},{\"jsonName\":\"cityAscii\",\"type\":\"string\"},{\"jsonName\":\"stateId\",\"type\":\"string\"},{\"jsonName\":\"stateName\",\"type\":\"string\"},{\"jsonName\":\"countyFips\",\"type\":\"string\"},{\"jsonName\":\"countyName\",\"type\":\"string\"},{\"jsonName\":\"lat\",\"type\":\"number\"},{\"jsonName\":\"lng\",\"type\":\"number\"},{\"jsonName\":\"population\",\"type\":\"number\"},{\"jsonName\":\"density\",\"type\":\"number\"},{\"jsonName\":\"source\",\"type\":\"string\"},{\"jsonName\":\"military\",\"type\":\"string\"},{\"jsonName\":\"incorporated\",\"type\":\"string\"},{\"jsonName\":\"timezone\",\"type\":\"string\"},{\"jsonName\":\"ranking\",\"type\":\"number\"},{\"jsonName\":\"zips\",\"type\":\"string\"},{\"jsonName\":\"id\",\"type\":\"number\"}],\"params\":[{\"jsonName\":\"State\",\"type\":\"in_set\",\"value\":\"NJ,AK\"}]}],\"chartLayout\":\"vertical\",\"attributes\":{\"chartType\":\"Geo Chart\",\"sortOrder\":\"Asc\",\"chartSubType\":\"map\"},\"chartName\":\"GEO Map\",\"compositeDataSource\":\"\",\"longitude\":{\"fields\":[\"lng\"]},\"latitude\":{\"fields\":[\"lat\"]},\"geoValue\":{\"fields\":[\"city\"]},\"location\":{\"fields\":[\"stateName\"]},\"geoField\":{}}"
  }
]